Workbook

Sheet Start
A1: HARBORLIGHT V3 • Premium, zadania i ekspedycje
A2: Wersja 3 uwzględnia wpisy z 22.10.2026, zachowuje wcześniejsze zasady i źródła. To dokument projektu; nie zmienia kodu gry. Modele kalkulatorów i otwarte interpretacje oznaczono osobno.
A5: Obszar | B5: Co zmieniono | C5: Gdzie sprawdzić
A6: Główna tabela | B6: 12 budynków + asset Człowiek; nowe koszty, limity własnego poziomu, efekty rozbudowy i czasy. | C6: Budynki
A7: Czasy | B7: 5 min — pełny kurs, jeden rodzaj towaru, ładunki 60/66/72; Ratusz/Dom 2 T, Latarnia 5 T, Kaplica 4 T/7 T/10 T. | C7: Czas budowy: 74 warianty (37 etapów × bazowy/kolejka).
A8: Kolejka | B8: Pełny koszt przy zleceniu +10%; dopłata materiałowa zmienia liczbę kursów i czas. | C8: Normalnie L budów + L miejsc kolejki. Czekanie w kolejce jest wyłączone z estymat.
A9: Zatrudnienie | B9: Własny limit 12 × poziom budynku; produkcja 10, 12, 13, 14…; 5 min do pracy i do domu. | C9: Czlowiek / Produkcja
A10: Offline | B10: Cała gospodarka działa również offline: podatki, jedzenie, szczęście, populacja, produkcja, transport i budowa. | C10: Transport i priorytety; Czlowiek
A11: Koszty | B11: Magazyn/Targ: 300 L każdego zasobu; Port: 400 L; Ratusz/Dom: 500 L; Latarnia: 500 × max(1, L). | C11: Parametry / Czas budowy
A12: Transport | B12: Rezerwa Food: 50 × poziom magazynu; priorytety: zaopatrzenie, potem budowy; własne załogi targu i portu. | C12: Transport i priorytety. Ratunkowy próg Food wymaga spójnego doprecyzowania.
A13: Ceny | B13: Port: podstawowe 40/50, produkty 140/150 za 100; podwyżki zakupowe +10% liniowo. Ostatnia korekta dotyczy PORTU, nie TARGU. | C13: Przystan; Targ: bez monet, marża 10%.
A14: Terminy | B14: Towar w porcie/targu nieodebrany przez 24 h przepada; portowa opłata 10 monet została zniesiona. | C14: Terminy zegarowe, również offline.
A15: Premie i wizyty | B15: Kaplica = błogosławieństwo, Latarnia = zwiedzanie. Latarnia ustawia szczęście na 100%, nie dodaje +100. | C15: Blogoslawienstwa; szczegóły wizyt pozostają otwarte.
A16: Premium | B16: 1 PLN = 10 monet; skrócenie budowy o 25/50/75% za 1 monetę za pełną minutę; transport: 10 monet/kurs; materiały według cen portu ×1,25 plus opłata czasowa. | C16: Premium / trzy kalkulatory Premium.
... A24: Balans i niejasności | B24: Duże zadania wymagają wcześniejszych zapasów, a nagrody mogą nie mieścić się w centrali. Rozliczanie pełnych minut może dawać cenę 0; pula ekspedycji rośnie wykładniczo. | C24: Bilans V3 / Decyzje i konflikty.

Sheet Budynki
A1: BUDYNKI V2 • uwzględnione wpisy i odpowiedzi
A2: Nowy plik 2; poprzednie pliki 0 i 1 pozostają. Czasy bazowe przy 6 DOSTĘPNYCH tragarzach, ładunki 60/66/72, pełny kurs 5 min. Bez zbierania, karmienia, oczekiwania w kolejce i wcześniejszych rozbudów. Kolejka ma osobne koszty i czasy z +10% w arkuszu Czas budowy. Wszystko działa offline.
A5: Budynek / asset | B5: Po co jest | C5: Ludzie | D5: Co daje rozbudowa | E5: Koszt bazowy | F5: Czas łączny | G5: Stan | H5: Notyfikacje | I5: Uwagi i reguły | J5: Premium | K5: Twoje uwagi3 / doprecyzowania | L5: Źródło zmian | M5: 1→2 transport+budowa | N5: 2→3 transport+budowa | O5: 3→4 transport+budowa
A6: Ratusz | B6: Wyznacza poziom gry i limity rozwoju; jest skarbcem monet i pokazuje podatek/h. | C6: Brak własnych pracowników. | D6: Maksymalna populacja: 24 × L; wyższy poziom innych budynków; L budów + L miejsc kolejki; lokalne bufory producentów: 200 × Ratusz. | E6: 500×L KAŻDEGO z 6 zasobów | F6: 2T = T transportu + T budowy | G6: Zasady uporządkowane; otwarte szczegóły w arkuszu Decyzje i konflikty. | H6: ZAWSZE: ukończenie budowy. Wcześniej także zlecenie/start/dostawa. | I6: Ranking = poziom ratusza × monety. L budów + L miejsc kolejki; zlecenia zakolejkowane mają koszt wyższy o 10%. | J6: V3: skrócenie budowy o 25/50/75% — 1 moneta za pełną zaoszczędzoną minutę. Kupno bez surowców: portowa wartość materiałów ×1,25 plus opłata czasowa. Podstawa czasu i szczegóły wyceny są oznaczone w Premium jako modele. Dotychczasowe natychmiastowe ukończenie nie ma zatwierdzonej ceny skrócenia o 100%. | K6: Budowa: Ratusz na poziomie 1 daje możliwość 1 rozbudowy w tym samym czasie i (o ile mam surowce) jednej zakolejkowanej, ale na tą zakolejkowaną muszę mieć surowce w momencie zlecania. Ratusz na poziomie 2 daje prawo do 2 budów I dwóch obiektów w kolejce pod tym samym warunkiem. Budynki zakolejkowane są o 10 % droższe niż te budowane bez kolejki. Później dopiszemy co oferuje premium (na pewno jedną z opcji będzie skróć czas budowy) | L6: Budynki!wiersz 6; potwierdzenia w Odpowiedzi i zmiany | M6: =TEXT('Czas budowy'!Y6,"0")&" min bazowo; T="&TEXT('Czas budowy'!V6,"0")&" min; budowa="&TEXT('Czas budowy'!X6,"0")&" min. Kolejka +10%: "&TEXT('Czas budowy'!Y7,"0")&" min (bez czekania)." -> 80 min bazowo; T=40 min; budowa=40 min. Kolejka +10%: 90 min (bez czekania). | N6: =TEXT('Czas budowy'!Y8,"0")&" min bazowo; T="&TEXT('Czas budowy'!V8,"0")&" min; budowa="&TEXT('Czas budowy'!X8,"0")&" min. Kolejka +10%: "&TEXT('Czas budowy'!Y9,"0")&" min (bez czekania)." -> 140 min bazowo; T=70 min; budowa=70 min. Kolejka +10%: 150 min (bez czekania). | O6: =TEXT('Czas budowy'!Y10,"0")&" min bazowo; T="&TEXT('Czas budowy'!V10,"0")&" min; budowa="&TEXT('Czas budowy'!X10,"0")&" min. Kolejka +10%: "&TEXT('Czas budowy'!Y11,"0")&" min (bez czekania)." -> 180 min bazowo; T=90 min; budowa=90 min. Kolejka +10%: 200 min (bez czekania).
A7: Dom | B7: Zapewnia miejsca mieszkalne, osobno od maksymalnego limitu ratusza. | C7: Brak własnych pracowników. | D7: Miejsca: 24 × poziom domu; zmniejszenie kary przeludnienia. Panel pokazuje ludzi i przydziały oraz pozwala wysyłać wizyty do kaplicy i latarni. | E7: 500×L KAŻDEGO z 6 zasobów | F7: 2T = T transportu + T budowy | G7: Zasady uporządkowane; otwarte szczegóły w arkuszu Decyzje i konflikty. | H7: ZAWSZE: ukończenie budowy. Wcześniej także zlecenie/start/dostawa. NOWE: przeludnienie; proponujemy na zmianę stanu, nie co klatkę. | I7: Kara przeludnienia: max(0, P − 24 × poziom domu) pp/h każdej osobie. Nowi mieszkańcy zawsze trafiają do domu. | J7: V3: skrócenie budowy o 25/50/75% — 1 moneta za pełną zaoszczędzoną minutę. Kupno bez surowców: portowa wartość materiałów ×1,25 plus opłata czasowa. Podstawa czasu i szczegóły wyceny są oznaczone w Premium jako modele. Dotychczasowe natychmiastowe ukończenie nie ma zatwierdzonej ceny skrócenia o 100%. | K7: Z poziomu domu widzę wszystkich ludzi gdzie są dopisani, mogę ich stąd wysyłać do kaplicy lub na latarnię | L7: Budynki!wiersz 7; potwierdzenia w Odpowiedzi i zmiany | M7: =TEXT('Czas budowy'!Y12,"0")&" min bazowo; T="&TEXT('Czas budowy'!V12,"0")&" min; budowa="&TEXT('Czas budowy'!X12,"0")&" min. Kolejka +10%: "&TEXT('Czas budowy'!Y13,"0")&" min (bez czekania)." -> 80 min bazowo; T=40 min; budowa=40 min. Kolejka +10%: 90 min (bez czekania). | N7: =TEXT('Czas budowy'!Y14,"0")&" min bazowo; T="&TEXT('Czas budowy'!V14,"0")&" min; budowa="&TEXT('Czas budowy'!X14,"0")&" min. Kolejka +10%: "&TEXT('Czas budowy'!Y15,"0")&" min (bez czekania)." -> 140 min bazowo; T=70 min; budowa=70 min. Kolejka +10%: 150 min (bez czekania). | O7: =TEXT('Czas budowy'!Y16,"0")&" min bazowo; T="&TEXT('Czas budowy'!V16,"0")&" min; budowa="&TEXT('Czas budowy'!X16,"0")&" min. Kolejka +10%: "&TEXT('Czas budowy'!Y17,"0")&" min (bez czekania)." -> 180 min bazowo; T=90 min; budowa=90 min. Kolejka +10%: 200 min (bez czekania).
A8: Farma | B8: Produkuje zboże do młyna, budowy i wymiany. | C8: Start: 0; limit 12 × WŁASNY poziom budynku, ograniczony liczbą istniejących dostępnych ludzi. Ratusz tylko ogranicza poziom rozbudowy. | D8: Własny poziom daje limit 12 × L pracowników i wydajność na osobę/h: 10, 12, 13, 14…; L1 = 10, L ≥ 2: L + 10. Bufor lokalny: 200 × Ratusz. | E8: L×(72 drewna+72 kamienia+120 zboża) | F8: 2T = T transportu + T budowy | G8: Zasady uporządkowane; otwarte szczegóły w arkuszu Decyzje i konflikty. | H8: ZAWSZE: ukończenie budowy. Wcześniej także zlecenie/start/dostawa. Powiadomienie o pełnym magazynie. | I8: Pełny lokalny bufor: produkcja STOP, osobny modyfikator −10…−50. Brak surowca/miejsca powoduje brak pracy; podatek i bonus +1 przy blokadzie pozostają do decyzji. Droga: 5 min w każdą stronę; drewno i zboże przez centralę. | J8: V3: skrócenie budowy o 25/50/75% — 1 moneta za pełną zaoszczędzoną minutę. Kupno bez surowców: portowa wartość materiałów ×1,25 plus opłata czasowa. Podstawa czasu i szczegóły wyceny są oznaczone w Premium jako modele. Dotychczasowe natychmiastowe ukończenie nie ma zatwierdzonej ceny skrócenia o 100%. Transport Premium: 10 monet za kurs; rozliczenie ostatniego niepełnego kursu pozostaje do potwierdzenia. | K8: Do wszystkich produkcyjnych, zwiększenie levelu zwiększa produkcję na 1 h, dla levelu 1 jest to 10 szt / h dla levelu 2 będzie to 12, dla levelu 3 -13 dla 4 - 14 etc W premium dla wszystkich produkcyjnych możłiwość natychmiastowego transportu do magazynu oneclickiem. | L8: Budynki!wiersz 8; potwierdzenia w Odpowiedzi i zmiany | M8: =TEXT('Czas budowy'!Y18,"0")&" min bazowo; T="&TEXT('Czas budowy'!V18,"0")&" min; budowa="&TEXT('Czas budowy'!X18,"0")&" min. Kolejka +10%: "&TEXT('Czas budowy'!Y19,"0")&" min (bez czekania)." -> 10 min bazowo; T=5 min; budowa=5 min. Kolejka +10%: 20 min (bez czekania). | N8: =TEXT('Czas budowy'!Y20,"0")&" min bazowo; T="&TEXT('Czas budowy'!V20,"0")&" min; budowa="&TEXT('Czas budowy'!X20,"0")&" min. Kolejka +10%: "&TEXT('Czas budowy'!Y21,"0")&" min (bez czekania)." -> 20 min bazowo; T=10 min; budowa=10 min. Kolejka +10%: 20 min (bez czekania). | O8: =TEXT('Czas budowy'!Y22,"0")&" min bazowo; T="&TEXT('Czas budowy'!V22,"0")&" min; budowa="&TEXT('Czas budowy'!X22,"0")&" min. Kolejka +10%: "&TEXT('Czas budowy'!Y23,"0")&" min (bez czekania)." -> 20 min bazowo; T=10 min; budowa=10 min. Kolejka +10%: 30 min (bez czekania).
A9: Młyn | B9: Przetwarza 2 zboża z centrali→1 żywność do lokalnego bufora. | C9: Start: 0; limit 12 × WŁASNY poziom budynku, ograniczony liczbą istniejących dostępnych ludzi. Ratusz tylko ogranicza poziom rozbudowy. | D9: Własny poziom daje limit 12 × L pracowników i wydajność na osobę/h: 10, 12, 13, 14…; L1 = 10, L ≥ 2: L + 10. Bufor lokalny: 200 × Ratusz. | E9: L×(72 drewna+72 kamienia+120 żywności) | F9: 2T = T transportu + T budowy | G9: Zasady uporządkowane; otwarte szczegóły w arkuszu Decyzje i konflikty. | H9: ZAWSZE: ukończenie budowy. Wcześniej także zlecenie/start/dostawa. Powiadomienie o pełnym magazynie. | I9: Pełny lokalny bufor: produkcja STOP, osobny modyfikator −10…−50. Brak surowca/miejsca powoduje brak pracy; podatek i bonus +1 przy blokadzie pozostają do decyzji. Droga: 5 min w każdą stronę; drewno i zboże przez centralę. | J9: V3: skrócenie budowy o 25/50/75% — 1 moneta za pełną zaoszczędzoną minutę. Kupno bez surowców: portowa wartość materiałów ×1,25 plus opłata czasowa. Podstawa czasu i szczegóły wyceny są oznaczone w Premium jako modele. Dotychczasowe natychmiastowe ukończenie nie ma zatwierdzonej ceny skrócenia o 100%. Transport Premium: 10 monet za kurs; rozliczenie ostatniego niepełnego kursu pozostaje do potwierdzenia. | L9: Budynki!wiersz 9; potwierdzenia w Odpowiedzi i zmiany | M9: =TEXT('Czas budowy'!Y24,"0")&" min bazowo; T="&TEXT('Czas budowy'!V24,"0")&" min; budowa="&TEXT('Czas budowy'!X24,"0")&" min. Kolejka +10%: "&TEXT('Czas budowy'!Y25,"0")&" min (bez czekania)." -> 10 min bazowo; T=5 min; budowa=5 min. Kolejka +10%: 20 min (bez czekania). | N9: =TEXT('Czas budowy'!Y26,"0")&" min bazowo; T="&TEXT('Czas budowy'!V26,"0")&" min; budowa="&TEXT('Czas budowy'!X26,"0")&" min. Kolejka +10%: "&TEXT('Czas budowy'!Y27,"0")&" min (bez czekania)." -> 20 min bazowo; T=10 min; budowa=10 min. Kolejka +10%: 20 min (bez czekania). | O9: =TEXT('Czas budowy'!Y28,"0")&" min bazowo; T="&TEXT('Czas budowy'!V28,"0")&" min; budowa="&TEXT('Czas budowy'!X28,"0")&" min. Kolejka +10%: "&TEXT('Czas budowy'!Y29,"0")&" min (bez czekania)." -> 20 min bazowo; T=10 min; budowa=10 min. Kolejka +10%: 30 min (bez czekania).
A10: Drwale | B10: Produkują drewno do tartaku i budowy. | C10: Start: 0; limit 12 × WŁASNY poziom budynku, ograniczony liczbą istniejących dostępnych ludzi. Ratusz tylko ogranicza poziom rozbudowy. | D10: Własny poziom daje limit 12 × L pracowników i wydajność na osobę/h: 10, 12, 13, 14…; L1 = 10, L ≥ 2: L + 10. Bufor lokalny: 200 × Ratusz. | E10: L×(192 drewna+72 kamienia) | F10: 2T = T transportu + T budowy | G10: Zasady uporządkowane; otwarte szczegóły w arkuszu Decyzje i konflikty. | H10: ZAWSZE: ukończenie budowy. Wcześniej także zlecenie/start/dostawa. Powiadomienie o pełnym magazynie. | I10: Pełny lokalny bufor: produkcja STOP, osobny modyfikator −10…−50. Brak surowca/miejsca powoduje brak pracy; podatek i bonus +1 przy blokadzie pozostają do decyzji. Droga: 5 min w każdą stronę; drewno i zboże przez centralę. | J10: V3: skrócenie budowy o 25/50/75% — 1 moneta za pełną zaoszczędzoną minutę. Kupno bez surowców: portowa wartość materiałów ×1,25 plus opłata czasowa. Podstawa czasu i szczegóły wyceny są oznaczone w Premium jako modele. Dotychczasowe natychmiastowe ukończenie nie ma zatwierdzonej ceny skrócenia o 100%. Transport Premium: 10 monet za kurs; rozliczenie ostatniego niepełnego kursu pozostaje do potwierdzenia. | L10: Budynki!wiersz 10; potwierdzenia w Odpowiedzi i zmiany | M10: =TEXT('Czas budowy'!Y30,"0")&" min bazowo; T="&TEXT('Czas budowy'!V30,"0")&" min; budowa="&TEXT('Czas budowy'!X30,"0")&" min. Kolejka +10%: "&TEXT('Czas budowy'!Y31,"0")&" min (bez czekania)." -> 10 min bazowo; T=5 min; budowa=5 min. Kolejka +10%: 10 min (bez czekania). | N10: =TEXT('Czas budowy'!Y32,"0")&" min bazowo; T="&TEXT('Czas budowy'!V32,"0")&" min; budowa="&TEXT('Czas budowy'!X32,"0")&" min. Kolejka +10%: "&TEXT('Czas budowy'!Y33,"0")&" min (bez czekania)." -> 20 min bazowo; T=10 min; budowa=10 min. Kolejka +10%: 20 min (bez czekania). | O10: =TEXT('Czas budowy'!Y34,"0")&" min bazowo; T="&TEXT('Czas budowy'!V34,"0")&" min; budowa="&TEXT('Czas budowy'!X34,"0")&" min. Kolejka +10%: "&TEXT('Czas budowy'!Y35,"0")&" min (bez czekania)." -> 20 min bazowo; T=10 min; budowa=10 min. Kolejka +10%: 30 min (bez czekania).
A11: Tartak | B11: Przetwarza 2 drewna z centrali→1 deskę do lokalnego bufora. | C11: Start: 0; limit 12 × WŁASNY poziom budynku, ograniczony liczbą istniejących dostępnych ludzi. Ratusz tylko ogranicza poziom rozbudowy. | D11: Własny poziom daje limit 12 × L pracowników i wydajność na osobę/h: 10, 12, 13, 14…; L1 = 10, L ≥ 2: L + 10. Bufor lokalny: 200 × Ratusz. | E11: L×(72 drewna+72 kamienia+120 desek) | F11: 2T = T transportu + T budowy | G11: Zasady uporządkowane; otwarte szczegóły w arkuszu Decyzje i konflikty. | H11: ZAWSZE: ukończenie budowy. Wcześniej także zlecenie/start/dostawa. Powiadomienie o pełnym magazynie. | I11: Pełny lokalny bufor: produkcja STOP, osobny modyfikator −10…−50. Brak surowca/miejsca powoduje brak pracy; podatek i bonus +1 przy blokadzie pozostają do decyzji. Droga: 5 min w każdą stronę; drewno i zboże przez centralę. | J11: V3: skrócenie budowy o 25/50/75% — 1 moneta za pełną zaoszczędzoną minutę. Kupno bez surowców: portowa wartość materiałów ×1,25 plus opłata czasowa. Podstawa czasu i szczegóły wyceny są oznaczone w Premium jako modele. Dotychczasowe natychmiastowe ukończenie nie ma zatwierdzonej ceny skrócenia o 100%. Transport Premium: 10 monet za kurs; rozliczenie ostatniego niepełnego kursu pozostaje do potwierdzenia. | L11: Budynki!wiersz 11; potwierdzenia w Odpowiedzi i zmiany | M11: =TEXT('Czas budowy'!Y36,"0")&" min bazowo; T="&TEXT('Czas budowy'!V36,"0")&" min; budowa="&TEXT('Czas budowy'!X36,"0")&" min. Kolejka +10%: "&TEXT('Czas budowy'!Y37,"0")&" min (bez czekania)." -> 10 min bazowo; T=5 min; budowa=5 min. Kolejka +10%: 20 min (bez czekania). | N11: =TEXT('Czas budowy'!Y38,"0")&" min bazowo; T="&TEXT('Czas budowy'!V38,"0")&" min; budowa="&TEXT('Czas budowy'!X38,"0")&" min. Kolejka +10%: "&TEXT('Czas budowy'!Y39,"0")&" min (bez czekania)." -> 20 min bazowo; T=10 min; budowa=10 min. Kolejka +10%: 20 min (bez czekania). | O11: =TEXT('Czas budowy'!Y40,"0")&" min bazowo; T="&TEXT('Czas budowy'!V40,"0")&" min; budowa="&TEXT('Czas budowy'!X40,"0")&" min. Kolejka +10%: "&TEXT('Czas budowy'!Y41,"0")&" min (bez czekania)." -> 20 min bazowo; T=10 min; budowa=10 min. Kolejka +10%: 30 min (bez czekania).
A12: Kamieniołom | B12: Produkuje kamień do budowy i wymiany. | C12: Start: 0; limit 12 × WŁASNY poziom budynku, ograniczony liczbą istniejących dostępnych ludzi. Ratusz tylko ogranicza poziom rozbudowy. | D12: Własny poziom daje limit 12 × L pracowników i wydajność na osobę/h: 10, 12, 13, 14…; L1 = 10, L ≥ 2: L + 10. Bufor lokalny: 200 × Ratusz. | E12: L×(72 drewna+192 kamienia) | F12: 2T = T transportu + T budowy | G12: Zasady uporządkowane; otwarte szczegóły w arkuszu Decyzje i konflikty. | H12: ZAWSZE: ukończenie budowy. Wcześniej także zlecenie/start/dostawa. Powiadomienie o pełnym magazynie. | I12: Pełny lokalny bufor: produkcja STOP, osobny modyfikator −10…−50. Brak surowca/miejsca powoduje brak pracy; podatek i bonus +1 przy blokadzie pozostają do decyzji. Droga: 5 min w każdą stronę; drewno i zboże przez centralę. | J12: V3: skrócenie budowy o 25/50/75% — 1 moneta za pełną zaoszczędzoną minutę. Kupno bez surowców: portowa wartość materiałów ×1,25 plus opłata czasowa. Podstawa czasu i szczegóły wyceny są oznaczone w Premium jako modele. Dotychczasowe natychmiastowe ukończenie nie ma zatwierdzonej ceny skrócenia o 100%. Transport Premium: 10 monet za kurs; rozliczenie ostatniego niepełnego kursu pozostaje do potwierdzenia. | L12: Budynki!wiersz 12; potwierdzenia w Odpowiedzi i zmiany | M12: =TEXT('Czas budowy'!Y42,"0")&" min bazowo; T="&TEXT('Czas budowy'!V42,"0")&" min; budowa="&TEXT('Czas budowy'!X42,"0")&" min. Kolejka +10%: "&TEXT('Czas budowy'!Y43,"0")&" min (bez czekania)." -> 10 min bazowo; T=5 min; budowa=5 min. Kolejka +10%: 10 min (bez czekania). | N12: =TEXT('Czas budowy'!Y44,"0")&" min bazowo; T="&TEXT('Czas budowy'!V44,"0")&" min; budowa="&TEXT('Czas budowy'!X44,"0")&" min. Kolejka +10%: "&TEXT('Czas budowy'!Y45,"0")&" min (bez czekania)." -> 20 min bazowo; T=10 min; budowa=10 min. Kolejka +10%: 20 min (bez czekania). | O12: =TEXT('Czas budowy'!Y46,"0")&" min bazowo; T="&TEXT('Czas budowy'!V46,"0")&" min; budowa="&TEXT('Czas budowy'!X46,"0")&" min. Kolejka +10%: "&TEXT('Czas budowy'!Y47,"0")&" min (bez czekania)." -> 20 min bazowo; T=10 min; budowa=10 min. Kolejka +10%: 30 min (bez czekania).
A13: Magazyn | B13: Przechowuje materiały; własna załoga nosi produkcję do centrali i materiały na budowy. Ludzie jedzą z centrali automatycznie. | C13: Start: 0; limit 12 × WŁASNY poziom budynku, ograniczony liczbą istniejących dostępnych ludzi. Ratusz tylko ogranicza poziom rozbudowy. | D13: Limit załogi: 12 × własny L; ładunek na kurs +10%/poziom. Pojemność ×1.5/poziom; magazyn/port: 1000 na rodzaj i 4000 łącznie na poziomie 1; targ: 1000 łącznie na poziomie 1. | E13: 300 × L każdego z 6 zasobów; w kolejce ×1,1. | F13: 2T = T transportu + T budowy | G13: Zasady uporządkowane; otwarte szczegóły w arkuszu Decyzje i konflikty. | H13: ZAWSZE: ukończenie budowy. Wcześniej także zlecenie/start/dostawa. Powiadomienie o pełnym magazynie. | I13: Rezerwa Food: 50 × poziom magazynu. Domyślnie uzupełnij centralę, potem budowy. Zmienne priorytety według budynku/zlecenia; ratunkowy 1 tragarz Food — próg do doprecyzowania. Pełny kurs: 5 min, 1 rodzaj towaru; niepełny ładunek wysyłany od razu. | J13: V3: skrócenie budowy o 25/50/75% — 1 moneta za pełną zaoszczędzoną minutę. Kupno bez surowców: portowa wartość materiałów ×1,25 plus opłata czasowa. Podstawa czasu i szczegóły wyceny są oznaczone w Premium jako modele. Dotychczasowe natychmiastowe ukończenie nie ma zatwierdzonej ceny skrócenia o 100%. Transport Premium: 10 monet za kurs; rozliczenie ostatniego niepełnego kursu pozostaje do potwierdzenia. | K13: Transport. Nie rozróżniamy odległości, transport produków zawsze trwa 5 min z/do magazynu x capacity tragarza czyli jeżeli tragarz bierze 60 a potrzebuje przenieść 100 to I tak musi wykonać 2 kursy w jednym bierze 60 w drugim 40, tragarz nie może brać 2 produktow na raz, nie może czekać na towar. Jak klikam rozbudowa np drwala podświetla sie napis ile potrzeba surowców a ile zostało już dostarczonych np 60 /100 i estymowany czas zakońćzenia budowy czyli suma czasu transportu przy aktualnych ustawieniach priorytetów, i budowy. Z poziomu magazynu domyślne prirytety jest najpierw zaopatrz magazyn pózniej budowy, można je zmieniać, dodatkowo też można zmienić ustalić prio na konkretne gospodarstwo bądz konretną budowę, 1 tragarz zawsze będzie nosił żywność o ile jest wyprodukowana a w magazynie jest mniej niż 50 Premium szybszy transport do puntu odbioru | L13: Budynki!wiersz 13; potwierdzenia w Odpowiedzi i zmiany | M13: =TEXT('Czas budowy'!Y48,"0")&" min bazowo; T="&TEXT('Czas budowy'!V48,"0")&" min; budowa="&TEXT('Czas budowy'!X48,"0")&" min. Kolejka +10%: "&TEXT('Czas budowy'!Y49,"0")&" min (bez czekania)." -> 50 min bazowo; T=25 min; budowa=25 min. Kolejka +10%: 50 min (bez czekania). | N13: =TEXT('Czas budowy'!Y50,"0")&" min bazowo; T="&TEXT('Czas budowy'!V50,"0")&" min; budowa="&TEXT('Czas budowy'!X50,"0")&" min. Kolejka +10%: "&TEXT('Czas budowy'!Y51,"0")&" min (bez czekania)." -> 90 min bazowo; T=45 min; budowa=45 min. Kolejka +10%: 90 min (bez czekania). | O13: =TEXT('Czas budowy'!Y52,"0")&" min bazowo; T="&TEXT('Czas budowy'!V52,"0")&" min; budowa="&TEXT('Czas budowy'!X52,"0")&" min. Kolejka +10%: "&TEXT('Czas budowy'!Y53,"0")&" min (bez czekania)." -> 110 min bazowo; T=55 min; budowa=55 min. Kolejka +10%: 120 min (bez czekania).
A14: Targ | B14: Od poziomu gracza 2: wymiana w grupach drewno/kamień/zboże lub deski/żywność, nominalnie 1:1 z marżą 10%. Bez kupowania za monety. | C14: Start: 0; limit 12 × WŁASNY poziom budynku, ograniczony liczbą istniejących dostępnych ludzi. Ratusz tylko ogranicza poziom rozbudowy. | D14: Limit załogi: 12 × własny L; ładunek na kurs +10%/poziom. Pojemność ×1.5/poziom; magazyn/port: 1000 na rodzaj i 4000 łącznie na poziomie 1; targ: 1000 łącznie na poziomie 1. | E14: 300 × L każdego z 6 zasobów; w kolejce ×1,1. | F14: 2T = T transportu + T budowy | G14: Zasady uporządkowane; otwarte szczegóły w arkuszu Decyzje i konflikty. | H14: ZAWSZE: ukończenie budowy. Wcześniej także zlecenie/start/dostawa. Powiadomienie o pełnym magazynie. | I14: Własna załoga w obu kierunkach. Barter w 2 grupach, marża 10%, bez monet. Pozostaje blokada dostaw 1 h; zapas przepada po 24 h od przyniesienia/wymiany. | J14: V3: skrócenie budowy o 25/50/75% — 1 moneta za pełną zaoszczędzoną minutę. Kupno bez surowców: portowa wartość materiałów ×1,25 plus opłata czasowa. Podstawa czasu i szczegóły wyceny są oznaczone w Premium jako modele. Dotychczasowe natychmiastowe ukończenie nie ma zatwierdzonej ceny skrócenia o 100%. Transport Premium: 10 monet za kurs; rozliczenie ostatniego niepełnego kursu pozostaje do potwierdzenia. | K14: Premium transport oneclick Ceny grupa 2 140/150 | L14: Budynki!wiersz 14; potwierdzenia w Odpowiedzi i zmiany | M14: =TEXT('Czas budowy'!Y54,"0")&" min bazowo; T="&TEXT('Czas budowy'!V54,"0")&" min; budowa="&TEXT('Czas budowy'!X54,"0")&" min. Kolejka +10%: "&TEXT('Czas budowy'!Y55,"0")&" min (bez czekania)." -> 50 min bazowo; T=25 min; budowa=25 min. Kolejka +10%: 50 min (bez czekania). | N14: =TEXT('Czas budowy'!Y56,"0")&" min bazowo; T="&TEXT('Czas budowy'!V56,"0")&" min; budowa="&TEXT('Czas budowy'!X56,"0")&" min. Kolejka +10%: "&TEXT('Czas budowy'!Y57,"0")&" min (bez czekania)." -> 90 min bazowo; T=45 min; budowa=45 min. Kolejka +10%: 90 min (bez czekania). | O14: =TEXT('Czas budowy'!Y58,"0")&" min bazowo; T="&TEXT('Czas budowy'!V58,"0")&" min; budowa="&TEXT('Czas budowy'!X58,"0")&" min. Kolejka +10%: "&TEXT('Czas budowy'!Y59,"0")&" min (bez czekania)." -> 110 min bazowo; T=55 min; budowa=55 min. Kolejka +10%: 120 min (bez czekania).
A15: Przystań | B15: Od poziomu gracza 4: kupno i sprzedaż pięciu materiałów za monety. Wyłącznie pełne paczki 100. Monety są środkiem płatności, nie osobnym towarem. | C15: Start: 0; limit 12 × WŁASNY poziom budynku, ograniczony liczbą istniejących dostępnych ludzi. Ratusz tylko ogranicza poziom rozbudowy. | D15: Limit załogi: 12 × własny L; ładunek na kurs +10%/poziom. Pojemność ×1.5/poziom; magazyn/port: 1000 na rodzaj i 4000 łącznie na poziomie 1; targ: 1000 łącznie na poziomie 1. | E15: 400 × L każdego z 6 zasobów; w kolejce ×1,1. | F15: 2T = T transportu + T budowy | G15: Zasady uporządkowane; otwarte szczegóły w arkuszu Decyzje i konflikty. | H15: ZAWSZE: ukończenie budowy. Wcześniej także zlecenie/start/dostawa. Powiadomienie o pełnym magazynie. | I15: Za 100: podstawowe 40/50, przetworzone 140/150. Podwyżka zakupu liniowo +10% w 3 h. Własna załoga, dwa cykle; statek = pojemność portu; płatność za sprzedaż przy wypłynięciu, za zakup przy przypłynięciu. Nieodebrane przez 24 h przepada, bez opłaty 10. | J15: V3: skrócenie budowy o 25/50/75% — 1 moneta za pełną zaoszczędzoną minutę. Kupno bez surowców: portowa wartość materiałów ×1,25 plus opłata czasowa. Podstawa czasu i szczegóły wyceny są oznaczone w Premium jako modele. Dotychczasowe natychmiastowe ukończenie nie ma zatwierdzonej ceny skrócenia o 100%. Transport Premium: 10 monet za kurs; rozliczenie ostatniego niepełnego kursu pozostaje do potwierdzenia. | K15: Tempo załogi jak w magazynie, premium jak w magazynie | L15: Budynki!wiersz 15; potwierdzenia w Odpowiedzi i zmiany | M15: =TEXT('Czas budowy'!Y60,"0")&" min bazowo; T="&TEXT('Czas budowy'!V60,"0")&" min; budowa="&TEXT('Czas budowy'!X60,"0")&" min. Kolejka +10%: "&TEXT('Czas budowy'!Y61,"0")&" min (bez czekania)." -> 60 min bazowo; T=30 min; budowa=30 min. Kolejka +10%: 70 min (bez czekania). | N15: =TEXT('Czas budowy'!Y62,"0")&" min bazowo; T="&TEXT('Czas budowy'!V62,"0")&" min; budowa="&TEXT('Czas budowy'!X62,"0")&" min. Kolejka +10%: "&TEXT('Czas budowy'!Y63,"0")&" min (bez czekania)." -> 110 min bazowo; T=55 min; budowa=55 min. Kolejka +10%: 120 min (bez czekania). | O15: =TEXT('Czas budowy'!Y64,"0")&" min bazowo; T="&TEXT('Czas budowy'!V64,"0")&" min; budowa="&TEXT('Czas budowy'!X64,"0")&" min. Kolejka +10%: "&TEXT('Czas budowy'!Y65,"0")&" min (bez czekania)." -> 150 min bazowo; T=75 min; budowa=75 min. Kolejka +10%: 160 min (bez czekania).
A16: Kaplica | B16: Daje premie szczęścia i podatków po rozbudowie; dotychczas była miejscem ręcznych błogosławieństw. | C16: Brak etatów; wizyty nie są zatrudnieniem. | D16: +1 użycie dotychczasowego błogosławieństwa; rozbudowa do N: +10 × N szczęścia, podatki ×2 na 10 h. Kaplica = błogosławieństwo. | E16: TYMCZASOWO:N×(180 monet+20 drewna+60 kamienia+10 desek). N=nowy poziom. | F16: T transportu + 3T × (N − 1) budowy; N = nowy poziom. Łącznie: 4T, 7T, 10T… | G16: Zasady uporządkowane; otwarte szczegóły w arkuszu Decyzje i konflikty. | H16: ZAWSZE: ukończenie budowy. Wcześniej także zlecenie/start/dostawa. Uruchomienie premii i ręczne błogosławieństwo. | I16: Ręczne: +50 każdego zasobu, +20 szczęścia na 1 h; nowe odstępy i reklamy nadal odłożone. Wyjaśnienie dawnych notatek D09/D16 w arkuszu Decyzje i konflikty. | J16: V3: skrócenie budowy o 25/50/75% — 1 moneta za pełną zaoszczędzoną minutę. Kupno bez surowców: portowa wartość materiałów ×1,25 plus opłata czasowa. Podstawa czasu i szczegóły wyceny są oznaczone w Premium jako modele. Dotychczasowe natychmiastowe ukończenie nie ma zatwierdzonej ceny skrócenia o 100%. | L16: Budynki!wiersz 16; potwierdzenia w Odpowiedzi i zmiany | M16: =TEXT('Czas budowy'!Y66,"0")&" min bazowo; T="&TEXT('Czas budowy'!V66,"0")&" min; budowa="&TEXT('Czas budowy'!X66,"0")&" min. Kolejka +10%: "&TEXT('Czas budowy'!Y67,"0")&" min (bez czekania)." -> 20 min bazowo; T=5 min; budowa=15 min. Kolejka +10%: 20 min (bez czekania). | N16: =TEXT('Czas budowy'!Y68,"0")&" min bazowo; T="&TEXT('Czas budowy'!V68,"0")&" min; budowa="&TEXT('Czas budowy'!X68,"0")&" min. Kolejka +10%: "&TEXT('Czas budowy'!Y69,"0")&" min (bez czekania)." -> 35 min bazowo; T=5 min; budowa=30 min. Kolejka +10%: 35 min (bez czekania). | O16: =TEXT('Czas budowy'!Y70,"0")&" min bazowo; T="&TEXT('Czas budowy'!V70,"0")&" min; budowa="&TEXT('Czas budowy'!X70,"0")&" min. Kolejka +10%: "&TEXT('Czas budowy'!Y71,"0")&" min (bez czekania)." -> 100 min bazowo; T=10 min; budowa=90 min. Kolejka +10%: 100 min (bez czekania).
A17: Latarnia | B17: Daje premie szczęścia i produkcji po ukończeniu poziomu. | C17: Brak etatów; wizyty nie są zatrudnieniem. | D17: Ustawia efektywne szczęście wszystkich na 100% i produkcję ×2 na 24 h × N. Latarnia = zwiedzanie; szczegóły wizyt nie zostały jeszcze opisane. | E17: 500×max(1, L) KAŻDEGO z 6 zasobów. Pierwsza budowa 0→1:500 każdego. | F17: 5T = T transportu + 4T budowy | G17: Zasady uporządkowane; otwarte szczegóły w arkuszu Decyzje i konflikty. | H17: ZAWSZE: ukończenie budowy. Wcześniej także zlecenie/start/dostawa. Uruchomienie premii latarni. | I17: 100% to nie +100; wszyscy mają maksymalne efektywne szczęście w czasie premii. Produkcja ×2, podatki i transport bez mnożnika. Wizyta niesprecyzowana, premium osobno. Osobny panel: 3 zadania małe/średnie/duże, 6 h każde, wpłaty z centrali bez transportu. Nie mylić z premią rozbudowy ani zwiedzaniem. | J17: V3: skrócenie budowy o 25/50/75% — 1 moneta za pełną zaoszczędzoną minutę. Kupno bez surowców: portowa wartość materiałów ×1,25 plus opłata czasowa. Podstawa czasu i szczegóły wyceny są oznaczone w Premium jako modele. Dotychczasowe natychmiastowe ukończenie nie ma zatwierdzonej ceny skrócenia o 100%. | K17: Nowe błogosławieństwo: kasa/challenge/udostępnienie/reklama. Zgodnie z decyzją użytkownika szczegóły ODŁOŻONE. Brak cen ani zatwierdzonej integracji. | L17: Budynki!wiersz 17; potwierdzenia w Odpowiedzi i zmiany | M17: =TEXT('Czas budowy'!Y72,"0")&" min bazowo; T="&TEXT('Czas budowy'!V72,"0")&" min; budowa="&TEXT('Czas budowy'!X72,"0")&" min. Kolejka +10%: "&TEXT('Czas budowy'!Y73,"0")&" min (bez czekania)." -> 200 min bazowo; T=40 min; budowa=160 min. Kolejka +10%: 225 min (bez czekania). | N17: =TEXT('Czas budowy'!Y74,"0")&" min bazowo; T="&TEXT('Czas budowy'!V74,"0")&" min; budowa="&TEXT('Czas budowy'!X74,"0")&" min. Kolejka +10%: "&TEXT('Czas budowy'!Y75,"0")&" min (bez czekania)." -> 350 min bazowo; T=70 min; budowa=280 min. Kolejka +10%: 375 min (bez czekania). | O17: =TEXT('Czas budowy'!Y76,"0")&" min bazowo; T="&TEXT('Czas budowy'!V76,"0")&" min; budowa="&TEXT('Czas budowy'!X76,"0")&" min. Kolejka +10%: "&TEXT('Czas budowy'!Y77,"0")&" min (bez czekania)." -> 450 min bazowo; T=90 min; budowa=360 min. Kolejka +10%: 500 min (bez czekania).
A18: CZŁOWIEK — ASSET | B18: Je, pracuje, produkuje/nosi, płaci podatki; własna historia szczęścia. | C18: 12 na starcie w domu; min. 6, max. 24 × Ratusz; jedno zatrudnienie, limit 12 × własny poziom budynku. | D18: Nie ulepsza się osoby poziomem; zmieniają się warunki życia i pracy. | E18: Utrzymanie: 1 Food/os./h; kupowania ludzi nie ustalono. | F18: Demografia zależy od średniego H, liczona zegarowo także offline. | G18: Karta Czlowiek zaktualizowana. | H18: Odejście, nigdy śmierć; nowy mieszkaniec zawsze w domu. | I18: +1 za jedzenie, +1 za pracę; po 12 h braku danego warunku −5; oba braki −10/h. Przeludnienie i osobne kary pełnego bufora. Podatki 1/h; wizyty po zdefiniowaniu. | J18: Brak oferty sprzedaży osób. | K18: Odejścia:najpierwDom,potemnajwiększazałoga;remisywgpriorytetów;patrzCzlowiek. | L18: Czlowiek/Ustalenia/Populacja; potwierdzeniaoffline. | M18: Nie dotyczy. | N18: Nie dotyczy. | O18: Nie dotyczy.

Sheet Czlowiek
A1: CZŁOWIEK • zaktualizowany asset
A2: Wersja 2: własny limit budynku 12×L, 5 min do pracy i 5 min do domu, cała gospodarka offline; nowi ludzie do Domu, ubytek to odejście. Latarnia ustawia 100%, nie dodaje 100. Tematy wizyt i zablokowanej produkcji oznaczone tam, gdzie brakuje szczegółów.
A5: Stan / obszar | B5: Zasada | C5: Wzór / liczby | D5: Konsekwencje | E5: Status
A6: Rola assetu | B6: Każda osoba ma trwałe ID, własne szczęście, stan pracy/pobytu i niezależne liczniki głodu oraz bezrobocia. | C6: 12 na starcie; minimum 6; maksimum 24 × poziom ratusza. | D6: Nowe osoby trafiają do domu. Ubytek oznacza odejście, nie śmierć. | E6: UZGODNIONE; NOWE DOPRECYZOWANIA
A7: Start i dom | B7: Na starcie wszyscy ludzie są w domu, bez przypisania do gospodarki. Z domu widać ich przydziały; można kierować do kaplicy i latarni. | C7: 12 w domu, 0 pracowników we wszystkich budynkach; każdy zasób na starcie 100. | D7: Przed pierwszym przydziałem nie ma produkcji ani podatków, ale ludzie jedzą. | E7: UZGODNIONE / NOWE
A8: Limit miejsca pracy | B8: Limit zależy od poziomu konkretnego miejsca pracy, nie samego ratusza. Jedna wspólna pula wolnych ludzi. | C8: 0…12 × poziom budynku; nowy przydział ograniczony faktycznie wolnymi osobami w domu. | D8: Ratusz 2 i drwale 1: limit drwali nadal 12. Drwale 2: limit 24, jeżeli tylu wolnych istnieje. Nie wolno ulepszyć ponad ratusz. | E8: ZMIENIONE I WYJAŚNIONE
A9: Jedzenie | B9: Każdy je automatycznie wyłącznie z magazynu centralnego, niezależnie od pracy lub drogi. | C9: 1 Food/os./h zegarowej. | D9: Lokalny młyn, targ i port nie karmią bez przewiezienia do centrali. Rezerwę można zjadać. | E9: UZGODNIONE; CZAS ZEGAROWY
A10: Rezerwa jedzenia | B10: Rezerwa na żywienie rośnie z poziomem magazynu. Operacje nieżywieniowe mają ją zachować. | C10: Minimum Food = 50 × poziom magazynu. | D10: Osobny wpis mówi o tragarzu żywności dopiero poniżej 50; próg 50 kontra 50 × poziom pozostaje do ujednolicenia. | E10: NOWE; PRÓG TRAGARZA DO DECYZJI
A11: Praca producenta | B11: Wydajność na osobę wynika z własnego poziomu producenta. | C11: Poziomy 1,2,3,4: dokładnie 10,12,13,14 szt./h; dalej +1 szt./h na poziom. | D11: Wybrany dosłowny ciąg zastępuje sprzeczny ogólny zapis +10%. Głód ×0,5, premia latarni ×2. | E11: POTWIERDZONE W ODPOWIEDZI
A12: Całe sztuki | B12: Każdy pracownik nalicza własny postęp; niedokończone części różnych osób nie łączą się. Zwolnienie odrzuca jego niedokończoną sztukę. | C12: Na poziomie 1: jedna sztuka/6 min; po 7 min 1, po 13 min 2. Na wyższych poziomach odstęp = 3600 / wydajność sekund. | D12: Gotowy produkt zostaje w lokalnym buforze i wymaga transportu. | E12: UZGODNIONE; DOSTOSOWANE DO WYDAJNOŚCI
A13: Przeróbka | B13: Młyn i tartak zużywają surowce centralne; zboże i drewno idą przez magazyn. | C13: 2 zboża → 1 Food; 2 drewna → 1 deska. | D13: Brak surowca lub miejsca zatrzymuje pracę. Nowy wpis nakazuje karę za brak pracy także mimo przypisania; szczegóły podatku do decyzji. | E13: UZGODNIONE + NOWY PRZESTÓJ
A14: Transport | B14: Tragarz wiezie jeden rodzaj towaru, nie czeka na pełne obłożenie. Pojemność to ładunek na kurs, nie sztuki na godzinę. | C14: Poziom 1: 60 szt./kurs; pełny kurs z powrotem 5 min; pojemność rośnie o 10% na poziom miejsca pracy. | D14: 100 jednego towaru wymaga dwóch kursów: 60 i 40. Magazyn, targ i port stosują takie same bazowe zasady; własne załogi. | E14: POTWIERDZONE; ZAOKRĄGLENIE POJEMNOŚCI DO DECYZJI
A15: Podatek przy pracy | B15: Pracujący płaci podatek, bezrobotny lub idący do domu nie płaci. Premia kaplicy podwaja dochód. | C15: 1 moneta/os./h zegarowej; podczas premii kaplicy 2. | D15: Dla osoby przypisanej, ale zablokowanej brakiem surowca lub miejsca, nowe zasady wymagają kary za brak pracy; dalsze naliczanie podatku nie zostało rozstrzygnięte. | E15: UZGODNIONE; PODATEK PODCZAS PRZESTOJU DO DECYZJI
A16: Je i pracuje | B16: Sumują się bonus jedzenia i bonus pracy. | C16: +1 pp/h za jedzenie +1 pp/h za pracę = +2 pp/h. | D16: Od osobistego 0% po 10 h takiego stanu ma 20%. | E16: UZGODNIONE
... A37: Ranking | B37: Ranking w ustawieniach według poziomu i posiadanych monet. | C37: Wynik = poziom ratusza × ilość złota. | D37: Moment aktualizacji i remisy nie zostały doprecyzowane. Wydanie monet może obniżyć wynik. | E37: NOWE

Sheet Premium
A1: PREMIUM V3 • ceny i warunki
A2: 1 PLN = 10 monet. Nowe stawki zastępują brak cennika z wersji 2. Kalkulatory rozdzielają uzgodnione ceny od roboczych interpretacji. Nie dodano sprzedaży ani płatności do gry.
A5: Akcja | B5: Zasada | C5: Wzór / stawka | D5: Uwagi | E5: Status
A6: Przelicznik płatności | B6: 1 PLN = 10 monet. | C6: Cena w PLN = cena w monetach / 10. | D6: Ustalono przelicznik; nie zdefiniowano wypłaty monet na PLN. | E6: POTWIERDZONE
A7: Waluta | B7: Monety służą do Premium; użytkownik używa także nazwy złoto. | C7: W gospodarce istnieją już monety z podatków i portu. | D7: Nie określono, czy złoto, monety zarobione i monety kupione to ta sama pula. Kalkulator roboczo pokazuje jedną monetę, bez nowego tokena. | E7: DO DOPRECYZOWANIA
A8: Przyspieszenie 25% | B8: Skrócenie o 25% pozostałego czasu budowy. | C8: Cena = pełne minuty zaoszczędzonego czasu × 1 moneta. | D8: Roboczo FLOOR(pozostałe sekundy × 0,25 / 60). Wybranie pozostałego czasu zamiast czasu początkowego jest interpretacją. | E8: STAWKA POTWIERDZONA; PODSTAWA DO DOPRECYZOWANIA
A9: Przyspieszenie 50% | B9: Skrócenie o 50% pozostałego czasu budowy. | C9: Cena = FLOOR(pozostałe sekundy × 0,50 / 60) monet. | D9: Należy wyświetlać czas skrócenia i cenę przed zatwierdzeniem. | E9: STAWKA POTWIERDZONA; WZÓR MODELOWY
A10: Przyspieszenie 75% | B10: Skrócenie o 75% pozostałego czasu budowy. | C10: Cena = FLOOR(pozostałe sekundy × 0,75 / 60) monet. | D10: Nie ustalono limitu kolejnych przyspieszeń ani minimalnej ceny. | E10: STAWKA POTWIERDZONA; WZÓR MODELOWY
A11: Budowa natychmiast z zasobami | B11: Dotychczasowa oferta została zachowana; nowy cennik podaje tylko skrócenia 25%, 50%, 75%. | C11: Cena skrócenia 100% nie została potwierdzona. | D11: Nie oznaczać automatycznie ceny 100% jako ustalonej. Nie wiadomo także, czy można przyspieszać transport i budowanie łącznie. | E11: DO DOPRECYZOWANIA
A12: Transport całego bufora producenta | B12: Natychmiastowe wysłanie całego gotowego lokalnego zapasu do centrali. | C12: 10 monet × liczba kursów potrzebnych do przewozu. | D12: Proponowane kursy = CEILING(ilość / ładunek). Ostatni niepełny kurs kosztuje tyle samo, zgodnie z zasadą 60 + 40 dla 100 sztuk. Słowo „pełnych” wymaga potwierdzenia. | E12: STAWKA POTWIERDZONA; NIEPEŁNY KURS DO DOPRECYZOWANIA
A13: Magazyn → budowa | B13: Natychmiastowy przewóz materiałów centralnych na konkretną budowę. | C13: 10 monet × SUMA CEILING(ilość każdego materiału / ładunek). | D13: Każdy materiał liczy się osobno. Monety nie wymagają transportu. Nie ustalono, czy jedno kliknięcie obejmuje wszystkie brakujące materiały. | E13: POTWIERDZONE; ZAKRES KLIKNIĘCIA DO DOPRECYZOWANIA
A14: Magazyn ↔ targ | B14: Takie samo rozliczenie transportu towarów w obu kierunkach. | C14: 10 monet za potrzebny kurs właściwej załogi, osobno dla każdego materiału. | D14: Premium nie tworzy towaru ani wolnej pojemności. Wpływ na blokadę 1 h i termin wygaśnięcia 24 h nadal nieustalony. | E14: STAWKA POTWIERDZONA
A15: Magazyn ↔ port | B15: Takie samo rozliczenie transportu towarów w obu kierunkach. | C15: 10 monet za potrzebny kurs właściwej załogi, osobno dla każdego materiału. | D15: Nie ustalono, czy opłata obejmuje również osobny etap port ↔ statek. Zachować rozróżnienie dwóch etapów portowych. | E15: STAWKA POTWIERDZONA; ETAP STATKU DO DOPRECYZOWANIA
A16: Kup budynek bez surowców | B16: Cena materiałów według zakupu w porcie × 1,25, powiększona o opłatę za skrócenie czasu. | C16: Cena = 1,25 × portowa wartość wymaganych materiałów + opłata czasowa. | D16: Do wyboru: materiały pełnego kosztu czy tylko brakujące; cena bazowa czy bieżąca po podwyżkach; proporcjonalna wartość czy pełne paczki 100. | E16: ZASADA POTWIERDZONA; WYCENA DO DOPRECYZOWANIA
... A27: Premia za zwiedzanie | B27: Zwiedzanie daje bonus/premię; odrębne od nazwy błogosławieństwa kaplicy. | C27: Cena, czas i limity nieustalone. | D27: Nie określono płatnej oferty ani warunków wejścia. Nie zakładać automatycznie globalnego bonusu rozbudowy za pojedynczą wizytę. | E27: NIEUSTALONE; NIE DOPISANO CENY

Sheet Premium - czas
A1: PRZYSPIESZENIA • kalkulator ceny
A2: Model: procent od POZOSTAŁEJ FAZY BUDOWANIA, bez transportu; opłata za pełne zaoszczędzone minuty, zaokrąglenie w dół. Te interpretacje i ewentualna cena minimalna nie są jeszcze rozstrzygnięte. Niebieskie pola są edytowalne.
A5: Pozostała budowa [min] | B5: Skrócenie | C5: Zaoszczędzony czas [min] | D5: Pozostało [min] | E5: Cena [monety] | F5: Cena zakupu monet [PLN] | G5: Uwagi
A6: 1.5 | B6: 0.25 | C6: =A6*B6 -> 0.375 | D6: =A6-C6 -> 1.125 | E6: =ROUNDDOWN(C6,0)*Parametry!$C$42 -> 0 | F6: =E6/Parametry!$C$41 -> 0 | G6: Jeśli cena wynosi 0, obliczenie ujawnia lukę przy niepełnej minucie. Brak zatwierdzonej minimalnej ceny; przykład nie ustanawia darmowych skróceń jako gotowej oferty.
A7: 1.5 | B7: 0.5 | C7: =A7*B7 -> 0.75 | D7: =A7-C7 -> 0.75 | E7: =ROUNDDOWN(C7,0)*Parametry!$C$42 -> 0 | F7: =E7/Parametry!$C$41 -> 0 | G7: Jeśli cena wynosi 0, obliczenie ujawnia lukę przy niepełnej minucie. Brak zatwierdzonej minimalnej ceny; przykład nie ustanawia darmowych skróceń jako gotowej oferty.
A8: 1.5 | B8: 0.75 | C8: =A8*B8 -> 1.125 | D8: =A8-C8 -> 0.375 | E8: =ROUNDDOWN(C8,0)*Parametry!$C$42 -> 1 | F8: =E8/Parametry!$C$41 -> 0.1 | G8: Jeśli cena wynosi 0, obliczenie ujawnia lukę przy niepełnej minucie. Brak zatwierdzonej minimalnej ceny; przykład nie ustanawia darmowych skróceń jako gotowej oferty.
A9: 10 | B9: 0.25 | C9: =A9*B9 -> 2.5 | D9: =A9-C9 -> 7.5 | E9: =ROUNDDOWN(C9,0)*Parametry!$C$42 -> 2 | F9: =E9/Parametry!$C$41 -> 0.2 | G9: Jeśli cena wynosi 0, obliczenie ujawnia lukę przy niepełnej minucie. Brak zatwierdzonej minimalnej ceny; przykład nie ustanawia darmowych skróceń jako gotowej oferty.
A10: 10 | B10: 0.5 | C10: =A10*B10 -> 5 | D10: =A10-C10 -> 5 | E10: =ROUNDDOWN(C10,0)*Parametry!$C$42 -> 5 | F10: =E10/Parametry!$C$41 -> 0.5 | G10: Jeśli cena wynosi 0, obliczenie ujawnia lukę przy niepełnej minucie. Brak zatwierdzonej minimalnej ceny; przykład nie ustanawia darmowych skróceń jako gotowej oferty.
A11: 10 | B11: 0.75 | C11: =A11*B11 -> 7.5 | D11: =A11-C11 -> 2.5 | E11: =ROUNDDOWN(C11,0)*Parametry!$C$42 -> 7 | F11: =E11/Parametry!$C$41 -> 0.7 | G11: Jeśli cena wynosi 0, obliczenie ujawnia lukę przy niepełnej minucie. Brak zatwierdzonej minimalnej ceny; przykład nie ustanawia darmowych skróceń jako gotowej oferty.
A12: 25 | B12: 0.25 | C12: =A12*B12 -> 6.25 | D12: =A12-C12 -> 18.75 | E12: =ROUNDDOWN(C12,0)*Parametry!$C$42 -> 6 | F12: =E12/Parametry!$C$41 -> 0.6 | G12: Jeśli cena wynosi 0, obliczenie ujawnia lukę przy niepełnej minucie. Brak zatwierdzonej minimalnej ceny; przykład nie ustanawia darmowych skróceń jako gotowej oferty.
A13: 25 | B13: 0.5 | C13: =A13*B13 -> 12.5 | D13: =A13-C13 -> 12.5 | E13: =ROUNDDOWN(C13,0)*Parametry!$C$42 -> 12 | F13: =E13/Parametry!$C$41 -> 1.2 | G13: Jeśli cena wynosi 0, obliczenie ujawnia lukę przy niepełnej minucie. Brak zatwierdzonej minimalnej ceny; przykład nie ustanawia darmowych skróceń jako gotowej oferty.
A14: 25 | B14: 0.75 | C14: =A14*B14 -> 18.75 | D14: =A14-C14 -> 6.25 | E14: =ROUNDDOWN(C14,0)*Parametry!$C$42 -> 18 | F14: =E14/Parametry!$C$41 -> 1.8 | G14: Jeśli cena wynosi 0, obliczenie ujawnia lukę przy niepełnej minucie. Brak zatwierdzonej minimalnej ceny; przykład nie ustanawia darmowych skróceń jako gotowej oferty.
A15: 60 | B15: 0.25 | C15: =A15*B15 -> 15 | D15: =A15-C15 -> 45 | E15: =ROUNDDOWN(C15,0)*Parametry!$C$42 -> 15 | F15: =E15/Parametry!$C$41 -> 1.5 | G15: Jeśli cena wynosi 0, obliczenie ujawnia lukę przy niepełnej minucie. Brak zatwierdzonej minimalnej ceny; przykład nie ustanawia darmowych skróceń jako gotowej oferty.
A16: 60 | B16: 0.5 | C16: =A16*B16 -> 30 | D16: =A16-C16 -> 30 | E16: =ROUNDDOWN(C16,0)*Parametry!$C$42 -> 30 | F16: =E16/Parametry!$C$41 -> 3 | G16: Jeśli cena wynosi 0, obliczenie ujawnia lukę przy niepełnej minucie. Brak zatwierdzonej minimalnej ceny; przykład nie ustanawia darmowych skróceń jako gotowej oferty.
A17: 60 | B17: 0.75 | C17: =A17*B17 -> 45 | D17: =A17-C17 -> 15 | E17: =ROUNDDOWN(C17,0)*Parametry!$C$42 -> 45 | F17: =E17/Parametry!$C$41 -> 4.5 | G17: Jeśli cena wynosi 0, obliczenie ujawnia lukę przy niepełnej minucie. Brak zatwierdzonej minimalnej ceny; przykład nie ustanawia darmowych skróceń jako gotowej oferty.
... A20: 120 | B20: 0.75 | C20: =A20*B20 -> 90 | D20: =A20-C20 -> 30 | E20: =ROUNDDOWN(C20,0)*Parametry!$C$42 -> 90 | F20: =E20/Parametry!$C$41 -> 9 | G20: Jeśli cena wynosi 0, obliczenie ujawnia lukę przy niepełnej minucie. Brak zatwierdzonej minimalnej ceny; przykład nie ustanawia darmowych skróceń jako gotowej oferty.

Sheet Premium - transport
A1: TRANSPORT PREMIUM • kursy i cena
A2: Model: ostatni niepełny kurs także kosztuje, SUMA(ROUNDUP(ilość rodzaju / ładunek)) × liczba odcinków × 10. Dwa rodzaje nie mogą dzielić kursu. Liczba pracowników zmienia czas, a nie liczbę płatnych kursów. Odpowiedź o niepełnym kursie jest oczekiwana.
A5: Trasa / przykład | B5: Towar A [szt.] | C5: Towar B [szt.] | D5: Ładunek/kurs | E5: Liczba odcinków | F5: Kursy A | G5: Kursy B | H5: Kursy razem | I5: Monety | J5: Cena zakupu monet [PLN] | K5: Uwagi
A6: Produkcja → magazyn: 40 | B6: 40 | C6: 0 | D6: 60 | E6: 1 | F6: =ROUNDUP(B6/D6,0) -> 1 | G6: =ROUNDUP(C6/D6,0) -> 0 | H6: =(F6+G6)*E6 -> 1 | I6: =H6*Parametry!$C$43 -> 10 | J6: =I6/Parametry!$C$41 -> 1 | K6: Cena zależy od potrzebnych kursów. Przykład 2 odcinków nie przesądza zakresu jednego kliknięcia portowego; doprecyzować załadunek i rozładunek.
A7: Produkcja → magazyn: 60 | B7: 60 | C7: 0 | D7: 60 | E7: 1 | F7: =ROUNDUP(B7/D7,0) -> 1 | G7: =ROUNDUP(C7/D7,0) -> 0 | H7: =(F7+G7)*E7 -> 1 | I7: =H7*Parametry!$C$43 -> 10 | J7: =I7/Parametry!$C$41 -> 1 | K7: Cena zależy od potrzebnych kursów. Przykład 2 odcinków nie przesądza zakresu jednego kliknięcia portowego; doprecyzować załadunek i rozładunek.
A8: Produkcja → magazyn: 100 | B8: 100 | C8: 0 | D8: 60 | E8: 1 | F8: =ROUNDUP(B8/D8,0) -> 2 | G8: =ROUNDUP(C8/D8,0) -> 0 | H8: =(F8+G8)*E8 -> 2 | I8: =H8*Parametry!$C$43 -> 20 | J8: =I8/Parametry!$C$41 -> 2 | K8: Cena zależy od potrzebnych kursów. Przykład 2 odcinków nie przesądza zakresu jednego kliknięcia portowego; doprecyzować załadunek i rozładunek.
A9: Magazyn → budowa: 180 | B9: 180 | C9: 0 | D9: 60 | E9: 1 | F9: =ROUNDUP(B9/D9,0) -> 3 | G9: =ROUNDUP(C9/D9,0) -> 0 | H9: =(F9+G9)*E9 -> 3 | I9: =H9*Parametry!$C$43 -> 30 | J9: =I9/Parametry!$C$41 -> 3 | K9: Cena zależy od potrzebnych kursów. Przykład 2 odcinków nie przesądza zakresu jednego kliknięcia portowego; doprecyzować załadunek i rozładunek.
A10: Magazyn → budowa: 181 | B10: 181 | C10: 0 | D10: 60 | E10: 1 | F10: =ROUNDUP(B10/D10,0) -> 4 | G10: =ROUNDUP(C10/D10,0) -> 0 | H10: =(F10+G10)*E10 -> 4 | I10: =H10*Parametry!$C$43 -> 40 | J10: =I10/Parametry!$C$41 -> 4 | K10: Cena zależy od potrzebnych kursów. Przykład 2 odcinków nie przesądza zakresu jednego kliknięcia portowego; doprecyzować załadunek i rozładunek.
A11: Dwa rodzaje po 100 | B11: 100 | C11: 100 | D11: 60 | E11: 1 | F11: =ROUNDUP(B11/D11,0) -> 2 | G11: =ROUNDUP(C11/D11,0) -> 2 | H11: =(F11+G11)*E11 -> 4 | I11: =H11*Parametry!$C$43 -> 40 | J11: =I11/Parametry!$C$41 -> 4 | K11: Cena zależy od potrzebnych kursów. Przykład 2 odcinków nie przesądza zakresu jednego kliknięcia portowego; doprecyzować załadunek i rozładunek.
A12: Magazyn → targ | B12: 200 | C12: 0 | D12: 60 | E12: 1 | F12: =ROUNDUP(B12/D12,0) -> 4 | G12: =ROUNDUP(C12/D12,0) -> 0 | H12: =(F12+G12)*E12 -> 4 | I12: =H12*Parametry!$C$43 -> 40 | J12: =I12/Parametry!$C$41 -> 4 | K12: Cena zależy od potrzebnych kursów. Przykład 2 odcinków nie przesądza zakresu jednego kliknięcia portowego; doprecyzować załadunek i rozładunek.
A13: Targ → magazyn | B13: 200 | C13: 0 | D13: 60 | E13: 1 | F13: =ROUNDUP(B13/D13,0) -> 4 | G13: =ROUNDUP(C13/D13,0) -> 0 | H13: =(F13+G13)*E13 -> 4 | I13: =H13*Parametry!$C$43 -> 40 | J13: =I13/Parametry!$C$41 -> 4 | K13: Cena zależy od potrzebnych kursów. Przykład 2 odcinków nie przesądza zakresu jednego kliknięcia portowego; doprecyzować załadunek i rozładunek.
A14: Magazyn → port | B14: 200 | C14: 0 | D14: 60 | E14: 1 | F14: =ROUNDUP(B14/D14,0) -> 4 | G14: =ROUNDUP(C14/D14,0) -> 0 | H14: =(F14+G14)*E14 -> 4 | I14: =H14*Parametry!$C$43 -> 40 | J14: =I14/Parametry!$C$41 -> 4 | K14: Cena zależy od potrzebnych kursów. Przykład 2 odcinków nie przesądza zakresu jednego kliknięcia portowego; doprecyzować załadunek i rozładunek.
A15: Port → magazyn | B15: 200 | C15: 0 | D15: 60 | E15: 1 | F15: =ROUNDUP(B15/D15,0) -> 4 | G15: =ROUNDUP(C15/D15,0) -> 0 | H15: =(F15+G15)*E15 -> 4 | I15: =H15*Parametry!$C$43 -> 40 | J15: =I15/Parametry!$C$41 -> 4 | K15: Cena zależy od potrzebnych kursów. Przykład 2 odcinków nie przesądza zakresu jednego kliknięcia portowego; doprecyzować załadunek i rozładunek.
A16: Dwa odcinki portowe — model | B16: 100 | C16: 0 | D16: 60 | E16: 2 | F16: =ROUNDUP(B16/D16,0) -> 2 | G16: =ROUNDUP(C16/D16,0) -> 0 | H16: =(F16+G16)*E16 -> 4 | I16: =H16*Parametry!$C$43 -> 40 | J16: =I16/Parametry!$C$41 -> 4 | K16: Cena zależy od potrzebnych kursów. Przykład 2 odcinków nie przesądza zakresu jednego kliknięcia portowego; doprecyzować załadunek i rozładunek.
A17: Ładunek wyższego poziomu | B17: 200 | C17: 0 | D17: 66 | E17: 1 | F17: =ROUNDUP(B17/D17,0) -> 4 | G17: =ROUNDUP(C17/D17,0) -> 0 | H17: =(F17+G17)*E17 -> 4 | I17: =H17*Parametry!$C$43 -> 40 | J17: =I17/Parametry!$C$41 -> 4 | K17: Cena zależy od potrzebnych kursów. Przykład 2 odcinków nie przesądza zakresu jednego kliknięcia portowego; doprecyzować załadunek i rozładunek.
A18: Brak towaru | B18: 0 | C18: 0 | D18: 60 | E18: 1 | F18: =ROUNDUP(B18/D18,0) -> 0 | G18: =ROUNDUP(C18/D18,0) -> 0 | H18: =(F18+G18)*E18 -> 0 | I18: =H18*Parametry!$C$43 -> 0 | J18: =I18/Parametry!$C$41 -> 0 | K18: Cena zależy od potrzebnych kursów. Przykład 2 odcinków nie przesądza zakresu jednego kliknięcia portowego; doprecyzować załadunek i rozładunek.

Sheet Premium - budynek
A1: BUDYNEK BEZ ZASOBÓW • porównanie wyceny
A2: DWA WARIANTY DO DECYZJI: cena bazowa zakupu w porcie, bez podwyżek z okna 3 h. Model dodaje nominalny koszt monet osobno, +25% tylko do materiałów, wybrane przyspieszenie czasu osobno; końcową cenę zaokrągla w górę. Pytanie o te zasady jest oczekiwane.
A5: Przykład | B5: Monety w koszcie | C5: Drewno | D5: Kamień | E5: Zboże | F5: Food | G5: Deski | H5: Port: proporcje | I5: Port: pełne paczki 100 | J5: Materiały ×1,25 | K5: Pozostała budowa [min] | L5: Skrócenie | M5: Cena czasu | N5: Razem proporcjonalnie | O5: Razem paczki 100 | P5: PLN: proporcje | Q5: Uwagi
A6: 100 drewna +100 Food | B6: 0 | C6: 100 | D6: 0 | E6: 0 | F6: 100 | G6: 0 | H6: =(C6+D6+E6)*Parametry!$C$32/100+(F6+G6)*Parametry!$C$34/100 -> 200 | I6: =(ROUNDUP(C6/100,0)+ROUNDUP(D6/100,0)+ROUNDUP(E6/100,0))*Parametry!$C$32+(ROUNDUP(F6/100,0)+ROUNDUP(G6/100,0))*Parametry!$C$34 -> 200 | J6: =H6*Parametry!$C$44 -> 250 | K6: 120 | L6: 0.5 | M6: =ROUNDDOWN(K6*L6,0)*Parametry!$C$42 -> 60 | N6: =ROUNDUP(B6+J6+M6,0) -> 310 | O6: =ROUNDUP(B6+I6*Parametry!$C$44+M6,0) -> 310 | P6: =N6/Parametry!$C$41 -> 31 | Q6: Porównanie modeli, nie zatwierdzony cennik końcowy. Brakujące czy wszystkie materiały, wpływ kolejki +10%, podwyżki portu i los resztek paczek pozostają do ustalenia.
A7: Farma 1→2 | B7: 0 | C7: 72 | D7: 72 | E7: 120 | F7: 0 | G7: 0 | H7: =(C7+D7+E7)*Parametry!$C$32/100+(F7+G7)*Parametry!$C$34/100 -> 132 | I7: =(ROUNDUP(C7/100,0)+ROUNDUP(D7/100,0)+ROUNDUP(E7/100,0))*Parametry!$C$32+(ROUNDUP(F7/100,0)+ROUNDUP(G7/100,0))*Parametry!$C$34 -> 200 | J7: =H7*Parametry!$C$44 -> 165 | K7: ='Czas budowy'!X18 -> 5 | L7: 0.5 | M7: =ROUNDDOWN(K7*L7,0)*Parametry!$C$42 -> 2 | N7: =ROUNDUP(B7+J7+M7,0) -> 167 | O7: =ROUNDUP(B7+I7*Parametry!$C$44+M7,0) -> 252 | P7: =N7/Parametry!$C$41 -> 16.7 | Q7: Farma 1→2: faza budowy 5 min z bazowej estymaty przy 6 dostępnych tragarzach. Koszt czasu przy skróceniu 50% = 2 monety za pełne 2 min z 2,5 min. Cena materiałów i zaokrąglenia to nadal modele do decyzji.
A8: Ratusz 1→2 | B8: 500 | C8: 500 | D8: 500 | E8: 500 | F8: 500 | G8: 500 | H8: =(C8+D8+E8)*Parametry!$C$32/100+(F8+G8)*Parametry!$C$34/100 -> 2250 | I8: =(ROUNDUP(C8/100,0)+ROUNDUP(D8/100,0)+ROUNDUP(E8/100,0))*Parametry!$C$32+(ROUNDUP(F8/100,0)+ROUNDUP(G8/100,0))*Parametry!$C$34 -> 2250 | J8: =H8*Parametry!$C$44 -> 2812.5 | K8: ='Czas budowy'!X6 -> 40 | L8: 0.5 | M8: =ROUNDDOWN(K8*L8,0)*Parametry!$C$42 -> 20 | N8: =ROUNDUP(B8+J8+M8,0) -> 3333 | O8: =ROUNDUP(B8+I8*Parametry!$C$44+M8,0) -> 3333 | P8: =N8/Parametry!$C$41 -> 333.3 | Q8: Porównanie modeli, nie zatwierdzony cennik końcowy. Brakujące czy wszystkie materiały, wpływ kolejki +10%, podwyżki portu i los resztek paczek pozostają do ustalenia.

Sheet Social i polecenia
A1: NAGRODY SPOŁECZNOŚCIOWE • kwoty i warunki
A2: Kwoty zapisane według użytkownika. Limity, potwierdzanie publikacji i nakładanie nagród nie są zdefiniowane. Przeliczenie na PLN pokazuje cenę zakupu takiej liczby monet, nie możliwość ich wypłaty. Platformy mają osobną zakładkę.
A5: Akcja | B5: Nagroda | C5: Warunek | D5: Otwarte szczegóły | E5: Wartość zakupu monet [PLN]
A6: Pochwalenie się, że gram | B6: 1000 | C6: Publikacja informująca o grze. | D6: Nie ustalono kanałów, limitu na konto, powtórzeń ani sposobu potwierdzania publikacji. | E6: =B6/Parametry!$C$41 -> 100
A7: Informacja o następnym poziomie | B7: 500 | C7: Publikacja po rzeczywistym osiągnięciu kolejnego poziomu ratusza. | D7: Jedna nagroda na osiągnięty poziom jest propozycją; zasady wielu platform i usuwania postów są nieustalone. | E7: =B7/Parametry!$C$41 -> 50
A8: Polecenie: nowe logowanie | B8: 1000 | C8: Polecona osoba rzeczywiście się zaloguje. | D8: Nie określono, czy nagrodę dostaje tylko polecający czy także polecony; źródłowo roboczo zapisano nagrodę polecającego. Kryterium nowego konta i limit poleceń nieustalone. | E8: =B8/Parametry!$C$41 -> 100
A9: Polecenie: trzeci aktywny dzień | B9: 500 każdego zasobu | C9: Polecona osoba jest aktywna w trzecim dniu. | D9: Do ustalenia: trzeci dzień od rejestracji czy trzy dni aktywności, minimalna aktywność, odbiorca premii, czy „każdy zasób” obejmuje monety oraz jak przyjąć materiały przy pełnej centrali. | E9: Zależne od zakresu „wszystkiego”
A10: Każdy trzeci post na Facebooku | B10: 1000 | C10: Nagroda za trzeci, szósty, dziewiąty itd. kwalifikowany post. | D10: Nie określono okresu, limitu, wymagań treści ani tego, czy posty „gram” i „kolejny poziom” liczą się do tej samej serii. Zgodność konkretnej akcji z regulaminem platformy wymaga weryfikacji. | E10: =B10/Parametry!$C$41 -> 100

Sheet Platformy
A1: PLATFORMY • kandydaci do publikacji graczy
A2: Lista serwisów podobnych lub uzupełniających Facebooka. Nie potwierdzono aktualnego brzmienia ich zasad: dostęp do próbowanych oficjalnych źródeł blokowało HTTP 403. Adresy służą do późniejszej weryfikacji programu nagród, nie stanowią potwierdzenia jego dopuszczalności.
A5: Platforma | B5: Pasujący format | C5: Zastosowanie | D5: Istotna zasada / kwestia do sprawdzenia | E5: Oficjalne adresy | F5: Status źródła | G5: Uwagi o nagrodach
A6: Facebook | B6: Post, informacja o poziomie, polecenie z linkiem. | C6: Nie dopisujemy automatycznych masowych publikacji ani publikacji do cudzych grup. | D6: Reguły promocji Facebooka znane z dotychczasowej dokumentacji ograniczają użycie prywatnych osi czasu i znajomych do udziału w promocjach, np. „udostępnij, aby dostać nagrodę”. Wymaga sprawdzenia aktualnych warunków przed wdrożeniem nagrody za post. | E6: https://www.facebook.com/policies_center/pages_groups_events | F6: Aktualne warunki niepotwierdzone online. Dostęp do próbowanych źródeł blokowało HTTP 403; nie wszystkie adresy odpytywano oddzielnie. | G6: Kwoty 1000 / 500 / 1000 za każdy 3. post są propozycją ekonomii gry; wykonalność programu promocyjnego nie została potwierdzona.
A7: Instagram | B7: Grafika wyspy, post, relacja lub krótki film Reels. | C7: Kandydat do ręcznego udostępnienia przez gracza. | D7: Sprawdzić wytyczne promocji, prawidłowe oznaczanie i zasady przeciw sztucznemu pozyskiwaniu aktywności. Nie zakładać, że polubienia lub obserwacje mogą być obowiązkowym warunkiem. | E7: https://help.instagram.com/179379842258600 | F7: Aktualne warunki niepotwierdzone online. Dostęp do próbowanych źródeł blokowało HTTP 403; nie wszystkie adresy odpytywano oddzielnie. | G7: Nagrody dla tej platformy i sposób weryfikacji do ustalenia.
A8: Threads | B8: Krótki wpis i zrzut wyspy; link polecający. | C8: Kandydat do dobrowolnej publikacji. | D8: Obowiązują zasady Meta przeciw spamowi; sprawdzić aktualną możliwość i zasady nagradzania publikacji. | E8: https://transparency.meta.com/policies/community-standards/spam/ | F8: Aktualne warunki niepotwierdzone online. Dostęp do próbowanych źródeł blokowało HTTP 403; nie wszystkie adresy odpytywano oddzielnie. | G8: Nagrody nie zostały automatycznie skopiowane z Facebooka.
A9: TikTok | B9: Krótki film z wyspą, budową albo ekspedycją. | C9: Kandydat do treści tworzonych przez graczy. | D9: Wytyczne integralności i autentyczności obejmują sztuczną aktywność. Zasady nagradzanych filmów oraz oznaczania zachęt wymagają weryfikacji. | E9: https://www.tiktok.com/community-guidelines/en/integrity-authenticity/ | F9: Aktualne warunki niepotwierdzone online. Dostęp do próbowanych źródeł blokowało HTTP 403; nie wszystkie adresy odpytywano oddzielnie. | G9: Nie uzależniać nagrody od liczby sztucznych wyświetleń, komentarzy czy obserwujących.
A10: YouTube / Shorts | B10: Krótki film lub dłuższy pokaz gry. | C10: Kandydat do materiałów graczy. | D10: YouTube ma odrębne zasady fake engagement oraz konkursów. Wynagradzanie za manipulowanie wyświetleniami, polubieniami lub innymi wskaźnikami jest ryzykowne; sprawdzić aktualne warunki konkretnego programu. | E10: https://support.google.com/youtube/answer/3399767?hl=en https://support.google.com/youtube/answer/1620498?hl=en | F10: Aktualne warunki niepotwierdzone online. Dostęp do próbowanych źródeł blokowało HTTP 403; nie wszystkie adresy odpytywano oddzielnie. | G10: Treść i dobrowolne polecenie odróżnić od kupowania aktywności.
A11: Discord | B11: Własny serwer gry i kanał do pokazywania wysp. | C11: Dobry kandydat do społeczności gry. | D11: Zasady Discorda zabraniają spamu i manipulowania platformą. Publikacja tylko w przeznaczonych do tego kanałach oraz zgodnie z zasadami konkretnego serwera. | E11: https://discord.com/guidelines | F11: Aktualne warunki niepotwierdzone online. Dostęp do próbowanych źródeł blokowało HTTP 403; nie wszystkie adresy odpytywano oddzielnie. | G11: Bez masowych wiadomości prywatnych lub botów rozsyłających polecenia.
A12: Reddit | B12: Wpisy o postępach gry, grafice i dziennik rozwoju. | C12: Kandydat warunkowy: właściwy subreddit i zgoda moderatorów. | D12: Reddit i poszczególne subreddity mają zasady dotyczące spamu, autopromocji oraz manipulacji głosami. Nagroda za powielane wpisy promocyjne wymaga szczególnej weryfikacji. | E12: https://support.reddithelp.com/hc/en-us/articles/360043504051-Spam | F12: Aktualne warunki niepotwierdzone online. Dostęp do próbowanych źródeł blokowało HTTP 403; nie wszystkie adresy odpytywano oddzielnie. | G12: Nie zakładać prawa do reklamowania gry w dowolnej społeczności.
A13: X | B13: Krótki post, obraz wyspy i link polecający. | C13: Kandydat do dobrowolnego udostępniania. | D13: Sprawdzić zasady promocji i manipulacji platformą; powtarzane identyczne wpisy oraz zduplikowane konta nie powinny generować nagród. | E13: https://help.x.com/en/rules-and-policies/platform-manipulation https://help.x.com/en/rules-and-policies/x-contest-rules | F13: Aktualne warunki niepotwierdzone online. Dostęp do próbowanych źródeł blokowało HTTP 403; nie wszystkie adresy odpytywano oddzielnie. | G13: Próg i ewentualny limit nagrody do ustalenia.
A14: Bluesky | B14: Post z obrazem wyspy i linkiem. | C14: Kandydat do dobrowolnego udostępniania. | D14: Wytyczne społeczności obejmują spam i zakłócanie działania. Sprawdzić zasady promocji przed uruchomieniem programu nagród. | E14: https://bsky.social/about/support/community-guidelines | F14: Aktualne warunki niepotwierdzone online. Dostęp do próbowanych źródeł blokowało HTTP 403; nie wszystkie adresy odpytywano oddzielnie. | G14: Nie zakładać automatycznej weryfikacji publikacji bez osobnego projektu.
A15: Mastodon | B15: Post z wyspą na wybranym serwerze. | C15: Kandydat warunkowy: reguły wybranego serwera. | D15: Mastodon jest siecią wielu serwerów. Zasady reklamy, promocji i spamu zależą od instancji; nie ma jednego zezwolenia obejmującego całą sieć. | E15: https://joinmastodon.org/ https://joinmastodon.org/covenant | F15: Aktualne warunki niepotwierdzone online. Dostęp do próbowanych źródeł blokowało HTTP 403; nie wszystkie adresy odpytywano oddzielnie. | G15: Nagrody i dopuszczalne serwery do ustalenia.
A16: Snapchat | B16: Dobrowolna relacja lub krótki film o grze. | C16: Kandydat do wizualnej prezentacji postępu. | D16: Sprawdzić wytyczne społeczności, zasady promocji i treści sponsorowanych; nie zakładać, że masowe rozsyłanie zaproszeń będzie dozwolone. | E16: https://values.snap.com/policy/policy-community-guidelines | F16: Aktualne warunki niepotwierdzone online. Dostęp do próbowanych źródeł blokowało HTTP 403; nie wszystkie adresy odpytywano oddzielnie. | G16: Kwoty oraz sposób weryfikacji relacji do ustalenia.

Sheet Zadania latarni
A1: LATARNIA • zasady zadań
A2: Zadania to dostawy dla latarni, odrębne od rozbudowy i zwiedzania. Zachowano Twoje reguły, a brakujące szczegóły wyraźnie oznaczono. W przykładach losowanie jest zamrożone; ponowne otwarcie pliku nie zmienia nagród ani kosztów.
A5: Obszar | B5: Status | C5: Zasada | D5: Wzór / liczby | E5: Uwagi
A6: Panel | B6: UZGODNIONE | C6: W prawym górnym rogu wyświetlamy trzy aktualne zadania latarni: małe, średnie i duże. | D6: 3 miejsca, po jednym na rozmiar | E6: Nagrody są widoczne zawsze, przed rozpoczęciem i wpłatami.
A7: Losowanie | B7: UZGODNIONE | C7: Koszty, wymagane produkty i nagrody losujemy przy pojawieniu się zadania. | D7: Małe: 2 produkty; średnie: 2–3; duże: 4 | E7: W przykładach losujemy różne rodzaje spośród drewna, kamienia, zboża, żywności i desek. Rodzaje nagród i koszty powinny być stałe przez życie zadania.
A8: Norma produkcyjna | B8: MODEL DO POTWIERDZENIA | C8: Koszt rodzaju i liczymy z maksymalnej obsady obecnego poziomu jego producenta, niezależnie od faktycznej obsady. | D8: R_i = 12 × L_i × p(L_i); p(1)=10, p(L≥2)=L+10; koszt_i = R_i × h | E8: Nie doliczamy bonusu latarni ×2 ani głodu: to trwała norma poziomu, nie chwilowa wydajność. Użytkownik nie wskazał wprost, czy brać własny poziom producenta, czy najwyższy wspólny poziom; wymaga zatwierdzenia.
A9: Małe | B9: UZGODNIONE | C9: Wymagane są dwa produkty, w ilości odpowiadającej 2–6 h maksymalnej produkcji. | D9: 2 rodzaje; h∈[2,6] | E9: L1: 12 osób × 10 szt./h = 120 szt./h, więc 240–720 każdego rodzaju.
A10: Średnie | B10: UZGODNIONE | C10: Wymagane są dwa lub trzy produkty, w ilości odpowiadającej 3–8 h maksymalnej produkcji, nie mniej niż bieżące małe. | D10: 2–3 rodzaje; h∈[3,8] | E10: Sposób porównania z małym nie jest zdefiniowany; przykład używa h_średnie ≥ h_małe oraz nie mniejszej sumy godzin znormalizowanych.
A11: Duże | B11: UZGODNIONE | C11: Wymagane są cztery produkty, w ilości odpowiadającej 4–10 h maksymalnej produkcji, nie mniej niż bieżące średnie. | D11: 4 rodzaje; h∈[4,10] | E11: W przykładzie h_duże ≥ h_średnie. Duże może wymagać więcej niż 6 h produkcji mimo terminu 6 h: zakłada wcześniejsze zapasy lub jest trudno osiągalne od zera.
A12: Ramy losowania | B12: MODEL PRZYKŁADU | C12: W przykładach jedna liczba pełnych godzin h obowiązuje wszystkie wymagane rodzaje danego zadania. | D12: h_małe ≤ h_średnie ≤ h_duże; H = Σ(koszt_i/R_i) | E12: Jest to czytelna interpretacja „nie mniejsze”, a nie dodatkowa zatwierdzona reguła. Użytkownik nie określił, czy godziny mają być całkowite ani wspólne dla wszystkich składników.
A13: Nagroda w monetach | B13: UZGODNIONE / DOLNY PRÓG CZĘŚCIOWO MODELOWY | C13: Małe losuje 100–200 monet; średnie do 400; duże do 600. | D13: Przykłady: 100–200, 100–400 i 100–600 monet | E13: Dolny próg 100 dla średniego i dużego jest interpretacją; użytkownik podał dla nich tylko górną granicę.
A14: Nagroda towarowa | B14: UZGODNIONE / LICZBA RODZAJÓW OTWARTA | C14: Każde zadanie daje także losowy towar lub towary w ilości 50–1000. | D14: Przykłady: 1 losowy rodzaj, 50–1000 szt. | E14: Do decyzji: liczba rodzajów nagród; limit na każdy rodzaj czy łącznie; obsługa braku miejsca w magazynie.
A15: Premia szybkiej reakcji | B15: UZGODNIONE | C15: Kliknięcie zadania w pierwszych 15 sekundach daje nagrodę ×3; później do 5 minut daje ×2; następnie ×1. | D15: Przykład granic: wiek <15 s → ×3; 15 s ≤ wiek <300 s → ×2; od 300 s → ×1 | E15: ×3 nie mnoży się ponownie przez ×2. Dokładne granice 15 s i 5 min oraz znaczenie kliknięcia wymagają ustalenia.
A16: Utrwalenie premii | B16: MODEL DO POTWIERDZENIA | C16: Przykład zakłada, że pierwsze świadome przyjęcie zadania utrwala mnożnik aż do ukończenia. | D16: Nagroda końcowa = bazowa nagroda × utrwalony mnożnik | E16: Samo otwarcie panelu, pierwsza wpłata czy ukończenie w oknie bonusowym to różne możliwe warianty. Nie przesądzamy ich jako ustalenia.
... A26: Produkcja maksymalna a realny czas | B26: OSTRZEŻENIE BALANSU | C26: Pełna załoga 12 × L w każdym z 2–4 zakładów nie może być założona jednocześnie przy jednej wspólnej populacji. | D26: L1: 12 osób na start, maks. 24; duże: 4 zakłady × 12 = 48 stanowisk | E26: Norma ma określać koszt zadania. Nie jest estymatą możliwego zebrania całości w 2–10 h; dodatkowo młyn i tartak zużywają po 2 surowce na produkt.

Sheet Zadania przyklady
A1: LATARNIA • 12 wylosowanych przykładów
A2: 4 zestawy dla poziomów 1–4, seed 20261022. Jedna norma h na rodzaj; w zestawie h małe ≤ h średnie ≤ h duże. Przykłady mają 1 rodzaj nagrody towarowej; 100 to modelowy dolny próg monet średniego/dużego. To wariant generatora do decyzji, nie wdrożona funkcja.
A5: Zestaw | B5: Rozmiar | C5: Nazwa / narracja | D5: Poziom producentów | E5: Maks. ludzi/producent | F5: Szt./os./h | G5: Maks. szt./h | H5: Norma godzin/rodzaj | I5: Liczba rodzajów | J5: Drewno | K5: Kamień | L5: Zboże | M5: Food | N5: Deski | O5: Wpłaty: format | P5: Złoto bazowe | Q5: Towar nagrody | R5: Ilość bazowa | S5: Złoto ×2 | T5: Złoto ×3 | U5: Towar ×2 | V5: Towar ×3 | W5: Termin [h] | X5: Uwagi
A6: 1 | B6: Małe | C6: Naprawa poręczy na schodach | D6: 1 | E6: =D6*12 -> 12 | F6: =IF(D6=1,10,D6+10) -> 10 | G6: =E6*F6 -> 120 | H6: 4 | I6: 2 | J6: =G6*H6 -> 480 | K6: =G6*H6 -> 480 | L6: 0 | M6: 0 | N6: 0 | O6: 0/480 drewno; 0/480 kamień | P6: 130 | Q6: kamień | R6: 52 | S6: =P6*2 -> 260 | T6: =P6*3 -> 390 | U6: =R6*2 -> 104 | V6: =R6*3 -> 156 | W6: =Parametry!$C$45 -> 6 | X6: Materiały służą remontowi i zabezpieczeniu obiektu, a żywność lub zboże — zaopatrzeniu ekipy latarników. Dobór rodzaju jest przykładowy i losowy. Mnożnik obejmuje monety i towary; limit 1000 dotyczy nagrody bazowej w tym modelu.
A7: 1 | B7: Średnie | C7: Remont barierek dla zwiedzających | D7: 1 | E7: =D7*12 -> 12 | F7: =IF(D7=1,10,D7+10) -> 10 | G7: =E7*F7 -> 120 | H7: 8 | I7: 2 | J7: 0 | K7: =G7*H7 -> 960 | L7: 0 | M7: 0 | N7: =G7*H7 -> 960 | O7: 0/960 deski; 0/960 kamień | P7: 201 | Q7: drewno | R7: 248 | S7: =P7*2 -> 402 | T7: =P7*3 -> 603 | U7: =R7*2 -> 496 | V7: =R7*3 -> 744 | W7: =Parametry!$C$45 -> 6 | X7: Materiały służą remontowi i zabezpieczeniu obiektu, a żywność lub zboże — zaopatrzeniu ekipy latarników. Dobór rodzaju jest przykładowy i losowy. Mnożnik obejmuje monety i towary; limit 1000 dotyczy nagrody bazowej w tym modelu.
A8: 1 | B8: Duże | C8: Generalny remont galerii widokowej | D8: 1 | E8: =D8*12 -> 12 | F8: =IF(D8=1,10,D8+10) -> 10 | G8: =E8*F8 -> 120 | H8: 9 | I8: 4 | J8: =G8*H8 -> 1080 | K8: 0 | L8: =G8*H8 -> 1080 | M8: =G8*H8 -> 1080 | N8: =G8*H8 -> 1080 | O8: 0/1080 zboże; 0/1080 drewno; 0/1080 deski; 0/1080 żywność | P8: 360 | Q8: kamień | R8: 168 | S8: =P8*2 -> 720 | T8: =P8*3 -> 1080 | U8: =R8*2 -> 336 | V8: =R8*3 -> 504 | W8: =Parametry!$C$45 -> 6 | X8: Materiały służą remontowi i zabezpieczeniu obiektu, a żywność lub zboże — zaopatrzeniu ekipy latarników. Dobór rodzaju jest przykładowy i losowy. Mnożnik obejmuje monety i towary; limit 1000 dotyczy nagrody bazowej w tym modelu.
A9: 2 | B9: Małe | C9: Łatanie podestu wejściowego | D9: 2 | E9: =D9*12 -> 24 | F9: =IF(D9=1,10,D9+10) -> 12 | G9: =E9*F9 -> 288 | H9: 3 | I9: 2 | J9: =G9*H9 -> 864 | K9: 0 | L9: 0 | M9: 0 | N9: =G9*H9 -> 864 | O9: 0/864 deski; 0/864 drewno | P9: 118 | Q9: zboże | R9: 648 | S9: =P9*2 -> 236 | T9: =P9*3 -> 354 | U9: =R9*2 -> 1296 | V9: =R9*3 -> 1944 | W9: =Parametry!$C$45 -> 6 | X9: Materiały służą remontowi i zabezpieczeniu obiektu, a żywność lub zboże — zaopatrzeniu ekipy latarników. Dobór rodzaju jest przykładowy i losowy. Mnożnik obejmuje monety i towary; limit 1000 dotyczy nagrody bazowej w tym modelu.
A10: 2 | B10: Średnie | C10: Wymiana osłon lampy | D10: 2 | E10: =D10*12 -> 24 | F10: =IF(D10=1,10,D10+10) -> 12 | G10: =E10*F10 -> 288 | H10: 7 | I10: 2 | J10: 0 | K10: 0 | L10: =G10*H10 -> 2016 | M10: =G10*H10 -> 2016 | N10: 0 | O10: 0/2016 zboże; 0/2016 żywność | P10: 131 | Q10: drewno | R10: 903 | S10: =P10*2 -> 262 | T10: =P10*3 -> 393 | U10: =R10*2 -> 1806 | V10: =R10*3 -> 2709 | W10: =Parametry!$C$45 -> 6 | X10: Materiały służą remontowi i zabezpieczeniu obiektu, a żywność lub zboże — zaopatrzeniu ekipy latarników. Dobór rodzaju jest przykładowy i losowy. Mnożnik obejmuje monety i towary; limit 1000 dotyczy nagrody bazowej w tym modelu.
A11: 2 | B11: Duże | C11: Odbudowa zaplecza latarników | D11: 2 | E11: =D11*12 -> 24 | F11: =IF(D11=1,10,D11+10) -> 12 | G11: =E11*F11 -> 288 | H11: 10 | I11: 4 | J11: =G11*H11 -> 2880 | K11: =G11*H11 -> 2880 | L11: 0 | M11: =G11*H11 -> 2880 | N11: =G11*H11 -> 2880 | O11: 0/2880 kamień; 0/2880 deski; 0/2880 żywność; 0/2880 drewno | P11: 388 | Q11: drewno | R11: 279 | S11: =P11*2 -> 776 | T11: =P11*3 -> 1164 | U11: =R11*2 -> 558 | V11: =R11*3 -> 837 | W11: =Parametry!$C$45 -> 6 | X11: Materiały służą remontowi i zabezpieczeniu obiektu, a żywność lub zboże — zaopatrzeniu ekipy latarników. Dobór rodzaju jest przykładowy i losowy. Mnożnik obejmuje monety i towary; limit 1000 dotyczy nagrody bazowej w tym modelu.
A12: 3 | B12: Małe | C12: Zabezpieczenie ścieżki do latarni | D12: 3 | E12: =D12*12 -> 36 | F12: =IF(D12=1,10,D12+10) -> 13 | G12: =E12*F12 -> 468 | H12: 6 | I12: 2 | J12: 0 | K12: =G12*H12 -> 2808 | L12: 0 | M12: =G12*H12 -> 2808 | N12: 0 | O12: 0/2808 kamień; 0/2808 żywność | P12: 197 | Q12: deski | R12: 476 | S12: =P12*2 -> 394 | T12: =P12*3 -> 591 | U12: =R12*2 -> 952 | V12: =R12*3 -> 1428 | W12: =Parametry!$C$45 -> 6 | X12: Materiały służą remontowi i zabezpieczeniu obiektu, a żywność lub zboże — zaopatrzeniu ekipy latarników. Dobór rodzaju jest przykładowy i losowy. Mnożnik obejmuje monety i towary; limit 1000 dotyczy nagrody bazowej w tym modelu.
A13: 3 | B13: Średnie | C13: Naprawa schodów na galerię | D13: 3 | E13: =D13*12 -> 36 | F13: =IF(D13=1,10,D13+10) -> 13 | G13: =E13*F13 -> 468 | H13: 8 | I13: 2 | J13: =G13*H13 -> 3744 | K13: 0 | L13: 0 | M13: =G13*H13 -> 3744 | N13: 0 | O13: 0/3744 drewno; 0/3744 żywność | P13: 123 | Q13: żywność | R13: 179 | S13: =P13*2 -> 246 | T13: =P13*3 -> 369 | U13: =R13*2 -> 358 | V13: =R13*3 -> 537 | W13: =Parametry!$C$45 -> 6 | X13: Materiały służą remontowi i zabezpieczeniu obiektu, a żywność lub zboże — zaopatrzeniu ekipy latarników. Dobór rodzaju jest przykładowy i losowy. Mnożnik obejmuje monety i towary; limit 1000 dotyczy nagrody bazowej w tym modelu.
A14: 3 | B14: Duże | C14: Renowacja wieży po sztormie | D14: 3 | E14: =D14*12 -> 36 | F14: =IF(D14=1,10,D14+10) -> 13 | G14: =E14*F14 -> 468 | H14: 9 | I14: 4 | J14: =G14*H14 -> 4212 | K14: =G14*H14 -> 4212 | L14: =G14*H14 -> 4212 | M14: =G14*H14 -> 4212 | N14: 0 | O14: 0/4212 żywność; 0/4212 kamień; 0/4212 drewno; 0/4212 zboże | P14: 149 | Q14: zboże | R14: 354 | S14: =P14*2 -> 298 | T14: =P14*3 -> 447 | U14: =R14*2 -> 708 | V14: =R14*3 -> 1062 | W14: =Parametry!$C$45 -> 6 | X14: Materiały służą remontowi i zabezpieczeniu obiektu, a żywność lub zboże — zaopatrzeniu ekipy latarników. Dobór rodzaju jest przykładowy i losowy. Mnożnik obejmuje monety i towary; limit 1000 dotyczy nagrody bazowej w tym modelu.
A15: 4 | B15: Małe | C15: Zaopatrzenie ekipy przeglądowej | D15: 4 | E15: =D15*12 -> 48 | F15: =IF(D15=1,10,D15+10) -> 14 | G15: =E15*F15 -> 672 | H15: 6 | I15: 2 | J15: =G15*H15 -> 4032 | K15: 0 | L15: 0 | M15: =G15*H15 -> 4032 | N15: 0 | O15: 0/4032 drewno; 0/4032 żywność | P15: 172 | Q15: kamień | R15: 548 | S15: =P15*2 -> 344 | T15: =P15*3 -> 516 | U15: =R15*2 -> 1096 | V15: =R15*3 -> 1644 | W15: =Parametry!$C$45 -> 6 | X15: Materiały służą remontowi i zabezpieczeniu obiektu, a żywność lub zboże — zaopatrzeniu ekipy latarników. Dobór rodzaju jest przykładowy i losowy. Mnożnik obejmuje monety i towary; limit 1000 dotyczy nagrody bazowej w tym modelu.
A16: 4 | B16: Średnie | C16: Odtworzenie pomostu widokowego | D16: 4 | E16: =D16*12 -> 48 | F16: =IF(D16=1,10,D16+10) -> 14 | G16: =E16*F16 -> 672 | H16: 6 | I16: 2 | J16: =G16*H16 -> 4032 | K16: 0 | L16: 0 | M16: =G16*H16 -> 4032 | N16: 0 | O16: 0/4032 żywność; 0/4032 drewno | P16: 130 | Q16: deski | R16: 424 | S16: =P16*2 -> 260 | T16: =P16*3 -> 390 | U16: =R16*2 -> 848 | V16: =R16*3 -> 1272 | W16: =Parametry!$C$45 -> 6 | X16: Materiały służą remontowi i zabezpieczeniu obiektu, a żywność lub zboże — zaopatrzeniu ekipy latarników. Dobór rodzaju jest przykładowy i losowy. Mnożnik obejmuje monety i towary; limit 1000 dotyczy nagrody bazowej w tym modelu.
A17: 4 | B17: Duże | C17: Przygotowanie latarni do sezonu | D17: 4 | E17: =D17*12 -> 48 | F17: =IF(D17=1,10,D17+10) -> 14 | G17: =E17*F17 -> 672 | H17: 6 | I17: 4 | J17: =G17*H17 -> 4032 | K17: =G17*H17 -> 4032 | L17: 0 | M17: =G17*H17 -> 4032 | N17: =G17*H17 -> 4032 | O17: 0/4032 drewno; 0/4032 żywność; 0/4032 deski; 0/4032 kamień | P17: 221 | Q17: drewno | R17: 956 | S17: =P17*2 -> 442 | T17: =P17*3 -> 663 | U17: =R17*2 -> 1912 | V17: =R17*3 -> 2868 | W17: =Parametry!$C$45 -> 6 | X17: Materiały służą remontowi i zabezpieczeniu obiektu, a żywność lub zboże — zaopatrzeniu ekipy latarników. Dobór rodzaju jest przykładowy i losowy. Mnożnik obejmuje monety i towary; limit 1000 dotyczy nagrody bazowej w tym modelu.

Sheet Zadania - zegary
A1: LATARNIA • niezależne zegary i raty
A2: To przykłady kalkulacji, nie działający licznik. Model: pierwsze kliknięcie utrwala mnożnik, a pełna wpłata przed upływem 6 h daje nagrodę. Wybrane granice: <15 s ×3; 15–<300 s ×2; od 300 s ×1. Sposób utrwalenia czeka na odpowiedź.
A5: Przykład | B5: Wiek zadania [s] | C5: Pozostało [min] | D5: Mnożnik po kliknięciu | E5: Wymagane | F5: Wpłacono | G5: Brakuje | H5: Następna rata | I5: Stan po racie | J5: Zwrot po terminie | K5: Uwagi
A6: Małe — szybkie przyjęcie | B6: 10 | C6: =MAX(0,(Parametry!$C$45*3600-B6)/60) -> 359.83333 | D6: =IF(B6<15,3,IF(B6<300,2,1)) -> 3 | E6: 200 | F6: 100 | G6: =MAX(0,E6-F6) -> 100 | H6: 50 | I6: =IF(C6>0,MIN(E6,F6+H6),0) -> 150 | J6: 0 | K6: Rata pobierana z centrali bez transportu; po terminie wpłaty przepadają. Zerowy stan po przedawnieniu oznacza utratę wpłat, nie wypłatę graczowi.
A7: Średnie — szybkie przyjęcie | B7: 120 | C7: =MAX(0,(Parametry!$C$45*3600-B7)/60) -> 358 | D7: =IF(B7<15,3,IF(B7<300,2,1)) -> 2 | E7: 400 | F7: 100 | G7: =MAX(0,E7-F7) -> 300 | H7: 300 | I7: =IF(C7>0,MIN(E7,F7+H7),0) -> 400 | J7: 0 | K7: Rata pobierana z centrali bez transportu; po terminie wpłaty przepadają. Zerowy stan po przedawnieniu oznacza utratę wpłat, nie wypłatę graczowi.
A8: Duże — zwykłe przyjęcie | B8: 1800 | C8: =MAX(0,(Parametry!$C$45*3600-B8)/60) -> 330 | D8: =IF(B8<15,3,IF(B8<300,2,1)) -> 1 | E8: 1200 | F8: 600 | G8: =MAX(0,E8-F8) -> 600 | H8: 100 | I8: =IF(C8>0,MIN(E8,F8+H8),0) -> 700 | J8: 0 | K8: Rata pobierana z centrali bez transportu; po terminie wpłaty przepadają. Zerowy stan po przedawnieniu oznacza utratę wpłat, nie wypłatę graczowi.
A9: Granica 15 sekund | B9: 15 | C9: =MAX(0,(Parametry!$C$45*3600-B9)/60) -> 359.75 | D9: =IF(B9<15,3,IF(B9<300,2,1)) -> 2 | E9: 200 | F9: 0 | G9: =MAX(0,E9-F9) -> 200 | H9: 0 | I9: =IF(C9>0,MIN(E9,F9+H9),0) -> 0 | J9: 0 | K9: Rata pobierana z centrali bez transportu; po terminie wpłaty przepadają. Zerowy stan po przedawnieniu oznacza utratę wpłat, nie wypłatę graczowi.
A10: Granica 5 minut | B10: 300 | C10: =MAX(0,(Parametry!$C$45*3600-B10)/60) -> 355 | D10: =IF(B10<15,3,IF(B10<300,2,1)) -> 1 | E10: 200 | F10: 0 | G10: =MAX(0,E10-F10) -> 200 | H10: 0 | I10: =IF(C10>0,MIN(E10,F10+H10),0) -> 0 | J10: 0 | K10: Rata pobierana z centrali bez transportu; po terminie wpłaty przepadają. Zerowy stan po przedawnieniu oznacza utratę wpłat, nie wypłatę graczowi.
A11: Zadanie przedawnione | B11: 21600 | C11: =MAX(0,(Parametry!$C$45*3600-B11)/60) -> 0 | D11: =IF(B11<15,3,IF(B11<300,2,1)) -> 1 | E11: 200 | F11: 100 | G11: =MAX(0,E11-F11) -> 100 | H11: 0 | I11: =IF(C11>0,MIN(E11,F11+H11),0) -> 0 | J11: 0 | K11: Rata pobierana z centrali bez transportu; po terminie wpłaty przepadają. Zerowy stan po przedawnieniu oznacza utratę wpłat, nie wypłatę graczowi.

Sheet Ekspedycje
A1: EKSPEDYCJE • przebieg i nagrody
A2: Panel poniżej zadań po prawej. Nagrody wyłącznie w monetach. Plansze, sterowanie, trudność, koszty dodatkowego czasu/ruchów i zasady jednosekundowego kodu pozostają do późniejszego opisania.
A5: Obszar | B5: Zasada | C5: Uwagi | D5: Status
A6: Umiejscowienie | B6: Po prawej stronie, pod bieżącymi zadaniami latarni. | C6: Zawsze dostępnych kilka ekspedycji. Konkretna liczba i rotacja nieustalone. | D6: POTWIERDZONE; LICZBA OTWARTA
A7: Rodzaje gry | B7: Plansza z labiryntem i piłeczką do przeprowadzenia do środka albo dobieranie takich samych puzzli. | C7: Dokładne sterowanie, plansze i zasady użytkownik opisze później. | D7: POTWIERDZONE; SZCZEGÓŁY PÓŹNIEJ
A8: Nagroda | B8: Wyłącznie złoto / monety. | C8: Ekspedycja nie przyznaje materiałów ani szczęścia. Nazwa waluty do ujednolicenia. | D8: POTWIERDZONE
A9: Pierwszy wygrany poziom | B9: 50 monet w nieodebranej puli. | C9: Można wypłacić pulę na wyspę albo postawić ją na dalszą grę. | D9: POTWIERDZONE
A10: Każda kolejna wygrana | B10: Podwaja całą dotychczasową pulę. | C10: Poziom n: 50 × 2^(n−1) monet. To nowa łączna pula, nie dodatkowa nagroda dodawana do poprzedniej. | D10: POTWIERDZONE
A11: Wypłata | B11: Przeniesienie aktualnej puli do gry na wyspie. | C11: Po wypłacie ekspedycja powinna zamknąć serię; to logiczna propozycja, nie zatwierdzony osobny szczegół. Nie określono restartów i opłaty wejściowej. | D11: WYBÓR WYPŁATY POTWIERDZONY
A12: Przegrana | B12: Utrata całej niewypłaconej puli danej serii. | C12: Nie ma podstaw do odbierania istniejących wcześniej monet z wyspy. Płatności za dodatkowe ruchy/czas nie są nagrodą i zasady ich zwrotu nie zostały określone. | D12: POTWIERDZONE; WYDATKI DO DOPRECYZOWANIA
A13: Ograniczenie poziomu | B13: Limit czasu albo liczby ruchów. | C13: Ilości i trudność poszczególnych poziomów nieustalone. Zatrzymywanie podczas reklam i po zamknięciu karty wymaga osobnej reguły. | D13: POTWIERDZONE; LIMITY OTWARTE
A14: Dodatkowy czas lub ruchy | B14: Zakup monetami albo obejrzenie reklamy. | C14: Nie ustalono ceny, przyrostu czasu/ruchów, liczby zakupów, momentu zakupu ani czy można uratować już przegraną próbę. | D14: POTWIERDZONE; CENNIK OTWARTY
A15: Reklama ekspedycji | B15: Najpierw materiał o własnej grze, później reklamy zewnętrzne; maksymalnie 30 sekund. | C15: To reguła reklam ekspedycyjnych. Wcześniejsze odłożone reklamy kaplicy miały 60 s; nie zastępować ich bez decyzji. | D15: POTWIERDZONE
A16: Jednosekundowy przekaz | B16: Reklama ma zawierać przez 1 sekundę przekaz do późniejszego wpisania. | C16: Przekaz pokazywany przez 1 sekundę; treść, miejsce wpisania, warunek uznania reklamy i ewentualna nagroda zostaną opisane później. | D16: POMYSŁ ZACHOWANY; DZIAŁANIE PÓŹNIEJ
A17: Brak limitu poziomów | B17: Obecny opis nie wyznacza końca serii. | C17: Podwajanie jest wykładnicze: poziom 10 = 25 600, poziom 20 = 26 214 400 monet. Limit, trudność i koszt ratowania mogą być potrzebne do balansu. | D17: UWAGA BALANSOWA, NIE NOWA REGUŁA

Sheet Ekspedycje - poziomy
A1: EKSPEDYCJE • podwajanie puli
A2: Pula = 50 × 2^(n−1). Każda wygrana podwaja aktualną pulę; nie dodajemy wszystkich poprzednich pul. Wypłata trafia na wyspę. Przegrana odbiera niewypłaconą pulę serii. Maksymalna liczba poziomów nie została ustalona.
A5: Wygrany poziom | B5: Pula do wypłaty [monety] | C5: Przyrost względem poprzedniego | D5: Po przegranej kolejnego | E5: Cena zakupu takiej liczby monet [PLN] | F5: Dodatkowy czas/ruchy | G5: Uwagi
A6: 1 | B6: =Parametry!$C$48*Parametry!$C$49^(A6-1) -> 50 | C6: =IF(A6=1,B6,B6/2) -> 50 | D6: 0 | E6: =B6/Parametry!$C$41 -> 5 | F6: Monety lub reklama ≤30 s; cena i ilość do ustalenia. | G6: Przeliczenie PLN opisuje cenę zakupu monet, nie wypłatę pieniędzy. Nagroda poziomu 20 pokazuje ryzyko wykładniczego wzrostu.
A7: 2 | B7: =Parametry!$C$48*Parametry!$C$49^(A7-1) -> 100 | C7: =IF(A7=1,B7,B7/2) -> 50 | D7: 0 | E7: =B7/Parametry!$C$41 -> 10 | F7: Monety lub reklama ≤30 s; cena i ilość do ustalenia. | G7: Przeliczenie PLN opisuje cenę zakupu monet, nie wypłatę pieniędzy. Nagroda poziomu 20 pokazuje ryzyko wykładniczego wzrostu.
A8: 3 | B8: =Parametry!$C$48*Parametry!$C$49^(A8-1) -> 200 | C8: =IF(A8=1,B8,B8/2) -> 100 | D8: 0 | E8: =B8/Parametry!$C$41 -> 20 | F8: Monety lub reklama ≤30 s; cena i ilość do ustalenia. | G8: Przeliczenie PLN opisuje cenę zakupu monet, nie wypłatę pieniędzy. Nagroda poziomu 20 pokazuje ryzyko wykładniczego wzrostu.
A9: 4 | B9: =Parametry!$C$48*Parametry!$C$49^(A9-1) -> 400 | C9: =IF(A9=1,B9,B9/2) -> 200 | D9: 0 | E9: =B9/Parametry!$C$41 -> 40 | F9: Monety lub reklama ≤30 s; cena i ilość do ustalenia. | G9: Przeliczenie PLN opisuje cenę zakupu monet, nie wypłatę pieniędzy. Nagroda poziomu 20 pokazuje ryzyko wykładniczego wzrostu.
A10: 5 | B10: =Parametry!$C$48*Parametry!$C$49^(A10-1) -> 800 | C10: =IF(A10=1,B10,B10/2) -> 400 | D10: 0 | E10: =B10/Parametry!$C$41 -> 80 | F10: Monety lub reklama ≤30 s; cena i ilość do ustalenia. | G10: Przeliczenie PLN opisuje cenę zakupu monet, nie wypłatę pieniędzy. Nagroda poziomu 20 pokazuje ryzyko wykładniczego wzrostu.
A11: 6 | B11: =Parametry!$C$48*Parametry!$C$49^(A11-1) -> 1600 | C11: =IF(A11=1,B11,B11/2) -> 800 | D11: 0 | E11: =B11/Parametry!$C$41 -> 160 | F11: Monety lub reklama ≤30 s; cena i ilość do ustalenia. | G11: Przeliczenie PLN opisuje cenę zakupu monet, nie wypłatę pieniędzy. Nagroda poziomu 20 pokazuje ryzyko wykładniczego wzrostu.
A12: 7 | B12: =Parametry!$C$48*Parametry!$C$49^(A12-1) -> 3200 | C12: =IF(A12=1,B12,B12/2) -> 1600 | D12: 0 | E12: =B12/Parametry!$C$41 -> 320 | F12: Monety lub reklama ≤30 s; cena i ilość do ustalenia. | G12: Przeliczenie PLN opisuje cenę zakupu monet, nie wypłatę pieniędzy. Nagroda poziomu 20 pokazuje ryzyko wykładniczego wzrostu.
A13: 8 | B13: =Parametry!$C$48*Parametry!$C$49^(A13-1) -> 6400 | C13: =IF(A13=1,B13,B13/2) -> 3200 | D13: 0 | E13: =B13/Parametry!$C$41 -> 640 | F13: Monety lub reklama ≤30 s; cena i ilość do ustalenia. | G13: Przeliczenie PLN opisuje cenę zakupu monet, nie wypłatę pieniędzy. Nagroda poziomu 20 pokazuje ryzyko wykładniczego wzrostu.
A14: 9 | B14: =Parametry!$C$48*Parametry!$C$49^(A14-1) -> 12800 | C14: =IF(A14=1,B14,B14/2) -> 6400 | D14: 0 | E14: =B14/Parametry!$C$41 -> 1280 | F14: Monety lub reklama ≤30 s; cena i ilość do ustalenia. | G14: Przeliczenie PLN opisuje cenę zakupu monet, nie wypłatę pieniędzy. Nagroda poziomu 20 pokazuje ryzyko wykładniczego wzrostu.
A15: 10 | B15: =Parametry!$C$48*Parametry!$C$49^(A15-1) -> 25600 | C15: =IF(A15=1,B15,B15/2) -> 12800 | D15: 0 | E15: =B15/Parametry!$C$41 -> 2560 | F15: Monety lub reklama ≤30 s; cena i ilość do ustalenia. | G15: Przeliczenie PLN opisuje cenę zakupu monet, nie wypłatę pieniędzy. Nagroda poziomu 20 pokazuje ryzyko wykładniczego wzrostu.
A16: 11 | B16: =Parametry!$C$48*Parametry!$C$49^(A16-1) -> 51200 | C16: =IF(A16=1,B16,B16/2) -> 25600 | D16: 0 | E16: =B16/Parametry!$C$41 -> 5120 | F16: Monety lub reklama ≤30 s; cena i ilość do ustalenia. | G16: Przeliczenie PLN opisuje cenę zakupu monet, nie wypłatę pieniędzy. Nagroda poziomu 20 pokazuje ryzyko wykładniczego wzrostu.
A17: 12 | B17: =Parametry!$C$48*Parametry!$C$49^(A17-1) -> 102400 | C17: =IF(A17=1,B17,B17/2) -> 51200 | D17: 0 | E17: =B17/Parametry!$C$41 -> 10240 | F17: Monety lub reklama ≤30 s; cena i ilość do ustalenia. | G17: Przeliczenie PLN opisuje cenę zakupu monet, nie wypłatę pieniędzy. Nagroda poziomu 20 pokazuje ryzyko wykładniczego wzrostu.
... A19: 20 | B19: =Parametry!$C$48*Parametry!$C$49^(A19-1) -> 26214400 | C19: =IF(A19=1,B19,B19/2) -> 13107200 | D19: 0 | E19: =B19/Parametry!$C$41 -> 2621440 | F19: Monety lub reklama ≤30 s; cena i ilość do ustalenia. | G19: Przeliczenie PLN opisuje cenę zakupu monet, nie wypłatę pieniędzy. Nagroda poziomu 20 pokazuje ryzyko wykładniczego wzrostu.

Sheet Bilans V3
A1: BILANS • miejsca wymagające decyzji
A2: Nie zmieniamy uzgodnionych wartości. Wskazujemy skutki, które mogą utrudnić grę albo generować nadmierne nagrody. Ukończenie zadania latarni wymaga zapasów i nie musi oznaczać zebrania wszystkiego od zera w jego 6 h.
A5: Temat | B5: Liczby / konsekwencje | C5: Status / uwaga
A6: Społecznościowe 1000 monet | B6: Przy 1 PLN = 10 monet nagroda odpowiada cenie zakupu 100 PLN. Przy 12 pracujących to 83 h 20 min podatków; nagrodę można wydać na 1000 min skrócenia budowy. | C6: To porównanie siły nabywczej, nie wypłata prawdziwych pieniędzy.
A7: Społecznościowe 500 monet | B7: Równowartość ceny zakupu 50 PLN; przy 12 pracujących: 41 h 40 min podatków. | C7: Do ustalenia częstotliwość i kumulacja.
A8: Transport a opłacalność | B8: 200 Food przy ładunku 60 to 4 kursy = 40 monet; bazowa wartość zakupu to 300 monet. Przewóz 200 drewna również kosztuje 40 monet, ale zakup tylko 100. | C8: Cena przewozu zależy od objętości, nie wartości produktu; to spójne z cennikiem użytkownika.
A9: Ekspedycja poziom 10 | B9: 25 600 monet; przy 12 pracujących: 2133 h 20 min podatków. | C9: Jeżeli seria powtarzalna i łatwa, nagrody mogą dominować nad ekonomią wyspy.
A10: Minimalna szansa dalszej wygranej | B10: Ryzykując pulę B o podwojenie, oczekiwana pula po próbie to 2pB. Arytmetyczny próg rentowności p = 50%, przed kosztami ratunku. | C10: To analiza balansu; nie zakładamy losowości ani stawki prawdopodobieństwa w zręcznościowej minigrze.
A11: Zadania latarni | B11: L1: małe: 6 h = 720 na rodzaj, nie 1440; 1440 to suma dwóch rodzajów. Duże: 10 h = 1200 na rodzaj > 1000 pojemności typu w magazynie L1; raty umożliwiają wykonanie bez jednoczesnego zapasu całego kosztu. | C11: UWAGA DO BALANSU
A12: Zadania latarni | B12: L2: małe: 6 h = 1728 na rodzaj > 1500 pojemności typu magazynu L2; wymagane raty nie są błędem, lecz muszą być czytelne. | C12: UWAGA DO BALANSU
A13: Zadania latarni | B13: Zadanie z normą 8–10 h może być niewykonalne od zera w 6 h. Jedna wspólna populacja, wejścia 2:1 i żywienie dodatkowo wydłużają realne zbieranie. | C13: UWAGA DO BALANSU
A14: Zadania latarni | B14: Losowe nagrody stałych zakresów nie muszą pokrywać wartości wpłat. To świadomy element balansu do oceny, nie błąd wzoru. | C14: UWAGA DO BALANSU
A15: Duże zadanie L1 od zera | B15: Minimum: 4 rodzaje × 4 h × 12 osób × 10/h = 1920 produktów. Przy 12 osobach to co najmniej 16 h sumarycznej pracy producentów, przed jedzeniem, zużyciem wejściowym 2:1 i transportem. Termin zadania wynosi 6 h. | C15: Zadanie jest celem na wcześniejsze zapasy lub wymaga oceny kosztów.
A16: Nagroda towarowa ×3 | B16: Bazowe 1000 ×3 = 3000 sztuk jednego towaru; magazyn poziomu 1 mieści 1000 każdego rodzaju i 4000 łącznie. | C16: Potrzebna reguła odbioru nadmiaru; nie kasujemy nagrody bez decyzji.
... A19: Serie publikacji | B19: Bez limitu powtarzania i definicji kwalifikowanego posta kwoty za każdy 3. post tworzą nieograniczony przychód. | C19: Zasady nagradzania oraz weryfikacja platform pozostają otwarte.

Sheet Produkcja
A1: PRODUKCJA I ŁADUNEK • korzyść własnego poziomu
A2: Użytkownik potwierdził dokładnie 10, 12, 13, 14… zamiast ogólnego +10%. Poziom producenta wpływa na wydajność i limit 12 × L; Ratusz jest warunkiem rozbudowy. Ładunek dotyczy własnego poziomu budynku transportowego; głód obniża efektywną wydajność transportu o połowę.
A5: Poziom budynku | B5: Wydajność/os./h | C5: Wydajność głodnego/os./h | D5: Limit załogi | E5: Ładunek magazyn/targ/port | F5: Uwagi
A6: 1 | B6: =IF(A6=1,10,A6+10) -> 10 | C6: =B6/2 -> 5 | D6: =A6*Parametry!$C$8 -> 12 | E6: =ROUNDDOWN(Parametry!$C$9*Parametry!$C$10^(A6-1),0) -> 60 | F6: Każda osoba osobno; całe sztuki i własna faza pracy. Młyn/tartak nadal 2:1. Bufor lokalny nadal 200×Ratusz.
A7: 2 | B7: =IF(A7=1,10,A7+10) -> 12 | C7: =B7/2 -> 6 | D7: =A7*Parametry!$C$8 -> 24 | E7: =ROUNDDOWN(Parametry!$C$9*Parametry!$C$10^(A7-1),0) -> 66 | F7: Każda osoba osobno; całe sztuki i własna faza pracy. Młyn/tartak nadal 2:1. Bufor lokalny nadal 200×Ratusz.
A8: 3 | B8: =IF(A8=1,10,A8+10) -> 13 | C8: =B8/2 -> 6.5 | D8: =A8*Parametry!$C$8 -> 36 | E8: =ROUNDDOWN(Parametry!$C$9*Parametry!$C$10^(A8-1),0) -> 72 | F8: Każda osoba osobno; całe sztuki i własna faza pracy. Młyn/tartak nadal 2:1. Bufor lokalny nadal 200×Ratusz.
A9: 4 | B9: =IF(A9=1,10,A9+10) -> 14 | C9: =B9/2 -> 7 | D9: =A9*Parametry!$C$8 -> 48 | E9: =ROUNDDOWN(Parametry!$C$9*Parametry!$C$10^(A9-1),0) -> 79 | F9: Każda osoba osobno; całe sztuki i własna faza pracy. Młyn/tartak nadal 2:1. Bufor lokalny nadal 200×Ratusz.
A10: 5 | B10: =IF(A10=1,10,A10+10) -> 15 | C10: =B10/2 -> 7.5 | D10: =A10*Parametry!$C$8 -> 60 | E10: =ROUNDDOWN(Parametry!$C$9*Parametry!$C$10^(A10-1),0) -> 87 | F10: Każda osoba osobno; całe sztuki i własna faza pracy. Młyn/tartak nadal 2:1. Bufor lokalny nadal 200×Ratusz.
A11: 6 | B11: =IF(A11=1,10,A11+10) -> 16 | C11: =B11/2 -> 8 | D11: =A11*Parametry!$C$8 -> 72 | E11: =ROUNDDOWN(Parametry!$C$9*Parametry!$C$10^(A11-1),0) -> 96 | F11: Każda osoba osobno; całe sztuki i własna faza pracy. Młyn/tartak nadal 2:1. Bufor lokalny nadal 200×Ratusz.
A12: 7 | B12: =IF(A12=1,10,A12+10) -> 17 | C12: =B12/2 -> 8.5 | D12: =A12*Parametry!$C$8 -> 84 | E12: =ROUNDDOWN(Parametry!$C$9*Parametry!$C$10^(A12-1),0) -> 106 | F12: Każda osoba osobno; całe sztuki i własna faza pracy. Młyn/tartak nadal 2:1. Bufor lokalny nadal 200×Ratusz.
A13: 8 | B13: =IF(A13=1,10,A13+10) -> 18 | C13: =B13/2 -> 9 | D13: =A13*Parametry!$C$8 -> 96 | E13: =ROUNDDOWN(Parametry!$C$9*Parametry!$C$10^(A13-1),0) -> 116 | F13: Każda osoba osobno; całe sztuki i własna faza pracy. Młyn/tartak nadal 2:1. Bufor lokalny nadal 200×Ratusz.
A14: 9 | B14: =IF(A14=1,10,A14+10) -> 19 | C14: =B14/2 -> 9.5 | D14: =A14*Parametry!$C$8 -> 108 | E14: =ROUNDDOWN(Parametry!$C$9*Parametry!$C$10^(A14-1),0) -> 128 | F14: Każda osoba osobno; całe sztuki i własna faza pracy. Młyn/tartak nadal 2:1. Bufor lokalny nadal 200×Ratusz.
A15: 10 | B15: =IF(A15=1,10,A15+10) -> 20 | C15: =B15/2 -> 10 | D15: =A15*Parametry!$C$8 -> 120 | E15: =ROUNDDOWN(Parametry!$C$9*Parametry!$C$10^(A15-1),0) -> 141 | F15: Każda osoba osobno; całe sztuki i własna faza pracy. Młyn/tartak nadal 2:1. Bufor lokalny nadal 200×Ratusz.

Sheet Czas budowy
A1: NOWE CZASY • liczymy kursy, nie sztuki na godzinę
A2: Potwierdzone:5 min cały kurs, 1 rodzaj na kurs; 6 tragarzy faktycznie dostępnych; materiały gotowe, bez zbierania, karmienia, wcześniejszych rozbudów i oczekiwania. Osobny wariant+10%kolejki zwiększa koszt i liczbę kursów. Pojemność bazowa 60, magazyn L→floor(60×1.1^(L−1)).
A5: Budynek | B5: Etap | C5: Tryb kosztu | D5: Obecny L | E5: Nowy N | F5: Poziom magazynu | G5: Dostępni tragarze | H5: Ładunek/os./kurs | I5: Monety | J5: Drewno | K5: Kamień | L5: Zboże | M5: Food | N5: Deski | O5: Kursy drewno | P5: Kursy kamień | Q5: Kursy zboże | R5: Kursy Food | S5: Kursy deski | T5: Kursy razem | U5: Fale | V5: Transport T [min] | W5: Łącznie ×T | X5: Sama budowa [min] | Y5: Razem [min] | Z5: Materiały razem | AA5: Założenia
A6: Ratusz | B6: 1→2 | C6: Bez kolejki | D6: 1 | E6: =D6+1 -> 2 | F6: 1 | G6: =Parametry!$C$12 -> 6 | H6: =ROUNDDOWN(Parametry!$C$9*Parametry!$C$10^(F6-1),0) -> 60 | I6: =ROUNDUP((Parametry!$C$20*MAX(1,D6))*1,0) -> 500 | J6: =ROUNDUP((Parametry!$C$20*MAX(1,D6))*1,0) -> 500 | K6: =ROUNDUP((Parametry!$C$20*MAX(1,D6))*1,0) -> 500 | L6: =ROUNDUP((Parametry!$C$20*MAX(1,D6))*1,0) -> 500 | M6: =ROUNDUP((Parametry!$C$20*MAX(1,D6))*1,0) -> 500 | N6: =ROUNDUP((Parametry!$C$20*MAX(1,D6))*1,0) -> 500 | O6: =ROUNDUP(J6/H6,0) -> 9 | P6: =ROUNDUP(K6/H6,0) -> 9 | Q6: =ROUNDUP(L6/H6,0) -> 9 | R6: =ROUNDUP(M6/H6,0) -> 9 | S6: =ROUNDUP(N6/H6,0) -> 9 | T6: =SUM(O6:S6) -> 45 | U6: =ROUNDUP(T6/G6,0) -> 8 | V6: =U6*Parametry!$C$11 -> 40 | W6: =2 -> 2 | X6: =V6*(W6-1) -> 40 | Y6: =V6*W6 -> 80 | Z6: =SUM(J6:N6) -> 2500 | AA6: Tylko ta budowa; 6 dostępnych po uwzględnieniu priorytetów; poziom magazynu=scenariusz L. Jeśli priorytety blokują dostawy, rzeczywiste ETA rośnie.
A7: Ratusz | B7: 1→2 | C7: Kolejka +10% | D7: 1 | E7: =D7+1 -> 2 | F7: 1 | G7: =Parametry!$C$12 -> 6 | H7: =ROUNDDOWN(Parametry!$C$9*Parametry!$C$10^(F7-1),0) -> 60 | I7: =ROUNDUP((Parametry!$C$20*MAX(1,D7))*Parametry!$C$15,0) -> 550 | J7: =ROUNDUP((Parametry!$C$20*MAX(1,D7))*Parametry!$C$15,0) -> 550 | K7: =ROUNDUP((Parametry!$C$20*MAX(1,D7))*Parametry!$C$15,0) -> 550 | L7: =ROUNDUP((Parametry!$C$20*MAX(1,D7))*Parametry!$C$15,0) -> 550 | M7: =ROUNDUP((Parametry!$C$20*MAX(1,D7))*Parametry!$C$15,0) -> 550 | N7: =ROUNDUP((Parametry!$C$20*MAX(1,D7))*Parametry!$C$15,0) -> 550 | O7: =ROUNDUP(J7/H7,0) -> 10 | P7: =ROUNDUP(K7/H7,0) -> 10 | Q7: =ROUNDUP(L7/H7,0) -> 10 | R7: =ROUNDUP(M7/H7,0) -> 10 | S7: =ROUNDUP(N7/H7,0) -> 10 | T7: =SUM(O7:S7) -> 50 | U7: =ROUNDUP(T7/G7,0) -> 9 | V7: =U7*Parametry!$C$11 -> 45 | W7: =2 -> 2 | X7: =V7*(W7-1) -> 45 | Y7: =V7*W7 -> 90 | Z7: =SUM(J7:N7) -> 2750 | AA7: Tylko ta budowa; 6 dostępnych po uwzględnieniu priorytetów; poziom magazynu=scenariusz L. Jeśli priorytety blokują dostawy, rzeczywiste ETA rośnie.
A8: Ratusz | B8: 2→3 | C8: Bez kolejki | D8: 2 | E8: =D8+1 -> 3 | F8: 2 | G8: =Parametry!$C$12 -> 6 | H8: =ROUNDDOWN(Parametry!$C$9*Parametry!$C$10^(F8-1),0) -> 66 | I8: =ROUNDUP((Parametry!$C$20*MAX(1,D8))*1,0) -> 1000 | J8: =ROUNDUP((Parametry!$C$20*MAX(1,D8))*1,0) -> 1000 | K8: =ROUNDUP((Parametry!$C$20*MAX(1,D8))*1,0) -> 1000 | L8: =ROUNDUP((Parametry!$C$20*MAX(1,D8))*1,0) -> 1000 | M8: =ROUNDUP((Parametry!$C$20*MAX(1,D8))*1,0) -> 1000 | N8: =ROUNDUP((Parametry!$C$20*MAX(1,D8))*1,0) -> 1000 | O8: =ROUNDUP(J8/H8,0) -> 16 | P8: =ROUNDUP(K8/H8,0) -> 16 | Q8: =ROUNDUP(L8/H8,0) -> 16 | R8: =ROUNDUP(M8/H8,0) -> 16 | S8: =ROUNDUP(N8/H8,0) -> 16 | T8: =SUM(O8:S8) -> 80 | U8: =ROUNDUP(T8/G8,0) -> 14 | V8: =U8*Parametry!$C$11 -> 70 | W8: =2 -> 2 | X8: =V8*(W8-1) -> 70 | Y8: =V8*W8 -> 140 | Z8: =SUM(J8:N8) -> 5000 | AA8: Tylko ta budowa; 6 dostępnych po uwzględnieniu priorytetów; poziom magazynu=scenariusz L. Jeśli priorytety blokują dostawy, rzeczywiste ETA rośnie.
A9: Ratusz | B9: 2→3 | C9: Kolejka +10% | D9: 2 | E9: =D9+1 -> 3 | F9: 2 | G9: =Parametry!$C$12 -> 6 | H9: =ROUNDDOWN(Parametry!$C$9*Parametry!$C$10^(F9-1),0) -> 66 | I9: =ROUNDUP((Parametry!$C$20*MAX(1,D9))*Parametry!$C$15,0) -> 1100 | J9: =ROUNDUP((Parametry!$C$20*MAX(1,D9))*Parametry!$C$15,0) -> 1100 | K9: =ROUNDUP((Parametry!$C$20*MAX(1,D9))*Parametry!$C$15,0) -> 1100 | L9: =ROUNDUP((Parametry!$C$20*MAX(1,D9))*Parametry!$C$15,0) -> 1100 | M9: =ROUNDUP((Parametry!$C$20*MAX(1,D9))*Parametry!$C$15,0) -> 1100 | N9: =ROUNDUP((Parametry!$C$20*MAX(1,D9))*Parametry!$C$15,0) -> 1100 | O9: =ROUNDUP(J9/H9,0) -> 17 | P9: =ROUNDUP(K9/H9,0) -> 17 | Q9: =ROUNDUP(L9/H9,0) -> 17 | R9: =ROUNDUP(M9/H9,0) -> 17 | S9: =ROUNDUP(N9/H9,0) -> 17 | T9: =SUM(O9:S9) -> 85 | U9: =ROUNDUP(T9/G9,0) -> 15 | V9: =U9*Parametry!$C$11 -> 75 | W9: =2 -> 2 | X9: =V9*(W9-1) -> 75 | Y9: =V9*W9 -> 150 | Z9: =SUM(J9:N9) -> 5500 | AA9: Tylko ta budowa; 6 dostępnych po uwzględnieniu priorytetów; poziom magazynu=scenariusz L. Jeśli priorytety blokują dostawy, rzeczywiste ETA rośnie.
A10: Ratusz | B10: 3→4 | C10: Bez kolejki | D10: 3 | E10: =D10+1 -> 4 | F10: 3 | G10: =Parametry!$C$12 -> 6 | H10: =ROUNDDOWN(Parametry!$C$9*Parametry!$C$10^(F10-1),0) -> 72 | I10: =ROUNDUP((Parametry!$C$20*MAX(1,D10))*1,0) -> 1500 | J10: =ROUNDUP((Parametry!$C$20*MAX(1,D10))*1,0) -> 1500 | K10: =ROUNDUP((Parametry!$C$20*MAX(1,D10))*1,0) -> 1500 | L10: =ROUNDUP((Parametry!$C$20*MAX(1,D10))*1,0) -> 1500 | M10: =ROUNDUP((Parametry!$C$20*MAX(1,D10))*1,0) -> 1500 | N10: =ROUNDUP((Parametry!$C$20*MAX(1,D10))*1,0) -> 1500 | O10: =ROUNDUP(J10/H10,0) -> 21 | P10: =ROUNDUP(K10/H10,0) -> 21 | Q10: =ROUNDUP(L10/H10,0) -> 21 | R10: =ROUNDUP(M10/H10,0) -> 21 | S10: =ROUNDUP(N10/H10,0) -> 21 | T10: =SUM(O10:S10) -> 105 | U10: =ROUNDUP(T10/G10,0) -> 18 | V10: =U10*Parametry!$C$11 -> 90 | W10: =2 -> 2 | X10: =V10*(W10-1) -> 90 | Y10: =V10*W10 -> 180 | Z10: =SUM(J10:N10) -> 7500 | AA10: Tylko ta budowa; 6 dostępnych po uwzględnieniu priorytetów; poziom magazynu=scenariusz L. Jeśli priorytety blokują dostawy, rzeczywiste ETA rośnie.
A11: Ratusz | B11: 3→4 | C11: Kolejka +10% | D11: 3 | E11: =D11+1 -> 4 | F11: 3 | G11: =Parametry!$C$12 -> 6 | H11: =ROUNDDOWN(Parametry!$C$9*Parametry!$C$10^(F11-1),0) -> 72 | I11: =ROUNDUP((Parametry!$C$20*MAX(1,D11))*Parametry!$C$15,0) -> 1650 | J11: =ROUNDUP((Parametry!$C$20*MAX(1,D11))*Parametry!$C$15,0) -> 1650 | K11: =ROUNDUP((Parametry!$C$20*MAX(1,D11))*Parametry!$C$15,0) -> 1650 | L11: =ROUNDUP((Parametry!$C$20*MAX(1,D11))*Parametry!$C$15,0) -> 1650 | M11: =ROUNDUP((Parametry!$C$20*MAX(1,D11))*Parametry!$C$15,0) -> 1650 | N11: =ROUNDUP((Parametry!$C$20*MAX(1,D11))*Parametry!$C$15,0) -> 1650 | O11: =ROUNDUP(J11/H11,0) -> 23 | P11: =ROUNDUP(K11/H11,0) -> 23 | Q11: =ROUNDUP(L11/H11,0) -> 23 | R11: =ROUNDUP(M11/H11,0) -> 23 | S11: =ROUNDUP(N11/H11,0) -> 23 | T11: =SUM(O11:S11) -> 115 | U11: =ROUNDUP(T11/G11,0) -> 20 | V11: =U11*Parametry!$C$11 -> 100 | W11: =2 -> 2 | X11: =V11*(W11-1) -> 100 | Y11: =V11*W11 -> 200 | Z11: =SUM(J11:N11) -> 8250 | AA11: Tylko ta budowa; 6 dostępnych po uwzględnieniu priorytetów; poziom magazynu=scenariusz L. Jeśli priorytety blokują dostawy, rzeczywiste ETA rośnie.
A12: Dom | B12: 1→2 | C12: Bez kolejki | D12: 1 | E12: =D12+1 -> 2 | F12: 1 | G12: =Parametry!$C$12 -> 6 | H12: =ROUNDDOWN(Parametry!$C$9*Parametry!$C$10^(F12-1),0) -> 60 | I12: =ROUNDUP((Parametry!$C$20*MAX(1,D12))*1,0) -> 500 | J12: =ROUNDUP((Parametry!$C$20*MAX(1,D12))*1,0) -> 500 | K12: =ROUNDUP((Parametry!$C$20*MAX(1,D12))*1,0) -> 500 | L12: =ROUNDUP((Parametry!$C$20*MAX(1,D12))*1,0) -> 500 | M12: =ROUNDUP((Parametry!$C$20*MAX(1,D12))*1,0) -> 500 | N12: =ROUNDUP((Parametry!$C$20*MAX(1,D12))*1,0) -> 500 | O12: =ROUNDUP(J12/H12,0) -> 9 | P12: =ROUNDUP(K12/H12,0) -> 9 | Q12: =ROUNDUP(L12/H12,0) -> 9 | R12: =ROUNDUP(M12/H12,0) -> 9 | S12: =ROUNDUP(N12/H12,0) -> 9 | T12: =SUM(O12:S12) -> 45 | U12: =ROUNDUP(T12/G12,0) -> 8 | V12: =U12*Parametry!$C$11 -> 40 | W12: =2 -> 2 | X12: =V12*(W12-1) -> 40 | Y12: =V12*W12 -> 80 | Z12: =SUM(J12:N12) -> 2500 | AA12: Tylko ta budowa; 6 dostępnych po uwzględnieniu priorytetów; poziom magazynu=scenariusz L. Jeśli priorytety blokują dostawy, rzeczywiste ETA rośnie.
A13: Dom | B13: 1→2 | C13: Kolejka +10% | D13: 1 | E13: =D13+1 -> 2 | F13: 1 | G13: =Parametry!$C$12 -> 6 | H13: =ROUNDDOWN(Parametry!$C$9*Parametry!$C$10^(F13-1),0) -> 60 | I13: =ROUNDUP((Parametry!$C$20*MAX(1,D13))*Parametry!$C$15,0) -> 550 | J13: =ROUNDUP((Parametry!$C$20*MAX(1,D13))*Parametry!$C$15,0) -> 550 | K13: =ROUNDUP((Parametry!$C$20*MAX(1,D13))*Parametry!$C$15,0) -> 550 | L13: =ROUNDUP((Parametry!$C$20*MAX(1,D13))*Parametry!$C$15,0) -> 550 | M13: =ROUNDUP((Parametry!$C$20*MAX(1,D13))*Parametry!$C$15,0) -> 550 | N13: =ROUNDUP((Parametry!$C$20*MAX(1,D13))*Parametry!$C$15,0) -> 550 | O13: =ROUNDUP(J13/H13,0) -> 10 | P13: =ROUNDUP(K13/H13,0) -> 10 | Q13: =ROUNDUP(L13/H13,0) -> 10 | R13: =ROUNDUP(M13/H13,0) -> 10 | S13: =ROUNDUP(N13/H13,0) -> 10 | T13: =SUM(O13:S13) -> 50 | U13: =ROUNDUP(T13/G13,0) -> 9 | V13: =U13*Parametry!$C$11 -> 45 | W13: =2 -> 2 | X13: =V13*(W13-1) -> 45 | Y13: =V13*W13 -> 90 | Z13: =SUM(J13:N13) -> 2750 | AA13: Tylko ta budowa; 6 dostępnych po uwzględnieniu priorytetów; poziom magazynu=scenariusz L. Jeśli priorytety blokują dostawy, rzeczywiste ETA rośnie.
A14: Dom | B14: 2→3 | C14: Bez kolejki | D14: 2 | E14: =D14+1 -> 3 | F14: 2 | G14: =Parametry!$C$12 -> 6 | H14: =ROUNDDOWN(Parametry!$C$9*Parametry!$C$10^(F14-1),0) -> 66 | I14: =ROUNDUP((Parametry!$C$20*MAX(1,D14))*1,0) -> 1000 | J14: =ROUNDUP((Parametry!$C$20*MAX(1,D14))*1,0) -> 1000 | K14: =ROUNDUP((Parametry!$C$20*MAX(1,D14))*1,0) -> 1000 | L14: =ROUNDUP((Parametry!$C$20*MAX(1,D14))*1,0) -> 1000 | M14: =ROUNDUP((Parametry!$C$20*MAX(1,D14))*1,0) -> 1000 | N14: =ROUNDUP((Parametry!$C$20*MAX(1,D14))*1,0) -> 1000 | O14: =ROUNDUP(J14/H14,0) -> 16 | P14: =ROUNDUP(K14/H14,0) -> 16 | Q14: =ROUNDUP(L14/H14,0) -> 16 | R14: =ROUNDUP(M14/H14,0) -> 16 | S14: =ROUNDUP(N14/H14,0) -> 16 | T14: =SUM(O14:S14) -> 80 | U14: =ROUNDUP(T14/G14,0) -> 14 | V14: =U14*Parametry!$C$11 -> 70 | W14: =2 -> 2 | X14: =V14*(W14-1) -> 70 | Y14: =V14*W14 -> 140 | Z14: =SUM(J14:N14) -> 5000 | AA14: Tylko ta budowa; 6 dostępnych po uwzględnieniu priorytetów; poziom magazynu=scenariusz L. Jeśli priorytety blokują dostawy, rzeczywiste ETA rośnie.
A15: Dom | B15: 2→3 | C15: Kolejka +10% | D15: 2 | E15: =D15+1 -> 3 | F15: 2 | G15: =Parametry!$C$12 -> 6 | H15: =ROUNDDOWN(Parametry!$C$9*Parametry!$C$10^(F15-1),0) -> 66 | I15: =ROUNDUP((Parametry!$C$20*MAX(1,D15))*Parametry!$C$15,0) -> 1100 | J15: =ROUNDUP((Parametry!$C$20*MAX(1,D15))*Parametry!$C$15,0) -> 1100 | K15: =ROUNDUP((Parametry!$C$20*MAX(1,D15))*Parametry!$C$15,0) -> 1100 | L15: =ROUNDUP((Parametry!$C$20*MAX(1,D15))*Parametry!$C$15,0) -> 1100 | M15: =ROUNDUP((Parametry!$C$20*MAX(1,D15))*Parametry!$C$15,0) -> 1100 | N15: =ROUNDUP((Parametry!$C$20*MAX(1,D15))*Parametry!$C$15,0) -> 1100 | O15: =ROUNDUP(J15/H15,0) -> 17 | P15: =ROUNDUP(K15/H15,0) -> 17 | Q15: =ROUNDUP(L15/H15,0) -> 17 | R15: =ROUNDUP(M15/H15,0) -> 17 | S15: =ROUNDUP(N15/H15,0) -> 17 | T15: =SUM(O15:S15) -> 85 | U15: =ROUNDUP(T15/G15,0) -> 15 | V15: =U15*Parametry!$C$11 -> 75 | W15: =2 -> 2 | X15: =V15*(W15-1) -> 75 | Y15: =V15*W15 -> 150 | Z15: =SUM(J15:N15) -> 5500 | AA15: Tylko ta budowa; 6 dostępnych po uwzględnieniu priorytetów; poziom magazynu=scenariusz L. Jeśli priorytety blokują dostawy, rzeczywiste ETA rośnie.
A16: Dom | B16: 3→4 | C16: Bez kolejki | D16: 3 | E16: =D16+1 -> 4 | F16: 3 | G16: =Parametry!$C$12 -> 6 | H16: =ROUNDDOWN(Parametry!$C$9*Parametry!$C$10^(F16-1),0) -> 72 | I16: =ROUNDUP((Parametry!$C$20*MAX(1,D16))*1,0) -> 1500 | J16: =ROUNDUP((Parametry!$C$20*MAX(1,D16))*1,0) -> 1500 | K16: =ROUNDUP((Parametry!$C$20*MAX(1,D16))*1,0) -> 1500 | L16: =ROUNDUP((Parametry!$C$20*MAX(1,D16))*1,0) -> 1500 | M16: =ROUNDUP((Parametry!$C$20*MAX(1,D16))*1,0) -> 1500 | N16: =ROUNDUP((Parametry!$C$20*MAX(1,D16))*1,0) -> 1500 | O16: =ROUNDUP(J16/H16,0) -> 21 | P16: =ROUNDUP(K16/H16,0) -> 21 | Q16: =ROUNDUP(L16/H16,0) -> 21 | R16: =ROUNDUP(M16/H16,0) -> 21 | S16: =ROUNDUP(N16/H16,0) -> 21 | T16: =SUM(O16:S16) -> 105 | U16: =ROUNDUP(T16/G16,0) -> 18 | V16: =U16*Parametry!$C$11 -> 90 | W16: =2 -> 2 | X16: =V16*(W16-1) -> 90 | Y16: =V16*W16 -> 180 | Z16: =SUM(J16:N16) -> 7500 | AA16: Tylko ta budowa; 6 dostępnych po uwzględnieniu priorytetów; poziom magazynu=scenariusz L. Jeśli priorytety blokują dostawy, rzeczywiste ETA rośnie.
A17: Dom | B17: 3→4 | C17: Kolejka +10% | D17: 3 | E17: =D17+1 -> 4 | F17: 3 | G17: =Parametry!$C$12 -> 6 | H17: =ROUNDDOWN(Parametry!$C$9*Parametry!$C$10^(F17-1),0) -> 72 | I17: =ROUNDUP((Parametry!$C$20*MAX(1,D17))*Parametry!$C$15,0) -> 1650 | J17: =ROUNDUP((Parametry!$C$20*MAX(1,D17))*Parametry!$C$15,0) -> 1650 | K17: =ROUNDUP((Parametry!$C$20*MAX(1,D17))*Parametry!$C$15,0) -> 1650 | L17: =ROUNDUP((Parametry!$C$20*MAX(1,D17))*Parametry!$C$15,0) -> 1650 | M17: =ROUNDUP((Parametry!$C$20*MAX(1,D17))*Parametry!$C$15,0) -> 1650 | N17: =ROUNDUP((Parametry!$C$20*MAX(1,D17))*Parametry!$C$15,0) -> 1650 | O17: =ROUNDUP(J17/H17,0) -> 23 | P17: =ROUNDUP(K17/H17,0) -> 23 | Q17: =ROUNDUP(L17/H17,0) -> 23 | R17: =ROUNDUP(M17/H17,0) -> 23 | S17: =ROUNDUP(N17/H17,0) -> 23 | T17: =SUM(O17:S17) -> 115 | U17: =ROUNDUP(T17/G17,0) -> 20 | V17: =U17*Parametry!$C$11 -> 100 | W17: =2 -> 2 | X17: =V17*(W17-1) -> 100 | Y17: =V17*W17 -> 200 | Z17: =SUM(J17:N17) -> 8250 | AA17: Tylko ta budowa; 6 dostępnych po uwzględnieniu priorytetów; poziom magazynu=scenariusz L. Jeśli priorytety blokują dostawy, rzeczywiste ETA rośnie.
A18: Farma | B18: 1→2 | C18: Bez kolejki | D18: 1 | E18: =D18+1 -> 2 | F18: 1 | G18: =Parametry!$C$12 -> 6 | H18: =ROUNDDOWN(Parametry!$C$9*Parametry!$C$10^(F18-1),0) -> 60 | I18: =ROUNDUP((0)*1,0) -> 0 | J18: =ROUNDUP((Parametry!$C$16*Parametry!$C$17*D18)*1,0) -> 72 | K18: =ROUNDUP((Parametry!$C$16*Parametry!$C$18*D18)*1,0) -> 72 | L18: =ROUNDUP((Parametry!$C$16*Parametry!$C$19*D18)*1,0) -> 120 | M18: =ROUNDUP((0)*1,0) -> 0 | N18: =ROUNDUP((0)*1,0) -> 0 | O18: =ROUNDUP(J18/H18,0) -> 2 | P18: =ROUNDUP(K18/H18,0) -> 2 | Q18: =ROUNDUP(L18/H18,0) -> 2 | R18: =ROUNDUP(M18/H18,0) -> 0 | S18: =ROUNDUP(N18/H18,0) -> 0 | T18: =SUM(O18:S18) -> 6 | U18: =ROUNDUP(T18/G18,0) -> 1 | V18: =U18*Parametry!$C$11 -> 5 | W18: =2 -> 2 | X18: =V18*(W18-1) -> 5 | Y18: =V18*W18 -> 10 | Z18: =SUM(J18:N18) -> 264 | AA18: Tylko ta budowa; 6 dostępnych po uwzględnieniu priorytetów; poziom magazynu=scenariusz L. Jeśli priorytety blokują dostawy, rzeczywiste ETA rośnie.
A19: Farma | B19: 1→2 | C19: Kolejka +10% | D19: 1 | E19: =D19+1 -> 2 | F19: 1 | G19: =Parametry!$C$12 -> 6 | H19: =ROUNDDOWN(Parametry!$C$9*Parametry!$C$10^(F19-1),0) -> 60 | I19: =ROUNDUP((0)*Parametry!$C$15,0) -> 0 | J19: =ROUNDUP((Parametry!$C$16*Parametry!$C$17*D19)*Parametry!$C$15,0) -> 80 | K19: =ROUNDUP((Parametry!$C$16*Parametry!$C$18*D19)*Parametry!$C$15,0) -> 80 | L19: =ROUNDUP((Parametry!$C$16*Parametry!$C$19*D19)*Parametry!$C$15,0) -> 132 | M19: =ROUNDUP((0)*Parametry!$C$15,0) -> 0 | N19: =ROUNDUP((0)*Parametry!$C$15,0) -> 0 | O19: =ROUNDUP(J19/H19,0) -> 2 | P19: =ROUNDUP(K19/H19,0) -> 2 | Q19: =ROUNDUP(L19/H19,0) -> 3 | R19: =ROUNDUP(M19/H19,0) -> 0 | S19: =ROUNDUP(N19/H19,0) -> 0 | T19: =SUM(O19:S19) -> 7 | U19: =ROUNDUP(T19/G19,0) -> 2 | V19: =U19*Parametry!$C$11 -> 10 | W19: =2 -> 2 | X19: =V19*(W19-1) -> 10 | Y19: =V19*W19 -> 20 | Z19: =SUM(J19:N19) -> 292 | AA19: Tylko ta budowa; 6 dostępnych po uwzględnieniu priorytetów; poziom magazynu=scenariusz L. Jeśli priorytety blokują dostawy, rzeczywiste ETA rośnie.
A20: Farma | B20: 2→3 | C20: Bez kolejki | D20: 2 | E20: =D20+1 -> 3 | F20: 2 | G20: =Parametry!$C$12 -> 6 | H20: =ROUNDDOWN(Parametry!$C$9*Parametry!$C$10^(F20-1),0) -> 66 | I20: =ROUNDUP((0)*1,0) -> 0 | J20: =ROUNDUP((Parametry!$C$16*Parametry!$C$17*D20)*1,0) -> 144 | K20: =ROUNDUP((Parametry!$C$16*Parametry!$C$18*D20)*1,0) -> 144 | L20: =ROUNDUP((Parametry!$C$16*Parametry!$C$19*D20)*1,0) -> 240 | M20: =ROUNDUP((0)*1,0) -> 0 | N20: =ROUNDUP((0)*1,0) -> 0 | O20: =ROUNDUP(J20/H20,0) -> 3 | P20: =ROUNDUP(K20/H20,0) -> 3 | Q20: =ROUNDUP(L20/H20,0) -> 4 | R20: =ROUNDUP(M20/H20,0) -> 0 | S20: =ROUNDUP(N20/H20,0) -> 0 | T20: =SUM(O20:S20) -> 10 | U20: =ROUNDUP(T20/G20,0) -> 2 | V20: =U20*Parametry!$C$11 -> 10 | W20: =2 -> 2 | X20: =V20*(W20-1) -> 10 | Y20: =V20*W20 -> 20 | Z20: =SUM(J20:N20) -> 528 | AA20: Tylko ta budowa; 6 dostępnych po uwzględnieniu priorytetów; poziom magazynu=scenariusz L. Jeśli priorytety blokują dostawy, rzeczywiste ETA rośnie.
A21: Farma | B21: 2→3 | C21: Kolejka +10% | D21: 2 | E21: =D21+1 -> 3 | F21: 2 | G21: =Parametry!$C$12 -> 6 | H21: =ROUNDDOWN(Parametry!$C$9*Parametry!$C$10^(F21-1),0) -> 66 | I21: =ROUNDUP((0)*Parametry!$C$15,0) -> 0 | J21: =ROUNDUP((Parametry!$C$16*Parametry!$C$17*D21)*Parametry!$C$15,0) -> 159 | K21: =ROUNDUP((Parametry!$C$16*Parametry!$C$18*D21)*Parametry!$C$15,0) -> 159 | L21: =ROUNDUP((Parametry!$C$16*Parametry!$C$19*D21)*Parametry!$C$15,0) -> 264 | M21: =ROUNDUP((0)*Parametry!$C$15,0) -> 0 | N21: =ROUNDUP((0)*Parametry!$C$15,0) -> 0 | O21: =ROUNDUP(J21/H21,0) -> 3 | P21: =ROUNDUP(K21/H21,0) -> 3 | Q21: =ROUNDUP(L21/H21,0) -> 4 | R21: =ROUNDUP(M21/H21,0) -> 0 | S21: =ROUNDUP(N21/H21,0) -> 0 | T21: =SUM(O21:S21) -> 10 | U21: =ROUNDUP(T21/G21,0) -> 2 | V21: =U21*Parametry!$C$11 -> 10 | W21: =2 -> 2 | X21: =V21*(W21-1) -> 10 | Y21: =V21*W21 -> 20 | Z21: =SUM(J21:N21) -> 582 | AA21: Tylko ta budowa; 6 dostępnych po uwzględnieniu priorytetów; poziom magazynu=scenariusz L. Jeśli priorytety blokują dostawy, rzeczywiste ETA rośnie.
A22: Farma | B22: 3→4 | C22: Bez kolejki | D22: 3 | E22: =D22+1 -> 4 | F22: 3 | G22: =Parametry!$C$12 -> 6 | H22: =ROUNDDOWN(Parametry!$C$9*Parametry!$C$10^(F22-1),0) -> 72 | I22: =ROUNDUP((0)*1,0) -> 0 | J22: =ROUNDUP((Parametry!$C$16*Parametry!$C$17*D22)*1,0) -> 216 | K22: =ROUNDUP((Parametry!$C$16*Parametry!$C$18*D22)*1,0) -> 216 | L22: =ROUNDUP((Parametry!$C$16*Parametry!$C$19*D22)*1,0) -> 360 | M22: =ROUNDUP((0)*1,0) -> 0 | N22: =ROUNDUP((0)*1,0) -> 0 | O22: =ROUNDUP(J22/H22,0) -> 3 | P22: =ROUNDUP(K22/H22,0) -> 3 | Q22: =ROUNDUP(L22/H22,0) -> 5 | R22: =ROUNDUP(M22/H22,0) -> 0 | S22: =ROUNDUP(N22/H22,0) -> 0 | T22: =SUM(O22:S22) -> 11 | U22: =ROUNDUP(T22/G22,0) -> 2 | V22: =U22*Parametry!$C$11 -> 10 | W22: =2 -> 2 | X22: =V22*(W22-1) -> 10 | Y22: =V22*W22 -> 20 | Z22: =SUM(J22:N22) -> 792 | AA22: Tylko ta budowa; 6 dostępnych po uwzględnieniu priorytetów; poziom magazynu=scenariusz L. Jeśli priorytety blokują dostawy, rzeczywiste ETA rośnie.
A23: Farma | B23: 3→4 | C23: Kolejka +10% | D23: 3 | E23: =D23+1 -> 4 | F23: 3 | G23: =Parametry!$C$12 -> 6 | H23: =ROUNDDOWN(Parametry!$C$9*Parametry!$C$10^(F23-1),0) -> 72 | I23: =ROUNDUP((0)*Parametry!$C$15,0) -> 0 | J23: =ROUNDUP((Parametry!$C$16*Parametry!$C$17*D23)*Parametry!$C$15,0) -> 238 | K23: =ROUNDUP((Parametry!$C$16*Parametry!$C$18*D23)*Parametry!$C$15,0) -> 238 | L23: =ROUNDUP((Parametry!$C$16*Parametry!$C$19*D23)*Parametry!$C$15,0) -> 396 | M23: =ROUNDUP((0)*Parametry!$C$15,0) -> 0 | N23: =ROUNDUP((0)*Parametry!$C$15,0) -> 0 | O23: =ROUNDUP(J23/H23,0) -> 4 | P23: =ROUNDUP(K23/H23,0) -> 4 | Q23: =ROUNDUP(L23/H23,0) -> 6 | R23: =ROUNDUP(M23/H23,0) -> 0 | S23: =ROUNDUP(N23/H23,0) -> 0 | T23: =SUM(O23:S23) -> 14 | U23: =ROUNDUP(T23/G23,0) -> 3 | V23: =U23*Parametry!$C$11 -> 15 | W23: =2 -> 2 | X23: =V23*(W23-1) -> 15 | Y23: =V23*W23 -> 30 | Z23: =SUM(J23:N23) -> 872 | AA23: Tylko ta budowa; 6 dostępnych po uwzględnieniu priorytetów; poziom magazynu=scenariusz L. Jeśli priorytety blokują dostawy, rzeczywiste ETA rośnie.
A24: Młyn | B24: 1→2 | C24: Bez kolejki | D24: 1 | E24: =D24+1 -> 2 | F24: 1 | G24: =Parametry!$C$12 -> 6 | H24: =ROUNDDOWN(Parametry!$C$9*Parametry!$C$10^(F24-1),0) -> 60 | I24: =ROUNDUP((0)*1,0) -> 0 | J24: =ROUNDUP((Parametry!$C$16*Parametry!$C$17*D24)*1,0) -> 72 | K24: =ROUNDUP((Parametry!$C$16*Parametry!$C$18*D24)*1,0) -> 72 | L24: =ROUNDUP((0)*1,0) -> 0 | M24: =ROUNDUP((Parametry!$C$16*Parametry!$C$19*D24)*1,0) -> 120 | N24: =ROUNDUP((0)*1,0) -> 0 | O24: =ROUNDUP(J24/H24,0) -> 2 | P24: =ROUNDUP(K24/H24,0) -> 2 | Q24: =ROUNDUP(L24/H24,0) -> 0 | R24: =ROUNDUP(M24/H24,0) -> 2 | S24: =ROUNDUP(N24/H24,0) -> 0 | T24: =SUM(O24:S24) -> 6 | U24: =ROUNDUP(T24/G24,0) -> 1 | V24: =U24*Parametry!$C$11 -> 5 | W24: =2 -> 2 | X24: =V24*(W24-1) -> 5 | Y24: =V24*W24 -> 10 | Z24: =SUM(J24:N24) -> 264 | AA24: Tylko ta budowa; 6 dostępnych po uwzględnieniu priorytetów; poziom magazynu=scenariusz L. Jeśli priorytety blokują dostawy, rzeczywiste ETA rośnie.
A25: Młyn | B25: 1→2 | C25: Kolejka +10% | D25: 1 | E25: =D25+1 -> 2 | F25: 1 | G25: =Parametry!$C$12 -> 6 | H25: =ROUNDDOWN(Parametry!$C$9*Parametry!$C$10^(F25-1),0) -> 60 | I25: =ROUNDUP((0)*Parametry!$C$15,0) -> 0 | J25: =ROUNDUP((Parametry!$C$16*Parametry!$C$17*D25)*Parametry!$C$15,0) -> 80 | K25: =ROUNDUP((Parametry!$C$16*Parametry!$C$18*D25)*Parametry!$C$15,0) -> 80 | L25: =ROUNDUP((0)*Parametry!$C$15,0) -> 0 | M25: =ROUNDUP((Parametry!$C$16*Parametry!$C$19*D25)*Parametry!$C$15,0) -> 132 | N25: =ROUNDUP((0)*Parametry!$C$15,0) -> 0 | O25: =ROUNDUP(J25/H25,0) -> 2 | P25: =ROUNDUP(K25/H25,0) -> 2 | Q25: =ROUNDUP(L25/H25,0) -> 0 | R25: =ROUNDUP(M25/H25,0) -> 3 | S25: =ROUNDUP(N25/H25,0) -> 0 | T25: =SUM(O25:S25) -> 7 | U25: =ROUNDUP(T25/G25,0) -> 2 | V25: =U25*Parametry!$C$11 -> 10 | W25: =2 -> 2 | X25: =V25*(W25-1) -> 10 | Y25: =V25*W25 -> 20 | Z25: =SUM(J25:N25) -> 292 | AA25: Tylko ta budowa; 6 dostępnych po uwzględnieniu priorytetów; poziom magazynu=scenariusz L. Jeśli priorytety blokują dostawy, rzeczywiste ETA rośnie.
A26: Młyn | B26: 2→3 | C26: Bez kolejki | D26: 2 | E26: =D26+1 -> 3 | F26: 2 | G26: =Parametry!$C$12 -> 6 | H26: =ROUNDDOWN(Parametry!$C$9*Parametry!$C$10^(F26-1),0) -> 66 | I26: =ROUNDUP((0)*1,0) -> 0 | J26: =ROUNDUP((Parametry!$C$16*Parametry!$C$17*D26)*1,0) -> 144 | K26: =ROUNDUP((Parametry!$C$16*Parametry!$C$18*D26)*1,0) -> 144 | L26: =ROUNDUP((0)*1,0) -> 0 | M26: =ROUNDUP((Parametry!$C$16*Parametry!$C$19*D26)*1,0) -> 240 | N26: =ROUNDUP((0)*1,0) -> 0 | O26: =ROUNDUP(J26/H26,0) -> 3 | P26: =ROUNDUP(K26/H26,0) -> 3 | Q26: =ROUNDUP(L26/H26,0) -> 0 | R26: =ROUNDUP(M26/H26,0) -> 4 | S26: =ROUNDUP(N26/H26,0) -> 0 | T26: =SUM(O26:S26) -> 10 | U26: =ROUNDUP(T26/G26,0) -> 2 | V26: =U26*Parametry!$C$11 -> 10 | W26: =2 -> 2 | X26: =V26*(W26-1) -> 10 | Y26: =V26*W26 -> 20 | Z26: =SUM(J26:N26) -> 528 | AA26: Tylko ta budowa; 6 dostępnych po uwzględnieniu priorytetów; poziom magazynu=scenariusz L. Jeśli priorytety blokują dostawy, rzeczywiste ETA rośnie.
A27: Młyn | B27: 2→3 | C27: Kolejka +10% | D27: 2 | E27: =D27+1 -> 3 | F27: 2 | G27: =Parametry!$C$12 -> 6 | H27: =ROUNDDOWN(Parametry!$C$9*Parametry!$C$10^(F27-1),0) -> 66 | I27: =ROUNDUP((0)*Parametry!$C$15,0) -> 0 | J27: =ROUNDUP((Parametry!$C$16*Parametry!$C$17*D27)*Parametry!$C$15,0) -> 159 | K27: =ROUNDUP((Parametry!$C$16*Parametry!$C$18*D27)*Parametry!$C$15,0) -> 159 | L27: =ROUNDUP((0)*Parametry!$C$15,0) -> 0 | M27: =ROUNDUP((Parametry!$C$16*Parametry!$C$19*D27)*Parametry!$C$15,0) -> 264 | N27: =ROUNDUP((0)*Parametry!$C$15,0) -> 0 | O27: =ROUNDUP(J27/H27,0) -> 3 | P27: =ROUNDUP(K27/H27,0) -> 3 | Q27: =ROUNDUP(L27/H27,0) -> 0 | R27: =ROUNDUP(M27/H27,0) -> 4 | S27: =ROUNDUP(N27/H27,0) -> 0 | T27: =SUM(O27:S27) -> 10 | U27: =ROUNDUP(T27/G27,0) -> 2 | V27: =U27*Parametry!$C$11 -> 10 | W27: =2 -> 2 | X27: =V27*(W27-1) -> 10 | Y27: =V27*W27 -> 20 | Z27: =SUM(J27:N27) -> 582 | AA27: Tylko ta budowa; 6 dostępnych po uwzględnieniu priorytetów; poziom magazynu=scenariusz L. Jeśli priorytety blokują dostawy, rzeczywiste ETA rośnie.
A28: Młyn | B28: 3→4 | C28: Bez kolejki | D28: 3 | E28: =D28+1 -> 4 | F28: 3 | G28: =Parametry!$C$12 -> 6 | H28: =ROUNDDOWN(Parametry!$C$9*Parametry!$C$10^(F28-1),0) -> 72 | I28: =ROUNDUP((0)*1,0) -> 0 | J28: =ROUNDUP((Parametry!$C$16*Parametry!$C$17*D28)*1,0) -> 216 | K28: =ROUNDUP((Parametry!$C$16*Parametry!$C$18*D28)*1,0) -> 216 | L28: =ROUNDUP((0)*1,0) -> 0 | M28: =ROUNDUP((Parametry!$C$16*Parametry!$C$19*D28)*1,0) -> 360 | N28: =ROUNDUP((0)*1,0) -> 0 | O28: =ROUNDUP(J28/H28,0) -> 3 | P28: =ROUNDUP(K28/H28,0) -> 3 | Q28: =ROUNDUP(L28/H28,0) -> 0 | R28: =ROUNDUP(M28/H28,0) -> 5 | S28: =ROUNDUP(N28/H28,0) -> 0 | T28: =SUM(O28:S28) -> 11 | U28: =ROUNDUP(T28/G28,0) -> 2 | V28: =U28*Parametry!$C$11 -> 10 | W28: =2 -> 2 | X28: =V28*(W28-1) -> 10 | Y28: =V28*W28 -> 20 | Z28: =SUM(J28:N28) -> 792 | AA28: Tylko ta budowa; 6 dostępnych po uwzględnieniu priorytetów; poziom magazynu=scenariusz L. Jeśli priorytety blokują dostawy, rzeczywiste ETA rośnie.
A29: Młyn | B29: 3→4 | C29: Kolejka +10% | D29: 3 | E29: =D29+1 -> 4 | F29: 3 | G29: =Parametry!$C$12 -> 6 | H29: =ROUNDDOWN(Parametry!$C$9*Parametry!$C$10^(F29-1),0) -> 72 | I29: =ROUNDUP((0)*Parametry!$C$15,0) -> 0 | J29: =ROUNDUP((Parametry!$C$16*Parametry!$C$17*D29)*Parametry!$C$15,0) -> 238 | K29: =ROUNDUP((Parametry!$C$16*Parametry!$C$18*D29)*Parametry!$C$15,0) -> 238 | L29: =ROUNDUP((0)*Parametry!$C$15,0) -> 0 | M29: =ROUNDUP((Parametry!$C$16*Parametry!$C$19*D29)*Parametry!$C$15,0) -> 396 | N29: =ROUNDUP((0)*Parametry!$C$15,0) -> 0 | O29: =ROUNDUP(J29/H29,0) -> 4 | P29: =ROUNDUP(K29/H29,0) -> 4 | Q29: =ROUNDUP(L29/H29,0) -> 0 | R29: =ROUNDUP(M29/H29,0) -> 6 | S29: =ROUNDUP(N29/H29,0) -> 0 | T29: =SUM(O29:S29) -> 14 | U29: =ROUNDUP(T29/G29,0) -> 3 | V29: =U29*Parametry!$C$11 -> 15 | W29: =2 -> 2 | X29: =V29*(W29-1) -> 15 | Y29: =V29*W29 -> 30 | Z29: =SUM(J29:N29) -> 872 | AA29: Tylko ta budowa; 6 dostępnych po uwzględnieniu priorytetów; poziom magazynu=scenariusz L. Jeśli priorytety blokują dostawy, rzeczywiste ETA rośnie.
A30: Drwale | B30: 1→2 | C30: Bez kolejki | D30: 1 | E30: =D30+1 -> 2 | F30: 1 | G30: =Parametry!$C$12 -> 6 | H30: =ROUNDDOWN(Parametry!$C$9*Parametry!$C$10^(F30-1),0) -> 60 | I30: =ROUNDUP((0)*1,0) -> 0 | J30: =ROUNDUP((Parametry!$C$16*Parametry!$C$17*D30+Parametry!$C$16*Parametry!$C$19*D30)*1,0) -> 192 | K30: =ROUNDUP((Parametry!$C$16*Parametry!$C$18*D30)*1,0) -> 72 | L30: =ROUNDUP((0)*1,0) -> 0 | M30: =ROUNDUP((0)*1,0) -> 0 | N30: =ROUNDUP((0)*1,0) -> 0 | O30: =ROUNDUP(J30/H30,0) -> 4 | P30: =ROUNDUP(K30/H30,0) -> 2 | Q30: =ROUNDUP(L30/H30,0) -> 0 | R30: =ROUNDUP(M30/H30,0) -> 0 | S30: =ROUNDUP(N30/H30,0) -> 0 | T30: =SUM(O30:S30) -> 6 | U30: =ROUNDUP(T30/G30,0) -> 1 | V30: =U30*Parametry!$C$11 -> 5 | W30: =2 -> 2 | X30: =V30*(W30-1) -> 5 | Y30: =V30*W30 -> 10 | Z30: =SUM(J30:N30) -> 264 | AA30: Tylko ta budowa; 6 dostępnych po uwzględnieniu priorytetów; poziom magazynu=scenariusz L. Jeśli priorytety blokują dostawy, rzeczywiste ETA rośnie.
A31: Drwale | B31: 1→2 | C31: Kolejka +10% | D31: 1 | E31: =D31+1 -> 2 | F31: 1 | G31: =Parametry!$C$12 -> 6 | H31: =ROUNDDOWN(Parametry!$C$9*Parametry!$C$10^(F31-1),0) -> 60 | I31: =ROUNDUP((0)*Parametry!$C$15,0) -> 0 | J31: =ROUNDUP((Parametry!$C$16*Parametry!$C$17*D31+Parametry!$C$16*Parametry!$C$19*D31)*Parametry!$C$15,0) -> 212 | K31: =ROUNDUP((Parametry!$C$16*Parametry!$C$18*D31)*Parametry!$C$15,0) -> 80 | L31: =ROUNDUP((0)*Parametry!$C$15,0) -> 0 | M31: =ROUNDUP((0)*Parametry!$C$15,0) -> 0 | N31: =ROUNDUP((0)*Parametry!$C$15,0) -> 0 | O31: =ROUNDUP(J31/H31,0) -> 4 | P31: =ROUNDUP(K31/H31,0) -> 2 | Q31: =ROUNDUP(L31/H31,0) -> 0 | R31: =ROUNDUP(M31/H31,0) -> 0 | S31: =ROUNDUP(N31/H31,0) -> 0 | T31: =SUM(O31:S31) -> 6 | U31: =ROUNDUP(T31/G31,0) -> 1 | V31: =U31*Parametry!$C$11 -> 5 | W31: =2 -> 2 | X31: =V31*(W31-1) -> 5 | Y31: =V31*W31 -> 10 | Z31: =SUM(J31:N31) -> 292 | AA31: Tylko ta budowa; 6 dostępnych po uwzględnieniu priorytetów; poziom magazynu=scenariusz L. Jeśli priorytety blokują dostawy, rzeczywiste ETA rośnie.
A32: Drwale | B32: 2→3 | C32: Bez kolejki | D32: 2 | E32: =D32+1 -> 3 | F32: 2 | G32: =Parametry!$C$12 -> 6 | H32: =ROUNDDOWN(Parametry!$C$9*Parametry!$C$10^(F32-1),0) -> 66 | I32: =ROUNDUP((0)*1,0) -> 0 | J32: =ROUNDUP((Parametry!$C$16*Parametry!$C$17*D32+Parametry!$C$16*Parametry!$C$19*D32)*1,0) -> 384 | K32: =ROUNDUP((Parametry!$C$16*Parametry!$C$18*D32)*1,0) -> 144 | L32: =ROUNDUP((0)*1,0) -> 0 | M32: =ROUNDUP((0)*1,0) -> 0 | N32: =ROUNDUP((0)*1,0) -> 0 | O32: =ROUNDUP(J32/H32,0) -> 6 | P32: =ROUNDUP(K32/H32,0) -> 3 | Q32: =ROUNDUP(L32/H32,0) -> 0 | R32: =ROUNDUP(M32/H32,0) -> 0 | S32: =ROUNDUP(N32/H32,0) -> 0 | T32: =SUM(O32:S32) -> 9 | U32: =ROUNDUP(T32/G32,0) -> 2 | V32: =U32*Parametry!$C$11 -> 10 | W32: =2 -> 2 | X32: =V32*(W32-1) -> 10 | Y32: =V32*W32 -> 20 | Z32: =SUM(J32:N32) -> 528 | AA32: Tylko ta budowa; 6 dostępnych po uwzględnieniu priorytetów; poziom magazynu=scenariusz L. Jeśli priorytety blokują dostawy, rzeczywiste ETA rośnie.
A33: Drwale | B33: 2→3 | C33: Kolejka +10% | D33: 2 | E33: =D33+1 -> 3 | F33: 2 | G33: =Parametry!$C$12 -> 6 | H33: =ROUNDDOWN(Parametry!$C$9*Parametry!$C$10^(F33-1),0) -> 66 | I33: =ROUNDUP((0)*Parametry!$C$15,0) -> 0 | J33: =ROUNDUP((Parametry!$C$16*Parametry!$C$17*D33+Parametry!$C$16*Parametry!$C$19*D33)*Parametry!$C$15,0) -> 423 | K33: =ROUNDUP((Parametry!$C$16*Parametry!$C$18*D33)*Parametry!$C$15,0) -> 159 | L33: =ROUNDUP((0)*Parametry!$C$15,0) -> 0 | M33: =ROUNDUP((0)*Parametry!$C$15,0) -> 0 | N33: =ROUNDUP((0)*Parametry!$C$15,0) -> 0 | O33: =ROUNDUP(J33/H33,0) -> 7 | P33: =ROUNDUP(K33/H33,0) -> 3 | Q33: =ROUNDUP(L33/H33,0) -> 0 | R33: =ROUNDUP(M33/H33,0) -> 0 | S33: =ROUNDUP(N33/H33,0) -> 0 | T33: =SUM(O33:S33) -> 10 | U33: =ROUNDUP(T33/G33,0) -> 2 | V33: =U33*Parametry!$C$11 -> 10 | W33: =2 -> 2 | X33: =V33*(W33-1) -> 10 | Y33: =V33*W33 -> 20 | Z33: =SUM(J33:N33) -> 582 | AA33: Tylko ta budowa; 6 dostępnych po uwzględnieniu priorytetów; poziom magazynu=scenariusz L. Jeśli priorytety blokują dostawy, rzeczywiste ETA rośnie.
A34: Drwale | B34: 3→4 | C34: Bez kolejki | D34: 3 | E34: =D34+1 -> 4 | F34: 3 | G34: =Parametry!$C$12 -> 6 | H34: =ROUNDDOWN(Parametry!$C$9*Parametry!$C$10^(F34-1),0) -> 72 | I34: =ROUNDUP((0)*1,0) -> 0 | J34: =ROUNDUP((Parametry!$C$16*Parametry!$C$17*D34+Parametry!$C$16*Parametry!$C$19*D34)*1,0) -> 576 | K34: =ROUNDUP((Parametry!$C$16*Parametry!$C$18*D34)*1,0) -> 216 | L34: =ROUNDUP((0)*1,0) -> 0 | M34: =ROUNDUP((0)*1,0) -> 0 | N34: =ROUNDUP((0)*1,0) -> 0 | O34: =ROUNDUP(J34/H34,0) -> 8 | P34: =ROUNDUP(K34/H34,0) -> 3 | Q34: =ROUNDUP(L34/H34,0) -> 0 | R34: =ROUNDUP(M34/H34,0) -> 0 | S34: =ROUNDUP(N34/H34,0) -> 0 | T34: =SUM(O34:S34) -> 11 | U34: =ROUNDUP(T34/G34,0) -> 2 | V34: =U34*Parametry!$C$11 -> 10 | W34: =2 -> 2 | X34: =V34*(W34-1) -> 10 | Y34: =V34*W34 -> 20 | Z34: =SUM(J34:N34) -> 792 | AA34: Tylko ta budowa; 6 dostępnych po uwzględnieniu priorytetów; poziom magazynu=scenariusz L. Jeśli priorytety blokują dostawy, rzeczywiste ETA rośnie.
A35: Drwale | B35: 3→4 | C35: Kolejka +10% | D35: 3 | E35: =D35+1 -> 4 | F35: 3 | G35: =Parametry!$C$12 -> 6 | H35: =ROUNDDOWN(Parametry!$C$9*Parametry!$C$10^(F35-1),0) -> 72 | I35: =ROUNDUP((0)*Parametry!$C$15,0) -> 0 | J35: =ROUNDUP((Parametry!$C$16*Parametry!$C$17*D35+Parametry!$C$16*Parametry!$C$19*D35)*Parametry!$C$15,0) -> 634 | K35: =ROUNDUP((Parametry!$C$16*Parametry!$C$18*D35)*Parametry!$C$15,0) -> 238 | L35: =ROUNDUP((0)*Parametry!$C$15,0) -> 0 | M35: =ROUNDUP((0)*Parametry!$C$15,0) -> 0 | N35: =ROUNDUP((0)*Parametry!$C$15,0) -> 0 | O35: =ROUNDUP(J35/H35,0) -> 9 | P35: =ROUNDUP(K35/H35,0) -> 4 | Q35: =ROUNDUP(L35/H35,0) -> 0 | R35: =ROUNDUP(M35/H35,0) -> 0 | S35: =ROUNDUP(N35/H35,0) -> 0 | T35: =SUM(O35:S35) -> 13 | U35: =ROUNDUP(T35/G35,0) -> 3 | V35: =U35*Parametry!$C$11 -> 15 | W35: =2 -> 2 | X35: =V35*(W35-1) -> 15 | Y35: =V35*W35 -> 30 | Z35: =SUM(J35:N35) -> 872 | AA35: Tylko ta budowa; 6 dostępnych po uwzględnieniu priorytetów; poziom magazynu=scenariusz L. Jeśli priorytety blokują dostawy, rzeczywiste ETA rośnie.
A36: Tartak | B36: 1→2 | C36: Bez kolejki | D36: 1 | E36: =D36+1 -> 2 | F36: 1 | G36: =Parametry!$C$12 -> 6 | H36: =ROUNDDOWN(Parametry!$C$9*Parametry!$C$10^(F36-1),0) -> 60 | I36: =ROUNDUP((0)*1,0) -> 0 | J36: =ROUNDUP((Parametry!$C$16*Parametry!$C$17*D36)*1,0) -> 72 | K36: =ROUNDUP((Parametry!$C$16*Parametry!$C$18*D36)*1,0) -> 72 | L36: =ROUNDUP((0)*1,0) -> 0 | M36: =ROUNDUP((0)*1,0) -> 0 | N36: =ROUNDUP((Parametry!$C$16*Parametry!$C$19*D36)*1,0) -> 120 | O36: =ROUNDUP(J36/H36,0) -> 2 | P36: =ROUNDUP(K36/H36,0) -> 2 | Q36: =ROUNDUP(L36/H36,0) -> 0 | R36: =ROUNDUP(M36/H36,0) -> 0 | S36: =ROUNDUP(N36/H36,0) -> 2 | T36: =SUM(O36:S36) -> 6 | U36: =ROUNDUP(T36/G36,0) -> 1 | V36: =U36*Parametry!$C$11 -> 5 | W36: =2 -> 2 | X36: =V36*(W36-1) -> 5 | Y36: =V36*W36 -> 10 | Z36: =SUM(J36:N36) -> 264 | AA36: Tylko ta budowa; 6 dostępnych po uwzględnieniu priorytetów; poziom magazynu=scenariusz L. Jeśli priorytety blokują dostawy, rzeczywiste ETA rośnie.
A37: Tartak | B37: 1→2 | C37: Kolejka +10% | D37: 1 | E37: =D37+1 -> 2 | F37: 1 | G37: =Parametry!$C$12 -> 6 | H37: =ROUNDDOWN(Parametry!$C$9*Parametry!$C$10^(F37-1),0) -> 60 | I37: =ROUNDUP((0)*Parametry!$C$15,0) -> 0 | J37: =ROUNDUP((Parametry!$C$16*Parametry!$C$17*D37)*Parametry!$C$15,0) -> 80 | K37: =ROUNDUP((Parametry!$C$16*Parametry!$C$18*D37)*Parametry!$C$15,0) -> 80 | L37: =ROUNDUP((0)*Parametry!$C$15,0) -> 0 | M37: =ROUNDUP((0)*Parametry!$C$15,0) -> 0 | N37: =ROUNDUP((Parametry!$C$16*Parametry!$C$19*D37)*Parametry!$C$15,0) -> 132 | O37: =ROUNDUP(J37/H37,0) -> 2 | P37: =ROUNDUP(K37/H37,0) -> 2 | Q37: =ROUNDUP(L37/H37,0) -> 0 | R37: =ROUNDUP(M37/H37,0) -> 0 | S37: =ROUNDUP(N37/H37,0) -> 3 | T37: =SUM(O37:S37) -> 7 | U37: =ROUNDUP(T37/G37,0) -> 2 | V37: =U37*Parametry!$C$11 -> 10 | W37: =2 -> 2 | X37: =V37*(W37-1) -> 10 | Y37: =V37*W37 -> 20 | Z37: =SUM(J37:N37) -> 292 | AA37: Tylko ta budowa; 6 dostępnych po uwzględnieniu priorytetów; poziom magazynu=scenariusz L. Jeśli priorytety blokują dostawy, rzeczywiste ETA rośnie.
A38: Tartak | B38: 2→3 | C38: Bez kolejki | D38: 2 | E38: =D38+1 -> 3 | F38: 2 | G38: =Parametry!$C$12 -> 6 | H38: =ROUNDDOWN(Parametry!$C$9*Parametry!$C$10^(F38-1),0) -> 66 | I38: =ROUNDUP((0)*1,0) -> 0 | J38: =ROUNDUP((Parametry!$C$16*Parametry!$C$17*D38)*1,0) -> 144 | K38: =ROUNDUP((Parametry!$C$16*Parametry!$C$18*D38)*1,0) -> 144 | L38: =ROUNDUP((0)*1,0) -> 0 | M38: =ROUNDUP((0)*1,0) -> 0 | N38: =ROUNDUP((Parametry!$C$16*Parametry!$C$19*D38)*1,0) -> 240 | O38: =ROUNDUP(J38/H38,0) -> 3 | P38: =ROUNDUP(K38/H38,0) -> 3 | Q38: =ROUNDUP(L38/H38,0) -> 0 | R38: =ROUNDUP(M38/H38,0) -> 0 | S38: =ROUNDUP(N38/H38,0) -> 4 | T38: =SUM(O38:S38) -> 10 | U38: =ROUNDUP(T38/G38,0) -> 2 | V38: =U38*Parametry!$C$11 -> 10 | W38: =2 -> 2 | X38: =V38*(W38-1) -> 10 | Y38: =V38*W38 -> 20 | Z38: =SUM(J38:N38) -> 528 | AA38: Tylko ta budowa; 6 dostępnych po uwzględnieniu priorytetów; poziom magazynu=scenariusz L. Jeśli priorytety blokują dostawy, rzeczywiste ETA rośnie.
A39: Tartak | B39: 2→3 | C39: Kolejka +10% | D39: 2 | E39: =D39+1 -> 3 | F39: 2 | G39: =Parametry!$C$12 -> 6 | H39: =ROUNDDOWN(Parametry!$C$9*Parametry!$C$10^(F39-1),0) -> 66 | I39: =ROUNDUP((0)*Parametry!$C$15,0) -> 0 | J39: =ROUNDUP((Parametry!$C$16*Parametry!$C$17*D39)*Parametry!$C$15,0) -> 159 | K39: =ROUNDUP((Parametry!$C$16*Parametry!$C$18*D39)*Parametry!$C$15,0) -> 159 | L39: =ROUNDUP((0)*Parametry!$C$15,0) -> 0 | M39: =ROUNDUP((0)*Parametry!$C$15,0) -> 0 | N39: =ROUNDUP((Parametry!$C$16*Parametry!$C$19*D39)*Parametry!$C$15,0) -> 264 | O39: =ROUNDUP(J39/H39,0) -> 3 | P39: =ROUNDUP(K39/H39,0) -> 3 | Q39: =ROUNDUP(L39/H39,0) -> 0 | R39: =ROUNDUP(M39/H39,0) -> 0 | S39: =ROUNDUP(N39/H39,0) -> 4 | T39: =SUM(O39:S39) -> 10 | U39: =ROUNDUP(T39/G39,0) -> 2 | V39: =U39*Parametry!$C$11 -> 10 | W39: =2 -> 2 | X39: =V39*(W39-1) -> 10 | Y39: =V39*W39 -> 20 | Z39: =SUM(J39:N39) -> 582 | AA39: Tylko ta budowa; 6 dostępnych po uwzględnieniu priorytetów; poziom magazynu=scenariusz L. Jeśli priorytety blokują dostawy, rzeczywiste ETA rośnie.
A40: Tartak | B40: 3→4 | C40: Bez kolejki | D40: 3 | E40: =D40+1 -> 4 | F40: 3 | G40: =Parametry!$C$12 -> 6 | H40: =ROUNDDOWN(Parametry!$C$9*Parametry!$C$10^(F40-1),0) -> 72 | I40: =ROUNDUP((0)*1,0) -> 0 | J40: =ROUNDUP((Parametry!$C$16*Parametry!$C$17*D40)*1,0) -> 216 | K40: =ROUNDUP((Parametry!$C$16*Parametry!$C$18*D40)*1,0) -> 216 | L40: =ROUNDUP((0)*1,0) -> 0 | M40: =ROUNDUP((0)*1,0) -> 0 | N40: =ROUNDUP((Parametry!$C$16*Parametry!$C$19*D40)*1,0) -> 360 | O40: =ROUNDUP(J40/H40,0) -> 3 | P40: =ROUNDUP(K40/H40,0) -> 3 | Q40: =ROUNDUP(L40/H40,0) -> 0 | R40: =ROUNDUP(M40/H40,0) -> 0 | S40: =ROUNDUP(N40/H40,0) -> 5 | T40: =SUM(O40:S40) -> 11 | U40: =ROUNDUP(T40/G40,0) -> 2 | V40: =U40*Parametry!$C$11 -> 10 | W40: =2 -> 2 | X40: =V40*(W40-1) -> 10 | Y40: =V40*W40 -> 20 | Z40: =SUM(J40:N40) -> 792 | AA40: Tylko ta budowa; 6 dostępnych po uwzględnieniu priorytetów; poziom magazynu=scenariusz L. Jeśli priorytety blokują dostawy, rzeczywiste ETA rośnie.
A41: Tartak | B41: 3→4 | C41: Kolejka +10% | D41: 3 | E41: =D41+1 -> 4 | F41: 3 | G41: =Parametry!$C$12 -> 6 | H41: =ROUNDDOWN(Parametry!$C$9*Parametry!$C$10^(F41-1),0) -> 72 | I41: =ROUNDUP((0)*Parametry!$C$15,0) -> 0 | J41: =ROUNDUP((Parametry!$C$16*Parametry!$C$17*D41)*Parametry!$C$15,0) -> 238 | K41: =ROUNDUP((Parametry!$C$16*Parametry!$C$18*D41)*Parametry!$C$15,0) -> 238 | L41: =ROUNDUP((0)*Parametry!$C$15,0) -> 0 | M41: =ROUNDUP((0)*Parametry!$C$15,0) -> 0 | N41: =ROUNDUP((Parametry!$C$16*Parametry!$C$19*D41)*Parametry!$C$15,0) -> 396 | O41: =ROUNDUP(J41/H41,0) -> 4 | P41: =ROUNDUP(K41/H41,0) -> 4 | Q41: =ROUNDUP(L41/H41,0) -> 0 | R41: =ROUNDUP(M41/H41,0) -> 0 | S41: =ROUNDUP(N41/H41,0) -> 6 | T41: =SUM(O41:S41) -> 14 | U41: =ROUNDUP(T41/G41,0) -> 3 | V41: =U41*Parametry!$C$11 -> 15 | W41: =2 -> 2 | X41: =V41*(W41-1) -> 15 | Y41: =V41*W41 -> 30 | Z41: =SUM(J41:N41) -> 872 | AA41: Tylko ta budowa; 6 dostępnych po uwzględnieniu priorytetów; poziom magazynu=scenariusz L. Jeśli priorytety blokują dostawy, rzeczywiste ETA rośnie.
A42: Kamieniołom | B42: 1→2 | C42: Bez kolejki | D42: 1 | E42: =D42+1 -> 2 | F42: 1 | G42: =Parametry!$C$12 -> 6 | H42: =ROUNDDOWN(Parametry!$C$9*Parametry!$C$10^(F42-1),0) -> 60 | I42: =ROUNDUP((0)*1,0) -> 0 | J42: =ROUNDUP((Parametry!$C$16*Parametry!$C$17*D42)*1,0) -> 72 | K42: =ROUNDUP((Parametry!$C$16*Parametry!$C$18*D42+Parametry!$C$16*Parametry!$C$19*D42)*1,0) -> 192 | L42: =ROUNDUP((0)*1,0) -> 0 | M42: =ROUNDUP((0)*1,0) -> 0 | N42: =ROUNDUP((0)*1,0) -> 0 | O42: =ROUNDUP(J42/H42,0) -> 2 | P42: =ROUNDUP(K42/H42,0) -> 4 | Q42: =ROUNDUP(L42/H42,0) -> 0 | R42: =ROUNDUP(M42/H42,0) -> 0 | S42: =ROUNDUP(N42/H42,0) -> 0 | T42: =SUM(O42:S42) -> 6 | U42: =ROUNDUP(T42/G42,0) -> 1 | V42: =U42*Parametry!$C$11 -> 5 | W42: =2 -> 2 | X42: =V42*(W42-1) -> 5 | Y42: =V42*W42 -> 10 | Z42: =SUM(J42:N42) -> 264 | AA42: Tylko ta budowa; 6 dostępnych po uwzględnieniu priorytetów; poziom magazynu=scenariusz L. Jeśli priorytety blokują dostawy, rzeczywiste ETA rośnie.
A43: Kamieniołom | B43: 1→2 | C43: Kolejka +10% | D43: 1 | E43: =D43+1 -> 2 | F43: 1 | G43: =Parametry!$C$12 -> 6 | H43: =ROUNDDOWN(Parametry!$C$9*Parametry!$C$10^(F43-1),0) -> 60 | I43: =ROUNDUP((0)*Parametry!$C$15,0) -> 0 | J43: =ROUNDUP((Parametry!$C$16*Parametry!$C$17*D43)*Parametry!$C$15,0) -> 80 | K43: =ROUNDUP((Parametry!$C$16*Parametry!$C$18*D43+Parametry!$C$16*Parametry!$C$19*D43)*Parametry!$C$15,0) -> 212 | L43: =ROUNDUP((0)*Parametry!$C$15,0) -> 0 | M43: =ROUNDUP((0)*Parametry!$C$15,0) -> 0 | N43: =ROUNDUP((0)*Parametry!$C$15,0) -> 0 | O43: =ROUNDUP(J43/H43,0) -> 2 | P43: =ROUNDUP(K43/H43,0) -> 4 | Q43: =ROUNDUP(L43/H43,0) -> 0 | R43: =ROUNDUP(M43/H43,0) -> 0 | S43: =ROUNDUP(N43/H43,0) -> 0 | T43: =SUM(O43:S43) -> 6 | U43: =ROUNDUP(T43/G43,0) -> 1 | V43: =U43*Parametry!$C$11 -> 5 | W43: =2 -> 2 | X43: =V43*(W43-1) -> 5 | Y43: =V43*W43 -> 10 | Z43: =SUM(J43:N43) -> 292 | AA43: Tylko ta budowa; 6 dostępnych po uwzględnieniu priorytetów; poziom magazynu=scenariusz L. Jeśli priorytety blokują dostawy, rzeczywiste ETA rośnie.
A44: Kamieniołom | B44: 2→3 | C44: Bez kolejki | D44: 2 | E44: =D44+1 -> 3 | F44: 2 | G44: =Parametry!$C$12 -> 6 | H44: =ROUNDDOWN(Parametry!$C$9*Parametry!$C$10^(F44-1),0) -> 66 | I44: =ROUNDUP((0)*1,0) -> 0 | J44: =ROUNDUP((Parametry!$C$16*Parametry!$C$17*D44)*1,0) -> 144 | K44: =ROUNDUP((Parametry!$C$16*Parametry!$C$18*D44+Parametry!$C$16*Parametry!$C$19*D44)*1,0) -> 384 | L44: =ROUNDUP((0)*1,0) -> 0 | M44: =ROUNDUP((0)*1,0) -> 0 | N44: =ROUNDUP((0)*1,0) -> 0 | O44: =ROUNDUP(J44/H44,0) -> 3 | P44: =ROUNDUP(K44/H44,0) -> 6 | Q44: =ROUNDUP(L44/H44,0) -> 0 | R44: =ROUNDUP(M44/H44,0) -> 0 | S44: =ROUNDUP(N44/H44,0) -> 0 | T44: =SUM(O44:S44) -> 9 | U44: =ROUNDUP(T44/G44,0) -> 2 | V44: =U44*Parametry!$C$11 -> 10 | W44: =2 -> 2 | X44: =V44*(W44-1) -> 10 | Y44: =V44*W44 -> 20 | Z44: =SUM(J44:N44) -> 528 | AA44: Tylko ta budowa; 6 dostępnych po uwzględnieniu priorytetów; poziom magazynu=scenariusz L. Jeśli priorytety blokują dostawy, rzeczywiste ETA rośnie.
A45: Kamieniołom | B45: 2→3 | C45: Kolejka +10% | D45: 2 | E45: =D45+1 -> 3 | F45: 2 | G45: =Parametry!$C$12 -> 6 | H45: =ROUNDDOWN(Parametry!$C$9*Parametry!$C$10^(F45-1),0) -> 66 | I45: =ROUNDUP((0)*Parametry!$C$15,0) -> 0 | J45: =ROUNDUP((Parametry!$C$16*Parametry!$C$17*D45)*Parametry!$C$15,0) -> 159 | K45: =ROUNDUP((Parametry!$C$16*Parametry!$C$18*D45+Parametry!$C$16*Parametry!$C$19*D45)*Parametry!$C$15,0) -> 423 | L45: =ROUNDUP((0)*Parametry!$C$15,0) -> 0 | M45: =ROUNDUP((0)*Parametry!$C$15,0) -> 0 | N45: =ROUNDUP((0)*Parametry!$C$15,0) -> 0 | O45: =ROUNDUP(J45/H45,0) -> 3 | P45: =ROUNDUP(K45/H45,0) -> 7 | Q45: =ROUNDUP(L45/H45,0) -> 0 | R45: =ROUNDUP(M45/H45,0) -> 0 | S45: =ROUNDUP(N45/H45,0) -> 0 | T45: =SUM(O45:S45) -> 10 | U45: =ROUNDUP(T45/G45,0) -> 2 | V45: =U45*Parametry!$C$11 -> 10 | W45: =2 -> 2 | X45: =V45*(W45-1) -> 10 | Y45: =V45*W45 -> 20 | Z45: =SUM(J45:N45) -> 582 | AA45: Tylko ta budowa; 6 dostępnych po uwzględnieniu priorytetów; poziom magazynu=scenariusz L. Jeśli priorytety blokują dostawy, rzeczywiste ETA rośnie.
A46: Kamieniołom | B46: 3→4 | C46: Bez kolejki | D46: 3 | E46: =D46+1 -> 4 | F46: 3 | G46: =Parametry!$C$12 -> 6 | H46: =ROUNDDOWN(Parametry!$C$9*Parametry!$C$10^(F46-1),0) -> 72 | I46: =ROUNDUP((0)*1,0) -> 0 | J46: =ROUNDUP((Parametry!$C$16*Parametry!$C$17*D46)*1,0) -> 216 | K46: =ROUNDUP((Parametry!$C$16*Parametry!$C$18*D46+Parametry!$C$16*Parametry!$C$19*D46)*1,0) -> 576 | L46: =ROUNDUP((0)*1,0) -> 0 | M46: =ROUNDUP((0)*1,0) -> 0 | N46: =ROUNDUP((0)*1,0) -> 0 | O46: =ROUNDUP(J46/H46,0) -> 3 | P46: =ROUNDUP(K46/H46,0) -> 8 | Q46: =ROUNDUP(L46/H46,0) -> 0 | R46: =ROUNDUP(M46/H46,0) -> 0 | S46: =ROUNDUP(N46/H46,0) -> 0 | T46: =SUM(O46:S46) -> 11 | U46: =ROUNDUP(T46/G46,0) -> 2 | V46: =U46*Parametry!$C$11 -> 10 | W46: =2 -> 2 | X46: =V46*(W46-1) -> 10 | Y46: =V46*W46 -> 20 | Z46: =SUM(J46:N46) -> 792 | AA46: Tylko ta budowa; 6 dostępnych po uwzględnieniu priorytetów; poziom magazynu=scenariusz L. Jeśli priorytety blokują dostawy, rzeczywiste ETA rośnie.
A47: Kamieniołom | B47: 3→4 | C47: Kolejka +10% | D47: 3 | E47: =D47+1 -> 4 | F47: 3 | G47: =Parametry!$C$12 -> 6 | H47: =ROUNDDOWN(Parametry!$C$9*Parametry!$C$10^(F47-1),0) -> 72 | I47: =ROUNDUP((0)*Parametry!$C$15,0) -> 0 | J47: =ROUNDUP((Parametry!$C$16*Parametry!$C$17*D47)*Parametry!$C$15,0) -> 238 | K47: =ROUNDUP((Parametry!$C$16*Parametry!$C$18*D47+Parametry!$C$16*Parametry!$C$19*D47)*Parametry!$C$15,0) -> 634 | L47: =ROUNDUP((0)*Parametry!$C$15,0) -> 0 | M47: =ROUNDUP((0)*Parametry!$C$15,0) -> 0 | N47: =ROUNDUP((0)*Parametry!$C$15,0) -> 0 | O47: =ROUNDUP(J47/H47,0) -> 4 | P47: =ROUNDUP(K47/H47,0) -> 9 | Q47: =ROUNDUP(L47/H47,0) -> 0 | R47: =ROUNDUP(M47/H47,0) -> 0 | S47: =ROUNDUP(N47/H47,0) -> 0 | T47: =SUM(O47:S47) -> 13 | U47: =ROUNDUP(T47/G47,0) -> 3 | V47: =U47*Parametry!$C$11 -> 15 | W47: =2 -> 2 | X47: =V47*(W47-1) -> 15 | Y47: =V47*W47 -> 30 | Z47: =SUM(J47:N47) -> 872 | AA47: Tylko ta budowa; 6 dostępnych po uwzględnieniu priorytetów; poziom magazynu=scenariusz L. Jeśli priorytety blokują dostawy, rzeczywiste ETA rośnie.
A48: Magazyn | B48: 1→2 | C48: Bez kolejki | D48: 1 | E48: =D48+1 -> 2 | F48: 1 | G48: =Parametry!$C$12 -> 6 | H48: =ROUNDDOWN(Parametry!$C$9*Parametry!$C$10^(F48-1),0) -> 60 | I48: =ROUNDUP((Parametry!$C$21*MAX(1,D48))*1,0) -> 300 | J48: =ROUNDUP((Parametry!$C$21*MAX(1,D48))*1,0) -> 300 | K48: =ROUNDUP((Parametry!$C$21*MAX(1,D48))*1,0) -> 300 | L48: =ROUNDUP((Parametry!$C$21*MAX(1,D48))*1,0) -> 300 | M48: =ROUNDUP((Parametry!$C$21*MAX(1,D48))*1,0) -> 300 | N48: =ROUNDUP((Parametry!$C$21*MAX(1,D48))*1,0) -> 300 | O48: =ROUNDUP(J48/H48,0) -> 5 | P48: =ROUNDUP(K48/H48,0) -> 5 | Q48: =ROUNDUP(L48/H48,0) -> 5 | R48: =ROUNDUP(M48/H48,0) -> 5 | S48: =ROUNDUP(N48/H48,0) -> 5 | T48: =SUM(O48:S48) -> 25 | U48: =ROUNDUP(T48/G48,0) -> 5 | V48: =U48*Parametry!$C$11 -> 25 | W48: =2 -> 2 | X48: =V48*(W48-1) -> 25 | Y48: =V48*W48 -> 50 | Z48: =SUM(J48:N48) -> 1500 | AA48: Tylko ta budowa; 6 dostępnych po uwzględnieniu priorytetów; poziom magazynu=scenariusz L. Jeśli priorytety blokują dostawy, rzeczywiste ETA rośnie.
A49: Magazyn | B49: 1→2 | C49: Kolejka +10% | D49: 1 | E49: =D49+1 -> 2 | F49: 1 | G49: =Parametry!$C$12 -> 6 | H49: =ROUNDDOWN(Parametry!$C$9*Parametry!$C$10^(F49-1),0) -> 60 | I49: =ROUNDUP((Parametry!$C$21*MAX(1,D49))*Parametry!$C$15,0) -> 330 | J49: =ROUNDUP((Parametry!$C$21*MAX(1,D49))*Parametry!$C$15,0) -> 330 | K49: =ROUNDUP((Parametry!$C$21*MAX(1,D49))*Parametry!$C$15,0) -> 330 | L49: =ROUNDUP((Parametry!$C$21*MAX(1,D49))*Parametry!$C$15,0) -> 330 | M49: =ROUNDUP((Parametry!$C$21*MAX(1,D49))*Parametry!$C$15,0) -> 330 | N49: =ROUNDUP((Parametry!$C$21*MAX(1,D49))*Parametry!$C$15,0) -> 330 | O49: =ROUNDUP(J49/H49,0) -> 6 | P49: =ROUNDUP(K49/H49,0) -> 6 | Q49: =ROUNDUP(L49/H49,0) -> 6 | R49: =ROUNDUP(M49/H49,0) -> 6 | S49: =ROUNDUP(N49/H49,0) -> 6 | T49: =SUM(O49:S49) -> 30 | U49: =ROUNDUP(T49/G49,0) -> 5 | V49: =U49*Parametry!$C$11 -> 25 | W49: =2 -> 2 | X49: =V49*(W49-1) -> 25 | Y49: =V49*W49 -> 50 | Z49: =SUM(J49:N49) -> 1650 | AA49: Tylko ta budowa; 6 dostępnych po uwzględnieniu priorytetów; poziom magazynu=scenariusz L. Jeśli priorytety blokują dostawy, rzeczywiste ETA rośnie.
A50: Magazyn | B50: 2→3 | C50: Bez kolejki | D50: 2 | E50: =D50+1 -> 3 | F50: 2 | G50: =Parametry!$C$12 -> 6 | H50: =ROUNDDOWN(Parametry!$C$9*Parametry!$C$10^(F50-1),0) -> 66 | I50: =ROUNDUP((Parametry!$C$21*MAX(1,D50))*1,0) -> 600 | J50: =ROUNDUP((Parametry!$C$21*MAX(1,D50))*1,0) -> 600 | K50: =ROUNDUP((Parametry!$C$21*MAX(1,D50))*1,0) -> 600 | L50: =ROUNDUP((Parametry!$C$21*MAX(1,D50))*1,0) -> 600 | M50: =ROUNDUP((Parametry!$C$21*MAX(1,D50))*1,0) -> 600 | N50: =ROUNDUP((Parametry!$C$21*MAX(1,D50))*1,0) -> 600 | O50: =ROUNDUP(J50/H50,0) -> 10 | P50: =ROUNDUP(K50/H50,0) -> 10 | Q50: =ROUNDUP(L50/H50,0) -> 10 | R50: =ROUNDUP(M50/H50,0) -> 10 | S50: =ROUNDUP(N50/H50,0) -> 10 | T50: =SUM(O50:S50) -> 50 | U50: =ROUNDUP(T50/G50,0) -> 9 | V50: =U50*Parametry!$C$11 -> 45 | W50: =2 -> 2 | X50: =V50*(W50-1) -> 45 | Y50: =V50*W50 -> 90 | Z50: =SUM(J50:N50) -> 3000 | AA50: Tylko ta budowa; 6 dostępnych po uwzględnieniu priorytetów; poziom magazynu=scenariusz L. Jeśli priorytety blokują dostawy, rzeczywiste ETA rośnie.
A51: Magazyn | B51: 2→3 | C51: Kolejka +10% | D51: 2 | E51: =D51+1 -> 3 | F51: 2 | G51: =Parametry!$C$12 -> 6 | H51: =ROUNDDOWN(Parametry!$C$9*Parametry!$C$10^(F51-1),0) -> 66 | I51: =ROUNDUP((Parametry!$C$21*MAX(1,D51))*Parametry!$C$15,0) -> 660 | J51: =ROUNDUP((Parametry!$C$21*MAX(1,D51))*Parametry!$C$15,0) -> 660 | K51: =ROUNDUP((Parametry!$C$21*MAX(1,D51))*Parametry!$C$15,0) -> 660 | L51: =ROUNDUP((Parametry!$C$21*MAX(1,D51))*Parametry!$C$15,0) -> 660 | M51: =ROUNDUP((Parametry!$C$21*MAX(1,D51))*Parametry!$C$15,0) -> 660 | N51: =ROUNDUP((Parametry!$C$21*MAX(1,D51))*Parametry!$C$15,0) -> 660 | O51: =ROUNDUP(J51/H51,0) -> 10 | P51: =ROUNDUP(K51/H51,0) -> 10 | Q51: =ROUNDUP(L51/H51,0) -> 10 | R51: =ROUNDUP(M51/H51,0) -> 10 | S51: =ROUNDUP(N51/H51,0) -> 10 | T51: =SUM(O51:S51) -> 50 | U51: =ROUNDUP(T51/G51,0) -> 9 | V51: =U51*Parametry!$C$11 -> 45 | W51: =2 -> 2 | X51: =V51*(W51-1) -> 45 | Y51: =V51*W51 -> 90 | Z51: =SUM(J51:N51) -> 3300 | AA51: Tylko ta budowa; 6 dostępnych po uwzględnieniu priorytetów; poziom magazynu=scenariusz L. Jeśli priorytety blokują dostawy, rzeczywiste ETA rośnie.
A52: Magazyn | B52: 3→4 | C52: Bez kolejki | D52: 3 | E52: =D52+1 -> 4 | F52: 3 | G52: =Parametry!$C$12 -> 6 | H52: =ROUNDDOWN(Parametry!$C$9*Parametry!$C$10^(F52-1),0) -> 72 | I52: =ROUNDUP((Parametry!$C$21*MAX(1,D52))*1,0) -> 900 | J52: =ROUNDUP((Parametry!$C$21*MAX(1,D52))*1,0) -> 900 | K52: =ROUNDUP((Parametry!$C$21*MAX(1,D52))*1,0) -> 900 | L52: =ROUNDUP((Parametry!$C$21*MAX(1,D52))*1,0) -> 900 | M52: =ROUNDUP((Parametry!$C$21*MAX(1,D52))*1,0) -> 900 | N52: =ROUNDUP((Parametry!$C$21*MAX(1,D52))*1,0) -> 900 | O52: =ROUNDUP(J52/H52,0) -> 13 | P52: =ROUNDUP(K52/H52,0) -> 13 | Q52: =ROUNDUP(L52/H52,0) -> 13 | R52: =ROUNDUP(M52/H52,0) -> 13 | S52: =ROUNDUP(N52/H52,0) -> 13 | T52: =SUM(O52:S52) -> 65 | U52: =ROUNDUP(T52/G52,0) -> 11 | V52: =U52*Parametry!$C$11 -> 55 | W52: =2 -> 2 | X52: =V52*(W52-1) -> 55 | Y52: =V52*W52 -> 110 | Z52: =SUM(J52:N52) -> 4500 | AA52: Tylko ta budowa; 6 dostępnych po uwzględnieniu priorytetów; poziom magazynu=scenariusz L. Jeśli priorytety blokują dostawy, rzeczywiste ETA rośnie.
A53: Magazyn | B53: 3→4 | C53: Kolejka +10% | D53: 3 | E53: =D53+1 -> 4 | F53: 3 | G53: =Parametry!$C$12 -> 6 | H53: =ROUNDDOWN(Parametry!$C$9*Parametry!$C$10^(F53-1),0) -> 72 | I53: =ROUNDUP((Parametry!$C$21*MAX(1,D53))*Parametry!$C$15,0) -> 990 | J53: =ROUNDUP((Parametry!$C$21*MAX(1,D53))*Parametry!$C$15,0) -> 990 | K53: =ROUNDUP((Parametry!$C$21*MAX(1,D53))*Parametry!$C$15,0) -> 990 | L53: =ROUNDUP((Parametry!$C$21*MAX(1,D53))*Parametry!$C$15,0) -> 990 | M53: =ROUNDUP((Parametry!$C$21*MAX(1,D53))*Parametry!$C$15,0) -> 990 | N53: =ROUNDUP((Parametry!$C$21*MAX(1,D53))*Parametry!$C$15,0) -> 990 | O53: =ROUNDUP(J53/H53,0) -> 14 | P53: =ROUNDUP(K53/H53,0) -> 14 | Q53: =ROUNDUP(L53/H53,0) -> 14 | R53: =ROUNDUP(M53/H53,0) -> 14 | S53: =ROUNDUP(N53/H53,0) -> 14 | T53: =SUM(O53:S53) -> 70 | U53: =ROUNDUP(T53/G53,0) -> 12 | V53: =U53*Parametry!$C$11 -> 60 | W53: =2 -> 2 | X53: =V53*(W53-1) -> 60 | Y53: =V53*W53 -> 120 | Z53: =SUM(J53:N53) -> 4950 | AA53: Tylko ta budowa; 6 dostępnych po uwzględnieniu priorytetów; poziom magazynu=scenariusz L. Jeśli priorytety blokują dostawy, rzeczywiste ETA rośnie.
A54: Targ | B54: 1→2 | C54: Bez kolejki | D54: 1 | E54: =D54+1 -> 2 | F54: 1 | G54: =Parametry!$C$12 -> 6 | H54: =ROUNDDOWN(Parametry!$C$9*Parametry!$C$10^(F54-1),0) -> 60 | I54: =ROUNDUP((Parametry!$C$21*MAX(1,D54))*1,0) -> 300 | J54: =ROUNDUP((Parametry!$C$21*MAX(1,D54))*1,0) -> 300 | K54: =ROUNDUP((Parametry!$C$21*MAX(1,D54))*1,0) -> 300 | L54: =ROUNDUP((Parametry!$C$21*MAX(1,D54))*1,0) -> 300 | M54: =ROUNDUP((Parametry!$C$21*MAX(1,D54))*1,0) -> 300 | N54: =ROUNDUP((Parametry!$C$21*MAX(1,D54))*1,0) -> 300 | O54: =ROUNDUP(J54/H54,0) -> 5 | P54: =ROUNDUP(K54/H54,0) -> 5 | Q54: =ROUNDUP(L54/H54,0) -> 5 | R54: =ROUNDUP(M54/H54,0) -> 5 | S54: =ROUNDUP(N54/H54,0) -> 5 | T54: =SUM(O54:S54) -> 25 | U54: =ROUNDUP(T54/G54,0) -> 5 | V54: =U54*Parametry!$C$11 -> 25 | W54: =2 -> 2 | X54: =V54*(W54-1) -> 25 | Y54: =V54*W54 -> 50 | Z54: =SUM(J54:N54) -> 1500 | AA54: Tylko ta budowa; 6 dostępnych po uwzględnieniu priorytetów; poziom magazynu=scenariusz L. Jeśli priorytety blokują dostawy, rzeczywiste ETA rośnie.
A55: Targ | B55: 1→2 | C55: Kolejka +10% | D55: 1 | E55: =D55+1 -> 2 | F55: 1 | G55: =Parametry!$C$12 -> 6 | H55: =ROUNDDOWN(Parametry!$C$9*Parametry!$C$10^(F55-1),0) -> 60 | I55: =ROUNDUP((Parametry!$C$21*MAX(1,D55))*Parametry!$C$15,0) -> 330 | J55: =ROUNDUP((Parametry!$C$21*MAX(1,D55))*Parametry!$C$15,0) -> 330 | K55: =ROUNDUP((Parametry!$C$21*MAX(1,D55))*Parametry!$C$15,0) -> 330 | L55: =ROUNDUP((Parametry!$C$21*MAX(1,D55))*Parametry!$C$15,0) -> 330 | M55: =ROUNDUP((Parametry!$C$21*MAX(1,D55))*Parametry!$C$15,0) -> 330 | N55: =ROUNDUP((Parametry!$C$21*MAX(1,D55))*Parametry!$C$15,0) -> 330 | O55: =ROUNDUP(J55/H55,0) -> 6 | P55: =ROUNDUP(K55/H55,0) -> 6 | Q55: =ROUNDUP(L55/H55,0) -> 6 | R55: =ROUNDUP(M55/H55,0) -> 6 | S55: =ROUNDUP(N55/H55,0) -> 6 | T55: =SUM(O55:S55) -> 30 | U55: =ROUNDUP(T55/G55,0) -> 5 | V55: =U55*Parametry!$C$11 -> 25 | W55: =2 -> 2 | X55: =V55*(W55-1) -> 25 | Y55: =V55*W55 -> 50 | Z55: =SUM(J55:N55) -> 1650 | AA55: Tylko ta budowa; 6 dostępnych po uwzględnieniu priorytetów; poziom magazynu=scenariusz L. Jeśli priorytety blokują dostawy, rzeczywiste ETA rośnie.
A56: Targ | B56: 2→3 | C56: Bez kolejki | D56: 2 | E56: =D56+1 -> 3 | F56: 2 | G56: =Parametry!$C$12 -> 6 | H56: =ROUNDDOWN(Parametry!$C$9*Parametry!$C$10^(F56-1),0) -> 66 | I56: =ROUNDUP((Parametry!$C$21*MAX(1,D56))*1,0) -> 600 | J56: =ROUNDUP((Parametry!$C$21*MAX(1,D56))*1,0) -> 600 | K56: =ROUNDUP((Parametry!$C$21*MAX(1,D56))*1,0) -> 600 | L56: =ROUNDUP((Parametry!$C$21*MAX(1,D56))*1,0) -> 600 | M56: =ROUNDUP((Parametry!$C$21*MAX(1,D56))*1,0) -> 600 | N56: =ROUNDUP((Parametry!$C$21*MAX(1,D56))*1,0) -> 600 | O56: =ROUNDUP(J56/H56,0) -> 10 | P56: =ROUNDUP(K56/H56,0) -> 10 | Q56: =ROUNDUP(L56/H56,0) -> 10 | R56: =ROUNDUP(M56/H56,0) -> 10 | S56: =ROUNDUP(N56/H56,0) -> 10 | T56: =SUM(O56:S56) -> 50 | U56: =ROUNDUP(T56/G56,0) -> 9 | V56: =U56*Parametry!$C$11 -> 45 | W56: =2 -> 2 | X56: =V56*(W56-1) -> 45 | Y56: =V56*W56 -> 90 | Z56: =SUM(J56:N56) -> 3000 | AA56: Tylko ta budowa; 6 dostępnych po uwzględnieniu priorytetów; poziom magazynu=scenariusz L. Jeśli priorytety blokują dostawy, rzeczywiste ETA rośnie.
A57: Targ | B57: 2→3 | C57: Kolejka +10% | D57: 2 | E57: =D57+1 -> 3 | F57: 2 | G57: =Parametry!$C$12 -> 6 | H57: =ROUNDDOWN(Parametry!$C$9*Parametry!$C$10^(F57-1),0) -> 66 | I57: =ROUNDUP((Parametry!$C$21*MAX(1,D57))*Parametry!$C$15,0) -> 660 | J57: =ROUNDUP((Parametry!$C$21*MAX(1,D57))*Parametry!$C$15,0) -> 660 | K57: =ROUNDUP((Parametry!$C$21*MAX(1,D57))*Parametry!$C$15,0) -> 660 | L57: =ROUNDUP((Parametry!$C$21*MAX(1,D57))*Parametry!$C$15,0) -> 660 | M57: =ROUNDUP((Parametry!$C$21*MAX(1,D57))*Parametry!$C$15,0) -> 660 | N57: =ROUNDUP((Parametry!$C$21*MAX(1,D57))*Parametry!$C$15,0) -> 660 | O57: =ROUNDUP(J57/H57,0) -> 10 | P57: =ROUNDUP(K57/H57,0) -> 10 | Q57: =ROUNDUP(L57/H57,0) -> 10 | R57: =ROUNDUP(M57/H57,0) -> 10 | S57: =ROUNDUP(N57/H57,0) -> 10 | T57: =SUM(O57:S57) -> 50 | U57: =ROUNDUP(T57/G57,0) -> 9 | V57: =U57*Parametry!$C$11 -> 45 | W57: =2 -> 2 | X57: =V57*(W57-1) -> 45 | Y57: =V57*W57 -> 90 | Z57: =SUM(J57:N57) -> 3300 | AA57: Tylko ta budowa; 6 dostępnych po uwzględnieniu priorytetów; poziom magazynu=scenariusz L. Jeśli priorytety blokują dostawy, rzeczywiste ETA rośnie.
A58: Targ | B58: 3→4 | C58: Bez kolejki | D58: 3 | E58: =D58+1 -> 4 | F58: 3 | G58: =Parametry!$C$12 -> 6 | H58: =ROUNDDOWN(Parametry!$C$9*Parametry!$C$10^(F58-1),0) -> 72 | I58: =ROUNDUP((Parametry!$C$21*MAX(1,D58))*1,0) -> 900 | J58: =ROUNDUP((Parametry!$C$21*MAX(1,D58))*1,0) -> 900 | K58: =ROUNDUP((Parametry!$C$21*MAX(1,D58))*1,0) -> 900 | L58: =ROUNDUP((Parametry!$C$21*MAX(1,D58))*1,0) -> 900 | M58: =ROUNDUP((Parametry!$C$21*MAX(1,D58))*1,0) -> 900 | N58: =ROUNDUP((Parametry!$C$21*MAX(1,D58))*1,0) -> 900 | O58: =ROUNDUP(J58/H58,0) -> 13 | P58: =ROUNDUP(K58/H58,0) -> 13 | Q58: =ROUNDUP(L58/H58,0) -> 13 | R58: =ROUNDUP(M58/H58,0) -> 13 | S58: =ROUNDUP(N58/H58,0) -> 13 | T58: =SUM(O58:S58) -> 65 | U58: =ROUNDUP(T58/G58,0) -> 11 | V58: =U58*Parametry!$C$11 -> 55 | W58: =2 -> 2 | X58: =V58*(W58-1) -> 55 | Y58: =V58*W58 -> 110 | Z58: =SUM(J58:N58) -> 4500 | AA58: Tylko ta budowa; 6 dostępnych po uwzględnieniu priorytetów; poziom magazynu=scenariusz L. Jeśli priorytety blokują dostawy, rzeczywiste ETA rośnie.
A59: Targ | B59: 3→4 | C59: Kolejka +10% | D59: 3 | E59: =D59+1 -> 4 | F59: 3 | G59: =Parametry!$C$12 -> 6 | H59: =ROUNDDOWN(Parametry!$C$9*Parametry!$C$10^(F59-1),0) -> 72 | I59: =ROUNDUP((Parametry!$C$21*MAX(1,D59))*Parametry!$C$15,0) -> 990 | J59: =ROUNDUP((Parametry!$C$21*MAX(1,D59))*Parametry!$C$15,0) -> 990 | K59: =ROUNDUP((Parametry!$C$21*MAX(1,D59))*Parametry!$C$15,0) -> 990 | L59: =ROUNDUP((Parametry!$C$21*MAX(1,D59))*Parametry!$C$15,0) -> 990 | M59: =ROUNDUP((Parametry!$C$21*MAX(1,D59))*Parametry!$C$15,0) -> 990 | N59: =ROUNDUP((Parametry!$C$21*MAX(1,D59))*Parametry!$C$15,0) -> 990 | O59: =ROUNDUP(J59/H59,0) -> 14 | P59: =ROUNDUP(K59/H59,0) -> 14 | Q59: =ROUNDUP(L59/H59,0) -> 14 | R59: =ROUNDUP(M59/H59,0) -> 14 | S59: =ROUNDUP(N59/H59,0) -> 14 | T59: =SUM(O59:S59) -> 70 | U59: =ROUNDUP(T59/G59,0) -> 12 | V59: =U59*Parametry!$C$11 -> 60 | W59: =2 -> 2 | X59: =V59*(W59-1) -> 60 | Y59: =V59*W59 -> 120 | Z59: =SUM(J59:N59) -> 4950 | AA59: Tylko ta budowa; 6 dostępnych po uwzględnieniu priorytetów; poziom magazynu=scenariusz L. Jeśli priorytety blokują dostawy, rzeczywiste ETA rośnie.
A60: Przystań | B60: 1→2 | C60: Bez kolejki | D60: 1 | E60: =D60+1 -> 2 | F60: 1 | G60: =Parametry!$C$12 -> 6 | H60: =ROUNDDOWN(Parametry!$C$9*Parametry!$C$10^(F60-1),0) -> 60 | I60: =ROUNDUP((Parametry!$C$22*MAX(1,D60))*1,0) -> 400 | J60: =ROUNDUP((Parametry!$C$22*MAX(1,D60))*1,0) -> 400 | K60: =ROUNDUP((Parametry!$C$22*MAX(1,D60))*1,0) -> 400 | L60: =ROUNDUP((Parametry!$C$22*MAX(1,D60))*1,0) -> 400 | M60: =ROUNDUP((Parametry!$C$22*MAX(1,D60))*1,0) -> 400 | N60: =ROUNDUP((Parametry!$C$22*MAX(1,D60))*1,0) -> 400 | O60: =ROUNDUP(J60/H60,0) -> 7 | P60: =ROUNDUP(K60/H60,0) -> 7 | Q60: =ROUNDUP(L60/H60,0) -> 7 | R60: =ROUNDUP(M60/H60,0) -> 7 | S60: =ROUNDUP(N60/H60,0) -> 7 | T60: =SUM(O60:S60) -> 35 | U60: =ROUNDUP(T60/G60,0) -> 6 | V60: =U60*Parametry!$C$11 -> 30 | W60: =2 -> 2 | X60: =V60*(W60-1) -> 30 | Y60: =V60*W60 -> 60 | Z60: =SUM(J60:N60) -> 2000 | AA60: Tylko ta budowa; 6 dostępnych po uwzględnieniu priorytetów; poziom magazynu=scenariusz L. Jeśli priorytety blokują dostawy, rzeczywiste ETA rośnie.
A61: Przystań | B61: 1→2 | C61: Kolejka +10% | D61: 1 | E61: =D61+1 -> 2 | F61: 1 | G61: =Parametry!$C$12 -> 6 | H61: =ROUNDDOWN(Parametry!$C$9*Parametry!$C$10^(F61-1),0) -> 60 | I61: =ROUNDUP((Parametry!$C$22*MAX(1,D61))*Parametry!$C$15,0) -> 440 | J61: =ROUNDUP((Parametry!$C$22*MAX(1,D61))*Parametry!$C$15,0) -> 440 | K61: =ROUNDUP((Parametry!$C$22*MAX(1,D61))*Parametry!$C$15,0) -> 440 | L61: =ROUNDUP((Parametry!$C$22*MAX(1,D61))*Parametry!$C$15,0) -> 440 | M61: =ROUNDUP((Parametry!$C$22*MAX(1,D61))*Parametry!$C$15,0) -> 440 | N61: =ROUNDUP((Parametry!$C$22*MAX(1,D61))*Parametry!$C$15,0) -> 440 | O61: =ROUNDUP(J61/H61,0) -> 8 | P61: =ROUNDUP(K61/H61,0) -> 8 | Q61: =ROUNDUP(L61/H61,0) -> 8 | R61: =ROUNDUP(M61/H61,0) -> 8 | S61: =ROUNDUP(N61/H61,0) -> 8 | T61: =SUM(O61:S61) -> 40 | U61: =ROUNDUP(T61/G61,0) -> 7 | V61: =U61*Parametry!$C$11 -> 35 | W61: =2 -> 2 | X61: =V61*(W61-1) -> 35 | Y61: =V61*W61 -> 70 | Z61: =SUM(J61:N61) -> 2200 | AA61: Tylko ta budowa; 6 dostępnych po uwzględnieniu priorytetów; poziom magazynu=scenariusz L. Jeśli priorytety blokują dostawy, rzeczywiste ETA rośnie.
A62: Przystań | B62: 2→3 | C62: Bez kolejki | D62: 2 | E62: =D62+1 -> 3 | F62: 2 | G62: =Parametry!$C$12 -> 6 | H62: =ROUNDDOWN(Parametry!$C$9*Parametry!$C$10^(F62-1),0) -> 66 | I62: =ROUNDUP((Parametry!$C$22*MAX(1,D62))*1,0) -> 800 | J62: =ROUNDUP((Parametry!$C$22*MAX(1,D62))*1,0) -> 800 | K62: =ROUNDUP((Parametry!$C$22*MAX(1,D62))*1,0) -> 800 | L62: =ROUNDUP((Parametry!$C$22*MAX(1,D62))*1,0) -> 800 | M62: =ROUNDUP((Parametry!$C$22*MAX(1,D62))*1,0) -> 800 | N62: =ROUNDUP((Parametry!$C$22*MAX(1,D62))*1,0) -> 800 | O62: =ROUNDUP(J62/H62,0) -> 13 | P62: =ROUNDUP(K62/H62,0) -> 13 | Q62: =ROUNDUP(L62/H62,0) -> 13 | R62: =ROUNDUP(M62/H62,0) -> 13 | S62: =ROUNDUP(N62/H62,0) -> 13 | T62: =SUM(O62:S62) -> 65 | U62: =ROUNDUP(T62/G62,0) -> 11 | V62: =U62*Parametry!$C$11 -> 55 | W62: =2 -> 2 | X62: =V62*(W62-1) -> 55 | Y62: =V62*W62 -> 110 | Z62: =SUM(J62:N62) -> 4000 | AA62: Tylko ta budowa; 6 dostępnych po uwzględnieniu priorytetów; poziom magazynu=scenariusz L. Jeśli priorytety blokują dostawy, rzeczywiste ETA rośnie.
A63: Przystań | B63: 2→3 | C63: Kolejka +10% | D63: 2 | E63: =D63+1 -> 3 | F63: 2 | G63: =Parametry!$C$12 -> 6 | H63: =ROUNDDOWN(Parametry!$C$9*Parametry!$C$10^(F63-1),0) -> 66 | I63: =ROUNDUP((Parametry!$C$22*MAX(1,D63))*Parametry!$C$15,0) -> 880 | J63: =ROUNDUP((Parametry!$C$22*MAX(1,D63))*Parametry!$C$15,0) -> 880 | K63: =ROUNDUP((Parametry!$C$22*MAX(1,D63))*Parametry!$C$15,0) -> 880 | L63: =ROUNDUP((Parametry!$C$22*MAX(1,D63))*Parametry!$C$15,0) -> 880 | M63: =ROUNDUP((Parametry!$C$22*MAX(1,D63))*Parametry!$C$15,0) -> 880 | N63: =ROUNDUP((Parametry!$C$22*MAX(1,D63))*Parametry!$C$15,0) -> 880 | O63: =ROUNDUP(J63/H63,0) -> 14 | P63: =ROUNDUP(K63/H63,0) -> 14 | Q63: =ROUNDUP(L63/H63,0) -> 14 | R63: =ROUNDUP(M63/H63,0) -> 14 | S63: =ROUNDUP(N63/H63,0) -> 14 | T63: =SUM(O63:S63) -> 70 | U63: =ROUNDUP(T63/G63,0) -> 12 | V63: =U63*Parametry!$C$11 -> 60 | W63: =2 -> 2 | X63: =V63*(W63-1) -> 60 | Y63: =V63*W63 -> 120 | Z63: =SUM(J63:N63) -> 4400 | AA63: Tylko ta budowa; 6 dostępnych po uwzględnieniu priorytetów; poziom magazynu=scenariusz L. Jeśli priorytety blokują dostawy, rzeczywiste ETA rośnie.
A64: Przystań | B64: 3→4 | C64: Bez kolejki | D64: 3 | E64: =D64+1 -> 4 | F64: 3 | G64: =Parametry!$C$12 -> 6 | H64: =ROUNDDOWN(Parametry!$C$9*Parametry!$C$10^(F64-1),0) -> 72 | I64: =ROUNDUP((Parametry!$C$22*MAX(1,D64))*1,0) -> 1200 | J64: =ROUNDUP((Parametry!$C$22*MAX(1,D64))*1,0) -> 1200 | K64: =ROUNDUP((Parametry!$C$22*MAX(1,D64))*1,0) -> 1200 | L64: =ROUNDUP((Parametry!$C$22*MAX(1,D64))*1,0) -> 1200 | M64: =ROUNDUP((Parametry!$C$22*MAX(1,D64))*1,0) -> 1200 | N64: =ROUNDUP((Parametry!$C$22*MAX(1,D64))*1,0) -> 1200 | O64: =ROUNDUP(J64/H64,0) -> 17 | P64: =ROUNDUP(K64/H64,0) -> 17 | Q64: =ROUNDUP(L64/H64,0) -> 17 | R64: =ROUNDUP(M64/H64,0) -> 17 | S64: =ROUNDUP(N64/H64,0) -> 17 | T64: =SUM(O64:S64) -> 85 | U64: =ROUNDUP(T64/G64,0) -> 15 | V64: =U64*Parametry!$C$11 -> 75 | W64: =2 -> 2 | X64: =V64*(W64-1) -> 75 | Y64: =V64*W64 -> 150 | Z64: =SUM(J64:N64) -> 6000 | AA64: Tylko ta budowa; 6 dostępnych po uwzględnieniu priorytetów; poziom magazynu=scenariusz L. Jeśli priorytety blokują dostawy, rzeczywiste ETA rośnie.
A65: Przystań | B65: 3→4 | C65: Kolejka +10% | D65: 3 | E65: =D65+1 -> 4 | F65: 3 | G65: =Parametry!$C$12 -> 6 | H65: =ROUNDDOWN(Parametry!$C$9*Parametry!$C$10^(F65-1),0) -> 72 | I65: =ROUNDUP((Parametry!$C$22*MAX(1,D65))*Parametry!$C$15,0) -> 1320 | J65: =ROUNDUP((Parametry!$C$22*MAX(1,D65))*Parametry!$C$15,0) -> 1320 | K65: =ROUNDUP((Parametry!$C$22*MAX(1,D65))*Parametry!$C$15,0) -> 1320 | L65: =ROUNDUP((Parametry!$C$22*MAX(1,D65))*Parametry!$C$15,0) -> 1320 | M65: =ROUNDUP((Parametry!$C$22*MAX(1,D65))*Parametry!$C$15,0) -> 1320 | N65: =ROUNDUP((Parametry!$C$22*MAX(1,D65))*Parametry!$C$15,0) -> 1320 | O65: =ROUNDUP(J65/H65,0) -> 19 | P65: =ROUNDUP(K65/H65,0) -> 19 | Q65: =ROUNDUP(L65/H65,0) -> 19 | R65: =ROUNDUP(M65/H65,0) -> 19 | S65: =ROUNDUP(N65/H65,0) -> 19 | T65: =SUM(O65:S65) -> 95 | U65: =ROUNDUP(T65/G65,0) -> 16 | V65: =U65*Parametry!$C$11 -> 80 | W65: =2 -> 2 | X65: =V65*(W65-1) -> 80 | Y65: =V65*W65 -> 160 | Z65: =SUM(J65:N65) -> 6600 | AA65: Tylko ta budowa; 6 dostępnych po uwzględnieniu priorytetów; poziom magazynu=scenariusz L. Jeśli priorytety blokują dostawy, rzeczywiste ETA rośnie.
A66: Kaplica | B66: 1→2 | C66: Bez kolejki | D66: 1 | E66: =D66+1 -> 2 | F66: 1 | G66: =Parametry!$C$12 -> 6 | H66: =ROUNDDOWN(Parametry!$C$9*Parametry!$C$10^(F66-1),0) -> 60 | I66: =ROUNDUP((180*E66)*1,0) -> 360 | J66: =ROUNDUP((20*E66)*1,0) -> 40 | K66: =ROUNDUP((60*E66)*1,0) -> 120 | L66: =ROUNDUP((0*E66)*1,0) -> 0 | M66: =ROUNDUP((0*E66)*1,0) -> 0 | N66: =ROUNDUP((10*E66)*1,0) -> 20 | O66: =ROUNDUP(J66/H66,0) -> 1 | P66: =ROUNDUP(K66/H66,0) -> 2 | Q66: =ROUNDUP(L66/H66,0) -> 0 | R66: =ROUNDUP(M66/H66,0) -> 0 | S66: =ROUNDUP(N66/H66,0) -> 1 | T66: =SUM(O66:S66) -> 4 | U66: =ROUNDUP(T66/G66,0) -> 1 | V66: =U66*Parametry!$C$11 -> 5 | W66: =1+3*(E66-1) -> 4 | X66: =V66*(W66-1) -> 15 | Y66: =V66*W66 -> 20 | Z66: =SUM(J66:N66) -> 180 | AA66: Tylko ta budowa; 6 dostępnych po uwzględnieniu priorytetów; poziom magazynu=scenariusz L. Jeśli priorytety blokują dostawy, rzeczywiste ETA rośnie.
A67: Kaplica | B67: 1→2 | C67: Kolejka +10% | D67: 1 | E67: =D67+1 -> 2 | F67: 1 | G67: =Parametry!$C$12 -> 6 | H67: =ROUNDDOWN(Parametry!$C$9*Parametry!$C$10^(F67-1),0) -> 60 | I67: =ROUNDUP((180*E67)*Parametry!$C$15,0) -> 396 | J67: =ROUNDUP((20*E67)*Parametry!$C$15,0) -> 44 | K67: =ROUNDUP((60*E67)*Parametry!$C$15,0) -> 132 | L67: =ROUNDUP((0*E67)*Parametry!$C$15,0) -> 0 | M67: =ROUNDUP((0*E67)*Parametry!$C$15,0) -> 0 | N67: =ROUNDUP((10*E67)*Parametry!$C$15,0) -> 22 | O67: =ROUNDUP(J67/H67,0) -> 1 | P67: =ROUNDUP(K67/H67,0) -> 3 | Q67: =ROUNDUP(L67/H67,0) -> 0 | R67: =ROUNDUP(M67/H67,0) -> 0 | S67: =ROUNDUP(N67/H67,0) -> 1 | T67: =SUM(O67:S67) -> 5 | U67: =ROUNDUP(T67/G67,0) -> 1 | V67: =U67*Parametry!$C$11 -> 5 | W67: =1+3*(E67-1) -> 4 | X67: =V67*(W67-1) -> 15 | Y67: =V67*W67 -> 20 | Z67: =SUM(J67:N67) -> 198 | AA67: Tylko ta budowa; 6 dostępnych po uwzględnieniu priorytetów; poziom magazynu=scenariusz L. Jeśli priorytety blokują dostawy, rzeczywiste ETA rośnie.
A68: Kaplica | B68: 2→3 | C68: Bez kolejki | D68: 2 | E68: =D68+1 -> 3 | F68: 2 | G68: =Parametry!$C$12 -> 6 | H68: =ROUNDDOWN(Parametry!$C$9*Parametry!$C$10^(F68-1),0) -> 66 | I68: =ROUNDUP((180*E68)*1,0) -> 540 | J68: =ROUNDUP((20*E68)*1,0) -> 60 | K68: =ROUNDUP((60*E68)*1,0) -> 180 | L68: =ROUNDUP((0*E68)*1,0) -> 0 | M68: =ROUNDUP((0*E68)*1,0) -> 0 | N68: =ROUNDUP((10*E68)*1,0) -> 30 | O68: =ROUNDUP(J68/H68,0) -> 1 | P68: =ROUNDUP(K68/H68,0) -> 3 | Q68: =ROUNDUP(L68/H68,0) -> 0 | R68: =ROUNDUP(M68/H68,0) -> 0 | S68: =ROUNDUP(N68/H68,0) -> 1 | T68: =SUM(O68:S68) -> 5 | U68: =ROUNDUP(T68/G68,0) -> 1 | V68: =U68*Parametry!$C$11 -> 5 | W68: =1+3*(E68-1) -> 7 | X68: =V68*(W68-1) -> 30 | Y68: =V68*W68 -> 35 | Z68: =SUM(J68:N68) -> 270 | AA68: Tylko ta budowa; 6 dostępnych po uwzględnieniu priorytetów; poziom magazynu=scenariusz L. Jeśli priorytety blokują dostawy, rzeczywiste ETA rośnie.
A69: Kaplica | B69: 2→3 | C69: Kolejka +10% | D69: 2 | E69: =D69+1 -> 3 | F69: 2 | G69: =Parametry!$C$12 -> 6 | H69: =ROUNDDOWN(Parametry!$C$9*Parametry!$C$10^(F69-1),0) -> 66 | I69: =ROUNDUP((180*E69)*Parametry!$C$15,0) -> 594 | J69: =ROUNDUP((20*E69)*Parametry!$C$15,0) -> 66 | K69: =ROUNDUP((60*E69)*Parametry!$C$15,0) -> 198 | L69: =ROUNDUP((0*E69)*Parametry!$C$15,0) -> 0 | M69: =ROUNDUP((0*E69)*Parametry!$C$15,0) -> 0 | N69: =ROUNDUP((10*E69)*Parametry!$C$15,0) -> 33 | O69: =ROUNDUP(J69/H69,0) -> 1 | P69: =ROUNDUP(K69/H69,0) -> 3 | Q69: =ROUNDUP(L69/H69,0) -> 0 | R69: =ROUNDUP(M69/H69,0) -> 0 | S69: =ROUNDUP(N69/H69,0) -> 1 | T69: =SUM(O69:S69) -> 5 | U69: =ROUNDUP(T69/G69,0) -> 1 | V69: =U69*Parametry!$C$11 -> 5 | W69: =1+3*(E69-1) -> 7 | X69: =V69*(W69-1) -> 30 | Y69: =V69*W69 -> 35 | Z69: =SUM(J69:N69) -> 297 | AA69: Tylko ta budowa; 6 dostępnych po uwzględnieniu priorytetów; poziom magazynu=scenariusz L. Jeśli priorytety blokują dostawy, rzeczywiste ETA rośnie.
A70: Kaplica | B70: 3→4 | C70: Bez kolejki | D70: 3 | E70: =D70+1 -> 4 | F70: 3 | G70: =Parametry!$C$12 -> 6 | H70: =ROUNDDOWN(Parametry!$C$9*Parametry!$C$10^(F70-1),0) -> 72 | I70: =ROUNDUP((180*E70)*1,0) -> 720 | J70: =ROUNDUP((20*E70)*1,0) -> 80 | K70: =ROUNDUP((60*E70)*1,0) -> 240 | L70: =ROUNDUP((0*E70)*1,0) -> 0 | M70: =ROUNDUP((0*E70)*1,0) -> 0 | N70: =ROUNDUP((10*E70)*1,0) -> 40 | O70: =ROUNDUP(J70/H70,0) -> 2 | P70: =ROUNDUP(K70/H70,0) -> 4 | Q70: =ROUNDUP(L70/H70,0) -> 0 | R70: =ROUNDUP(M70/H70,0) -> 0 | S70: =ROUNDUP(N70/H70,0) -> 1 | T70: =SUM(O70:S70) -> 7 | U70: =ROUNDUP(T70/G70,0) -> 2 | V70: =U70*Parametry!$C$11 -> 10 | W70: =1+3*(E70-1) -> 10 | X70: =V70*(W70-1) -> 90 | Y70: =V70*W70 -> 100 | Z70: =SUM(J70:N70) -> 360 | AA70: Tylko ta budowa; 6 dostępnych po uwzględnieniu priorytetów; poziom magazynu=scenariusz L. Jeśli priorytety blokują dostawy, rzeczywiste ETA rośnie.
A71: Kaplica | B71: 3→4 | C71: Kolejka +10% | D71: 3 | E71: =D71+1 -> 4 | F71: 3 | G71: =Parametry!$C$12 -> 6 | H71: =ROUNDDOWN(Parametry!$C$9*Parametry!$C$10^(F71-1),0) -> 72 | I71: =ROUNDUP((180*E71)*Parametry!$C$15,0) -> 792 | J71: =ROUNDUP((20*E71)*Parametry!$C$15,0) -> 88 | K71: =ROUNDUP((60*E71)*Parametry!$C$15,0) -> 264 | L71: =ROUNDUP((0*E71)*Parametry!$C$15,0) -> 0 | M71: =ROUNDUP((0*E71)*Parametry!$C$15,0) -> 0 | N71: =ROUNDUP((10*E71)*Parametry!$C$15,0) -> 44 | O71: =ROUNDUP(J71/H71,0) -> 2 | P71: =ROUNDUP(K71/H71,0) -> 4 | Q71: =ROUNDUP(L71/H71,0) -> 0 | R71: =ROUNDUP(M71/H71,0) -> 0 | S71: =ROUNDUP(N71/H71,0) -> 1 | T71: =SUM(O71:S71) -> 7 | U71: =ROUNDUP(T71/G71,0) -> 2 | V71: =U71*Parametry!$C$11 -> 10 | W71: =1+3*(E71-1) -> 10 | X71: =V71*(W71-1) -> 90 | Y71: =V71*W71 -> 100 | Z71: =SUM(J71:N71) -> 396 | AA71: Tylko ta budowa; 6 dostępnych po uwzględnieniu priorytetów; poziom magazynu=scenariusz L. Jeśli priorytety blokują dostawy, rzeczywiste ETA rośnie.
A72: Latarnia | B72: 1→2 | C72: Bez kolejki | D72: 1 | E72: =D72+1 -> 2 | F72: 1 | G72: =Parametry!$C$12 -> 6 | H72: =ROUNDDOWN(Parametry!$C$9*Parametry!$C$10^(F72-1),0) -> 60 | I72: =ROUNDUP((Parametry!$C$23*MAX(1,D72))*1,0) -> 500 | J72: =ROUNDUP((Parametry!$C$23*MAX(1,D72))*1,0) -> 500 | K72: =ROUNDUP((Parametry!$C$23*MAX(1,D72))*1,0) -> 500 | L72: =ROUNDUP((Parametry!$C$23*MAX(1,D72))*1,0) -> 500 | M72: =ROUNDUP((Parametry!$C$23*MAX(1,D72))*1,0) -> 500 | N72: =ROUNDUP((Parametry!$C$23*MAX(1,D72))*1,0) -> 500 | O72: =ROUNDUP(J72/H72,0) -> 9 | P72: =ROUNDUP(K72/H72,0) -> 9 | Q72: =ROUNDUP(L72/H72,0) -> 9 | R72: =ROUNDUP(M72/H72,0) -> 9 | S72: =ROUNDUP(N72/H72,0) -> 9 | T72: =SUM(O72:S72) -> 45 | U72: =ROUNDUP(T72/G72,0) -> 8 | V72: =U72*Parametry!$C$11 -> 40 | W72: =5 -> 5 | X72: =V72*(W72-1) -> 160 | Y72: =V72*W72 -> 200 | Z72: =SUM(J72:N72) -> 2500 | AA72: Tylko ta budowa; 6 dostępnych po uwzględnieniu priorytetów; poziom magazynu=scenariusz L. Jeśli priorytety blokują dostawy, rzeczywiste ETA rośnie.
A73: Latarnia | B73: 1→2 | C73: Kolejka +10% | D73: 1 | E73: =D73+1 -> 2 | F73: 1 | G73: =Parametry!$C$12 -> 6 | H73: =ROUNDDOWN(Parametry!$C$9*Parametry!$C$10^(F73-1),0) -> 60 | I73: =ROUNDUP((Parametry!$C$23*MAX(1,D73))*Parametry!$C$15,0) -> 550 | J73: =ROUNDUP((Parametry!$C$23*MAX(1,D73))*Parametry!$C$15,0) -> 550 | K73: =ROUNDUP((Parametry!$C$23*MAX(1,D73))*Parametry!$C$15,0) -> 550 | L73: =ROUNDUP((Parametry!$C$23*MAX(1,D73))*Parametry!$C$15,0) -> 550 | M73: =ROUNDUP((Parametry!$C$23*MAX(1,D73))*Parametry!$C$15,0) -> 550 | N73: =ROUNDUP((Parametry!$C$23*MAX(1,D73))*Parametry!$C$15,0) -> 550 | O73: =ROUNDUP(J73/H73,0) -> 10 | P73: =ROUNDUP(K73/H73,0) -> 10 | Q73: =ROUNDUP(L73/H73,0) -> 10 | R73: =ROUNDUP(M73/H73,0) -> 10 | S73: =ROUNDUP(N73/H73,0) -> 10 | T73: =SUM(O73:S73) -> 50 | U73: =ROUNDUP(T73/G73,0) -> 9 | V73: =U73*Parametry!$C$11 -> 45 | W73: =5 -> 5 | X73: =V73*(W73-1) -> 180 | Y73: =V73*W73 -> 225 | Z73: =SUM(J73:N73) -> 2750 | AA73: Tylko ta budowa; 6 dostępnych po uwzględnieniu priorytetów; poziom magazynu=scenariusz L. Jeśli priorytety blokują dostawy, rzeczywiste ETA rośnie.
A74: Latarnia | B74: 2→3 | C74: Bez kolejki | D74: 2 | E74: =D74+1 -> 3 | F74: 2 | G74: =Parametry!$C$12 -> 6 | H74: =ROUNDDOWN(Parametry!$C$9*Parametry!$C$10^(F74-1),0) -> 66 | I74: =ROUNDUP((Parametry!$C$23*MAX(1,D74))*1,0) -> 1000 | J74: =ROUNDUP((Parametry!$C$23*MAX(1,D74))*1,0) -> 1000 | K74: =ROUNDUP((Parametry!$C$23*MAX(1,D74))*1,0) -> 1000 | L74: =ROUNDUP((Parametry!$C$23*MAX(1,D74))*1,0) -> 1000 | M74: =ROUNDUP((Parametry!$C$23*MAX(1,D74))*1,0) -> 1000 | N74: =ROUNDUP((Parametry!$C$23*MAX(1,D74))*1,0) -> 1000 | O74: =ROUNDUP(J74/H74,0) -> 16 | P74: =ROUNDUP(K74/H74,0) -> 16 | Q74: =ROUNDUP(L74/H74,0) -> 16 | R74: =ROUNDUP(M74/H74,0) -> 16 | S74: =ROUNDUP(N74/H74,0) -> 16 | T74: =SUM(O74:S74) -> 80 | U74: =ROUNDUP(T74/G74,0) -> 14 | V74: =U74*Parametry!$C$11 -> 70 | W74: =5 -> 5 | X74: =V74*(W74-1) -> 280 | Y74: =V74*W74 -> 350 | Z74: =SUM(J74:N74) -> 5000 | AA74: Tylko ta budowa; 6 dostępnych po uwzględnieniu priorytetów; poziom magazynu=scenariusz L. Jeśli priorytety blokują dostawy, rzeczywiste ETA rośnie.
A75: Latarnia | B75: 2→3 | C75: Kolejka +10% | D75: 2 | E75: =D75+1 -> 3 | F75: 2 | G75: =Parametry!$C$12 -> 6 | H75: =ROUNDDOWN(Parametry!$C$9*Parametry!$C$10^(F75-1),0) -> 66 | I75: =ROUNDUP((Parametry!$C$23*MAX(1,D75))*Parametry!$C$15,0) -> 1100 | J75: =ROUNDUP((Parametry!$C$23*MAX(1,D75))*Parametry!$C$15,0) -> 1100 | K75: =ROUNDUP((Parametry!$C$23*MAX(1,D75))*Parametry!$C$15,0) -> 1100 | L75: =ROUNDUP((Parametry!$C$23*MAX(1,D75))*Parametry!$C$15,0) -> 1100 | M75: =ROUNDUP((Parametry!$C$23*MAX(1,D75))*Parametry!$C$15,0) -> 1100 | N75: =ROUNDUP((Parametry!$C$23*MAX(1,D75))*Parametry!$C$15,0) -> 1100 | O75: =ROUNDUP(J75/H75,0) -> 17 | P75: =ROUNDUP(K75/H75,0) -> 17 | Q75: =ROUNDUP(L75/H75,0) -> 17 | R75: =ROUNDUP(M75/H75,0) -> 17 | S75: =ROUNDUP(N75/H75,0) -> 17 | T75: =SUM(O75:S75) -> 85 | U75: =ROUNDUP(T75/G75,0) -> 15 | V75: =U75*Parametry!$C$11 -> 75 | W75: =5 -> 5 | X75: =V75*(W75-1) -> 300 | Y75: =V75*W75 -> 375 | Z75: =SUM(J75:N75) -> 5500 | AA75: Tylko ta budowa; 6 dostępnych po uwzględnieniu priorytetów; poziom magazynu=scenariusz L. Jeśli priorytety blokują dostawy, rzeczywiste ETA rośnie.
A76: Latarnia | B76: 3→4 | C76: Bez kolejki | D76: 3 | E76: =D76+1 -> 4 | F76: 3 | G76: =Parametry!$C$12 -> 6 | H76: =ROUNDDOWN(Parametry!$C$9*Parametry!$C$10^(F76-1),0) -> 72 | I76: =ROUNDUP((Parametry!$C$23*MAX(1,D76))*1,0) -> 1500 | J76: =ROUNDUP((Parametry!$C$23*MAX(1,D76))*1,0) -> 1500 | K76: =ROUNDUP((Parametry!$C$23*MAX(1,D76))*1,0) -> 1500 | L76: =ROUNDUP((Parametry!$C$23*MAX(1,D76))*1,0) -> 1500 | M76: =ROUNDUP((Parametry!$C$23*MAX(1,D76))*1,0) -> 1500 | N76: =ROUNDUP((Parametry!$C$23*MAX(1,D76))*1,0) -> 1500 | O76: =ROUNDUP(J76/H76,0) -> 21 | P76: =ROUNDUP(K76/H76,0) -> 21 | Q76: =ROUNDUP(L76/H76,0) -> 21 | R76: =ROUNDUP(M76/H76,0) -> 21 | S76: =ROUNDUP(N76/H76,0) -> 21 | T76: =SUM(O76:S76) -> 105 | U76: =ROUNDUP(T76/G76,0) -> 18 | V76: =U76*Parametry!$C$11 -> 90 | W76: =5 -> 5 | X76: =V76*(W76-1) -> 360 | Y76: =V76*W76 -> 450 | Z76: =SUM(J76:N76) -> 7500 | AA76: Tylko ta budowa; 6 dostępnych po uwzględnieniu priorytetów; poziom magazynu=scenariusz L. Jeśli priorytety blokują dostawy, rzeczywiste ETA rośnie.
A77: Latarnia | B77: 3→4 | C77: Kolejka +10% | D77: 3 | E77: =D77+1 -> 4 | F77: 3 | G77: =Parametry!$C$12 -> 6 | H77: =ROUNDDOWN(Parametry!$C$9*Parametry!$C$10^(F77-1),0) -> 72 | I77: =ROUNDUP((Parametry!$C$23*MAX(1,D77))*Parametry!$C$15,0) -> 1650 | J77: =ROUNDUP((Parametry!$C$23*MAX(1,D77))*Parametry!$C$15,0) -> 1650 | K77: =ROUNDUP((Parametry!$C$23*MAX(1,D77))*Parametry!$C$15,0) -> 1650 | L77: =ROUNDUP((Parametry!$C$23*MAX(1,D77))*Parametry!$C$15,0) -> 1650 | M77: =ROUNDUP((Parametry!$C$23*MAX(1,D77))*Parametry!$C$15,0) -> 1650 | N77: =ROUNDUP((Parametry!$C$23*MAX(1,D77))*Parametry!$C$15,0) -> 1650 | O77: =ROUNDUP(J77/H77,0) -> 23 | P77: =ROUNDUP(K77/H77,0) -> 23 | Q77: =ROUNDUP(L77/H77,0) -> 23 | R77: =ROUNDUP(M77/H77,0) -> 23 | S77: =ROUNDUP(N77/H77,0) -> 23 | T77: =SUM(O77:S77) -> 115 | U77: =ROUNDUP(T77/G77,0) -> 20 | V77: =U77*Parametry!$C$11 -> 100 | W77: =5 -> 5 | X77: =V77*(W77-1) -> 400 | Y77: =V77*W77 -> 500 | Z77: =SUM(J77:N77) -> 8250 | AA77: Tylko ta budowa; 6 dostępnych po uwzględnieniu priorytetów; poziom magazynu=scenariusz L. Jeśli priorytety blokują dostawy, rzeczywiste ETA rośnie.
A78: Latarnia | B78: 0→1 | C78: Bez kolejki | D78: 0 | E78: =D78+1 -> 1 | F78: 1 | G78: =Parametry!$C$12 -> 6 | H78: =ROUNDDOWN(Parametry!$C$9*Parametry!$C$10^(F78-1),0) -> 60 | I78: =ROUNDUP((Parametry!$C$23*MAX(1,D78))*1,0) -> 500 | J78: =ROUNDUP((Parametry!$C$23*MAX(1,D78))*1,0) -> 500 | K78: =ROUNDUP((Parametry!$C$23*MAX(1,D78))*1,0) -> 500 | L78: =ROUNDUP((Parametry!$C$23*MAX(1,D78))*1,0) -> 500 | M78: =ROUNDUP((Parametry!$C$23*MAX(1,D78))*1,0) -> 500 | N78: =ROUNDUP((Parametry!$C$23*MAX(1,D78))*1,0) -> 500 | O78: =ROUNDUP(J78/H78,0) -> 9 | P78: =ROUNDUP(K78/H78,0) -> 9 | Q78: =ROUNDUP(L78/H78,0) -> 9 | R78: =ROUNDUP(M78/H78,0) -> 9 | S78: =ROUNDUP(N78/H78,0) -> 9 | T78: =SUM(O78:S78) -> 45 | U78: =ROUNDUP(T78/G78,0) -> 8 | V78: =U78*Parametry!$C$11 -> 40 | W78: =5 -> 5 | X78: =V78*(W78-1) -> 160 | Y78: =V78*W78 -> 200 | Z78: =SUM(J78:N78) -> 2500 | AA78: Tylko ta budowa; 6 dostępnych po uwzględnieniu priorytetów; poziom magazynu=scenariusz L. Jeśli priorytety blokują dostawy, rzeczywiste ETA rośnie.
A79: Latarnia | B79: 0→1 | C79: Kolejka +10% | D79: 0 | E79: =D79+1 -> 1 | F79: 1 | G79: =Parametry!$C$12 -> 6 | H79: =ROUNDDOWN(Parametry!$C$9*Parametry!$C$10^(F79-1),0) -> 60 | I79: =ROUNDUP((Parametry!$C$23*MAX(1,D79))*Parametry!$C$15,0) -> 550 | J79: =ROUNDUP((Parametry!$C$23*MAX(1,D79))*Parametry!$C$15,0) -> 550 | K79: =ROUNDUP((Parametry!$C$23*MAX(1,D79))*Parametry!$C$15,0) -> 550 | L79: =ROUNDUP((Parametry!$C$23*MAX(1,D79))*Parametry!$C$15,0) -> 550 | M79: =ROUNDUP((Parametry!$C$23*MAX(1,D79))*Parametry!$C$15,0) -> 550 | N79: =ROUNDUP((Parametry!$C$23*MAX(1,D79))*Parametry!$C$15,0) -> 550 | O79: =ROUNDUP(J79/H79,0) -> 10 | P79: =ROUNDUP(K79/H79,0) -> 10 | Q79: =ROUNDUP(L79/H79,0) -> 10 | R79: =ROUNDUP(M79/H79,0) -> 10 | S79: =ROUNDUP(N79/H79,0) -> 10 | T79: =SUM(O79:S79) -> 50 | U79: =ROUNDUP(T79/G79,0) -> 9 | V79: =U79*Parametry!$C$11 -> 45 | W79: =5 -> 5 | X79: =V79*(W79-1) -> 180 | Y79: =V79*W79 -> 225 | Z79: =SUM(J79:N79) -> 2750 | AA79: Tylko ta budowa; 6 dostępnych po uwzględnieniu priorytetów; poziom magazynu=scenariusz L. Jeśli priorytety blokują dostawy, rzeczywiste ETA rośnie.

Sheet Transport i priorytety
A1: LOGISTYKA • ujednolicone nowe zasady
A2: Źródło: Twoje wpisy w K13/K14/K15 oraz odpowiedzi. Nie wdrażamy niczego w grze. Czas offline i paczki transportowe zastępują dawny model godzinowy i zatrzymywanie po wylogowaniu.
A5: Obszar | B5: Zasada | C5: Uwaga | D5: Status
A6: Kurs | B6: Pełny kurs z powrotem 5 min. Każdy tragarz niesie tylko 1 rodzaj. Ładunek bazowo 60, rośnie z poziomem własnego magazynu/targu/portu. | C6: Nie wolno liczyć ceil(sumy materiałów/C); liczymy SUMĘ ceil(każdy rodzaj/C). | D6: POTWIERDZONE
A7: Niepełny ładunek | B7: Towar pobiera od razu; nie czeka, aż uzbiera pełny ładunek C. 100 szt. przy C=60 wymaga 2 kursów: 60+40. | C7: Gotowe zasoby w estymacie; przy rzeczywistej produkcji częściowe kursy mogą zwiększyć ich liczbę. | D7: POTWIERDZONE
A8: Droga przetwórstwa | B8: Zboże i drewno zawsze przez magazyn centralny przed zużyciem przez młyn/tartak. | C8: Nie ma darmowego bezpośredniego bufora farma→młyn lub drwale→tartak. | D8: POTWIERDZONE
A9: Rezerwa żywności | B9: 50 × poziom magazynu na potrzeby ludzi. Wysyłka/rezerwacja nieżywieniowa chroni to minimum; ludzie mogą je zjadać. | C9: Sam bufor nie gwarantuje braku głodu; estymaty zakładają nakarmioną obsadę. | D9: NOWE
A10: Ratunkowy tragarz Food | B10: 1 tragarz ma nosić Food, jeśli jest gotowy i centrala poniżej progu. | C10: Notatka mówi <50, podczas gdy nowe minimum to 50 × L. Robocze ujednolicenie: próg 50 × L; do potwierdzenia. Przy 0 tragarzy nie tworzymy nowej osoby. | D10: SZCZEGÓŁ DO DECYZJI
A11: Domyślne priorytety | B11: Najpierw zaopatrzenie centralnego magazynu, potem dostawy na budowy. | C11: Gracz może zmienić kolejność i nadać priorytet konkretnemu gospodarstwu lub budowie. | D11: POTWIERDZONE
A12: ETA budowy | B12: Pokazuje wymagane/dostarczone materiały, np. 60/100, oraz estymatę transportu i budowy przy aktualnych priorytetach. | C12: 6 tragarzy w kalkulatorze oznacza 6 dostępnych DO TEGO ZLECENIA, nie całkowitą obsadę magazynu. | D12: POTWIERDZONE
A13: Targ | B13: Tylko własna załoga nosi w obie strony: centrala → targ i targ → centrala. | C13: Każda dostawa zablokowana 1 h; zapas wygasa 24 h po przyniesieniu, wynik wymiany ma nowe 24 h. | D13: NOWE / UJEDNOLICONE
A14: Port-sprzedaż | B14: Centrala → port: pierwszy cykl; port → statek: drugi taki sam. Własna załoga, według zasad magazynu. | C14: Pojemność statku=pojemność portu. Przy wypłynięciu notyfikacja i zapłata do skarbca. | D14: POTWIERDZONE
A15: Port-zakup | B15: Gdy statek przypływa następuje zapłata, potem rozładunek i transport własną załogą do centrali. | C15: Towar w porcie nie jest jeszcze dostępny do jedzenia ani budowy. Rezerwowanie monet przed rejsem i czas rejsu są nieokreślone. | D15: TRASA POTWIERDZONA; SZCZEGÓŁY OTWARTE
A16: Port-wygaśnięcie | B16: Towar nieodebrany po 24 h przepada. To zastępuje poprzednie 10 monet za składowanie. | C16: Śledzić czas oddzielnych partii; terminy zegarowe działają offline. | D16: POTWIERDZONE
... A19: Offline | B19: Wszystkie mechaniki działają według czasu zegarowego również po zamknięciu karty. | C19: Produkcja, transport, jedzenie, podatki, szczęście, populacja, budowa, port/targ i premie. Nie używamy już zasady ukryta karta=stop. | D19: POTWIERDZONE W ROZMOWIE

Sheet Parametry
A1: PARAMETRY V2 • aktualne liczby i jednostki
A2: Niebieskie wartości edytowalne. Wszystkie zegary gospodarki działają również offline. +10% ładunku roboczo składane i zaokrąglone w dół do całych sztuk; koszt kolejki osobno w górę. Estymaty tylko transport+budowa.
A5: ID | B5: Parametr | C5: Wartość | D5: Jednostka | E5: Status | F5: Uwagi
A6: people_start | B6: Ludzie na starcie | C6: 12 | D6: osób | E6: AKTUALNE | F6: W domu, wolni; wszystkie 6 zasobów po 100.
A7: town_cap | B7: Populacja / poziom ratusza | C7: 24 | D7: osób | E7: AKTUALNE | F7: Dom osobno daje 24 miejsc/poziom.
A8: job_cap | B8: Limit pracy / poziom własnego budynku | C8: 12 | D8: osób | E8: POTWIERDZONE W V1 | F8: Limit 12×poziom miejsca pracy, z jednej puli faktycznie wolnych ludzi.
A9: capacity | B9: Ładunek tragarza na poziomie 1 | C9: 60 | D9: szt./kurs | E9: POTWIERDZONE | F9: Jeden rodzaj towaru; nie 60 szt./h.
A10: capacity_growth | B10: Mnożnik ładunku na kolejny poziom | C10: 1.1 | D10: mnożnik | E10: WZROST POTWIERDZONY | F10: Roboczo wzrost składany, pojemność całkowita FLOOR; 60,66,72…
A11: trip | B11: Pełny kurs, z powrotem | C11: 5 | D11: min | E11: POTWIERDZONE W ROZMOWIE | F11: Wszystkie odległości; częściowy ładunek dopuszczalny, bez czekania na pełny.
A12: crew | B12: Dostępni dla danej budowy tragarze | C12: 6 | D12: osób | E12: ZAŁOŻENIE ESTYMATY | F12: Po odjęciu pilniejszych zadań i ratunkowych dostaw Food; edytowalne.
A13: reserve | B13: Rezerwa Food / poziom magazynu | C13: 50 | D13: Food/poziom | E13: NOWE POTWIERDZONE | F13: Rezerwa 50 × poziom magazynu. Ludzie mogą ją zjadać.
A14: travel | B14: Droga człowieka do pracy / do domu | C14: 5 | D14: min/odcinek | E14: POTWIERDZONE W V1 | F14: W drodze nie pracuje; 5 min w każdą stronę.
A15: queue | B15: Dopłata do zlecenia w kolejce | C15: 1.1 | D15: mnożnik kosztu | E15: NOWE POTWIERDZONE | F15: Obejmuje całą cenę; każdy składnik zaokrąglony w górę — interpretacja dla całych zasobów.
A16: norm | B16: Norma kosztu producenta | C16: 240 | D16: szt./dobę×L | E16: AKTUALNE | F16: 30%drewna, 30%kamienia, 50%produktu; norma cenowa nie realna produkcja.
A17: wood_share | B17: Drewno: udział normy | C17: 0.3 | D17: udział | E17: AKTUALNE | F17: Sumuje się z własnym produktem drwali.
... A51: ad_code | B51: Czas pokazania przekazu | C51: 1 | D51: sekunda | E51: UZGODNIONE | F51: Sposób wpisania i jego wpływ na nagrodę do opisania później.

Sheet Decyzje i konflikty
A1: DECYZJE V2 • co ustalone, co nadal otwarte
A2: Wszystkie odpowiedzi uwzględniono. Zamknięte pytania nie wracają jako alarmy. Niejednoznaczne szczegóły zostały jawnie oznaczone, bez wybierania za gracza. Dane z pliku 1 są archiwizowane.
A5: ID | B5: Stan | C5: Temat | D5: Wynik / zasada | E5: Uwagi / pytanie
A6: Q01 | B6: ROZSTRZYGNIĘTE | C6: Wydajność | D6: Dokładnie 10, 12, 13, 14… | E6: Potwierdzenie w rozmowie; nie +10% produkcji.
A7: Q02 | B7: ROZSTRZYGNIĘTE | C7: Latarnia | D7: 5T=T+4T | E7: Potwierdzenie w rozmowie.
A8: Q03 | B8: ROZSTRZYGNIĘTE | C8: Kaplica | D8: T + 3T × (N−1), N = nowy poziom: 4T, 7T, 10T | E8: Potwierdzenie w rozmowie.
A9: Q04 | B9: ROZSTRZYGNIĘTE | C9: Kurs | D9: 5 min — pełny kurs z powrotem | E9: Nie ma dodatkowego powrotu; 5 min jest całym cyklem.
A10: Q05 | B10: ROZSTRZYGNIĘTE | C10: Ceny | D10: 140/150 w PORCIE; TARG bez monet | E10: Ostatnia korekta zastępuje pierwszą odpowiedź.
A11: Q06 | B11: ROZSTRZYGNIĘTE | C11: Offline | D11: Cała gospodarka działa zegarowo również offline | E11: Także jedzenie, podatki, szczęście i demografia.
A12: Q07 | B12: DO DOPRECYZOWANIA | C12: Zablokowany producent | D12: Dodana kara za brak pracy | E12: Czy znika bonus +1 za pracę i podatek? Czy kara −5/h zaczyna działać po 12 h blokady? Czy pełny bufor daje równocześnie osobny modyfikator −10…−50?
A13: Q08 | B13: DO DOPRECYZOWANIA | C13: Ratunkowy transport Food | D13: Rezerwa 50 × L, a w notatce próg tragarza <50 | E13: Roboczo ujednolicono do 50 × poziom magazynu; bez tworzenia pracownika, gdy obsada wynosi 0.
A14: Q09 | B14: DO DOPRECYZOWANIA | C14: Odejścia | D14: Dom, największa załoga, remisy według podanej listy | E14: Nie określono miejsca targu ani osób w drodze w kolejności; farma, młyn i transport nie są w pełni uszeregowane.
A15: Q10 | B15: DO DOPRECYZOWANIA | C15: Licznik zakupów w oknie 3 h | D15: Wzrost liniowy potwierdzony | E15: Osobno na produkt czy globalnie? Czy zamówienie zamraża cenę zakupu, czy cena jest liczona przy przypłynięciu?
A16: Q11 | B16: CZĘŚCIOWO ROZSTRZYGNIĘTE V3 | C16: Przyspieszenia | D16: Przyspieszenie budynku25/50/75%,1 moneta za pełną minutę. Transport:10 monet/kurs. | E16: Zakres przyspieszenia, zaokrąglenia i szczegóły cennika w Premium oraz decyzjach V3.
... A38: V3-L08 | B38: DO USTALENIA | C38: Food i rezerwa | D38: Czy do wpłat można używać chronionej rezerwy jedzenia? | E38: Poprzednia reguła zakazuje wywożenia rezerwy do innych celów niż karmienie; zadanie nie powinno omijać jej niejawnie.

Sheet Ustalenia - uwagi
A1: USTALENIA V2 • starsze wartości zastąpione jawnie
A2: Pełny rejestr dotychczasowych ustaleń z aktualizacją po pliku 1 i odpowiedziach. ZASTĄPIONE oznacza historię, nie obecną zasadę. Nowe komentarze źródłowe zachowano osobno. Bez implementacji w grze.
A5: ID | B5: Obszar | C5: Assety | D5: Status | E5: Zasada | F5: Uwagi / źródło
A6: U001 | B6: Start | C6: Wszystkie | D6: AKTUALNE | E6: Nowa wyspa: Ratusz 1, Dom 1,12 mieszkańców, szczęście 0; 100 każdego zasobu. | F6: Zasoby: monety, drewno, kamień, zboże, Food, deski.
A7: U002 | B7: Start | C7: Człowiek | D7: NOWSZE USTALENIE | E7: W gospodarce 0 pracowników na starcie; 12 wolnych ludzi do ręcznego przydziału. | F7: Zastępuje wcześniejsze 6 startowych przydziałów.
A8: U003 | B8: Start | C8: Wszystkie | D8: AKTUALNE | E8: Odświeżenie zachowuje postęp; zestaw startowy nie jest przyznawany ponownie. | F8: Logowanie i serwer to przyszły zakres; plik Excel niczego nie wdraża.
A9: U004 | B9: Poziom | C9: Ratusz | D9: AKTUALNE | E9: Poziom gracza=poziom Ratusza. | F9: Ratusz nie zatrudnia pracowników.
A10: U005 | B10: Poziom | C10: Wszystkie | D10: AKTUALNE | E10: Pozostałe budynki mogą mieć najwyżej poziom Ratusza. | F10: Podniesienie ratusza odblokowuje możliwość rozbudowy, nie wykonuje jej za gracza.
A11: U006 | B11: Ludność | C11: Ratusz | D11: AKTUALNE | E11: Teoretyczny limit mieszkańców=24×poziom Ratusza. | F11: Przykład Ratusz 4→96; Ratusz 6→144. To limit, nie automatyczna liczba osób.
A12: U007 | B12: Mieszkania | C12: Dom | D12: AKTUALNE | E12: Dom daje 24×swój poziom miejsc mieszkalnych. | F12: Ratusz i Dom mają niezależne limity; Ratusz 4, Dom 3→limit 96, miejsca 72.
A13: U008 | B13: Mieszkania | C13: Dom;Człowiek | D13: AKTUALNE | E13: Przeludnienie U=max(0, P−24×poziom Domu). Każdej osobie naliczamy−Upp/h. | F13: 78 osób/72 miejsca→−6 pp/h każdemu; kara sumuje się z innymi stawkami.
A14: U009 | B14: Mieszkania | C14: Dom;Człowiek | D14: AKTUALNE | E14: Nowe miejsca po ukończeniu Domu zatrzymują przyszłą karę w pokrytym zakresie, bez zwracania utraconego szczęścia. | F14: Nie ma natychmiastowego dodania ludzi po rozbudowie.
A15: U010 | B15: Limit pracy | C15: Człowiek;Wszystkie | D15: POTWIERDZONE V2 | E15: Limit każdego miejsca pracy=12×POZIOM TEGO BUDYNKU, ograniczony faktyczną pulą wolnych. | F15: Drwale 1:max 12; Ratusz 2 bezdrwali 2 nicniezmienia; drwale 2:max 24.
A16: U011 | B16: Limit pracy | C16: Człowiek;Wszystkie | D16: ZASTĄPIONE | E16: Wcześniej limit zapisano jako połowę aktualnej populacji. | F16: W tym Excelu po najnowszym doprecyzowaniu obowiązuje połowa MAKSIMUM z Ratusza.
... A187: V3-052 | B187: Ekspedycje | C187: Gracz; ekspedycja | D187: UWAGA BALANSOWA, NIE NOWA REGUŁA | E187: Obecny opis nie wyznacza końca serii. | F187: Podwajanie jest wykładnicze: poziom 10 = 25 600, poziom 20 = 26 214 400 monet. Limit, trudność i koszt ratowania mogą być potrzebne do balansu. Źródło: wiadomość 22.10.2026 / docs/arkusze/pomysły.

Sheet Populacja i szczescie
A1: POPULACJA • przyrost i ubytek zostały ustalone
A2: Wszystko działa offline według czasu zegarowego; ubytek oznacza wyłącznie odejście, nie śmierć. Nowi zawsze trafiają do domu. Minimum 6, maksimum 24 × Ratusz, nie Dom. Używamy dokładnej średniej indywidualnego H, nie zaokrąglonego procentu.
A5: Szczęście dokładne [%] | B5: Zmiana osób / h | C5: Czas na 1 osobę [h] | D5: Znaczenie | E5: Uwagi
A6: -100 | B6: =SIGN(A6)*IF(ABS(A6)<=50,ABS(A6)/300,1/6+(ABS(A6)-50)/60) -> -1 | C6: =IF(B6=0,"brak zmiany",1/ABS(B6)) -> 1 | D6: Ubywa | E6: Minimum 6, maksimum 24 × Ratusz; nowi do domu. Odejście: najpierw dom, potem największa załoga. Przy remisie: port, tartak, kamieniołom, drwale; produkcja żywności i transport na końcu. Targ, farma/młyn i osoby w drodze: pełna kolejność do decyzji.
A7: -75 | B7: =SIGN(A7)*IF(ABS(A7)<=50,ABS(A7)/300,1/6+(ABS(A7)-50)/60) -> -0.58333333 | C7: =IF(B7=0,"brak zmiany",1/ABS(B7)) -> 1.7142857 | D7: Ubywa | E7: Minimum 6, maksimum 24 × Ratusz; nowi do domu. Odejście: najpierw dom, potem największa załoga. Przy remisie: port, tartak, kamieniołom, drwale; produkcja żywności i transport na końcu. Targ, farma/młyn i osoby w drodze: pełna kolejność do decyzji.
A8: -50 | B8: =SIGN(A8)*IF(ABS(A8)<=50,ABS(A8)/300,1/6+(ABS(A8)-50)/60) -> -0.16666667 | C8: =IF(B8=0,"brak zmiany",1/ABS(B8)) -> 6 | D8: Ubywa | E8: Minimum 6, maksimum 24 × Ratusz; nowi do domu. Odejście: najpierw dom, potem największa załoga. Przy remisie: port, tartak, kamieniołom, drwale; produkcja żywności i transport na końcu. Targ, farma/młyn i osoby w drodze: pełna kolejność do decyzji.
A9: -25 | B9: =SIGN(A9)*IF(ABS(A9)<=50,ABS(A9)/300,1/6+(ABS(A9)-50)/60) -> -0.083333333 | C9: =IF(B9=0,"brak zmiany",1/ABS(B9)) -> 12 | D9: Ubywa | E9: Minimum 6, maksimum 24 × Ratusz; nowi do domu. Odejście: najpierw dom, potem największa załoga. Przy remisie: port, tartak, kamieniołom, drwale; produkcja żywności i transport na końcu. Targ, farma/młyn i osoby w drodze: pełna kolejność do decyzji.
A10: 0 | B10: =SIGN(A10)*IF(ABS(A10)<=50,ABS(A10)/300,1/6+(ABS(A10)-50)/60) -> 0 | C10: =IF(B10=0,"brak zmiany",1/ABS(B10)) -> brak zmiany | D10: Populacja bez zmian | E10: Minimum 6, maksimum 24 × Ratusz; nowi do domu. Odejście: najpierw dom, potem największa załoga. Przy remisie: port, tartak, kamieniołom, drwale; produkcja żywności i transport na końcu. Targ, farma/młyn i osoby w drodze: pełna kolejność do decyzji.
A11: 25 | B11: =SIGN(A11)*IF(ABS(A11)<=50,ABS(A11)/300,1/6+(ABS(A11)-50)/60) -> 0.083333333 | C11: =IF(B11=0,"brak zmiany",1/ABS(B11)) -> 12 | D11: Przybywa | E11: Minimum 6, maksimum 24 × Ratusz; nowi do domu. Odejście: najpierw dom, potem największa załoga. Przy remisie: port, tartak, kamieniołom, drwale; produkcja żywności i transport na końcu. Targ, farma/młyn i osoby w drodze: pełna kolejność do decyzji.
A12: 50 | B12: =SIGN(A12)*IF(ABS(A12)<=50,ABS(A12)/300,1/6+(ABS(A12)-50)/60) -> 0.16666667 | C12: =IF(B12=0,"brak zmiany",1/ABS(B12)) -> 6 | D12: Przybywa | E12: Minimum 6, maksimum 24 × Ratusz; nowi do domu. Odejście: najpierw dom, potem największa załoga. Przy remisie: port, tartak, kamieniołom, drwale; produkcja żywności i transport na końcu. Targ, farma/młyn i osoby w drodze: pełna kolejność do decyzji.
A13: 75 | B13: =SIGN(A13)*IF(ABS(A13)<=50,ABS(A13)/300,1/6+(ABS(A13)-50)/60) -> 0.58333333 | C13: =IF(B13=0,"brak zmiany",1/ABS(B13)) -> 1.7142857 | D13: Przybywa | E13: Minimum 6, maksimum 24 × Ratusz; nowi do domu. Odejście: najpierw dom, potem największa załoga. Przy remisie: port, tartak, kamieniołom, drwale; produkcja żywności i transport na końcu. Targ, farma/młyn i osoby w drodze: pełna kolejność do decyzji.
A14: 100 | B14: =SIGN(A14)*IF(ABS(A14)<=50,ABS(A14)/300,1/6+(ABS(A14)-50)/60) -> 1 | C14: =IF(B14=0,"brak zmiany",1/ABS(B14)) -> 1 | D14: Przybywa | E14: Minimum 6, maksimum 24 × Ratusz; nowi do domu. Odejście: najpierw dom, potem największa załoga. Przy remisie: port, tartak, kamieniołom, drwale; produkcja żywności i transport na końcu. Targ, farma/młyn i osoby w drodze: pełna kolejność do decyzji.
A17: WZÓR I PRZYKŁAD
A18: Dla H=|szczęście|: tempo=H/300 osoby/h dla 0…50%; dla 50…100%:1/6+(H−50)/60. Znak dodatni daje przyrost, ujemny ubytek. ±75% daje 1 osobę co 1 h 42 min 51 s. Przy 0% brak zmiany. Nowa osoba ma własne szczęście 0, dopiero potem otrzymuje aktualne premie wyspy.

Sheet Przystan
A1: PORT • nowe 140/150 i liniowa podwyżka
A2: Ceny za 100. Port 40/50 podstawowe i 140/150 przetworzone. Targ bez monetowy+marża 10%. Od 2 paczki zakupu w ruchomych 3 h liniowo+10%ceny bazowej; zakres licznika globalny/per materiał jeszcze do określenia. Przykład dla kolejnych paczekjednego rodzaju bez wygaśnięć okna.
A5: Numer paczki100 | B5: Kupno podstawowych | C5: Kupno przetworzonych | D5: Sprzedaż podstawowych | E5: Sprzedaż przetworzonych | F5: Suma kupna podstawowych | G5: Suma kupna przetworzonych | H5: Uwagi
A6: 1 | B6: =Parametry!$C$32*(1+Parametry!$C$35*(A6-1)) -> 50 | C6: =Parametry!$C$34*(1+Parametry!$C$35*(A6-1)) -> 150 | D6: =Parametry!$C$31 -> 40 | E6: =Parametry!$C$33 -> 140 | F6: =Parametry!$C$32*(A6+Parametry!$C$35*A6*(A6-1)/2) -> 50 | G6: =Parametry!$C$34*(A6+Parametry!$C$35*A6*(A6-1)/2) -> 150 | H6: Jedno zamówienie 500 szt.liczy 5 paczek; dopłata dla każdej kolejnej paczki. Sprzedaż bez tej dopłaty.
A7: 2 | B7: =Parametry!$C$32*(1+Parametry!$C$35*(A7-1)) -> 55 | C7: =Parametry!$C$34*(1+Parametry!$C$35*(A7-1)) -> 165 | D7: =Parametry!$C$31 -> 40 | E7: =Parametry!$C$33 -> 140 | F7: =Parametry!$C$32*(A7+Parametry!$C$35*A7*(A7-1)/2) -> 105 | G7: =Parametry!$C$34*(A7+Parametry!$C$35*A7*(A7-1)/2) -> 315 | H7: Jedno zamówienie 500 szt.liczy 5 paczek; dopłata dla każdej kolejnej paczki. Sprzedaż bez tej dopłaty.
A8: 3 | B8: =Parametry!$C$32*(1+Parametry!$C$35*(A8-1)) -> 60 | C8: =Parametry!$C$34*(1+Parametry!$C$35*(A8-1)) -> 180 | D8: =Parametry!$C$31 -> 40 | E8: =Parametry!$C$33 -> 140 | F8: =Parametry!$C$32*(A8+Parametry!$C$35*A8*(A8-1)/2) -> 165 | G8: =Parametry!$C$34*(A8+Parametry!$C$35*A8*(A8-1)/2) -> 495 | H8: Jedno zamówienie 500 szt.liczy 5 paczek; dopłata dla każdej kolejnej paczki. Sprzedaż bez tej dopłaty.
A9: 4 | B9: =Parametry!$C$32*(1+Parametry!$C$35*(A9-1)) -> 65 | C9: =Parametry!$C$34*(1+Parametry!$C$35*(A9-1)) -> 195 | D9: =Parametry!$C$31 -> 40 | E9: =Parametry!$C$33 -> 140 | F9: =Parametry!$C$32*(A9+Parametry!$C$35*A9*(A9-1)/2) -> 230 | G9: =Parametry!$C$34*(A9+Parametry!$C$35*A9*(A9-1)/2) -> 690 | H9: Jedno zamówienie 500 szt.liczy 5 paczek; dopłata dla każdej kolejnej paczki. Sprzedaż bez tej dopłaty.
A10: 5 | B10: =Parametry!$C$32*(1+Parametry!$C$35*(A10-1)) -> 70 | C10: =Parametry!$C$34*(1+Parametry!$C$35*(A10-1)) -> 210 | D10: =Parametry!$C$31 -> 40 | E10: =Parametry!$C$33 -> 140 | F10: =Parametry!$C$32*(A10+Parametry!$C$35*A10*(A10-1)/2) -> 300 | G10: =Parametry!$C$34*(A10+Parametry!$C$35*A10*(A10-1)/2) -> 900 | H10: Jedno zamówienie 500 szt.liczy 5 paczek; dopłata dla każdej kolejnej paczki. Sprzedaż bez tej dopłaty.
A11: 6 | B11: =Parametry!$C$32*(1+Parametry!$C$35*(A11-1)) -> 75 | C11: =Parametry!$C$34*(1+Parametry!$C$35*(A11-1)) -> 225 | D11: =Parametry!$C$31 -> 40 | E11: =Parametry!$C$33 -> 140 | F11: =Parametry!$C$32*(A11+Parametry!$C$35*A11*(A11-1)/2) -> 375 | G11: =Parametry!$C$34*(A11+Parametry!$C$35*A11*(A11-1)/2) -> 1125 | H11: Jedno zamówienie 500 szt.liczy 5 paczek; dopłata dla każdej kolejnej paczki. Sprzedaż bez tej dopłaty.
A12: 7 | B12: =Parametry!$C$32*(1+Parametry!$C$35*(A12-1)) -> 80 | C12: =Parametry!$C$34*(1+Parametry!$C$35*(A12-1)) -> 240 | D12: =Parametry!$C$31 -> 40 | E12: =Parametry!$C$33 -> 140 | F12: =Parametry!$C$32*(A12+Parametry!$C$35*A12*(A12-1)/2) -> 455 | G12: =Parametry!$C$34*(A12+Parametry!$C$35*A12*(A12-1)/2) -> 1365 | H12: Jedno zamówienie 500 szt.liczy 5 paczek; dopłata dla każdej kolejnej paczki. Sprzedaż bez tej dopłaty.
A13: 8 | B13: =Parametry!$C$32*(1+Parametry!$C$35*(A13-1)) -> 85 | C13: =Parametry!$C$34*(1+Parametry!$C$35*(A13-1)) -> 255 | D13: =Parametry!$C$31 -> 40 | E13: =Parametry!$C$33 -> 140 | F13: =Parametry!$C$32*(A13+Parametry!$C$35*A13*(A13-1)/2) -> 540 | G13: =Parametry!$C$34*(A13+Parametry!$C$35*A13*(A13-1)/2) -> 1620 | H13: Jedno zamówienie 500 szt.liczy 5 paczek; dopłata dla każdej kolejnej paczki. Sprzedaż bez tej dopłaty.
A14: 9 | B14: =Parametry!$C$32*(1+Parametry!$C$35*(A14-1)) -> 90 | C14: =Parametry!$C$34*(1+Parametry!$C$35*(A14-1)) -> 270 | D14: =Parametry!$C$31 -> 40 | E14: =Parametry!$C$33 -> 140 | F14: =Parametry!$C$32*(A14+Parametry!$C$35*A14*(A14-1)/2) -> 630 | G14: =Parametry!$C$34*(A14+Parametry!$C$35*A14*(A14-1)/2) -> 1890 | H14: Jedno zamówienie 500 szt.liczy 5 paczek; dopłata dla każdej kolejnej paczki. Sprzedaż bez tej dopłaty.
A15: 10 | B15: =Parametry!$C$32*(1+Parametry!$C$35*(A15-1)) -> 95 | C15: =Parametry!$C$34*(1+Parametry!$C$35*(A15-1)) -> 285 | D15: =Parametry!$C$31 -> 40 | E15: =Parametry!$C$33 -> 140 | F15: =Parametry!$C$32*(A15+Parametry!$C$35*A15*(A15-1)/2) -> 725 | G15: =Parametry!$C$34*(A15+Parametry!$C$35*A15*(A15-1)/2) -> 2175 | H15: Jedno zamówienie 500 szt.liczy 5 paczek; dopłata dla każdej kolejnej paczki. Sprzedaż bez tej dopłaty.
A17: Rentowność2:1 | H17: 200 drewna sprzedane jako surowiec=80 monet; po przeróbce 100 desek=140. Zakup 200 drewna=100; 100 desek=150. Nowy cennik usuwa poprzednią odwrotną zachętę.
A18: Przepływ/terminy | H18: Dwa cykle sprzedaży, pojemność statku=port, płatność przy wypłynięciu. Zakup:płatność przy przypłynięciu, rozładunek i dowóz. Towar 24 hnieodebrany przepada; opłata 10 monet zniesiona.

Sheet Blogoslawienstwa
A1: KAPLICA / LATARNIA • dwa źródła premii
A2: Kaplica = błogosławieństwo, Latarnia = zwiedzanie. W domu widać ludzi i ich przydziały; można ich stamtąd wysyłać. Nowe zasady wizyt są odrębne od premii ZA ukończenie rozbudowy i nie zastępują ich bez decyzji.
A5: Element | B5: Aktualna zasada | C5: Co pozostaje do później
A6: Kaplica: rozbudowa | B6: +10 × N szczęścia i podatki ×2 przez 10 h; poziom 1 bez pasywnego bonusu. | C6: Koszt kaplicy nadal tymczasowy; premia po ukończeniu.
A7: Kaplica: błogosławieństwo | B7: Dotychczas: +50 każdego zasobu, +20 szczęścia na 1 h; liczba bezpłatnych użyć = poziom kaplicy. | C7: Czas pobytu, indywidualny/globalny bonus wizyt, praca, podatki i powrót.
A8: Latarnia: rozbudowa | B8: Efektywne szczęście WSZYSTKICH 100%, produkcja materiałów ×2; obie premie przez 24 h × N. | C8: Nie dodajemy+100; po zakończeniu powrót do bieżących osobistych liczników jest interpretacją modelu.
A9: Latarnia: zwiedzanie | B9: Ludzi można wysłać z Domu; zwiedzanie prowadzi do premii. | C9: Czas wizyty, liczba ludzi, konkretna nagroda i limity.
A10: Cooldown/reklamy/zakup | B10: Notatkę źródłową zachowano; oferty zebrano w Premium. | C10: Nadal odłożone: rosnące odstępy +25%, reklama 60 s, 2/h, natychmiastowe zakupy.

Sheet Odpowiedzi i zmiany
A1: POTWIERDZENIA • odpowiedzi z rozmowy
A2: 22.10.2026, Europa/Warszawa. Ten arkusz pozwala odróżnić Twoje dosłowne odpowiedzi od roboczych interpretacji. Wersja 2 to wynik analizy, nie kod ani wdrożenie.
A5: Temat | B5: Potwierdzenie | C5: Zastosowanie
A6: Produkcja | B6: Dokładnie 10, 12, 13, 14… | C6: Wszystkie 5 producentów; szczegóły Produkcja.
A7: Latarnia | B7: Łącznie 5T: transport T + budowa 4T | C7: Czasy przeliczone.
A8: Kaplica | B8: Użyj nowego poziomu N: 4T, 7T, 10T | C8: Czasy przeliczone.
A9: Transport | B9: Cały kurs z powrotem trwa 5 min | C9: Kalkulacja podzielona według ładunków.
A10: Ceny-produkty | B10: Ostatnia korekta: 140/150 w PORCIE; na TARGU wymiana bez monet z marżą. | C10: Zastępuje 70/80 w porcie oraz wcześniejszą odpowiedź dotyczącą targu.
A11: Offline | B11: Wszystkie mechaniki działają również offline | C11: Nie tylko budowa i port.
A12: Źródło | B12: HARBORLIGHT1-zasady.xlsx, commit d8f424d | C12: Oryginał niezmieniony; nowy plik: HARBORLIGHT2-zasady.xlsx.
A13: Wersja 3 | B13: Nowe reguły Premium, zadań latarni, social i ekspedycji. | C13: Źródło: docs/arkusze/pomysły, commit 748b1eb oraz wiadomość z 22.10.2026.
A14: Pytania V3 | B14: Ostatni niepełny kurs; proporcjonalna wycena materiałów i monety osobno; utrwalenie bonusu zadania po kliknięciu. | C14: Pytania wysłano; do odpowiedzi warianty pozostają oznaczone jako modele.

Sheet Pomysly
A1: POMYSŁY • nowe wpisy z repozytorium
A2: Pomysły z pliku docs/arkusze/pomysły, dodane podczas pracy nad arkuszem. Zachowujemy je jako pomysły, bez dopisywania mechanik, cen ani zasad.
A5: Oryginalny wpis | B5: Źródło | C5: Status / brakujące szczegóły
A6: shakomat na komórkę z kólką | B6: docs/arkusze/pomysły; commit 30b10ec | C6: Mechanika labiryntu i piłeczki związana z ekspedycjami; sterowanie i wykorzystanie ruchu telefonu użytkownik opisze później.
A7: ekspedycje | B7: docs/arkusze/pomysły; commit 30b10ec | C7: Rozwinięte w arkuszach Ekspedycje oraz Ekspedycje - poziomy.
A8: wyzwania do latarni | B8: docs/arkusze/pomysły; commit 30b10ec | C8: Rozwinięte w arkuszach Zadania latarni, Zadania przyklady i Zadania - zegary.

Sheet Twoje wpisy v1
A1: TWOJE WPISY • zachowane z pliku1
A2: Oryginał HARBORLIGHT1-zasady.xlsx pozostaje nienaruszony. To archiwum75 zmian tekstowych, w tym przesunięć nagłówków; przeniesione formuły nie są liczone jako nowe zasady. Wiążące odpowiedzi z rozmowy mają osobną zakładkę.
A5: Źródło | B5: Poprzednio | C5: Twój wpis — bez zmian | D5: Obsługa w wersji2
A6: Start!E9 | C6: zdefiniowane w innym miejscu | D6: Uwzględnione w uporządkowanych zasadach lub jawnie oznaczone jako szczegół do decyzji; patrz Odpowiedzi i zmiany.
A7: Start!E12 | C7: zakładamy nakarmionych tragarzy, ale zwiekszamy limit min pożywienia w magazynie na 50 x Level | D7: Uwzględnione w uporządkowanych zasadach lub jawnie oznaczone jako szczegół do decyzji; patrz Odpowiedzi i zmiany.
A8: Start!E13 | C8: tak potwierdzam wraz z rozbudową magazynu wzrasta ilość materiałów jakie tragarz może ze sobą zabrać, logika też jest osobno opisana przy magazynie | D8: Uwzględnione w uporządkowanych zasadach lub jawnie oznaczone jako szczegół do decyzji; patrz Odpowiedzi i zmiany.
A9: Start!E16 | C9: nie nazywajmy ubytku śmiercią | D9: Uwzględnione w uporządkowanych zasadach lub jawnie oznaczone jako szczegół do decyzji; patrz Odpowiedzi i zmiany.
A10: Budynki!K5 | B10: 1→2: transport + budowa | C10: Uwagi 3 | D10: Uwzględnione w uporządkowanych zasadach lub jawnie oznaczone jako szczegół do decyzji; patrz Odpowiedzi i zmiany.
A11: Budynki!M5 | B11: 3→4: transport + budowa | C11: 1→2: transport + budowa | D11: Uwzględnione w uporządkowanych zasadach lub jawnie oznaczone jako szczegół do decyzji; patrz Odpowiedzi i zmiany.
A12: Budynki!N5 | C12: 2→3: transport + budowa | D12: Uwzględnione w uporządkowanych zasadach lub jawnie oznaczone jako szczegół do decyzji; patrz Odpowiedzi i zmiany.
A13: Budynki!O5 | C13: 3→4: transport + budowa | D13: Uwzględnione w uporządkowanych zasadach lub jawnie oznaczone jako szczegół do decyzji; patrz Odpowiedzi i zmiany.
A14: Budynki!F6 | B14: ŁĄCZNIE3T: transportT +budowa2T. | C14: ŁĄCZNIE3T: transportT +budowa2T. Zmiana, czas 2 T | D14: Uwzględnione w uporządkowanych zasadach lub jawnie oznaczone jako szczegół do decyzji; patrz Odpowiedzi i zmiany.
A15: Budynki!J6 | B15: Oferta dla tego budynku nieustalona. Wcześniejszy projekt globalnego pakietu: +4 równoległe budowy, dowolna kolejka i planowanie z estymaty dostaw na czas pakietu; cena/czas nieustalone. | C15: Premium, zbuduj 2 x szybciej, zbuduj natychmiast (oba jak masz zasoby) kup budynek jak nie masz surowców | D15: Uwzględnione w uporządkowanych zasadach lub jawnie oznaczone jako szczegół do decyzji; patrz Odpowiedzi i zmiany.
A16: Budynki!K6 | B16: '=TEXT('Czas budowy'!S6,"0.00")&" h łącznie; T="&TEXT('Czas budowy'!P6,"0.00")&" h, budowa="&TEXT('Czas budowy'!R6,"0.00")&" h. Założenia: Czas budowy / D02." | C16: Budowa: Ratusz na poziomie 1 daje możliwość 1 rozbudowy w tym samym czasie i (o ile mam surowce) jednej zakolejkowanej, ale na tą zakolejkowaną muszę mieć surowce w momencie zlecania. Ratusz na poziomie 2 daje prawo do 2 budów I dwóch obiektów w kolejce pod tym samym warunkiem. Budynki zakolejkowane są o 10 % droższe niż te budowane bez kolejki. Później dopiszemy co oferuje premium (na pewno jedną z opcji będzie skróć czas budowy) | D16: Uwzględnione w uporządkowanych zasadach lub jawnie oznaczone jako szczegół do decyzji; patrz Odpowiedzi i zmiany.
A17: Budynki!F7 | B17: ŁĄCZNIE3T: transportT +budowa2T. | C17: ŁĄCZNIE3T: transportT +budowa2T. Zmiana, czas 2 T | D17: Uwzględnione w uporządkowanych zasadach lub jawnie oznaczone jako szczegół do decyzji; patrz Odpowiedzi i zmiany.
A18: Budynki!J7 | B18: Oferta dla tego budynku nieustalona. Wcześniejszy projekt globalnego pakietu: +4 równoległe budowy, dowolna kolejka i planowanie z estymaty dostaw na czas pakietu; cena/czas nieustalone. | C18: Premium, zbuduj 2 x szybciej, zbuduj natychmiast (oba jak masz zasoby) kup budynek jak nie masz surowców | D18: Uwzględnione w uporządkowanych zasadach lub jawnie oznaczone jako szczegół do decyzji; patrz Odpowiedzi i zmiany.
A19: Budynki!K7 | B19: '=TEXT('Czas budowy'!S9,"0.00")&" h łącznie; T="&TEXT('Czas budowy'!P9,"0.00")&" h, budowa="&TEXT('Czas budowy'!R9,"0.00")&" h. Założenia: Czas budowy / D02." | C19: Z poziomu domu widzę wszystkich ludzi gdzie są dopisani, mogę ich stąd wysyłać do kaplicy lub na latarnię | D19: Uwzględnione w uporządkowanych zasadach lub jawnie oznaczone jako szczegół do decyzji; patrz Odpowiedzi i zmiany.
A20: Budynki!C8 | B20: Start0. Limit na budynek12×poziom ratusza, ale tylko faktycznie wolni ludzie ze wspólnej puli. Nie można przypisać jednej osoby dwa razy. | C20: Start0. Limit na budynek12×poziom ratusza, ale tylko faktycznie wolni ludzie ze wspólnej puli. Nie można przypisać jednej osoby dwa razy. Start wszystkie zasoby = 100 | D20: Uwzględnione w uporządkowanych zasadach lub jawnie oznaczone jako szczegół do decyzji; patrz Odpowiedzi i zmiany.
A21: Budynki!D8 | B21: Zamiar z pliku: większa możliwa produkcja dzięki większej obsadzie. Limit obsady został wyjaśniony jako zależny od RATUSZA, nie własnego poziomu producenta. Osobna korzyść ulepszenia tego budynku nadal nie została określona. | C21: Zamiar z pliku: większa możliwa produkcja dzięki większej obsadzie. Limit obsady został wyjaśniony jako zależny od RATUSZA, nie własnego poziomu producenta. Osobna korzyść ulepszenia tego budynku nadal nie została określona. Rozbudowa na kolejny poziom daje zawsze dodatkowo 10% extra efektywności pracy czyli zwiększa w tym przypadku zboże analogicznie też drewno kamien etc | D21: Uwzględnione w uporządkowanych zasadach lub jawnie oznaczone jako szczegół do decyzji; patrz Odpowiedzi i zmiany.
A22: Budynki!J8 | B22: Oferta dla tego budynku nieustalona. Wcześniejszy projekt globalnego pakietu: +4 równoległe budowy, dowolna kolejka i planowanie z estymaty dostaw na czas pakietu; cena/czas nieustalone. | C22: Premium, zbuduj 2 x szybciej, zbuduj natychmiast (oba jak masz zasoby) kup budynek jak nie masz surowców | D22: Uwzględnione w uporządkowanych zasadach lub jawnie oznaczone jako szczegół do decyzji; patrz Odpowiedzi i zmiany.
A23: Budynki!K8 | B23: '=TEXT('Czas budowy'!S12,"0.00")&" h łącznie; T="&TEXT('Czas budowy'!P12,"0.00")&" h, budowa="&TEXT('Czas budowy'!R12,"0.00")&" h. Założenia: Czas budowy / D02." | C23: Do wszystkich produkcyjnych, zwiększenie levelu zwiększa produkcję na 1 h, dla levelu 1 jest to 10 szt / h dla levelu 2 będzie to 12, dla levelu 3 -13 dla 4 - 14 etc W premium dla wszystkich produkcyjnych możłiwość natychmiastowego transportu do magazynu oneclickiem. | D23: Uwzględnione w uporządkowanych zasadach lub jawnie oznaczone jako szczegół do decyzji; patrz Odpowiedzi i zmiany.
A24: Budynki!J9 | B24: Oferta dla tego budynku nieustalona. Wcześniejszy projekt globalnego pakietu: +4 równoległe budowy, dowolna kolejka i planowanie z estymaty dostaw na czas pakietu; cena/czas nieustalone. | C24: Premium, zbuduj 2 x szybciej, zbuduj natychmiast (oba jak masz zasoby) kup budynek jak nie masz surowców | D24: Uwzględnione w uporządkowanych zasadach lub jawnie oznaczone jako szczegół do decyzji; patrz Odpowiedzi i zmiany.
A25: Budynki!J10 | B25: Oferta dla tego budynku nieustalona. Wcześniejszy projekt globalnego pakietu: +4 równoległe budowy, dowolna kolejka i planowanie z estymaty dostaw na czas pakietu; cena/czas nieustalone. | C25: Premium, zbuduj 2 x szybciej, zbuduj natychmiast (oba jak masz zasoby) kup budynek jak nie masz surowców | D25: Uwzględnione w uporządkowanych zasadach lub jawnie oznaczone jako szczegół do decyzji; patrz Odpowiedzi i zmiany.
... A43: Budynki!M18 | B43: Nie dotyczy. | C43: Nie dotyczy — osoba nie ma rozbudowy1→2. | D43: Uwzględnione w uporządkowanych zasadach lub jawnie oznaczone jako szczegół do decyzji; patrz Odpowiedzi i zmiany.
