Workbook

Sheet Start
A1: HARBORLIGHT • EXCEL DO UZGADNIANIA ZASAD
A2: 22.10.2026 • Uzupełniona tabela użytkownika,13 assetów (12 budynków+człowiek). Pełny rejestr zasad i komentarze komórek w pliku. Bez zmian w kodzie i zapisach gry. Formuły są w arkuszu; niebieskie komórki Parametry są edytowalne. Oryginalny tekst zachowano w Zrodlo.
A5: Obszar | B5: Co jest w pliku | C5: Status / następny krok
A6: Otwórz tabelę budynków | B6: Budynki — główna tabela; Czlowiek — karta assetu; Czas budowy — wszystkie etapy; Populacja i szczescie — tempo demografii; Parametry — edycja; Przystan — ceny; Blogoslawienstwa — odłożone; Decyzje i konflikty — otwarte punkty. | C6: Arkusz budynków zachowuje13 kolumn źródła, zmieniając nagłówki czasu zgodnie z ostatnią instrukcją.
A7: Doprecyzowanie1: limit ludzi | B7: 0–połowa maksymalnej liczby mieszkańców z ratusza:12×ratusz na budynek, ale z rzeczywistej wolnej puli. | C7: Nowy plik: wszyscy pracownicy0 na starcie, więc12 wolnych. Własny poziom producenta nie występuje w tym limicie.
A8: Doprecyzowanie2: błogosławieństwa | B8: Konflikt zakupu natychmiast/reklamy/aktywnego efektu oraz nowe odstępy zostają na później. | C8: ODŁOŻONE. Nie wybrano mechaniki ani nie obliczano cooldownów.
A9: Doprecyzowanie3: ceny | B9: Potwierdzone za100:podstawowe40sprzedaż/50kupno;przetworzone70/80. | C9: Zapisane bez zmiany. Przy2:1,200raw→100produktu, więc sama wartość sprzedaży spada80→70; przykład pozostaje uwagą o opłacalności. | E9: zdefiniowane w innym miejscu
A10: Doprecyzowanie4: czas | B10: Liczymy tylko transport i samą budowę. Bez zbierania, karmienia, wcześniejszych rozbudów i oczekiwania w kolejce. | C10: Nagłówki doable path zastąpiono transport+budowa. Dom/ratusz3T,kaplica4T,latarnia6T,pozostałe2T — sumy obu etapów.
A11: Zaakceptowana zależność | B11: PrzedRatuszem3 wymaganyMagazyn2, przedRatuszem4 Magazyn3, aby cały koszt zmieścił się centralnie. | C11: Użytkownik zaakceptował tę uwagę. Jest ograniczeniem drogi rozwoju, ale jej czasu nie doliczamy do estymat.
A12: Zaakceptowana uwaga o żywności | B12: Rezerwa50 może nie wystarczyć na przewóz materiałów. Przy12osobach to4h10; przewóz2500/6nakarmionych trwa6h57. | C12: Użytkownik zaakceptował uwagę. Nie doliczamy karmienia do czasu; zakładamy nakarmionych tragarzy. Zabezpieczenie Foodpooperacji≥50 zapisano jawnie. | E12: zakładamy nakarmionych tragarzy, ale zwiekszamy limit min pożywienia w magazynie na 50 x Level
A13: Ważne założenie czasów | B13: 6tragarzy; magazyn poziomu L; +10% na kolejny poziom roboczo interpretowane jako przepustowość60×1.1^(L−1). | C13: D02 nadal otwarte: wzrost pojemności kursu a wzrost szybkości. Bez tej interpretacji brakuje czasu kursu do policzenia bonusu. | E13: tak potwierdzam wraz z rozbudową magazynu wzrasta ilość materiałów jakie tragarz może ze sobą zabrać, logika też jest osobno opisana przy magazynie
A14: Nieuzgodnione efekty rozbudowy | B14: Limit12×ratusz wyjaśnia większą obsadę po rozbudowie ratusza, ale nie korzyść ulepszania samej farmy/młyna/drwali/tartaku/kamieniołomu. | C14: Wpisano DO USTALENIA zamiast wymyślonego bonusu. Nie zmieniono wydajności10szt./os./h.
A15: Przystań: brakujące szczegóły | B15: Opłata10monet po24h:jednostka/powtarzanie; zakupy:rozładunek/dowóz; +10%cen:globalnie/perprodukt i liniowo/składanie; bazowe tempo załogi. | C15: W źródle nowe zasady; w pliku oznaczono otwarte warianty, nie fikcyjne ustalenia.
A16: Otwórz asset Człowiek | B16: Własne ID, szczęście i liczniki; jedzenie, przydział, podatek, wydajność, 5min powrotu, kary pełnego magazynu/przeludnienia i premie. | C16: Szczegóły w Czlowiek. Tempo przyrostu/ubytku było ustalone; ubytek nie został nazwany koniecznie śmiercią. | E16: nie nazywajmy ubytku śmiercią
A17: Zakres pracy | B17: Utworzono plikExcel i materiały do sprawdzenia. Plik udostępniono w katalogu dokumentacji repozytorium. | C17: Bez developmentu i zmian logiki gry; opublikowano wyłącznie arkusz jako dokumentację.
A18: Otwórz wszystkie ustalenia | B18: 92 pozycji w Ustalenia - uwagi. W Budynki kolumna Uwagi2 zawiera komentarze komórek z regułami danego assetu. To dokładnie wcześniejsze ustalenia, nowe doprecyzowania, zasady zastąpione i tematy odłożone.

Sheet Budynki
A1: HARBORLIGHT • uzupełniona tabela + człowiek
A2: TYLKO PROJEKT W EXCELU — bez zmian w grze. Uwzględniono ostatnie doprecyzowania: limit połowy maksimum ratusza, błogosławieństwa odłożone, ceny40/50 i70/80 za100, czasy tylko transport+budowa. Czerwone/żółte pola oznaczają otwarte kwestie. Szczegóły człowieka w osobnym arkuszu.
A5: Budynek / asset | B5: Po co jest w grze | C5: Liczba ludzi — start / limit | D5: Co daje rozbudowa | E5: Koszty rozbudowy | F5: Czas rozbudowy | G5: Stan projektu | H5: Notyfikacja / uwagi | I5: Uwagi2 — reguły i kary | J5: Płatne / challenge / social / reklama | K5: Uwagi 3 | M5: 1→2: transport + budowa | N5: 2→3: transport + budowa | O5: 3→4: transport + budowa
A6: Ratusz | B6: Wyznacza poziom gry i limity rozwoju; jest skarbcem monet i pokazuje podatek/h. | C6: Brak własnych pracowników. | D6: +24 maksymalnej populacji, wyższy maksymalny poziom innych budynków, +1 budowa i+1 miejsce kolejki, +200 pojemności lokalnej każdego producenta. Limit obsady każdego miejsca pracy rośnie o12, jeżeli są wolni mieszkańcy. Odblokowanie targ2,port4. | E6: 500×L KAŻDEGO z6 zasobów | F6: ŁĄCZNIE3T: transportT +budowa2T. Zmiana, czas 2 T | G6: ZASADY OPISANE; bez wdrożenia nowych zmian. | H6: ZAWSZE: ukończenie budowy. Wcześniej także zlecenie/start/dostawa. | I6: Podatek1moneta/przypisanego/h; bezrobotni i wracający0. Kaplica czasowo podwaja podatek. Ratusz nie zatrudnia. PrzedRatuszem3 potrzebnyMagazyn2; przedRatuszem4 Magazyn3 — zależność zaakceptowana. | J6: Premium, zbuduj 2 x szybciej, zbuduj natychmiast (oba jak masz zasoby) kup budynek jak nie masz surowców | K6: Budowa: Ratusz na poziomie 1 daje możliwość 1 rozbudowy w tym samym czasie i (o ile mam surowce) jednej zakolejkowanej, ale na tą zakolejkowaną muszę mieć surowce w momencie zlecania. Ratusz na poziomie 2 daje prawo do 2 budów I dwóch obiektów w kolejce pod tym samym warunkiem. Budynki zakolejkowane są o 10 % droższe niż te budowane bez kolejki. Później dopiszemy co oferuje premium (na pewno jedną z opcji będzie skróć czas budowy) | M6: =TEXT('Czas budowy'!S6,"0.00")&" h łącznie; T="&TEXT('Czas budowy'!P6,"0.00")&" h, budowa="&TEXT('Czas budowy'!R6,"0.00")&" h. Założenia: Czas budowy / D02." -> 20.85 h łącznie; T=6.95 h, budowa=13.90 h. Założenia: Czas budowy / D02. | N6: =TEXT('Czas budowy'!S7,"0.00")&" h łącznie; T="&TEXT('Czas budowy'!P7,"0.00")&" h, budowa="&TEXT('Czas budowy'!R7,"0.00")&" h. Założenia: Czas budowy / D02." -> 37.91 h łącznie; T=12.64 h, budowa=25.27 h. Założenia: Czas budowy / D02. | O6: =TEXT('Czas budowy'!S8,"0.00")&" h łącznie; T="&TEXT('Czas budowy'!P8,"0.00")&" h, budowa="&TEXT('Czas budowy'!R8,"0.00")&" h. Założenia: Czas budowy / D02." -> 51.65 h łącznie; T=17.22 h, budowa=34.44 h. Założenia: Czas budowy / D02.
A7: Dom | B7: Zapewnia miejsca mieszkalne, osobno od maksymalnego limitu ratusza. | C7: Brak własnych pracowników. Dom mieści24×poziom domu; mieszkańcy domu nie są jego pracownikami. | D7: +24 miejsca, przez co ogranicza albo zatrzymuje dalszą karę przeludnienia. | E7: 500×L KAŻDEGO z6 zasobów | F7: ŁĄCZNIE3T: transportT +budowa2T. Zmiana, czas 2 T | G7: ZASADY OPISANE; bez wdrożenia nowych zmian. | H7: ZAWSZE: ukończenie budowy. Wcześniej także zlecenie/start/dostawa. NOWE: przeludnienie; proponujemy na zmianę stanu, nie co klatkę. | I7: Kara:U=max(0,P−24×poziom domu); KAŻDEMU mieszkańcowi−Upp/h. Np.78/72→−6pp/h każdemu. Ulepszenie zatrzymuje dalszą karę, nie oddaje punktów. | J7: Premium, zbuduj 2 x szybciej, zbuduj natychmiast (oba jak masz zasoby) kup budynek jak nie masz surowców | K7: Z poziomu domu widzę wszystkich ludzi gdzie są dopisani, mogę ich stąd wysyłać do kaplicy lub na latarnię | M7: =TEXT('Czas budowy'!S9,"0.00")&" h łącznie; T="&TEXT('Czas budowy'!P9,"0.00")&" h, budowa="&TEXT('Czas budowy'!R9,"0.00")&" h. Założenia: Czas budowy / D02." -> 20.85 h łącznie; T=6.95 h, budowa=13.90 h. Założenia: Czas budowy / D02. | N7: =TEXT('Czas budowy'!S10,"0.00")&" h łącznie; T="&TEXT('Czas budowy'!P10,"0.00")&" h, budowa="&TEXT('Czas budowy'!R10,"0.00")&" h. Założenia: Czas budowy / D02." -> 37.91 h łącznie; T=12.64 h, budowa=25.27 h. Założenia: Czas budowy / D02. | O7: =TEXT('Czas budowy'!S11,"0.00")&" h łącznie; T="&TEXT('Czas budowy'!P11,"0.00")&" h, budowa="&TEXT('Czas budowy'!R11,"0.00")&" h. Założenia: Czas budowy / D02." -> 51.65 h łącznie; T=17.22 h, budowa=34.44 h. Założenia: Czas budowy / D02.
A8: Farma | B8: Produkuje zboże do młyna, budowy i wymiany. | C8: Start0. Limit na budynek12×poziom ratusza, ale tylko faktycznie wolni ludzie ze wspólnej puli. Nie można przypisać jednej osoby dwa razy. Start wszystkie zasoby = 100 | D8: Zamiar z pliku: większa możliwa produkcja dzięki większej obsadzie. Limit obsady został wyjaśniony jako zależny od RATUSZA, nie własnego poziomu producenta. Osobna korzyść ulepszenia tego budynku nadal nie została określona. Rozbudowa na kolejny poziom daje zawsze dodatkowo 10% extra efektywności pracy czyli zwiększa w tym przypadku zboże analogicznie też drewno kamien etc | E8: L×(72 drewna+72 kamienia+120 zboża) | F8: ŁĄCZNIE2T: transportT +budowa1T. | G8: DO USTALENIA: osobny efekt własnego poziomu; produkcja10/os./h nadal bazą. | H8: ZAWSZE: ukończenie budowy. Wcześniej także zlecenie/start/dostawa. Powiadomienie o pełnym magazynie. | I8: Pełny lokalny magazyn: produkcja STOP; załoga−10 szczęścia od razu, następne−10 co24h do−50. Opróżnienie usuwa tę osobną karę. Powrót do domu5min, bez pracy/podatku i bez możliwości przydziału; część rozpoczętej sztuki przepada. Dojście do pracy osobno nieustalone. Produkcja10/os./h, głód5. Lokalny bufor200×poziom ratusza. | J8: Premium, zbuduj 2 x szybciej, zbuduj natychmiast (oba jak masz zasoby) kup budynek jak nie masz surowców | K8: Do wszystkich produkcyjnych, zwiększenie levelu zwiększa produkcję na 1 h, dla levelu 1 jest to 10 szt / h dla levelu 2 będzie to 12, dla levelu 3 -13 dla 4 - 14 etc W premium dla wszystkich produkcyjnych możłiwość natychmiastowego transportu do magazynu oneclickiem. | M8: =TEXT('Czas budowy'!S12,"0.00")&" h łącznie; T="&TEXT('Czas budowy'!P12,"0.00")&" h, budowa="&TEXT('Czas budowy'!R12,"0.00")&" h. Założenia: Czas budowy / D02." -> 1.47 h łącznie; T=0.73 h, budowa=0.73 h. Założenia: Czas budowy / D02. | N8: =TEXT('Czas budowy'!S13,"0.00")&" h łącznie; T="&TEXT('Czas budowy'!P13,"0.00")&" h, budowa="&TEXT('Czas budowy'!R13,"0.00")&" h. Założenia: Czas budowy / D02." -> 2.67 h łącznie; T=1.33 h, budowa=1.33 h. Założenia: Czas budowy / D02. | O8: =TEXT('Czas budowy'!S14,"0.00")&" h łącznie; T="&TEXT('Czas budowy'!P14,"0.00")&" h, budowa="&TEXT('Czas budowy'!R14,"0.00")&" h. Założenia: Czas budowy / D02." -> 3.64 h łącznie; T=1.82 h, budowa=1.82 h. Założenia: Czas budowy / D02.
A9: Młyn | B9: Przetwarza2 zboża z centrali→1 żywność do lokalnego bufora. | C9: Start0. Limit na budynek12×poziom ratusza, ale tylko faktycznie wolni ludzie ze wspólnej puli. Nie można przypisać jednej osoby dwa razy. | D9: Zamiar z pliku: większa możliwa produkcja dzięki większej obsadzie. Limit obsady został wyjaśniony jako zależny od RATUSZA, nie własnego poziomu producenta. Osobna korzyść ulepszenia tego budynku nadal nie została określona. | E9: L×(72 drewna+72 kamienia+120 żywności) | F9: ŁĄCZNIE2T: transportT +budowa1T. | G9: DO USTALENIA: osobny efekt własnego poziomu; produkcja10/os./h nadal bazą. | H9: ZAWSZE: ukończenie budowy. Wcześniej także zlecenie/start/dostawa. Powiadomienie o pełnym magazynie. | I9: Pełny lokalny magazyn: produkcja STOP; załoga−10 szczęścia od razu, następne−10 co24h do−50. Opróżnienie usuwa tę osobną karę. Powrót do domu5min, bez pracy/podatku i bez możliwości przydziału; część rozpoczętej sztuki przepada. Dojście do pracy osobno nieustalone. Produkcja10/os./h, głód5. Lokalny bufor200×poziom ratusza. | J9: Premium, zbuduj 2 x szybciej, zbuduj natychmiast (oba jak masz zasoby) kup budynek jak nie masz surowców | M9: =TEXT('Czas budowy'!S15,"0.00")&" h łącznie; T="&TEXT('Czas budowy'!P15,"0.00")&" h, budowa="&TEXT('Czas budowy'!R15,"0.00")&" h. Założenia: Czas budowy / D02." -> 1.47 h łącznie; T=0.73 h, budowa=0.73 h. Założenia: Czas budowy / D02. | N9: =TEXT('Czas budowy'!S16,"0.00")&" h łącznie; T="&TEXT('Czas budowy'!P16,"0.00")&" h, budowa="&TEXT('Czas budowy'!R16,"0.00")&" h. Założenia: Czas budowy / D02." -> 2.67 h łącznie; T=1.33 h, budowa=1.33 h. Założenia: Czas budowy / D02. | O9: =TEXT('Czas budowy'!S17,"0.00")&" h łącznie; T="&TEXT('Czas budowy'!P17,"0.00")&" h, budowa="&TEXT('Czas budowy'!R17,"0.00")&" h. Założenia: Czas budowy / D02." -> 3.64 h łącznie; T=1.82 h, budowa=1.82 h. Założenia: Czas budowy / D02.
A10: Drwale | B10: Produkują drewno do tartaku i budowy. | C10: Start0. Limit na budynek12×poziom ratusza, ale tylko faktycznie wolni ludzie ze wspólnej puli. Nie można przypisać jednej osoby dwa razy. | D10: Zamiar z pliku: większa możliwa produkcja dzięki większej obsadzie. Limit obsady został wyjaśniony jako zależny od RATUSZA, nie własnego poziomu producenta. Osobna korzyść ulepszenia tego budynku nadal nie została określona. | E10: L×(192 drewna+72 kamienia) | F10: ŁĄCZNIE2T: transportT +budowa1T. | G10: DO USTALENIA: osobny efekt własnego poziomu; produkcja10/os./h nadal bazą. | H10: ZAWSZE: ukończenie budowy. Wcześniej także zlecenie/start/dostawa. Powiadomienie o pełnym magazynie. | I10: Pełny lokalny magazyn: produkcja STOP; załoga−10 szczęścia od razu, następne−10 co24h do−50. Opróżnienie usuwa tę osobną karę. Powrót do domu5min, bez pracy/podatku i bez możliwości przydziału; część rozpoczętej sztuki przepada. Dojście do pracy osobno nieustalone. Produkcja10/os./h, głód5. Lokalny bufor200×poziom ratusza. | J10: Premium, zbuduj 2 x szybciej, zbuduj natychmiast (oba jak masz zasoby) kup budynek jak nie masz surowców | M10: =TEXT('Czas budowy'!S18,"0.00")&" h łącznie; T="&TEXT('Czas budowy'!P18,"0.00")&" h, budowa="&TEXT('Czas budowy'!R18,"0.00")&" h. Założenia: Czas budowy / D02." -> 1.47 h łącznie; T=0.73 h, budowa=0.73 h. Założenia: Czas budowy / D02. | N10: =TEXT('Czas budowy'!S19,"0.00")&" h łącznie; T="&TEXT('Czas budowy'!P19,"0.00")&" h, budowa="&TEXT('Czas budowy'!R19,"0.00")&" h. Założenia: Czas budowy / D02." -> 2.67 h łącznie; T=1.33 h, budowa=1.33 h. Założenia: Czas budowy / D02. | O10: =TEXT('Czas budowy'!S20,"0.00")&" h łącznie; T="&TEXT('Czas budowy'!P20,"0.00")&" h, budowa="&TEXT('Czas budowy'!R20,"0.00")&" h. Założenia: Czas budowy / D02." -> 3.64 h łącznie; T=1.82 h, budowa=1.82 h. Założenia: Czas budowy / D02.
A11: Tartak | B11: Przetwarza2 drewna z centrali→1 deskę do lokalnego bufora. | C11: Start0. Limit na budynek12×poziom ratusza, ale tylko faktycznie wolni ludzie ze wspólnej puli. Nie można przypisać jednej osoby dwa razy. | D11: Zamiar z pliku: większa możliwa produkcja dzięki większej obsadzie. Limit obsady został wyjaśniony jako zależny od RATUSZA, nie własnego poziomu producenta. Osobna korzyść ulepszenia tego budynku nadal nie została określona. | E11: L×(72 drewna+72 kamienia+120 desek) | F11: ŁĄCZNIE2T: transportT +budowa1T. | G11: DO USTALENIA: osobny efekt własnego poziomu; produkcja10/os./h nadal bazą. | H11: ZAWSZE: ukończenie budowy. Wcześniej także zlecenie/start/dostawa. Powiadomienie o pełnym magazynie. | I11: Pełny lokalny magazyn: produkcja STOP; załoga−10 szczęścia od razu, następne−10 co24h do−50. Opróżnienie usuwa tę osobną karę. Powrót do domu5min, bez pracy/podatku i bez możliwości przydziału; część rozpoczętej sztuki przepada. Dojście do pracy osobno nieustalone. Produkcja10/os./h, głód5. Lokalny bufor200×poziom ratusza. | J11: Premium, zbuduj 2 x szybciej, zbuduj natychmiast (oba jak masz zasoby) kup budynek jak nie masz surowców | M11: =TEXT('Czas budowy'!S21,"0.00")&" h łącznie; T="&TEXT('Czas budowy'!P21,"0.00")&" h, budowa="&TEXT('Czas budowy'!R21,"0.00")&" h. Założenia: Czas budowy / D02." -> 1.47 h łącznie; T=0.73 h, budowa=0.73 h. Założenia: Czas budowy / D02. | N11: =TEXT('Czas budowy'!S22,"0.00")&" h łącznie; T="&TEXT('Czas budowy'!P22,"0.00")&" h, budowa="&TEXT('Czas budowy'!R22,"0.00")&" h. Założenia: Czas budowy / D02." -> 2.67 h łącznie; T=1.33 h, budowa=1.33 h. Założenia: Czas budowy / D02. | O11: =TEXT('Czas budowy'!S23,"0.00")&" h łącznie; T="&TEXT('Czas budowy'!P23,"0.00")&" h, budowa="&TEXT('Czas budowy'!R23,"0.00")&" h. Założenia: Czas budowy / D02." -> 3.64 h łącznie; T=1.82 h, budowa=1.82 h. Założenia: Czas budowy / D02.
A12: Kamieniołom | B12: Produkuje kamień do budowy i wymiany. | C12: Start0. Limit na budynek12×poziom ratusza, ale tylko faktycznie wolni ludzie ze wspólnej puli. Nie można przypisać jednej osoby dwa razy. | D12: Zamiar z pliku: większa możliwa produkcja dzięki większej obsadzie. Limit obsady został wyjaśniony jako zależny od RATUSZA, nie własnego poziomu producenta. Osobna korzyść ulepszenia tego budynku nadal nie została określona. | E12: L×(72 drewna+192 kamienia) | F12: ŁĄCZNIE2T: transportT +budowa1T. | G12: DO USTALENIA: osobny efekt własnego poziomu; produkcja10/os./h nadal bazą. | H12: ZAWSZE: ukończenie budowy. Wcześniej także zlecenie/start/dostawa. Powiadomienie o pełnym magazynie. | I12: Pełny lokalny magazyn: produkcja STOP; załoga−10 szczęścia od razu, następne−10 co24h do−50. Opróżnienie usuwa tę osobną karę. Powrót do domu5min, bez pracy/podatku i bez możliwości przydziału; część rozpoczętej sztuki przepada. Dojście do pracy osobno nieustalone. Produkcja10/os./h, głód5. Lokalny bufor200×poziom ratusza. | J12: Premium, zbuduj 2 x szybciej, zbuduj natychmiast (oba jak masz zasoby) kup budynek jak nie masz surowców | M12: =TEXT('Czas budowy'!S24,"0.00")&" h łącznie; T="&TEXT('Czas budowy'!P24,"0.00")&" h, budowa="&TEXT('Czas budowy'!R24,"0.00")&" h. Założenia: Czas budowy / D02." -> 1.47 h łącznie; T=0.73 h, budowa=0.73 h. Założenia: Czas budowy / D02. | N12: =TEXT('Czas budowy'!S25,"0.00")&" h łącznie; T="&TEXT('Czas budowy'!P25,"0.00")&" h, budowa="&TEXT('Czas budowy'!R25,"0.00")&" h. Założenia: Czas budowy / D02." -> 2.67 h łącznie; T=1.33 h, budowa=1.33 h. Założenia: Czas budowy / D02. | O12: =TEXT('Czas budowy'!S26,"0.00")&" h łącznie; T="&TEXT('Czas budowy'!P26,"0.00")&" h, budowa="&TEXT('Czas budowy'!R26,"0.00")&" h. Założenia: Czas budowy / D02." -> 3.64 h łącznie; T=1.82 h, budowa=1.82 h. Założenia: Czas budowy / D02.
A13: Magazyn | B13: Przechowuje materiały; własna załoga nosi produkcję do centrali i materiały na budowy. Ludzie jedzą z centrali automatycznie. | C13: Start0. Limit na budynek12×poziom ratusza, ale tylko faktycznie wolni ludzie ze wspólnej puli. Nie można przypisać jednej osoby dwa razy. | D13: Pojemność centralna×1.5. Nowy zamiar:+10% pojemności tragarzy na każdy poziom; w kalkulatorze roboczo przepustowość60×1.1^(poziom−1). Więcej ludzi można mieć dzięki limitowi ratusza; własny limit obsady nie jest potrzebny. | E13: 300×L KAŻDEGO z6 zasobów | F13: ŁĄCZNIE2T: transportT +budowa1T. | G13: DO DECYZJI D02: znaczenie+10% tragarzy. | H13: ZAWSZE: ukończenie budowy. Wcześniej także zlecenie/start/dostawa. Powiadomienie o pełnym magazynie. | I13: Poziom1:1000 każdego materiału,4000 łącznie; oba limity×1.5 na kolejny poziom. Monety osobno. Food: do nieżywieniowych operacji max(0,Food−50), z uwzględnieniem rezerwacji budowy i wysyłki na targ/port. Ludzie mogą zjadać rezerwę. Rezerwa50 nie gwarantuje braku głodu przy długim transporcie — uwaga zaakceptowana. | J13: Premium, zbuduj 2 x szybciej, zbuduj natychmiast (oba jak masz zasoby) kup budynek jak nie masz surowców | K13: Transport. Nie rozróżniamy odległości, transport produków zawsze trwa 5 min z/do magazynu x capacity tragarza czyli jeżeli tragarz bierze 60 a potrzebuje przenieść 100 to I tak musi wykonać 2 kursy w jednym bierze 60 w drugim 40, tragarz nie może brać 2 produktow na raz, nie może czekać na towar. Jak klikam rozbudowa np drwala podświetla sie napis ile potrzeba surowców a ile zostało już dostarczonych np 60 /100 i estymowany czas zakońćzenia budowy czyli suma czasu transportu przy aktualnych ustawieniach priorytetów, i budowy. Z poziomu magazynu domyślne prirytety jest najpierw zaopatrz magazyn pózniej budowy, można je zmieniać, dodatkowo też można zmienić ustalić prio na konkretne gospodarstwo bądz konretną budowę, 1 tragarz zawsze będzie nosił żywność o ile jest wyprodukowana a w magazynie jest mniej niż 50 Premium szybszy transport do puntu odbioru | M13: =TEXT('Czas budowy'!S27,"0.00")&" h łącznie; T="&TEXT('Czas budowy'!P27,"0.00")&" h, budowa="&TEXT('Czas budowy'!R27,"0.00")&" h. Założenia: Czas budowy / D02." -> 13.90 h łącznie; T=6.95 h, budowa=6.95 h. Założenia: Czas budowy / D02. | N13: =TEXT('Czas budowy'!S28,"0.00")&" h łącznie; T="&TEXT('Czas budowy'!P28,"0.00")&" h, budowa="&TEXT('Czas budowy'!R28,"0.00")&" h. Założenia: Czas budowy / D02." -> 25.27 h łącznie; T=12.64 h, budowa=12.64 h. Założenia: Czas budowy / D02. | O13: =TEXT('Czas budowy'!S29,"0.00")&" h łącznie; T="&TEXT('Czas budowy'!P29,"0.00")&" h, budowa="&TEXT('Czas budowy'!R29,"0.00")&" h. Założenia: Czas budowy / D02." -> 34.44 h łącznie; T=17.22 h, budowa=17.22 h. Założenia: Czas budowy / D02.
A14: Targ | B14: Od poziomu gracza2: wymiana w grupach drewno/kamień/zboże lub deski/żywność, nominalnie1:1 z marżą10%. Bez kupowania za monety. | C14: Start0. Limit na budynek12×poziom ratusza, ale tylko faktycznie wolni ludzie ze wspólnej puli. Nie można przypisać jednej osoby dwa razy. Odblokowanie ratusz2. | D14: Pojemność×1.5:1000,1500,2250… Wynik wymiany czeka na targu na zamówiony odbiór do centrali. Targ ma swoich ludzi, tylko oni noszą na targ I do magazynu, jeżeli chcesz sprzedać musisz miec towar na targu czyli musisz polecić jego przyniesienie, towar na targu znika po 24 h od przyniesienia, jak na coś sie wymienisz towar jest na targu 24 i znika, | E14: 300×L KAŻDEGO z6 zasobów | F14: ŁĄCZNIE2T: transportT +budowa1T. | G14: ZASADY OPISANE; bez wdrożenia nowych zmian. | H14: ZAWSZE: ukończenie budowy. Wcześniej także zlecenie/start/dostawa. Powiadomienie o pełnym magazynie. | I14: Pracownicy donoszą60/os./h bazowo; każdy przywieziony towar blokowany1h. Marża10%, np.10drewna→9kamienia. Grupy nie mieszają surowców podstawowych z przetworzonymi. | J14: Premium, zbuduj 2 x szybciej, zbuduj natychmiast (oba jak masz zasoby) kup budynek jak nie masz surowców | K14: Premium transport oneclick Ceny grupa 2 140/150 | M14: =TEXT('Czas budowy'!S30,"0.00")&" h łącznie; T="&TEXT('Czas budowy'!P30,"0.00")&" h, budowa="&TEXT('Czas budowy'!R30,"0.00")&" h. Założenia: Czas budowy / D02." -> 13.90 h łącznie; T=6.95 h, budowa=6.95 h. Założenia: Czas budowy / D02. | N14: =TEXT('Czas budowy'!S31,"0.00")&" h łącznie; T="&TEXT('Czas budowy'!P31,"0.00")&" h, budowa="&TEXT('Czas budowy'!R31,"0.00")&" h. Założenia: Czas budowy / D02." -> 25.27 h łącznie; T=12.64 h, budowa=12.64 h. Założenia: Czas budowy / D02. | O14: =TEXT('Czas budowy'!S32,"0.00")&" h łącznie; T="&TEXT('Czas budowy'!P32,"0.00")&" h, budowa="&TEXT('Czas budowy'!R32,"0.00")&" h. Założenia: Czas budowy / D02." -> 34.44 h łącznie; T=17.22 h, budowa=17.22 h. Założenia: Czas budowy / D02.
A15: Przystań | B15: Od poziomu gracza4: kupno i sprzedaż pięciu materiałów za monety. Wyłącznie pełne paczki100. Monety są środkiem płatności, nie osobnym towarem. | C15: Start0. Limit na budynek12×poziom ratusza, ale tylko faktycznie wolni ludzie ze wspólnej puli. Nie można przypisać jednej osoby dwa razy. Odblokowanie ratusz4. | D15: Nowa pojemność jak magazyn:1000/rodzaj i4000łącznie na1, potem×1.5. Załoga przenosi z centrali i ładuje statek, bez magazynierów. Osobny bonus szybkości poziomu portu nieustalony. | E15: 400×L KAŻDEGO z6 zasobów | F15: ŁĄCZNIE2T: transportT +budowa1T. | G15: Ceny potwierdzone. DO DECYZJI: zakupy, tempo załogi, dopłaty i opłata24h. | H15: ZAWSZE: ukończenie budowy. Wcześniej także zlecenie/start/dostawa. Powiadomienie o pełnym magazynie. | I15: Poziom1:1000 każdego materiału,4000 łącznie; oba limity×1.5 na kolejny poziom. Monety osobno. Ceny za100:podstawowe sprzedaż40/kupno50;przetworzone70/80. Od2.paczki zakupu w ostatnich3h+10% (wariant do decyzji). Po24h składowania10monet — jednostka i powtarzanie do decyzji. Zakupowa droga powrotna do uzupełnienia. | J15: Premium, zbuduj 2 x szybciej, zbuduj natychmiast (oba jak masz zasoby) kup budynek jak nie masz surowców | K15: Tempo załogi jak w magazynie, premium jak w magazynie | M15: =TEXT('Czas budowy'!S33,"0.00")&" h łącznie; T="&TEXT('Czas budowy'!P33,"0.00")&" h, budowa="&TEXT('Czas budowy'!R33,"0.00")&" h. Założenia: Czas budowy / D02." -> 13.90 h łącznie; T=6.95 h, budowa=6.95 h. Założenia: Czas budowy / D02. | N15: =TEXT('Czas budowy'!S34,"0.00")&" h łącznie; T="&TEXT('Czas budowy'!P34,"0.00")&" h, budowa="&TEXT('Czas budowy'!R34,"0.00")&" h. Założenia: Czas budowy / D02." -> 25.27 h łącznie; T=12.64 h, budowa=12.64 h. Założenia: Czas budowy / D02. | O15: =TEXT('Czas budowy'!S35,"0.00")&" h łącznie; T="&TEXT('Czas budowy'!P35,"0.00")&" h, budowa="&TEXT('Czas budowy'!R35,"0.00")&" h. Założenia: Czas budowy / D02." -> 34.44 h łącznie; T=17.22 h, budowa=17.22 h. Założenia: Czas budowy / D02.
A16: Kaplica | B16: Daje premie szczęścia i podatków po rozbudowie; dotychczas była miejscem ręcznych błogosławieństw. | C16: Brak własnych pracowników. | D16: +1 do łącznej liczby jednorazowych darmowych błogosławieństw według poprzedniej reguły; po rozbudowie doN:+10×N szczęścia wszystkim i podatki×2 przez10h. | E16: TYMCZASOWO:N×(180 monet+20 drewna+60 kamienia+10 desek). N=nowy poziom. | F16: ŁĄCZNIE4T: transportT +(budowa3Tx aktualny level-1) | G16: Premie przypomniane; koszt tymczasowy; nowe błogosławieństwa ODŁOŻONE. | H16: ZAWSZE: ukończenie budowy. Wcześniej także zlecenie/start/dostawa. Uruchomienie premii i ręczne błogosławieństwo. | I16: Poziom1 nie daje pasywnej premii. Ręczne błogosławieństwo dotąd:+50każdego zasobu,+20szczęścia na1h, bez nakładania. Nowa lokalizacja/cooldown/reklamy ODŁOŻONE przez użytkownika. | J16: Premium, zbuduj 2 x szybciej, zbuduj natychmiast (oba jak masz zasoby) kup budynek jak nie masz surowców Nowe błogosławieństwo: kasa/challenge/udostępnienie/reklama. Zgodnie z decyzją użytkownika szczegóły ODŁOŻONE. Brak cen ani zatwierdzonej integracji. | M16: =TEXT('Czas budowy'!S36,"0.00")&" h łącznie; T="&TEXT('Czas budowy'!P36,"0.00")&" h, budowa="&TEXT('Czas budowy'!R36,"0.00")&" h. Założenia: Czas budowy / D02." -> 2.00 h łącznie; T=0.50 h, budowa=1.50 h. Założenia: Czas budowy / D02. | N16: =TEXT('Czas budowy'!S37,"0.00")&" h łącznie; T="&TEXT('Czas budowy'!P37,"0.00")&" h, budowa="&TEXT('Czas budowy'!R37,"0.00")&" h. Założenia: Czas budowy / D02." -> 2.73 h łącznie; T=0.68 h, budowa=2.05 h. Założenia: Czas budowy / D02. | O16: =TEXT('Czas budowy'!S38,"0.00")&" h łącznie; T="&TEXT('Czas budowy'!P38,"0.00")&" h, budowa="&TEXT('Czas budowy'!R38,"0.00")&" h. Założenia: Czas budowy / D02." -> 3.31 h łącznie; T=0.83 h, budowa=2.48 h. Założenia: Czas budowy / D02.
A17: Latarnia | B17: Daje premie szczęścia i produkcji po ukończeniu poziomu. | C17: Brak własnych pracowników. | D17: +100 szczęścia wszystkim i produkcja pięciu materiałów×2. OBA efekty przez24h×N. Wyższy poziom odświeża/wydłuża czas, nie zwiększa produkcji do×4. | E17: 500×max(1,L) KAŻDEGO z6 zasobów. Pierwsza budowa0→1:500 każdego. | F17: ŁĄCZNIE6T: transportT +budowa4T. | G17: Premia opisana; nowe błogosławieństwa przy latarni ODŁOŻONE. | H17: ZAWSZE: ukończenie budowy. Wcześniej także zlecenie/start/dostawa. Uruchomienie premii latarni. | I17: Podatki i transport bez mnożnika latarni. W źródle opisano tu błogosławieństwo+50zasobów/+20szczęścia1h, odstępy+25%, zakupy/challenge/share/reklamy. Zachowano notatkę; szczegóły ODŁOŻONE. | J17: Premium, zbuduj 2 x szybciej, zbuduj natychmiast (oba jak masz zasoby) kup budynek jak nie masz surowców Nowe błogosławieństwo: kasa/challenge/udostępnienie/reklama. Zgodnie z decyzją użytkownika szczegóły ODŁOŻONE. Brak cen ani zatwierdzonej integracji. | K17: Nowe błogosławieństwo: kasa/challenge/udostępnienie/reklama. Zgodnie z decyzją użytkownika szczegóły ODŁOŻONE. Brak cen ani zatwierdzonej integracji. | M17: =TEXT('Czas budowy'!S39,"0.00")&" h łącznie; T="&TEXT('Czas budowy'!P39,"0.00")&" h, budowa="&TEXT('Czas budowy'!R39,"0.00")&" h. Założenia: Czas budowy / D02." -> 41.70 h łącznie; T=6.95 h, budowa=34.75 h. Założenia: Czas budowy / D02. | N17: =TEXT('Czas budowy'!S40,"0.00")&" h łącznie; T="&TEXT('Czas budowy'!P40,"0.00")&" h, budowa="&TEXT('Czas budowy'!R40,"0.00")&" h. Założenia: Czas budowy / D02." -> 75.82 h łącznie; T=12.64 h, budowa=63.18 h. Założenia: Czas budowy / D02. | O17: =TEXT('Czas budowy'!S41,"0.00")&" h łącznie; T="&TEXT('Czas budowy'!P41,"0.00")&" h, budowa="&TEXT('Czas budowy'!R41,"0.00")&" h. Założenia: Czas budowy / D02." -> 103.31 h łącznie; T=17.22 h, budowa=86.09 h. Założenia: Czas budowy / D02.
A18: CZŁOWIEK — ASSET | B18: Je, pracuje, produkuje/nosi, płaci podatki; ma indywidualną historię i szczęście. | C18: 12 na starcie, wszyscy wolni. Minimum6; maksimum24×ratusz. Jeden przydział na osobę. | D18: Nie ulepsza się człowieka poziomem. Stan zmieniają jedzenie, praca, mieszkania, pełne magazyny i premie wyspy. | E18: Utrzymanie1Food/os./h; osobnego kupowania człowieka nie ustalono. | F18: Przyrost/ubytek zależny od średniej szczęścia; przy±100%1os./h, przy±50%1/6h. | G18: UZGODNIONE; szczegółowa karta: Czlowiek. | H18: Powiadomienia o pełnym magazynie/przeludnieniu z budynków; alarm o głodzie nie został osobno ustalony. | I18: Je+pracuje:+2pp/h. Bez danego braku pierwsze12h bez kary, potem każdy brak−5pp/h. Je+bezrobotny po12h:−4;głodny+pracuje po12h:−4;oba braki po12h:−10. Głód wydajność×0.5; podatek nadal1przy przypisaniu. Każdy±100%, potem średnia. | M18: Nie dotyczy — osoba nie ma rozbudowy1→2. | N18: Nie dotyczy. | O18: Nie dotyczy.

Sheet Czlowiek
A1: CZŁOWIEK • asset gry i wszystkie reguły
A2: Każdy człowiek ma trwałe ID, własne szczęście, przydział do pracy, licznik głodu, licznik bezrobocia i czas powrotu. To opis projektu w Excelu, bez wdrażania. Zakaz nakładania nowych błogosławieństw i reklamy pozostawiono do późniejszej decyzji.
A5: Obszar / stan | B5: Reguła | C5: Liczby / wzór | D5: Szczęście / podatki / wydajność | E5: Status / powiązanie
A6: Rola assetu | B6: Mieszkaniec zużywa żywność, może pracować, produkować lub nosić towary i płacić podatek. | C6: Start12; minimum6; maksimum24×ratusz. | D6: Nowy człowiek zaczyna z osobistym0% szczęścia, nie dziedziczy historii innych. | E6: UZGODNIONE
A7: Start i wolna pula | B7: Nowy plik ustawia0 pracowników w każdym budynku. | C7: 12 wolnych na starcie; przypisanie możliwe od razu. Na starcie ludzie są w "Domu" | D7: Przed przypisaniem brak produkcji i podatków; jedzenie jest zużywane. | E7: NOWE W ŹRÓDLE
A8: Limit zatrudnienia | B8: Jedno miejsce pracy na osobę; wszystkie budynki korzystają z jednej puli. | C8: 0…12×poziom ratusza na budynek; zatrudnić można najwyżej obecnych wolnych ludzi. UWAGA ZMIANA na poziomie 1 mam 24 ludzi wiec w w kazdym gospodarstwie mogę mieć połowę limitu czyli 12 (o ile mam tylu ludzi i o ile są dostępni w domu), niezależnie od poziomu ratusza póki nie zwiększe poziomu budynky nie mogę mieć wiecej, jeżeli np drwala podniosę do poziomu 2 to mogę mieć połowę maxa czyli 24 etc, a nie mogę podnieść drwala nie podnosząc ratusza bo to jest prerequisit | D8: W tej wersji Excel: połowa maksymalnej populacji z ratusza. To nie połowa aktualnej liczby ludzi i nie własny poziom producenta. | E8: WYJAŚNIONE PRZEZ UŻYTKOWNIKA
A9: Jedzenie | B9: Automatycznie zużywa Food z centralnego magazynu. Lokalny młyn, targ i port nie karmią bez dostawy centralnej. | C9: 1 Food/os./h aktywnej gry. | D9: Jedzenie daje+1pp/h. Rezerwa50 chroni przed wynoszeniem, ale ludzie mogą ją zjadać. | E9: UZGODNIONE + NOWA REZERWA
A10: Praca produkcyjna | B10: Indywidualne całe sztuki; niedokończona część przepada po zwolnieniu. | C10: Nakarmiony10/h, czyli1 co6min; głodny5/h, czyli1 co12min. Młyn/tartak2surowca→1produkt. | D10: Przydział daje+1pp/h i1monetę/h. Przy latarni produkcja×2; głód×0.5, razem daje podstawowe10/h. | E10: UZGODNIONE
A11: Transport | B11: Magazynierzy przewożą produkcję i materiały budowy; załoga portu ma obsługiwać port oddzielnie. | C11: Bazowo60 szt./os./h; głód30/h. +10% magazynu jest interpretowane w modelu jako przepustowość. | D11: Podatek i bonus pracy pozostają przy przypisaniu. Tempo portu i znaczenie+10%: D02/D07. | E11: BAZA UZGODNIONA; NOWE SZCZEGÓŁY DO DECYZJI
A12: Podatek | B12: Tylko przydzieleni pracownicy. Bezrobotni i wracający nie płacą. | C12: 1 moneta/os./h; podczas premii kaplicy2 monety/os./h. | D12: Przy przypisaniu podatek działa także przy braku surowca lub pełnym lokalnym składzie, zgodnie z wcześniejszym modelem. | E12: UZGODNIONE
A13: Je i pracuje | B13: Dwa niezależne dodatnie składniki. | C13: +1 za jedzenie +1 za pracę = +2pp/h. | D13: Od0 po10h ma20%. | E13: UZGODNIONE
A14: Je; bez pracy do12h | B14: Działa bonus jedzenia; bezrobocie jeszcze bez kary. | C14: +1pp/h. | D14: Po10h jedzenia i pracy20%; potem12h jedzenia bez pracy32%. | E14: UZGODNIONE
A15: Je; bez pracy ponad12h | B15: Kara bezrobocia po własnym ciągłym okresie12h. | C15: +1 za jedzenie −5 za bezrobocie = −4pp/h. | D15: Po powyższych32% następna godzina daje28%. | E15: UZGODNIONE
A16: Nie je do12h; pracuje | B16: Brak bonusu jedzenia; pozostaje bonus przydziału. | C16: +1pp/h. | D16: Wydajność50% OD RAZU, podatki nadal1moneta/h. | E16: UZGODNIONE
... A29: Czas aktywny | B29: Godziny potrzeb i pracy nie są przyspieszane zegarem1×/2×/4×. | C29: Pauza, ukrycie karty i offline zatrzymują mechanikę. Tu zmiana, czas jest czasem realnym, tzn jeżeli gram karta aktywna I mam info że budynek sie robi 2 h to on sie robi 2h realne zegarowe, jeżeli sie wyloguje zamknę kartę to wciąż ten budynek będzie sie robił 2 h, guziki przyspieszenia czasu działają czasowo powiązane są z premiami | D29: Nowy portowy próg24h i okno zakupów3h wymagają wyboru czasu aktywnego lub zegarowego., zegarowy | E29: BAZA UZGODNIONA; PORT DO DECYZJI

Sheet Ustalenia - uwagi
A1: WSZYSTKIE USTALENIA • rejestr i historia zmian
A2: Rejestr scalony z całej rozmowy i wklejonej tabeli. NOWSZE zastępuje sprzeczną starszą wartość; ODŁOŻONE nie jest wybraną mechaniką. Arkusz nie jest dokumentem wdrożenia. Powiązane ustalenia dodano także jako komentarze komórek w kolumnie Uwagi2 głównej tabeli.
A5: ID | B5: Obszar | C5: Dotyczy assetów | D5: Status | E5: Reguła / ustalenie | F5: Uwagi i rozróżnienia
A6: U001 | B6: Start | C6: Wszystkie | D6: AKTUALNE | E6: Nowa wyspa: Ratusz1, Dom1,12 mieszkańców, szczęście0;100 każdego zasobu. | F6: Zasoby: monety,drewno,kamień,zboże,Food,deski.
A7: U002 | B7: Start | C7: Człowiek | D7: NOWSZE USTALENIE | E7: W gospodarce0 pracowników na starcie;12 wolnych ludzi do ręcznego przydziału. | F7: Zastępuje wcześniejsze6 startowych przydziałów.
A8: U003 | B8: Start | C8: Wszystkie | D8: AKTUALNE | E8: Odświeżenie zachowuje postęp; zestaw startowy nie jest przyznawany ponownie. | F8: Logowanie i serwer to przyszły zakres; plikExcel niczego nie wdraża.
A9: U004 | B9: Poziom | C9: Ratusz | D9: AKTUALNE | E9: Poziom gracza=poziom Ratusza. W ustawieniach trzeba dodać ranking, ranking ustalany jako level x ilość złota | F9: Ratusz nie zatrudnia pracowników.
A10: U005 | B10: Poziom | C10: Wszystkie | D10: AKTUALNE | E10: Pozostałe budynki mogą mieć najwyżej poziom Ratusza. | F10: Podniesienie ratusza odblokowuje możliwość rozbudowy, nie wykonuje jej za gracza.
A11: U006 | B11: Ludność | C11: Ratusz | D11: AKTUALNE | E11: Teoretyczny limit mieszkańców=24×poziom Ratusza. | F11: PrzykładRatusz4→96;Ratusz6→144. To limit, nie automatyczna liczba osób.
A12: U007 | B12: Mieszkania | C12: Dom | D12: AKTUALNE | E12: Dom daje24×swój poziom miejsc mieszkalnych. | F12: Ratusz i Dom mają niezależne limity; Ratusz4,Dom3→limit96,miejsca72.
A13: U008 | B13: Mieszkania | C13: Dom;Człowiek | D13: AKTUALNE | E13: PrzeludnienieU=max(0,P−24×poziom Domu). Każdej osobie naliczamy−Upp/h. | F13: 78osób/72miejsca→−6pp/h każdemu; kara sumuje się z innymi stawkami.
A14: U009 | B14: Mieszkania | C14: Dom;Człowiek | D14: AKTUALNE | E14: Nowe miejsca po ukończeniu Domu zatrzymują przyszłą karę w pokrytym zakresie, bez zwracania utraconego szczęścia. | F14: Nie ma natychmiastowego dodania ludzi po rozbudowie.
A15: U010 | B15: Limit pracy | C15: Człowiek;Wszystkie | D15: NOWSZE DOPRECYZOWANIE | E15: Na każde z8 miejsc pracy można przypisać0…12×poziom Ratusza osób, bo to połowa maksimum populacji. | F15: Zawsze ograniczenie do faktycznie istniejących wolnych osób; jedna wspólna pula.
A16: U011 | B16: Limit pracy | C16: Człowiek;Wszystkie | D16: ZASTĄPIONE | E16: Wcześniej limit zapisano jako połowę aktualnej populacji. | F16: W tymExcelu po najnowszym doprecyzowaniu obowiązuje połowa MAKSIMUM z Ratusza.
... A53: U048 | B53: Demografia | C53: Człowiek;Ratusz | D53: AKTUALNE | E53: Co najmniej6osób; maksymalnie24×ratusz; przy minimum gra nadal grywalna. | F53: Rozbudowa domu/ratusza nie dodaje ludzi natychmiast.
A54: U049 | B54: Czas | C54: Wszystkie | D54: AKTUALNE | E54: Jedzenie, szczęście, produkcja, podatki i transport używają rzeczywistych aktywnych godzin.
A55: U050 | B55: Targ | C55: Targ | D55: AKTUALNE | E55: Targ dostępny od poziomu gracza2. | F55: Przystań od4; odblokowanie następuje z poziomu ratusza.
A56: U051 | B56: Targ | C56: Targ | D56: AKTUALNE | E56: Wymiana dowolnej ilości, ale tylko w grupach:drewno/kamień/zboże lub deski/Food. | F56: Brak wymiany między grupami; brak kupowania za pieniądze.
A57: U052 | B57: Targ | C57: Targ | D57: AKTUALNE | E57: Nominalnie1:1;marża10%,np.10drewna→9kamienia.
A58: U053 | B58: Targ | C58: Targ | D58: AKTUALNE | E58: Pojemność1000na1,1500na2,2250na3…;każdy poziom×1.5. | F58: Jeden limit łączny własnego targu, nie1000każdego materiału.
A59: U054 | B59: Targ | C59: Targ;Magazyn | D59: AKTUALNE | E59: Pracownicy targu donoszą towary jak magazynierzy bazowo60/os./h;każda partia od przybycia zablokowana1h. | F59: Nie wymieniamy towaru w trakcie blokady.
A60: U055 | B60: Targ | C60: Targ;Magazyn | D60: AKTUALNE | E60: Wynik wymiany pozostaje na targu, aż magazynierzy odbiorą go do centrali. | F60: Nie można wydać targowego towaru bez transportu centralnego.
A61: U056 | B61: Kaplica | C61: Kaplica | D61: AKTUALNE | E61: Na poziomie1 bez pasywnego plusa/minusa. Po rozbudowie doN:+10×Nszczęścia wszystkim i podatek×2przez10h. | F61: Premia za ukończenie rozbudowy; kolejna odświeża okres, bez nakładania mnożnika do×4.
A62: U057 | B62: Błogosławieństwo | C62: Kaplica;Latarnia;Człowiek | D62: WCZEŚNIEJ UZGODNIONE / NOWE SZCZEGÓŁY ODŁOŻONE | E62: Ręczne użycie:+50każdego zasobu,+20szczęścia wszystkim na1h. | F62: Dotąd funkcja kaplicy i liczba darmowych użyć=poziom; nowa notatka przy latarni pozostaje do późniejszej decyzji.
A63: U058 | B63: Błogosławieństwo | C63: Kaplica;Latarnia | D63: ODŁOŻONE | E63: Nowe odstępy+25%,zakup/challenge/share/reklama i natychmiastowe użycie. | F63: Konflikt z godzinnym efektem bez nakładania zostawiony na później zgodnie z instrukcją.
A64: U059 | B64: Reklamy | C64: Kaplica;Latarnia | D64: ODŁOŻONE | E64: Nowa notatka:60sreklamy skraca pozostały czas o połowę, maks.2na1hgry. | F64: Nie wybieramy resetu, czasu okna, początku cooldownu ani harmonogramu.
A65: U060 | B65: Lojalność | C65: Człowiek;Wszystkie | D65: ZASADA UZGODNIONA / NAGRODA NIEUSTALONA | E65: Kolejny dzień logowania zwiększa lojalność do10dni; bonus lojalnościowy zostanie zdefiniowany później. | F65: Nie wymyślono nagród. Poprzedni model używał dni Warszawy; szczegóły konta są przyszłe.
A66: U061 | B66: Koszt producenta | C66: Farma;Młyn;Drwale;Tartak;Kamieniołom | D66: AKTUALNE | E66: Norma240×obecny poziom/dobę. Koszt30%drewna,30%kamienia,50%własnego produktu. | F66: 72Ldrewna+72Lkamienia+120Lproduktu;nakładające się materiały sumujemy.
A67: U062 | B67: Koszt producenta | C67: Drwale;Kamieniołom | D67: AKTUALNE | E67: Drwale192Ldrewna+72Lkamienia;kamieniołom72Ldrewna+192Lkamienia. | F67: To nie dodatkowe podwójne naliczenie; suma składnika bazowego i produktu.
A68: U063 | B68: Koszty | C68: Ratusz;Dom;Targ;Magazyn;Przystań | D68: AKTUALNE | E68: 500każdego z6zasobów×obecny poziom. | F68: W tym monety;do przewozu5materiałów,czyli2500×Ljednostek.
A69: U064 | B69: Koszty | C69: Kaplica | D69: TYMCZASOWE | E69: N×(180monet+20drewna+60kamienia+10desek),Nnowy poziom. | F69: Cena nie była docelowo ustalona;do przewozu90×N.
... A97: U092 | B97: Projekt | C97: Wszystkie | D97: AKTUALNE POLECENIE | E97: Wyłącznie Excel i analiza logiczna; bez developmentu. | F97: Plik i instrukcja pobierania są dokumentacją; nie zmieniają kodu gry,zasad ani zapisów.

Sheet Czas budowy
A1: CZAS • tylko transport i sama budowa
A2: Zgodnie z doprecyzowaniem użytkownika NIE uwzględniamy zbierania, karmienia, wcześniejszych rozbudów ani kolejki. Zakładamy gotowe materiały, stale nakarmionych6 tragarzy i zerowe fazy startowe. +10% tragarzy roboczo jako przepustowość; D02 nadal do decyzji. Magazyn na poziomie L, min1.
A5: Budynek | B5: Etap | C5: Obecny L | D5: Nowy N | E5: Ratusz wymagany | F5: Magazyn w scenariuszu | G5: Tragarze | H5: Wydajność/os./h | I5: Monety | J5: Drewno | K5: Kamień | L5: Zboże | M5: Food | N5: Deski | O5: Towary do przewozu | P5: Transport T [h] | Q5: Łącznie ×T | R5: Sama budowa [h] | S5: Transport + budowa [h] | T5: Stan wyliczenia | U5: Założenia
A6: Ratusz | B6: 1→2 | C6: 1 | D6: =C6+1 -> 2 | E6: 1 | F6: 1 | G6: =Parametry!$C$12 -> 6 | H6: =Parametry!$C$9*IF(Parametry!$C$11="Składany",Parametry!$C$10^(F6-1),1+(Parametry!$C$10-1)*(F6-1)) -> 60 | I6: =Parametry!$C$31*MAX(1,C6) -> 500 | J6: =Parametry!$C$31*MAX(1,C6) -> 500 | K6: =Parametry!$C$31*MAX(1,C6) -> 500 | L6: =Parametry!$C$31*MAX(1,C6) -> 500 | M6: =Parametry!$C$31*MAX(1,C6) -> 500 | N6: =Parametry!$C$31*MAX(1,C6) -> 500 | O6: =SUM(J6:N6) -> 2500 | P6: =ROUNDUP(O6/G6,0)/H6 -> 6.95 | Q6: =Parametry!$C$32 -> 3 | R6: =(Q6-1)*P6 -> 13.9 | S6: =Q6*P6 -> 20.85 | T6: SCENARIUSZ WARUNKOWY: D02 | U6: Wyłącznie transport i budowa. Gotowe materiały, bez jedzenia w estymacie, brak kolejki,6 nakarmionych, magazyn poziomu L.
A7: Ratusz | B7: 2→3 | C7: 2 | D7: =C7+1 -> 3 | E7: 2 | F7: 2 | G7: =Parametry!$C$12 -> 6 | H7: =Parametry!$C$9*IF(Parametry!$C$11="Składany",Parametry!$C$10^(F7-1),1+(Parametry!$C$10-1)*(F7-1)) -> 66 | I7: =Parametry!$C$31*MAX(1,C7) -> 1000 | J7: =Parametry!$C$31*MAX(1,C7) -> 1000 | K7: =Parametry!$C$31*MAX(1,C7) -> 1000 | L7: =Parametry!$C$31*MAX(1,C7) -> 1000 | M7: =Parametry!$C$31*MAX(1,C7) -> 1000 | N7: =Parametry!$C$31*MAX(1,C7) -> 1000 | O7: =SUM(J7:N7) -> 5000 | P7: =ROUNDUP(O7/G7,0)/H7 -> 12.636364 | Q7: =Parametry!$C$32 -> 3 | R7: =(Q7-1)*P7 -> 25.272727 | S7: =Q7*P7 -> 37.909091 | T7: SCENARIUSZ WARUNKOWY: D02 | U7: Wyłącznie transport i budowa. Gotowe materiały, bez jedzenia w estymacie, brak kolejki,6 nakarmionych, magazyn poziomu L.
A8: Ratusz | B8: 3→4 | C8: 3 | D8: =C8+1 -> 4 | E8: 3 | F8: 3 | G8: =Parametry!$C$12 -> 6 | H8: =Parametry!$C$9*IF(Parametry!$C$11="Składany",Parametry!$C$10^(F8-1),1+(Parametry!$C$10-1)*(F8-1)) -> 72.6 | I8: =Parametry!$C$31*MAX(1,C8) -> 1500 | J8: =Parametry!$C$31*MAX(1,C8) -> 1500 | K8: =Parametry!$C$31*MAX(1,C8) -> 1500 | L8: =Parametry!$C$31*MAX(1,C8) -> 1500 | M8: =Parametry!$C$31*MAX(1,C8) -> 1500 | N8: =Parametry!$C$31*MAX(1,C8) -> 1500 | O8: =SUM(J8:N8) -> 7500 | P8: =ROUNDUP(O8/G8,0)/H8 -> 17.217631 | Q8: =Parametry!$C$32 -> 3 | R8: =(Q8-1)*P8 -> 34.435262 | S8: =Q8*P8 -> 51.652893 | T8: SCENARIUSZ WARUNKOWY: D02 | U8: Wyłącznie transport i budowa. Gotowe materiały, bez jedzenia w estymacie, brak kolejki,6 nakarmionych, magazyn poziomu L.
A9: Dom | B9: 1→2 | C9: 1 | D9: =C9+1 -> 2 | E9: 2 | F9: 1 | G9: =Parametry!$C$12 -> 6 | H9: =Parametry!$C$9*IF(Parametry!$C$11="Składany",Parametry!$C$10^(F9-1),1+(Parametry!$C$10-1)*(F9-1)) -> 60 | I9: =Parametry!$C$31*MAX(1,C9) -> 500 | J9: =Parametry!$C$31*MAX(1,C9) -> 500 | K9: =Parametry!$C$31*MAX(1,C9) -> 500 | L9: =Parametry!$C$31*MAX(1,C9) -> 500 | M9: =Parametry!$C$31*MAX(1,C9) -> 500 | N9: =Parametry!$C$31*MAX(1,C9) -> 500 | O9: =SUM(J9:N9) -> 2500 | P9: =ROUNDUP(O9/G9,0)/H9 -> 6.95 | Q9: =Parametry!$C$32 -> 3 | R9: =(Q9-1)*P9 -> 13.9 | S9: =Q9*P9 -> 20.85 | T9: SCENARIUSZ WARUNKOWY: D02 | U9: Wyłącznie transport i budowa. Gotowe materiały, bez jedzenia w estymacie, brak kolejki,6 nakarmionych, magazyn poziomu L.
A10: Dom | B10: 2→3 | C10: 2 | D10: =C10+1 -> 3 | E10: 3 | F10: 2 | G10: =Parametry!$C$12 -> 6 | H10: =Parametry!$C$9*IF(Parametry!$C$11="Składany",Parametry!$C$10^(F10-1),1+(Parametry!$C$10-1)*(F10-1)) -> 66 | I10: =Parametry!$C$31*MAX(1,C10) -> 1000 | J10: =Parametry!$C$31*MAX(1,C10) -> 1000 | K10: =Parametry!$C$31*MAX(1,C10) -> 1000 | L10: =Parametry!$C$31*MAX(1,C10) -> 1000 | M10: =Parametry!$C$31*MAX(1,C10) -> 1000 | N10: =Parametry!$C$31*MAX(1,C10) -> 1000 | O10: =SUM(J10:N10) -> 5000 | P10: =ROUNDUP(O10/G10,0)/H10 -> 12.636364 | Q10: =Parametry!$C$32 -> 3 | R10: =(Q10-1)*P10 -> 25.272727 | S10: =Q10*P10 -> 37.909091 | T10: SCENARIUSZ WARUNKOWY: D02 | U10: Wyłącznie transport i budowa. Gotowe materiały, bez jedzenia w estymacie, brak kolejki,6 nakarmionych, magazyn poziomu L.
A11: Dom | B11: 3→4 | C11: 3 | D11: =C11+1 -> 4 | E11: 4 | F11: 3 | G11: =Parametry!$C$12 -> 6 | H11: =Parametry!$C$9*IF(Parametry!$C$11="Składany",Parametry!$C$10^(F11-1),1+(Parametry!$C$10-1)*(F11-1)) -> 72.6 | I11: =Parametry!$C$31*MAX(1,C11) -> 1500 | J11: =Parametry!$C$31*MAX(1,C11) -> 1500 | K11: =Parametry!$C$31*MAX(1,C11) -> 1500 | L11: =Parametry!$C$31*MAX(1,C11) -> 1500 | M11: =Parametry!$C$31*MAX(1,C11) -> 1500 | N11: =Parametry!$C$31*MAX(1,C11) -> 1500 | O11: =SUM(J11:N11) -> 7500 | P11: =ROUNDUP(O11/G11,0)/H11 -> 17.217631 | Q11: =Parametry!$C$32 -> 3 | R11: =(Q11-1)*P11 -> 34.435262 | S11: =Q11*P11 -> 51.652893 | T11: SCENARIUSZ WARUNKOWY: D02 | U11: Wyłącznie transport i budowa. Gotowe materiały, bez jedzenia w estymacie, brak kolejki,6 nakarmionych, magazyn poziomu L.
A12: Farma | B12: 1→2 | C12: 1 | D12: =C12+1 -> 2 | E12: 2 | F12: 1 | G12: =Parametry!$C$12 -> 6 | H12: =Parametry!$C$9*IF(Parametry!$C$11="Składany",Parametry!$C$10^(F12-1),1+(Parametry!$C$10-1)*(F12-1)) -> 60 | I12: =0 -> 0 | J12: =Parametry!$C$27*Parametry!$C$28*C12 -> 72 | K12: =Parametry!$C$27*Parametry!$C$29*C12 -> 72 | L12: =Parametry!$C$27*Parametry!$C$30*C12 -> 120 | M12: =0 -> 0 | N12: =0 -> 0 | O12: =SUM(J12:N12) -> 264 | P12: =ROUNDUP(O12/G12,0)/H12 -> 0.73333333 | Q12: =Parametry!$C$33 -> 2 | R12: =(Q12-1)*P12 -> 0.73333333 | S12: =Q12*P12 -> 1.4666667 | T12: SCENARIUSZ WARUNKOWY: D02 | U12: Wyłącznie transport i budowa. Gotowe materiały, bez jedzenia w estymacie, brak kolejki,6 nakarmionych, magazyn poziomu L.
A13: Farma | B13: 2→3 | C13: 2 | D13: =C13+1 -> 3 | E13: 3 | F13: 2 | G13: =Parametry!$C$12 -> 6 | H13: =Parametry!$C$9*IF(Parametry!$C$11="Składany",Parametry!$C$10^(F13-1),1+(Parametry!$C$10-1)*(F13-1)) -> 66 | I13: =0 -> 0 | J13: =Parametry!$C$27*Parametry!$C$28*C13 -> 144 | K13: =Parametry!$C$27*Parametry!$C$29*C13 -> 144 | L13: =Parametry!$C$27*Parametry!$C$30*C13 -> 240 | M13: =0 -> 0 | N13: =0 -> 0 | O13: =SUM(J13:N13) -> 528 | P13: =ROUNDUP(O13/G13,0)/H13 -> 1.3333333 | Q13: =Parametry!$C$33 -> 2 | R13: =(Q13-1)*P13 -> 1.3333333 | S13: =Q13*P13 -> 2.6666667 | T13: SCENARIUSZ WARUNKOWY: D02 | U13: Wyłącznie transport i budowa. Gotowe materiały, bez jedzenia w estymacie, brak kolejki,6 nakarmionych, magazyn poziomu L.
A14: Farma | B14: 3→4 | C14: 3 | D14: =C14+1 -> 4 | E14: 4 | F14: 3 | G14: =Parametry!$C$12 -> 6 | H14: =Parametry!$C$9*IF(Parametry!$C$11="Składany",Parametry!$C$10^(F14-1),1+(Parametry!$C$10-1)*(F14-1)) -> 72.6 | I14: =0 -> 0 | J14: =Parametry!$C$27*Parametry!$C$28*C14 -> 216 | K14: =Parametry!$C$27*Parametry!$C$29*C14 -> 216 | L14: =Parametry!$C$27*Parametry!$C$30*C14 -> 360 | M14: =0 -> 0 | N14: =0 -> 0 | O14: =SUM(J14:N14) -> 792 | P14: =ROUNDUP(O14/G14,0)/H14 -> 1.8181818 | Q14: =Parametry!$C$33 -> 2 | R14: =(Q14-1)*P14 -> 1.8181818 | S14: =Q14*P14 -> 3.6363636 | T14: SCENARIUSZ WARUNKOWY: D02 | U14: Wyłącznie transport i budowa. Gotowe materiały, bez jedzenia w estymacie, brak kolejki,6 nakarmionych, magazyn poziomu L.
A15: Młyn | B15: 1→2 | C15: 1 | D15: =C15+1 -> 2 | E15: 2 | F15: 1 | G15: =Parametry!$C$12 -> 6 | H15: =Parametry!$C$9*IF(Parametry!$C$11="Składany",Parametry!$C$10^(F15-1),1+(Parametry!$C$10-1)*(F15-1)) -> 60 | I15: =0 -> 0 | J15: =Parametry!$C$27*Parametry!$C$28*C15 -> 72 | K15: =Parametry!$C$27*Parametry!$C$29*C15 -> 72 | L15: =0 -> 0 | M15: =Parametry!$C$27*Parametry!$C$30*C15 -> 120 | N15: =0 -> 0 | O15: =SUM(J15:N15) -> 264 | P15: =ROUNDUP(O15/G15,0)/H15 -> 0.73333333 | Q15: =Parametry!$C$33 -> 2 | R15: =(Q15-1)*P15 -> 0.73333333 | S15: =Q15*P15 -> 1.4666667 | T15: SCENARIUSZ WARUNKOWY: D02 | U15: Wyłącznie transport i budowa. Gotowe materiały, bez jedzenia w estymacie, brak kolejki,6 nakarmionych, magazyn poziomu L.
A16: Młyn | B16: 2→3 | C16: 2 | D16: =C16+1 -> 3 | E16: 3 | F16: 2 | G16: =Parametry!$C$12 -> 6 | H16: =Parametry!$C$9*IF(Parametry!$C$11="Składany",Parametry!$C$10^(F16-1),1+(Parametry!$C$10-1)*(F16-1)) -> 66 | I16: =0 -> 0 | J16: =Parametry!$C$27*Parametry!$C$28*C16 -> 144 | K16: =Parametry!$C$27*Parametry!$C$29*C16 -> 144 | L16: =0 -> 0 | M16: =Parametry!$C$27*Parametry!$C$30*C16 -> 240 | N16: =0 -> 0 | O16: =SUM(J16:N16) -> 528 | P16: =ROUNDUP(O16/G16,0)/H16 -> 1.3333333 | Q16: =Parametry!$C$33 -> 2 | R16: =(Q16-1)*P16 -> 1.3333333 | S16: =Q16*P16 -> 2.6666667 | T16: SCENARIUSZ WARUNKOWY: D02 | U16: Wyłącznie transport i budowa. Gotowe materiały, bez jedzenia w estymacie, brak kolejki,6 nakarmionych, magazyn poziomu L.
A17: Młyn | B17: 3→4 | C17: 3 | D17: =C17+1 -> 4 | E17: 4 | F17: 3 | G17: =Parametry!$C$12 -> 6 | H17: =Parametry!$C$9*IF(Parametry!$C$11="Składany",Parametry!$C$10^(F17-1),1+(Parametry!$C$10-1)*(F17-1)) -> 72.6 | I17: =0 -> 0 | J17: =Parametry!$C$27*Parametry!$C$28*C17 -> 216 | K17: =Parametry!$C$27*Parametry!$C$29*C17 -> 216 | L17: =0 -> 0 | M17: =Parametry!$C$27*Parametry!$C$30*C17 -> 360 | N17: =0 -> 0 | O17: =SUM(J17:N17) -> 792 | P17: =ROUNDUP(O17/G17,0)/H17 -> 1.8181818 | Q17: =Parametry!$C$33 -> 2 | R17: =(Q17-1)*P17 -> 1.8181818 | S17: =Q17*P17 -> 3.6363636 | T17: SCENARIUSZ WARUNKOWY: D02 | U17: Wyłącznie transport i budowa. Gotowe materiały, bez jedzenia w estymacie, brak kolejki,6 nakarmionych, magazyn poziomu L.
A18: Drwale | B18: 1→2 | C18: 1 | D18: =C18+1 -> 2 | E18: 2 | F18: 1 | G18: =Parametry!$C$12 -> 6 | H18: =Parametry!$C$9*IF(Parametry!$C$11="Składany",Parametry!$C$10^(F18-1),1+(Parametry!$C$10-1)*(F18-1)) -> 60 | I18: =0 -> 0 | J18: =Parametry!$C$27*Parametry!$C$28*C18+Parametry!$C$27*Parametry!$C$30*C18 -> 192 | K18: =Parametry!$C$27*Parametry!$C$29*C18 -> 72 | L18: =0 -> 0 | M18: =0 -> 0 | N18: =0 -> 0 | O18: =SUM(J18:N18) -> 264 | P18: =ROUNDUP(O18/G18,0)/H18 -> 0.73333333 | Q18: =Parametry!$C$33 -> 2 | R18: =(Q18-1)*P18 -> 0.73333333 | S18: =Q18*P18 -> 1.4666667 | T18: SCENARIUSZ WARUNKOWY: D02 | U18: Wyłącznie transport i budowa. Gotowe materiały, bez jedzenia w estymacie, brak kolejki,6 nakarmionych, magazyn poziomu L.
A19: Drwale | B19: 2→3 | C19: 2 | D19: =C19+1 -> 3 | E19: 3 | F19: 2 | G19: =Parametry!$C$12 -> 6 | H19: =Parametry!$C$9*IF(Parametry!$C$11="Składany",Parametry!$C$10^(F19-1),1+(Parametry!$C$10-1)*(F19-1)) -> 66 | I19: =0 -> 0 | J19: =Parametry!$C$27*Parametry!$C$28*C19+Parametry!$C$27*Parametry!$C$30*C19 -> 384 | K19: =Parametry!$C$27*Parametry!$C$29*C19 -> 144 | L19: =0 -> 0 | M19: =0 -> 0 | N19: =0 -> 0 | O19: =SUM(J19:N19) -> 528 | P19: =ROUNDUP(O19/G19,0)/H19 -> 1.3333333 | Q19: =Parametry!$C$33 -> 2 | R19: =(Q19-1)*P19 -> 1.3333333 | S19: =Q19*P19 -> 2.6666667 | T19: SCENARIUSZ WARUNKOWY: D02 | U19: Wyłącznie transport i budowa. Gotowe materiały, bez jedzenia w estymacie, brak kolejki,6 nakarmionych, magazyn poziomu L.
A20: Drwale | B20: 3→4 | C20: 3 | D20: =C20+1 -> 4 | E20: 4 | F20: 3 | G20: =Parametry!$C$12 -> 6 | H20: =Parametry!$C$9*IF(Parametry!$C$11="Składany",Parametry!$C$10^(F20-1),1+(Parametry!$C$10-1)*(F20-1)) -> 72.6 | I20: =0 -> 0 | J20: =Parametry!$C$27*Parametry!$C$28*C20+Parametry!$C$27*Parametry!$C$30*C20 -> 576 | K20: =Parametry!$C$27*Parametry!$C$29*C20 -> 216 | L20: =0 -> 0 | M20: =0 -> 0 | N20: =0 -> 0 | O20: =SUM(J20:N20) -> 792 | P20: =ROUNDUP(O20/G20,0)/H20 -> 1.8181818 | Q20: =Parametry!$C$33 -> 2 | R20: =(Q20-1)*P20 -> 1.8181818 | S20: =Q20*P20 -> 3.6363636 | T20: SCENARIUSZ WARUNKOWY: D02 | U20: Wyłącznie transport i budowa. Gotowe materiały, bez jedzenia w estymacie, brak kolejki,6 nakarmionych, magazyn poziomu L.
A21: Tartak | B21: 1→2 | C21: 1 | D21: =C21+1 -> 2 | E21: 2 | F21: 1 | G21: =Parametry!$C$12 -> 6 | H21: =Parametry!$C$9*IF(Parametry!$C$11="Składany",Parametry!$C$10^(F21-1),1+(Parametry!$C$10-1)*(F21-1)) -> 60 | I21: =0 -> 0 | J21: =Parametry!$C$27*Parametry!$C$28*C21 -> 72 | K21: =Parametry!$C$27*Parametry!$C$29*C21 -> 72 | L21: =0 -> 0 | M21: =0 -> 0 | N21: =Parametry!$C$27*Parametry!$C$30*C21 -> 120 | O21: =SUM(J21:N21) -> 264 | P21: =ROUNDUP(O21/G21,0)/H21 -> 0.73333333 | Q21: =Parametry!$C$33 -> 2 | R21: =(Q21-1)*P21 -> 0.73333333 | S21: =Q21*P21 -> 1.4666667 | T21: SCENARIUSZ WARUNKOWY: D02 | U21: Wyłącznie transport i budowa. Gotowe materiały, bez jedzenia w estymacie, brak kolejki,6 nakarmionych, magazyn poziomu L.
A22: Tartak | B22: 2→3 | C22: 2 | D22: =C22+1 -> 3 | E22: 3 | F22: 2 | G22: =Parametry!$C$12 -> 6 | H22: =Parametry!$C$9*IF(Parametry!$C$11="Składany",Parametry!$C$10^(F22-1),1+(Parametry!$C$10-1)*(F22-1)) -> 66 | I22: =0 -> 0 | J22: =Parametry!$C$27*Parametry!$C$28*C22 -> 144 | K22: =Parametry!$C$27*Parametry!$C$29*C22 -> 144 | L22: =0 -> 0 | M22: =0 -> 0 | N22: =Parametry!$C$27*Parametry!$C$30*C22 -> 240 | O22: =SUM(J22:N22) -> 528 | P22: =ROUNDUP(O22/G22,0)/H22 -> 1.3333333 | Q22: =Parametry!$C$33 -> 2 | R22: =(Q22-1)*P22 -> 1.3333333 | S22: =Q22*P22 -> 2.6666667 | T22: SCENARIUSZ WARUNKOWY: D02 | U22: Wyłącznie transport i budowa. Gotowe materiały, bez jedzenia w estymacie, brak kolejki,6 nakarmionych, magazyn poziomu L.
A23: Tartak | B23: 3→4 | C23: 3 | D23: =C23+1 -> 4 | E23: 4 | F23: 3 | G23: =Parametry!$C$12 -> 6 | H23: =Parametry!$C$9*IF(Parametry!$C$11="Składany",Parametry!$C$10^(F23-1),1+(Parametry!$C$10-1)*(F23-1)) -> 72.6 | I23: =0 -> 0 | J23: =Parametry!$C$27*Parametry!$C$28*C23 -> 216 | K23: =Parametry!$C$27*Parametry!$C$29*C23 -> 216 | L23: =0 -> 0 | M23: =0 -> 0 | N23: =Parametry!$C$27*Parametry!$C$30*C23 -> 360 | O23: =SUM(J23:N23) -> 792 | P23: =ROUNDUP(O23/G23,0)/H23 -> 1.8181818 | Q23: =Parametry!$C$33 -> 2 | R23: =(Q23-1)*P23 -> 1.8181818 | S23: =Q23*P23 -> 3.6363636 | T23: SCENARIUSZ WARUNKOWY: D02 | U23: Wyłącznie transport i budowa. Gotowe materiały, bez jedzenia w estymacie, brak kolejki,6 nakarmionych, magazyn poziomu L.
A24: Kamieniołom | B24: 1→2 | C24: 1 | D24: =C24+1 -> 2 | E24: 2 | F24: 1 | G24: =Parametry!$C$12 -> 6 | H24: =Parametry!$C$9*IF(Parametry!$C$11="Składany",Parametry!$C$10^(F24-1),1+(Parametry!$C$10-1)*(F24-1)) -> 60 | I24: =0 -> 0 | J24: =Parametry!$C$27*Parametry!$C$28*C24 -> 72 | K24: =Parametry!$C$27*Parametry!$C$29*C24+Parametry!$C$27*Parametry!$C$30*C24 -> 192 | L24: =0 -> 0 | M24: =0 -> 0 | N24: =0 -> 0 | O24: =SUM(J24:N24) -> 264 | P24: =ROUNDUP(O24/G24,0)/H24 -> 0.73333333 | Q24: =Parametry!$C$33 -> 2 | R24: =(Q24-1)*P24 -> 0.73333333 | S24: =Q24*P24 -> 1.4666667 | T24: SCENARIUSZ WARUNKOWY: D02 | U24: Wyłącznie transport i budowa. Gotowe materiały, bez jedzenia w estymacie, brak kolejki,6 nakarmionych, magazyn poziomu L.
A25: Kamieniołom | B25: 2→3 | C25: 2 | D25: =C25+1 -> 3 | E25: 3 | F25: 2 | G25: =Parametry!$C$12 -> 6 | H25: =Parametry!$C$9*IF(Parametry!$C$11="Składany",Parametry!$C$10^(F25-1),1+(Parametry!$C$10-1)*(F25-1)) -> 66 | I25: =0 -> 0 | J25: =Parametry!$C$27*Parametry!$C$28*C25 -> 144 | K25: =Parametry!$C$27*Parametry!$C$29*C25+Parametry!$C$27*Parametry!$C$30*C25 -> 384 | L25: =0 -> 0 | M25: =0 -> 0 | N25: =0 -> 0 | O25: =SUM(J25:N25) -> 528 | P25: =ROUNDUP(O25/G25,0)/H25 -> 1.3333333 | Q25: =Parametry!$C$33 -> 2 | R25: =(Q25-1)*P25 -> 1.3333333 | S25: =Q25*P25 -> 2.6666667 | T25: SCENARIUSZ WARUNKOWY: D02 | U25: Wyłącznie transport i budowa. Gotowe materiały, bez jedzenia w estymacie, brak kolejki,6 nakarmionych, magazyn poziomu L.
A26: Kamieniołom | B26: 3→4 | C26: 3 | D26: =C26+1 -> 4 | E26: 4 | F26: 3 | G26: =Parametry!$C$12 -> 6 | H26: =Parametry!$C$9*IF(Parametry!$C$11="Składany",Parametry!$C$10^(F26-1),1+(Parametry!$C$10-1)*(F26-1)) -> 72.6 | I26: =0 -> 0 | J26: =Parametry!$C$27*Parametry!$C$28*C26 -> 216 | K26: =Parametry!$C$27*Parametry!$C$29*C26+Parametry!$C$27*Parametry!$C$30*C26 -> 576 | L26: =0 -> 0 | M26: =0 -> 0 | N26: =0 -> 0 | O26: =SUM(J26:N26) -> 792 | P26: =ROUNDUP(O26/G26,0)/H26 -> 1.8181818 | Q26: =Parametry!$C$33 -> 2 | R26: =(Q26-1)*P26 -> 1.8181818 | S26: =Q26*P26 -> 3.6363636 | T26: SCENARIUSZ WARUNKOWY: D02 | U26: Wyłącznie transport i budowa. Gotowe materiały, bez jedzenia w estymacie, brak kolejki,6 nakarmionych, magazyn poziomu L.
A27: Magazyn | B27: 1→2 | C27: 1 | D27: =C27+1 -> 2 | E27: 2 | F27: 1 | G27: =Parametry!$C$12 -> 6 | H27: =Parametry!$C$9*IF(Parametry!$C$11="Składany",Parametry!$C$10^(F27-1),1+(Parametry!$C$10-1)*(F27-1)) -> 60 | I27: =Parametry!$C$31*MAX(1,C27) -> 500 | J27: =Parametry!$C$31*MAX(1,C27) -> 500 | K27: =Parametry!$C$31*MAX(1,C27) -> 500 | L27: =Parametry!$C$31*MAX(1,C27) -> 500 | M27: =Parametry!$C$31*MAX(1,C27) -> 500 | N27: =Parametry!$C$31*MAX(1,C27) -> 500 | O27: =SUM(J27:N27) -> 2500 | P27: =ROUNDUP(O27/G27,0)/H27 -> 6.95 | Q27: =Parametry!$C$34 -> 2 | R27: =(Q27-1)*P27 -> 6.95 | S27: =Q27*P27 -> 13.9 | T27: SCENARIUSZ WARUNKOWY: D02 | U27: Wyłącznie transport i budowa. Gotowe materiały, bez jedzenia w estymacie, brak kolejki,6 nakarmionych, magazyn poziomu L.
A28: Magazyn | B28: 2→3 | C28: 2 | D28: =C28+1 -> 3 | E28: 3 | F28: 2 | G28: =Parametry!$C$12 -> 6 | H28: =Parametry!$C$9*IF(Parametry!$C$11="Składany",Parametry!$C$10^(F28-1),1+(Parametry!$C$10-1)*(F28-1)) -> 66 | I28: =Parametry!$C$31*MAX(1,C28) -> 1000 | J28: =Parametry!$C$31*MAX(1,C28) -> 1000 | K28: =Parametry!$C$31*MAX(1,C28) -> 1000 | L28: =Parametry!$C$31*MAX(1,C28) -> 1000 | M28: =Parametry!$C$31*MAX(1,C28) -> 1000 | N28: =Parametry!$C$31*MAX(1,C28) -> 1000 | O28: =SUM(J28:N28) -> 5000 | P28: =ROUNDUP(O28/G28,0)/H28 -> 12.636364 | Q28: =Parametry!$C$34 -> 2 | R28: =(Q28-1)*P28 -> 12.636364 | S28: =Q28*P28 -> 25.272727 | T28: SCENARIUSZ WARUNKOWY: D02 | U28: Wyłącznie transport i budowa. Gotowe materiały, bez jedzenia w estymacie, brak kolejki,6 nakarmionych, magazyn poziomu L.
A29: Magazyn | B29: 3→4 | C29: 3 | D29: =C29+1 -> 4 | E29: 4 | F29: 3 | G29: =Parametry!$C$12 -> 6 | H29: =Parametry!$C$9*IF(Parametry!$C$11="Składany",Parametry!$C$10^(F29-1),1+(Parametry!$C$10-1)*(F29-1)) -> 72.6 | I29: =Parametry!$C$31*MAX(1,C29) -> 1500 | J29: =Parametry!$C$31*MAX(1,C29) -> 1500 | K29: =Parametry!$C$31*MAX(1,C29) -> 1500 | L29: =Parametry!$C$31*MAX(1,C29) -> 1500 | M29: =Parametry!$C$31*MAX(1,C29) -> 1500 | N29: =Parametry!$C$31*MAX(1,C29) -> 1500 | O29: =SUM(J29:N29) -> 7500 | P29: =ROUNDUP(O29/G29,0)/H29 -> 17.217631 | Q29: =Parametry!$C$34 -> 2 | R29: =(Q29-1)*P29 -> 17.217631 | S29: =Q29*P29 -> 34.435262 | T29: SCENARIUSZ WARUNKOWY: D02 | U29: Wyłącznie transport i budowa. Gotowe materiały, bez jedzenia w estymacie, brak kolejki,6 nakarmionych, magazyn poziomu L.
A30: Targ | B30: 1→2 | C30: 1 | D30: =C30+1 -> 2 | E30: 2 | F30: 1 | G30: =Parametry!$C$12 -> 6 | H30: =Parametry!$C$9*IF(Parametry!$C$11="Składany",Parametry!$C$10^(F30-1),1+(Parametry!$C$10-1)*(F30-1)) -> 60 | I30: =Parametry!$C$31*MAX(1,C30) -> 500 | J30: =Parametry!$C$31*MAX(1,C30) -> 500 | K30: =Parametry!$C$31*MAX(1,C30) -> 500 | L30: =Parametry!$C$31*MAX(1,C30) -> 500 | M30: =Parametry!$C$31*MAX(1,C30) -> 500 | N30: =Parametry!$C$31*MAX(1,C30) -> 500 | O30: =SUM(J30:N30) -> 2500 | P30: =ROUNDUP(O30/G30,0)/H30 -> 6.95 | Q30: =Parametry!$C$34 -> 2 | R30: =(Q30-1)*P30 -> 6.95 | S30: =Q30*P30 -> 13.9 | T30: SCENARIUSZ WARUNKOWY: D02 | U30: Wyłącznie transport i budowa. Gotowe materiały, bez jedzenia w estymacie, brak kolejki,6 nakarmionych, magazyn poziomu L.
A31: Targ | B31: 2→3 | C31: 2 | D31: =C31+1 -> 3 | E31: 3 | F31: 2 | G31: =Parametry!$C$12 -> 6 | H31: =Parametry!$C$9*IF(Parametry!$C$11="Składany",Parametry!$C$10^(F31-1),1+(Parametry!$C$10-1)*(F31-1)) -> 66 | I31: =Parametry!$C$31*MAX(1,C31) -> 1000 | J31: =Parametry!$C$31*MAX(1,C31) -> 1000 | K31: =Parametry!$C$31*MAX(1,C31) -> 1000 | L31: =Parametry!$C$31*MAX(1,C31) -> 1000 | M31: =Parametry!$C$31*MAX(1,C31) -> 1000 | N31: =Parametry!$C$31*MAX(1,C31) -> 1000 | O31: =SUM(J31:N31) -> 5000 | P31: =ROUNDUP(O31/G31,0)/H31 -> 12.636364 | Q31: =Parametry!$C$34 -> 2 | R31: =(Q31-1)*P31 -> 12.636364 | S31: =Q31*P31 -> 25.272727 | T31: SCENARIUSZ WARUNKOWY: D02 | U31: Wyłącznie transport i budowa. Gotowe materiały, bez jedzenia w estymacie, brak kolejki,6 nakarmionych, magazyn poziomu L.
A32: Targ | B32: 3→4 | C32: 3 | D32: =C32+1 -> 4 | E32: 4 | F32: 3 | G32: =Parametry!$C$12 -> 6 | H32: =Parametry!$C$9*IF(Parametry!$C$11="Składany",Parametry!$C$10^(F32-1),1+(Parametry!$C$10-1)*(F32-1)) -> 72.6 | I32: =Parametry!$C$31*MAX(1,C32) -> 1500 | J32: =Parametry!$C$31*MAX(1,C32) -> 1500 | K32: =Parametry!$C$31*MAX(1,C32) -> 1500 | L32: =Parametry!$C$31*MAX(1,C32) -> 1500 | M32: =Parametry!$C$31*MAX(1,C32) -> 1500 | N32: =Parametry!$C$31*MAX(1,C32) -> 1500 | O32: =SUM(J32:N32) -> 7500 | P32: =ROUNDUP(O32/G32,0)/H32 -> 17.217631 | Q32: =Parametry!$C$34 -> 2 | R32: =(Q32-1)*P32 -> 17.217631 | S32: =Q32*P32 -> 34.435262 | T32: SCENARIUSZ WARUNKOWY: D02 | U32: Wyłącznie transport i budowa. Gotowe materiały, bez jedzenia w estymacie, brak kolejki,6 nakarmionych, magazyn poziomu L.
A33: Przystań | B33: 1→2 | C33: 1 | D33: =C33+1 -> 2 | E33: 4 | F33: 1 | G33: =Parametry!$C$12 -> 6 | H33: =Parametry!$C$9*IF(Parametry!$C$11="Składany",Parametry!$C$10^(F33-1),1+(Parametry!$C$10-1)*(F33-1)) -> 60 | I33: =Parametry!$C$31*MAX(1,C33) -> 500 | J33: =Parametry!$C$31*MAX(1,C33) -> 500 | K33: =Parametry!$C$31*MAX(1,C33) -> 500 | L33: =Parametry!$C$31*MAX(1,C33) -> 500 | M33: =Parametry!$C$31*MAX(1,C33) -> 500 | N33: =Parametry!$C$31*MAX(1,C33) -> 500 | O33: =SUM(J33:N33) -> 2500 | P33: =ROUNDUP(O33/G33,0)/H33 -> 6.95 | Q33: =Parametry!$C$34 -> 2 | R33: =(Q33-1)*P33 -> 6.95 | S33: =Q33*P33 -> 13.9 | T33: SCENARIUSZ WARUNKOWY: D02 | U33: Wyłącznie transport i budowa. Gotowe materiały, bez jedzenia w estymacie, brak kolejki,6 nakarmionych, magazyn poziomu L.
A34: Przystań | B34: 2→3 | C34: 2 | D34: =C34+1 -> 3 | E34: 4 | F34: 2 | G34: =Parametry!$C$12 -> 6 | H34: =Parametry!$C$9*IF(Parametry!$C$11="Składany",Parametry!$C$10^(F34-1),1+(Parametry!$C$10-1)*(F34-1)) -> 66 | I34: =Parametry!$C$31*MAX(1,C34) -> 1000 | J34: =Parametry!$C$31*MAX(1,C34) -> 1000 | K34: =Parametry!$C$31*MAX(1,C34) -> 1000 | L34: =Parametry!$C$31*MAX(1,C34) -> 1000 | M34: =Parametry!$C$31*MAX(1,C34) -> 1000 | N34: =Parametry!$C$31*MAX(1,C34) -> 1000 | O34: =SUM(J34:N34) -> 5000 | P34: =ROUNDUP(O34/G34,0)/H34 -> 12.636364 | Q34: =Parametry!$C$34 -> 2 | R34: =(Q34-1)*P34 -> 12.636364 | S34: =Q34*P34 -> 25.272727 | T34: SCENARIUSZ WARUNKOWY: D02 | U34: Wyłącznie transport i budowa. Gotowe materiały, bez jedzenia w estymacie, brak kolejki,6 nakarmionych, magazyn poziomu L.
A35: Przystań | B35: 3→4 | C35: 3 | D35: =C35+1 -> 4 | E35: 4 | F35: 3 | G35: =Parametry!$C$12 -> 6 | H35: =Parametry!$C$9*IF(Parametry!$C$11="Składany",Parametry!$C$10^(F35-1),1+(Parametry!$C$10-1)*(F35-1)) -> 72.6 | I35: =Parametry!$C$31*MAX(1,C35) -> 1500 | J35: =Parametry!$C$31*MAX(1,C35) -> 1500 | K35: =Parametry!$C$31*MAX(1,C35) -> 1500 | L35: =Parametry!$C$31*MAX(1,C35) -> 1500 | M35: =Parametry!$C$31*MAX(1,C35) -> 1500 | N35: =Parametry!$C$31*MAX(1,C35) -> 1500 | O35: =SUM(J35:N35) -> 7500 | P35: =ROUNDUP(O35/G35,0)/H35 -> 17.217631 | Q35: =Parametry!$C$34 -> 2 | R35: =(Q35-1)*P35 -> 17.217631 | S35: =Q35*P35 -> 34.435262 | T35: SCENARIUSZ WARUNKOWY: D02 | U35: Wyłącznie transport i budowa. Gotowe materiały, bez jedzenia w estymacie, brak kolejki,6 nakarmionych, magazyn poziomu L.
A36: Kaplica | B36: 1→2 | C36: 1 | D36: =C36+1 -> 2 | E36: 2 | F36: 1 | G36: =Parametry!$C$12 -> 6 | H36: =Parametry!$C$9*IF(Parametry!$C$11="Składany",Parametry!$C$10^(F36-1),1+(Parametry!$C$10-1)*(F36-1)) -> 60 | I36: =180*D36 -> 360 | J36: =20*D36 -> 40 | K36: =60*D36 -> 120 | L36: =0*D36 -> 0 | M36: =0*D36 -> 0 | N36: =10*D36 -> 20 | O36: =SUM(J36:N36) -> 180 | P36: =ROUNDUP(O36/G36,0)/H36 -> 0.5 | Q36: =Parametry!$C$35 -> 4 | R36: =(Q36-1)*P36 -> 1.5 | S36: =Q36*P36 -> 2 | T36: SCENARIUSZ WARUNKOWY: D02 | U36: Wyłącznie transport i budowa. Gotowe materiały, bez jedzenia w estymacie, brak kolejki,6 nakarmionych, magazyn poziomu L.
A37: Kaplica | B37: 2→3 | C37: 2 | D37: =C37+1 -> 3 | E37: 3 | F37: 2 | G37: =Parametry!$C$12 -> 6 | H37: =Parametry!$C$9*IF(Parametry!$C$11="Składany",Parametry!$C$10^(F37-1),1+(Parametry!$C$10-1)*(F37-1)) -> 66 | I37: =180*D37 -> 540 | J37: =20*D37 -> 60 | K37: =60*D37 -> 180 | L37: =0*D37 -> 0 | M37: =0*D37 -> 0 | N37: =10*D37 -> 30 | O37: =SUM(J37:N37) -> 270 | P37: =ROUNDUP(O37/G37,0)/H37 -> 0.68181818 | Q37: =Parametry!$C$35 -> 4 | R37: =(Q37-1)*P37 -> 2.0454545 | S37: =Q37*P37 -> 2.7272727 | T37: SCENARIUSZ WARUNKOWY: D02 | U37: Wyłącznie transport i budowa. Gotowe materiały, bez jedzenia w estymacie, brak kolejki,6 nakarmionych, magazyn poziomu L.
A38: Kaplica | B38: 3→4 | C38: 3 | D38: =C38+1 -> 4 | E38: 4 | F38: 3 | G38: =Parametry!$C$12 -> 6 | H38: =Parametry!$C$9*IF(Parametry!$C$11="Składany",Parametry!$C$10^(F38-1),1+(Parametry!$C$10-1)*(F38-1)) -> 72.6 | I38: =180*D38 -> 720 | J38: =20*D38 -> 80 | K38: =60*D38 -> 240 | L38: =0*D38 -> 0 | M38: =0*D38 -> 0 | N38: =10*D38 -> 40 | O38: =SUM(J38:N38) -> 360 | P38: =ROUNDUP(O38/G38,0)/H38 -> 0.82644628 | Q38: =Parametry!$C$35 -> 4 | R38: =(Q38-1)*P38 -> 2.4793388 | S38: =Q38*P38 -> 3.3057851 | T38: SCENARIUSZ WARUNKOWY: D02 | U38: Wyłącznie transport i budowa. Gotowe materiały, bez jedzenia w estymacie, brak kolejki,6 nakarmionych, magazyn poziomu L.
A39: Latarnia | B39: 1→2 | C39: 1 | D39: =C39+1 -> 2 | E39: 2 | F39: 1 | G39: =Parametry!$C$12 -> 6 | H39: =Parametry!$C$9*IF(Parametry!$C$11="Składany",Parametry!$C$10^(F39-1),1+(Parametry!$C$10-1)*(F39-1)) -> 60 | I39: =Parametry!$C$31*MAX(1,C39) -> 500 | J39: =Parametry!$C$31*MAX(1,C39) -> 500 | K39: =Parametry!$C$31*MAX(1,C39) -> 500 | L39: =Parametry!$C$31*MAX(1,C39) -> 500 | M39: =Parametry!$C$31*MAX(1,C39) -> 500 | N39: =Parametry!$C$31*MAX(1,C39) -> 500 | O39: =SUM(J39:N39) -> 2500 | P39: =ROUNDUP(O39/G39,0)/H39 -> 6.95 | Q39: =Parametry!$C$36 -> 6 | R39: =(Q39-1)*P39 -> 34.75 | S39: =Q39*P39 -> 41.7 | T39: SCENARIUSZ WARUNKOWY: D02 | U39: Wyłącznie transport i budowa. Gotowe materiały, bez jedzenia w estymacie, brak kolejki,6 nakarmionych, magazyn poziomu L.
A40: Latarnia | B40: 2→3 | C40: 2 | D40: =C40+1 -> 3 | E40: 3 | F40: 2 | G40: =Parametry!$C$12 -> 6 | H40: =Parametry!$C$9*IF(Parametry!$C$11="Składany",Parametry!$C$10^(F40-1),1+(Parametry!$C$10-1)*(F40-1)) -> 66 | I40: =Parametry!$C$31*MAX(1,C40) -> 1000 | J40: =Parametry!$C$31*MAX(1,C40) -> 1000 | K40: =Parametry!$C$31*MAX(1,C40) -> 1000 | L40: =Parametry!$C$31*MAX(1,C40) -> 1000 | M40: =Parametry!$C$31*MAX(1,C40) -> 1000 | N40: =Parametry!$C$31*MAX(1,C40) -> 1000 | O40: =SUM(J40:N40) -> 5000 | P40: =ROUNDUP(O40/G40,0)/H40 -> 12.636364 | Q40: =Parametry!$C$36 -> 6 | R40: =(Q40-1)*P40 -> 63.181818 | S40: =Q40*P40 -> 75.818182 | T40: SCENARIUSZ WARUNKOWY: D02 | U40: Wyłącznie transport i budowa. Gotowe materiały, bez jedzenia w estymacie, brak kolejki,6 nakarmionych, magazyn poziomu L.
A41: Latarnia | B41: 3→4 | C41: 3 | D41: =C41+1 -> 4 | E41: 4 | F41: 3 | G41: =Parametry!$C$12 -> 6 | H41: =Parametry!$C$9*IF(Parametry!$C$11="Składany",Parametry!$C$10^(F41-1),1+(Parametry!$C$10-1)*(F41-1)) -> 72.6 | I41: =Parametry!$C$31*MAX(1,C41) -> 1500 | J41: =Parametry!$C$31*MAX(1,C41) -> 1500 | K41: =Parametry!$C$31*MAX(1,C41) -> 1500 | L41: =Parametry!$C$31*MAX(1,C41) -> 1500 | M41: =Parametry!$C$31*MAX(1,C41) -> 1500 | N41: =Parametry!$C$31*MAX(1,C41) -> 1500 | O41: =SUM(J41:N41) -> 7500 | P41: =ROUNDUP(O41/G41,0)/H41 -> 17.217631 | Q41: =Parametry!$C$36 -> 6 | R41: =(Q41-1)*P41 -> 86.088154 | S41: =Q41*P41 -> 103.30579 | T41: SCENARIUSZ WARUNKOWY: D02 | U41: Wyłącznie transport i budowa. Gotowe materiały, bez jedzenia w estymacie, brak kolejki,6 nakarmionych, magazyn poziomu L.
A42: Latarnia | B42: 0→1 | C42: 0 | D42: =C42+1 -> 1 | E42: 1 | F42: 1 | G42: =Parametry!$C$12 -> 6 | H42: =Parametry!$C$9*IF(Parametry!$C$11="Składany",Parametry!$C$10^(F42-1),1+(Parametry!$C$10-1)*(F42-1)) -> 60 | I42: =Parametry!$C$31*MAX(1,C42) -> 500 | J42: =Parametry!$C$31*MAX(1,C42) -> 500 | K42: =Parametry!$C$31*MAX(1,C42) -> 500 | L42: =Parametry!$C$31*MAX(1,C42) -> 500 | M42: =Parametry!$C$31*MAX(1,C42) -> 500 | N42: =Parametry!$C$31*MAX(1,C42) -> 500 | O42: =SUM(J42:N42) -> 2500 | P42: =ROUNDUP(O42/G42,0)/H42 -> 6.95 | Q42: =Parametry!$C$36 -> 6 | R42: =(Q42-1)*P42 -> 34.75 | S42: =Q42*P42 -> 41.7 | T42: SCENARIUSZ WARUNKOWY: D02 | U42: Wyłącznie transport i budowa. Gotowe materiały, bez jedzenia w estymacie, brak kolejki,6 nakarmionych, magazyn poziomu L.

Sheet Parametry
A1: PARAMETRY • niebieskie komórki można zmieniać
A2: Zielone reguły przypominają ustalenia; bursztynowe są interpretacją lub scenariuszem. Zmiana parametrów nie jest zmianą gry. Czasy obejmują tylko transport i budowę, bez zbierania, karmienia, kolejki i wcześniejszych rozbudów.
A5: ID | B5: Parametr | C5: Wartość | D5: Jednostka | E5: Status | F5: Znaczenie / zastrzeżenie
A6: pop1 | B6: Populacja na starcie | C6: 12 | D6: osób | E6: UZGODNIONE | F6: W nowej tabeli wszystkie12 osób są wolne.
A7: townlevel | B7: Poziom ratusza — przykład limitu | C7: 1 | D7: poziom | E7: PRZYKŁAD | F7: Limit ludności24×ratusz, przydział do budynku do połowy tego maksimum.
A8: prod | B8: Produkcja nakarmionego pracownika | C8: 10 | D8: szt./h | E8: UZGODNIONE | F8: Głód od razu obniża do 5; latarnia mnoży produkcję ×2.
A9: carry | B9: Transport bazowy pracownika na magazynie poziom1 | C9: 60 | D9: szt./h | E9: UZGODNIONE | F9: Dotychczasowa reguła; głód obniża o połowę. Podniesienie poziomu magazynu zwiększa jak ustalone w innym miejscu, takie same zasady dla targu I przystani
A10: carrygrowth | B10: Wzrost przepustowości magazyniera | C10: 1.1 | D10: mnożnik/poziom | E10: ZAŁOŻENIE DO DECYZJI | F10: Interpretujemy +10% pojemności jako przepustowość. Zobacz D02.
A11: carrymode | B11: Sposób wzrostu +10% | C11: Składany | D11: tryb | E11: ZAŁOŻENIE DO DECYZJI | F11: Składany: 60,66,72.6. Liniowy: 60,66,72. D02.
A12: crew | B12: Bazowa obsada transportu w przykładach | C12: 6 | D12: osób | E12: ZAŁOŻENIE MODELU | F12: Kalkulator podnosi obsadę, jeżeli bufor jedzenia nie mieści się z kosztem.
A13: food | B13: Spożycie jednego mieszkańca | C13: 1 | D13: Food/os./h | E13: UZGODNIONE | F13: Automatycznie wyłącznie z centralnego magazynu.
A14: reserve | B14: Rezerwa Food na żywienie | C14: 50 | D14: szt. | E14: ZAAKCEPTOWANE | F14: Food po operacji nieżywieniowej ≥50; ludzie mogą zjadać rezerwę. Uwaga o niewystarczającym buforze zaakceptowana. D03.
A15: home | B15: Powrót zwolnionego do domu | C15: 5 | D15: min | E15: UZGODNIONE | F15: Brak pracy/podatku podczas powrotu; czas dojścia do pracy nieustalony.
A16: per | B16: Magazyn poziom 1: na materiał | C16: 1000 | D16: szt. | E16: UZGODNIONE | F16: Przystań według nowego wpisu ma dostać takie same limity.
A17: total | B17: Magazyn poziom 1: łącznie | C17: 4000 | D17: szt. | E17: UZGODNIONE | F17: Pięć materiałów; monety osobno w skarbcu.
A18: storegrowth | B18: Wzrost pojemności magazynu/portu | C18: 1.5 | D18: mnożnik/poziom | E18: UZGODNIONE / NOWE DLA PORTU | F18: Oba limity, z zaokrągleniem w dół.
A19: buffer | B19: Lokalny bufor producenta | C19: 200 | D19: szt./poziom ratusza | E19: WCZEŚNIEJ UZGODNIONE | F19: Nowe wpisy nie zmieniły pojemności lokalnej na poziom producenta.
A20: towncap | B20: Limit ludności / miejsca domu | C20: 24 | D20: osób/poziom | E20: UZGODNIONE | F20: Ratusz: limit populacji; dom: rzeczywiste miejsca.
A21: minpop | B21: Minimalna populacja | C21: 6 | D21: osób | E21: UZGODNIONE | F21: Ubytek poniżej tej wartości jest blokowany.
A22: tax | B22: Podatek przypisanego pracownika | C22: 1 | D22: moneta/os./h | E22: UZGODNIONE | F22: Kaplica ×2 tylko przez swój bonus. Model zbierania bez bonusu.
A23: feedhappy | B23: Bonus za jedzenie | C23: 1 | D23: pp/os./h | E23: UZGODNIONE | F23: Własny licznik i własne szczęście każdego mieszkańca.
... A53: adfactor | B53: Pozostały cooldown po reklamie | C53: 0.5 | D53: mnożnik | E53: NOWE W ŹRÓDLE | F53: Wyłącznie cooldown; aktywna premia nadal może blokować nowe użycie.

Sheet Decyzje i konflikty
A1: TU COŚ SIĘ NIE SPINA • rejestr decyzji
A2: Żółte i czerwone pozycje nie są nowymi uzgodnieniami. Zachowano instrukcje z pliku, ale nie wypełniono luk arbitralnymi cenami ani rzekomo zatwierdzonymi mechanikami.
A5: ID | B5: Waga | C5: Temat | D5: Co się nie spina | E5: Robocze uzupełnienie / propozycja | F5: Co trzeba rozstrzygnąć | G5: Wpływ na plan
A6: D01 | B6: WYJAŚNIONE CZĘŚCIOWO | C6: Limit pracowników z maksimum ratusza | D6: Użytkownik przypomniał zakres0–połowa maksymalnej populacji. Przyjmujemy w tym projekcie limit12×poziom ratusza oraz dostępność faktycznych wolnych osób. | E6: Maks. przydział docelowy=min(12×ratusz,obecna obsada+wolni). Nie wymaga osobnego wzoru własnego poziomu drwala. Wszędzie tak samo min 0 max połowa z ludzi dostępnych na poziomie budynku od ratusza, czyli ratusz poziom 1 max ludzi 24 wszystkich, max ludzi w każdej z usług 12 Bo to połowa z dostępnych ludzi zakładajc że tyle jest wolnych, jeżei ratusz jest na 2 a np drwal na 1 to nic sie nie zmienia ale jak podniosę drwala do 2 to max dla drwala będzie 24 bo to połowa z 48 etc | F6: Osobny efekt rozbudowy SAMEGO producenta nadal nie wynika z tego limitu. | G6: Rozbudowa ratusza może zwiększyć dostępny limit; nie dodaje automatycznie pracowników.
A7: D02 | B7: DO DECYZJI | C7: +10% pojemności tragarzy | D7: Pojemność jednego kursu nie jest tym samym co liczba sztuk/h; nie ustalono czasu kursu ani wzrostu liniowego/składanego. | E7: Kalkulator roboczo: 60×1.1^(poziom magazynu−1) szt./os./h, głód ×0.5. Przełącznik wzrostu w Parametry. | F7: Potwierdzić interpretację oraz czy premia dotyczy tylko magazynierów. | G7: Wszystkie czasy używające przyspieszenia są warunkowe.
A8: D03 | B8: ZAAKCEPTOWANE | C8: Rezerwa i ryzyko głodu | D8: Rezerwa50 może nie wystarczyć na długi transport; zależność zaakceptowana przez użytkownika. | E8: Chronimy50 przed wynoszeniem; ludzie mogą je jeść. Przykład12osób:50Food wystarcza4h10, a2500materiałów/6tragarzy jedzie6h57. | F8: Uwagi zachowano jako zaakceptowane; nie zwiększamy obsady w kalkulatorze i nie doliczamy karmienia. | G8: Czas nadal liczy wyłącznie transport i budowę przy nakarmionej stałej obsadzie. | I8: Uwaga zaktaulizowane w innym miejscu
A9: D04 | B9: DO DECYZJI | C9: Droga portowa i moment płatności | D9: Sprzedaż ma pobranie z centrali i załadunek; zakupowi brakuje rozładunku i drogi port→centrala. | E9: Sprzedaż: rezerwacja towaru, własna załoga przenosi T, ładuje T, dopiero wpływ monet. Zakup: dopisać symetryczny przepływ i rezerwację pojemności. | F9: Kto rozładowuje i donosi zakup? Kiedy pobierane są monety? Czy jest czas rejsu? | G9: Towar portowy nie może jednocześnie opłacać centralnej budowy/żywienia. | I9: Kazdy towar jest pobierany z magazynu I oddawany do magazynu aby mógł być użyty. Zgodnie z harmonograem prędkością pracy pracowników portu zdefiniwane w innym miejscu, pamiętaj że to są dwa cykle, z magazynu do portu I z portu na statek, przyjmujemy że statek ma pojemność magazynu portu. jak statek wypływa notyfikacja i zapłata, przy zakupie jak statek przypływa zapłata, rozładunek i transport do magazynu
A10: D05 | B10: DO DECYZJI | C10: Dopłata za zakup w ostatnich3h | D10: Nie ustalono globalnego/perprodukt licznika, liniowego/składanego wzrostu, zaokrąglenia i czasu okna. | E10: Liczyć każdą kupioną paczkę100, także kilka w jednym zamówieniu. Propozycja: globalne ruchome okno i liniowe +10% ceny bazowej. | F10: Wybrać wariant. Czy sprzedaż też podnosi ceny? Źródło mówi o zakupach. | G10: Arkusz Przystan pokazuje oba warianty, nie narzuca wyniku. | I10: tak chodzi o to że jak będę intensywnie coś kupował to cena tego będzie rosła, dostosuj liniowo
A11: D06 | B11: DO DECYZJI | C11: 10 monet po24h w porcie | D11: Brakuje jednostki opłaty, powtarzania, płatnika, zachowania przy braku monet i zasad FIFO/wieku partii. | E11: Propozycja do oceny:10 za każdą partię100 po24h; ustalić czy jednorazowo czy codziennie. | F11: Za paczkę, materiał czy cały port? Czy opłata dotyczy własnego zakupu i towaru na sprzedaż? | G11: Nie można wiarygodnie policzyć zysku netto i ryzyka bankructwa. | I11: to jest wyjaśnione w innym miejscu towar nie odebrany w 24 h przepada
A12: D07 | B12: DO DECYZJI | C12: Załoga portu i tempo pracy | D12: Załoga ma sama przenosić i ładować towary; bazowe tempo i udział w+10% magazynu nie są określone. | E12: Roboczo60 szt./os./h na etap; bez automatycznego bonusu magazynu; głód×0.5. | F12: Potwierdzić tempo, kolejność zleceń i podział ludzi między etapy. | G12: Nie używać magazynierów jako bezpłatnej załogi portu. | I12: tak jak w magazynie z bonusami I zwiększeniem ewektywności zależności od levelu
A13: D08 | B13: ODŁOŻONE | C13: Błogosławieństwo: kaplica czy latarnia | D13: Wcześniej ręczne błogosławieństwo należało do kaplicy, w pliku nową mechanikę wpisano przy latarni. | E13: Zachować oba wpisy i oznaczyć przynależność jako DO DECYZJI. | F13: Użytkownik zdecydował: wracamy do tego później. | G13: Wpływa na liczbę użyć, koszty, odblokowanie i oferty. | I13: błogosławieństwo = kaplica, zwiedzanie = latarnia oba prowadzą do "bonusu/premii"
A14: D09 | B14: ODŁOŻONE | C14: Odstępy+25% i darmowe użycia | D14: Przykład0,1,215 wygląda na momenty0:00,1:00,2:15. Nie określono początku/resetu cooldownu i zgodności z liczbą użyć=poziom kaplicy. | E14: Pokazujemy odstępy1h,1h15,1h33m45… i ich sumę. | F14: Użytkownik zdecydował: wracamy do tego później. | G14: Tabela Blogoslawienstwa jest demonstracją, nie zatwierdzonym harmonogramem. | I14: nie rozumiem
A15: D10 | B15: ODŁOŻONE | C15: Zakup natychmiast i reklama kontra aktywny efekt | D15: Stary efekt trwa1h i blokuje kolejny. Połowienie1h do30min nie pozwoli użyć kolejnego po30min, jeśli pierwszy nadal działa. | E15: Rozdzielić posiadanie użycia, cooldown i blokadę aktywnego efektu. Roboczo next=max(koniec efektu,koniec cooldownu). | F15: Użytkownik zdecydował: wracamy do tego później. | G15: Obietnica „natychmiast” jest sprzeczna z zakazem nakładania, dopóki nie ustalimy zachowania.
A16: D11 | B16: INTERPRETACJA | C16: 3T/4T/6T: suma czy sama budowa | D16: Dotychczas kolumna oznaczała łączny czas. Nowe wartości mogłyby zostać pomylone z czasem samego budowania. | E16: Przyjmujemy SUMĘ: ratusz/dom T+2T; kaplica T+3T; latarnia T+5T. | F16: Potwierdzić tylko jeśli intencją było inne znaczenie. | G16: Arkusz rozdziela T, fazę budowy i sumę. | I16: jest ok transport + budowa, uwaga zmieniłem w niektroych miejscach czasy budowy do ponownego przeliczenia
A17: D12 | B17: WYJAŚNIONE | C17: Zakres estymat czasu | D17: Użytkownik wyłączył zbieranie, karmienie i wymagane wcześniejsze rozbudowy z obliczania czasu. | E17: Liczymy T przewozu i fazę budowy; razem kT. Zasoby są już przygotowane, tragarze nakarmieni i dostępni. | F17: Brak potrzeby liczenia pełnej ścieżki w tym pliku. | G17: Nie ma arkusza ani liczb minimum zbierania. Kolumny czasu zmieniono z doable path na transport+budowa.
A18: D13 | B18: DO DECYZJI | C18: Dojście do pracy i zejście do domu | D18: Uzgodniono powrót5min. Wcześniej przypisanie do pracy było natychmiastowe, nie ustalono czasu wyjścia. | E18: Przypomnienie: powrót5min, brak pracy/podatku i dostępności; niedokończona sztuka przepada. | F18: Czy dojście do pracy też5min? Czy w drodze liczy się jako bezrobocie? | G18: Nie dopisano symetrycznego5min jako uzgodnionego faktu.
A19: D14 | B19: UWAGA O OPŁACALNOŚCI | C19: Potwierdzone ceny portowe | D19: Użytkownik potwierdził40/50 za100 podstawowych oraz70/80 za100 przetworzonych. | E19: Zachowano ceny. Przy2:1:200drewna bez przeróbki sprzedaje się za80, a powstałe100desek za70. | F19: Nie zmieniamy cennika. To konsekwencja obecnych cen, nie pomylenie jednostek. | G19: Przeróbka może służyć budowie i potrzebom osady, ale nie zwiększa wartości sprzedaży w porcie. | I19: zmienione w innym miejscu
A20: D15 | B20: ODŁOŻONE | C20: Reklamy2/h i czas oglądania | D20: Nie ustalono bloków godzinowych/ruchomych60min, liczenia czasu gry i chwili połowienia pozostałego oczekiwania. | E20: Propozycja: ruchome60min aktywnej gry, nagroda po zakończonej60s reklamie, raz za daną reklamę. | F20: Użytkownik zdecydował: wracamy do tego później. | G20: Wyliczenie W/2 iW/4 jest samym rabatem, nie zawiera60s oglądania. | I20: później, zrób dodatkową zakładkę premium gdzie zbierzemy taki rodzaj akcji
A21: D16 | B21: DO DECYZJI | C21: Tymczasowy koszt kaplicy | D21: Źródło pozostawia koszt N×(180monet+20drewna+60kamienia+10desek) jako tymczasowy. | E21: Zachowano cenę i wyróżniono ostrzeżenie. | F21: Zatwierdzić tę cenę lub podać nową. | G21: Jej przykład czasowy jest warunkowy względem tej ceny. | I21: nie rozumiem
A22: D17 | B22: DO DECYZJI | C22: Płatne/challenge/social/reklama | D22: Poza opisem błogosławieństw brak cen, ilości, czasu, limitów i warunków rozliczenia. Nie zdefiniowano też challenge. | E22: TBC zamieniono na jawne „do ustalenia”. Zachowano wcześniejszy pomysł globalnego pakietu budowy, bez ceny ani sprzedaży. | F22: Co można kupić, za ile, jaki challenge i co uznajemy za udostępnienie? | G22: Nie wpisano fikcyjnych cen ani działającej integracji z FB/Instagram. | I22: później, zrób dodatkową zakładkę premium gdzie zbierzemy taki rodzaj akcji
A23: D18 | B23: UZGODNIONE Z UZUPEŁNIENIEM | C23: Demografia przy szczęściu | D23: Tempo już ustalono; spadek populacji nie został nazwany jednoznacznie śmiercią. | E23: 0%=0; ±25%=1/12h;±50%=1/6h;±75%=1/1h43;±100%=1/h; min6; max24×ratusz. | F23: Opcjonalnie nazwać ubytek: odejście czy śmierć. | G23: To tempo płynnie zależne od dokładnej średniej, nie zaokrąglonego procentu. | I23: ubytek odejście nie śmierć zdefiniowane w innym miejscu
A24: D19 | B24: INFORMACJA | C24: Start0 pracowników | D24: Nowy plik ustawia0 w gospodarce zamiast wcześniejszych6 startowych przypisań. | E24: 12 wolnych mieszkańców, ręczny przydział dostępny od razu; przed przydziałem brak produkcji i podatków. | F24: Nie blokować ręcznego startu kosztem monet ani zasobów. | G24: 100Food starcza12 osobom na8h20 aktywnej gry bez nowych dostaw; potem stopniowo działają reguły głodu.
A25: D20 | B25: NOWE WYMAGANIE | C25: Powiadomienia o przeludnieniu | D25: W źródle dodano komunikat o przeludnieniu; nie należy nazywać go już wdrożonym. | E25: Projekt: przy przejściu z braku do przeludnienia oraz po zmianie liczby osób bez miejsca, bez spamu co klatkę. | F25: Potwierdzić powtarzanie/próg przypomnienia. | G25: Arkusz opisuje projekt. Żadne nowe powiadomienie nie zostało zaimplementowane.

Sheet Populacja i szczescie
A1: POPULACJA • przyrost i ubytek zostały ustalone
A2: Wartość jest średnią indywidualnego szczęścia. Czas aktywny: pauza, ukrycie i offline zatrzymują mechanikę. Ustalono ubytek populacji, nie nazwano go jednoznacznie śmiercią. Obliczenia zachowują ułamki; prezentacja zaokrągla w górę.
A5: Szczęście dokładne [%] | B5: Zmiana osób / h | C5: Czas na1 osobę [h] | D5: Znaczenie | E5: Uwagi
A6: -100 | B6: =SIGN(A6)*IF(ABS(A6)<=50,ABS(A6)/300,1/6+(ABS(A6)-50)/60) -> -1 | C6: =IF(B6=0,"brak zmiany",1/ABS(B6)) -> 1 | D6: Ubywa | E6: Minimum6 osób; maksimum24×poziom ratusza. Narodziny/ubytek nie są liczone skokiem raz na godzinę. Zabierasz ludzi z domu, jak nie ma w domu to z gospodarki w której jest ich najwiecej, jak wszędzie jest równo to najpierw z portu, później z produkcji desek, kamieniołomu drwala, na końcu z produkcji z żywności i transportu
A7: -75 | B7: =SIGN(A7)*IF(ABS(A7)<=50,ABS(A7)/300,1/6+(ABS(A7)-50)/60) -> -0.58333333 | C7: =IF(B7=0,"brak zmiany",1/ABS(B7)) -> 1.7142857 | D7: Ubywa | E7: Minimum6 osób; maksimum24×poziom ratusza. Narodziny/ubytek nie są liczone skokiem raz na godzinę.
A8: -50 | B8: =SIGN(A8)*IF(ABS(A8)<=50,ABS(A8)/300,1/6+(ABS(A8)-50)/60) -> -0.16666667 | C8: =IF(B8=0,"brak zmiany",1/ABS(B8)) -> 6 | D8: Ubywa | E8: Minimum6 osób; maksimum24×poziom ratusza. Narodziny/ubytek nie są liczone skokiem raz na godzinę.
A9: -25 | B9: =SIGN(A9)*IF(ABS(A9)<=50,ABS(A9)/300,1/6+(ABS(A9)-50)/60) -> -0.083333333 | C9: =IF(B9=0,"brak zmiany",1/ABS(B9)) -> 12 | D9: Ubywa | E9: Minimum6 osób; maksimum24×poziom ratusza. Narodziny/ubytek nie są liczone skokiem raz na godzinę.
A10: 0 | B10: =SIGN(A10)*IF(ABS(A10)<=50,ABS(A10)/300,1/6+(ABS(A10)-50)/60) -> 0 | C10: =IF(B10=0,"brak zmiany",1/ABS(B10)) -> brak zmiany | D10: Populacja bez zmian | E10: Minimum6 osób; maksimum24×poziom ratusza. Narodziny/ubytek nie są liczone skokiem raz na godzinę.
A11: 25 | B11: =SIGN(A11)*IF(ABS(A11)<=50,ABS(A11)/300,1/6+(ABS(A11)-50)/60) -> 0.083333333 | C11: =IF(B11=0,"brak zmiany",1/ABS(B11)) -> 12 | D11: Przybywa | E11: Minimum6 osób; maksimum24×poziom ratusza. Narodziny/ubytek nie są liczone skokiem raz na godzinę. Dokładasz ludzi zawsze do domu
A12: 50 | B12: =SIGN(A12)*IF(ABS(A12)<=50,ABS(A12)/300,1/6+(ABS(A12)-50)/60) -> 0.16666667 | C12: =IF(B12=0,"brak zmiany",1/ABS(B12)) -> 6 | D12: Przybywa | E12: Minimum6 osób; maksimum24×poziom ratusza. Narodziny/ubytek nie są liczone skokiem raz na godzinę.
A13: 75 | B13: =SIGN(A13)*IF(ABS(A13)<=50,ABS(A13)/300,1/6+(ABS(A13)-50)/60) -> 0.58333333 | C13: =IF(B13=0,"brak zmiany",1/ABS(B13)) -> 1.7142857 | D13: Przybywa | E13: Minimum6 osób; maksimum24×poziom ratusza. Narodziny/ubytek nie są liczone skokiem raz na godzinę.
A14: 100 | B14: =SIGN(A14)*IF(ABS(A14)<=50,ABS(A14)/300,1/6+(ABS(A14)-50)/60) -> 1 | C14: =IF(B14=0,"brak zmiany",1/ABS(B14)) -> 1 | D14: Przybywa | E14: Minimum6 osób; maksimum24×poziom ratusza. Narodziny/ubytek nie są liczone skokiem raz na godzinę.
A17: WZÓR I PRZYKŁAD
A18: Dla H=|szczęście|: tempo=H/300 osoby/h dla0…50%; dla50…100%:1/6+(H−50)/60. Znak dodatni daje przyrost, ujemny ubytek. ±75% daje1 osobę co1h42min51s. Przy0% brak zmiany. Nowa osoba ma własne szczęście0, dopiero potem otrzymuje aktualne premie wyspy.

Sheet Przystan
A1: PRZYSTAŃ • projekt cen i przepływu
A2: Wszystkie ceny za100 sztuk. Pierwsza paczka bez dopłaty. Kolejne zakupy w ruchomym oknie3h mają+10%, ale wariant/globalność/zaokrąglenie wymagają D05. Formuły pokazują obie interpretacje; sprzedaż pozostaje bazowa. Nie dopisano czasu rejsu.
A5: Paczka100 nr w oknie | B5: Surowce zakup: liniowo | C5: Produkty zakup: liniowo | D5: Surowce zakup: składanie | E5: Produkty zakup: składanie | F5: Sprzedaż surowców | G5: Sprzedaż produktów | H5: Znaczenie / warunki
A6: 1 | B6: =Parametry!$C$38*(1+Parametry!$C$43*(A6-1)) -> 50 | C6: =Parametry!$C$40*(1+Parametry!$C$43*(A6-1)) -> 80 | D6: =Parametry!$C$38*(1+Parametry!$C$43)^(A6-1) -> 50 | E6: =Parametry!$C$40*(1+Parametry!$C$43)^(A6-1) -> 80 | F6: =Parametry!$C$37 -> 40 | G6: =Parametry!$C$39 -> 70 | H6: Kolejne paczki w tym samym oknie, bez wygaśnięć między nimi. Nie cena za sztukę i nie liczba kliknięć.
A7: 2 | B7: =Parametry!$C$38*(1+Parametry!$C$43*(A7-1)) -> 55 | C7: =Parametry!$C$40*(1+Parametry!$C$43*(A7-1)) -> 88 | D7: =Parametry!$C$38*(1+Parametry!$C$43)^(A7-1) -> 55 | E7: =Parametry!$C$40*(1+Parametry!$C$43)^(A7-1) -> 88 | F7: =Parametry!$C$37 -> 40 | G7: =Parametry!$C$39 -> 70 | H7: Kolejne paczki w tym samym oknie, bez wygaśnięć między nimi. Nie cena za sztukę i nie liczba kliknięć.
A8: 3 | B8: =Parametry!$C$38*(1+Parametry!$C$43*(A8-1)) -> 60 | C8: =Parametry!$C$40*(1+Parametry!$C$43*(A8-1)) -> 96 | D8: =Parametry!$C$38*(1+Parametry!$C$43)^(A8-1) -> 60.5 | E8: =Parametry!$C$40*(1+Parametry!$C$43)^(A8-1) -> 96.8 | F8: =Parametry!$C$37 -> 40 | G8: =Parametry!$C$39 -> 70 | H8: Kolejne paczki w tym samym oknie, bez wygaśnięć między nimi. Nie cena za sztukę i nie liczba kliknięć.
A9: 4 | B9: =Parametry!$C$38*(1+Parametry!$C$43*(A9-1)) -> 65 | C9: =Parametry!$C$40*(1+Parametry!$C$43*(A9-1)) -> 104 | D9: =Parametry!$C$38*(1+Parametry!$C$43)^(A9-1) -> 66.55 | E9: =Parametry!$C$40*(1+Parametry!$C$43)^(A9-1) -> 106.48 | F9: =Parametry!$C$37 -> 40 | G9: =Parametry!$C$39 -> 70 | H9: Kolejne paczki w tym samym oknie, bez wygaśnięć między nimi. Nie cena za sztukę i nie liczba kliknięć.
A10: 5 | B10: =Parametry!$C$38*(1+Parametry!$C$43*(A10-1)) -> 70 | C10: =Parametry!$C$40*(1+Parametry!$C$43*(A10-1)) -> 112 | D10: =Parametry!$C$38*(1+Parametry!$C$43)^(A10-1) -> 73.205 | E10: =Parametry!$C$40*(1+Parametry!$C$43)^(A10-1) -> 117.128 | F10: =Parametry!$C$37 -> 40 | G10: =Parametry!$C$39 -> 70 | H10: Kolejne paczki w tym samym oknie, bez wygaśnięć między nimi. Nie cena za sztukę i nie liczba kliknięć.
A11: 6 | B11: =Parametry!$C$38*(1+Parametry!$C$43*(A11-1)) -> 75 | C11: =Parametry!$C$40*(1+Parametry!$C$43*(A11-1)) -> 120 | D11: =Parametry!$C$38*(1+Parametry!$C$43)^(A11-1) -> 80.5255 | E11: =Parametry!$C$40*(1+Parametry!$C$43)^(A11-1) -> 128.8408 | F11: =Parametry!$C$37 -> 40 | G11: =Parametry!$C$39 -> 70 | H11: Kolejne paczki w tym samym oknie, bez wygaśnięć między nimi. Nie cena za sztukę i nie liczba kliknięć.
A12: 7 | B12: =Parametry!$C$38*(1+Parametry!$C$43*(A12-1)) -> 80 | C12: =Parametry!$C$40*(1+Parametry!$C$43*(A12-1)) -> 128 | D12: =Parametry!$C$38*(1+Parametry!$C$43)^(A12-1) -> 88.57805 | E12: =Parametry!$C$40*(1+Parametry!$C$43)^(A12-1) -> 141.72488 | F12: =Parametry!$C$37 -> 40 | G12: =Parametry!$C$39 -> 70 | H12: Kolejne paczki w tym samym oknie, bez wygaśnięć między nimi. Nie cena za sztukę i nie liczba kliknięć.
A13: 8 | B13: =Parametry!$C$38*(1+Parametry!$C$43*(A13-1)) -> 85 | C13: =Parametry!$C$40*(1+Parametry!$C$43*(A13-1)) -> 136 | D13: =Parametry!$C$38*(1+Parametry!$C$43)^(A13-1) -> 97.435855 | E13: =Parametry!$C$40*(1+Parametry!$C$43)^(A13-1) -> 155.89737 | F13: =Parametry!$C$37 -> 40 | G13: =Parametry!$C$39 -> 70 | H13: Kolejne paczki w tym samym oknie, bez wygaśnięć między nimi. Nie cena za sztukę i nie liczba kliknięć.
A14: 9 | B14: =Parametry!$C$38*(1+Parametry!$C$43*(A14-1)) -> 90 | C14: =Parametry!$C$40*(1+Parametry!$C$43*(A14-1)) -> 144 | D14: =Parametry!$C$38*(1+Parametry!$C$43)^(A14-1) -> 107.17944 | E14: =Parametry!$C$40*(1+Parametry!$C$43)^(A14-1) -> 171.4871 | F14: =Parametry!$C$37 -> 40 | G14: =Parametry!$C$39 -> 70 | H14: Kolejne paczki w tym samym oknie, bez wygaśnięć między nimi. Nie cena za sztukę i nie liczba kliknięć.
A15: 10 | B15: =Parametry!$C$38*(1+Parametry!$C$43*(A15-1)) -> 95 | C15: =Parametry!$C$40*(1+Parametry!$C$43*(A15-1)) -> 152 | D15: =Parametry!$C$38*(1+Parametry!$C$43)^(A15-1) -> 117.89738 | E15: =Parametry!$C$40*(1+Parametry!$C$43)^(A15-1) -> 188.63582 | F15: =Parametry!$C$37 -> 40 | G15: =Parametry!$C$39 -> 70 | H15: Kolejne paczki w tym samym oknie, bez wygaśnięć między nimi. Nie cena za sztukę i nie liczba kliknięć.
A18: PRZEPŁYW I OPŁATA — do decyzji, nie implementacja
A19: Sprzedaż | B19: Tylko pełne100. Centrala→port własną załogą T; załadunek statku T. Złoto proponowane po ukończeniu. Monety trafiają do skarbca.
A20: Zakup | B20: Tylko pełne100. DO DECYZJI: moment zapłaty, rozładunek, droga port→centrala, ewentualny rejs i rezerwacja pojemności. Food w porcie nie karmi ludzi.
A21: Pojemność | B21: Jak magazyn:1000 na materiał i4000 łącznie na poziomie1, oba×1.5 na poziom. Nie 4000 na każdy materiał. Monety osobno.
A22: Opłata po24h | B22: Wpisano10monet, ale nie wskazano czy za100, rodzaj czy cały port oraz czy raz czy co dobę. Przykład, nie reguła:10 za100 pochłania25% sprzedaży surowców40 i14.29% produktów70.
A23: BALANS przetwarzania | B23: 200raw→100produktów: sprzedaż bez przeróbki80, po przeróbce70. Zakup200raw100, zakup100produktu80. Potwierdzone przez użytkownika ceny zachowane. Jest to konsekwencja cennika przy przeliczniku2:1.
A24: Rezerwa Food | B24: Propozycja: można wydać max(0,centralnyFood−50), z uwzględnieniem już zarezerwowanych zleceń. Każda pełna paczka100 na sprzedaż wymaga co najmniej150Food w centrali.

Sheet Blogoslawienstwa
A1: BŁOGOSŁAWIEŃSTWA • odłożone przez użytkownika
A2: Użytkownik zdecydował, aby konflikt cooldownu/reklam/natychmiastowego użycia zostawić na później. Nie obliczamy nowych harmonogramów i nie wybieramy mechaniki. Źródło zachowuje pełną notatkę.
A5: Element | B5: Dotychczasowe ustalenie | C5: Nowa notatka ze źródła | D5: Stan
A6: Kaplica: premia rozbudowy | B6: +10×nowy poziom szczęścia wszystkim i podatki×2 przez10h; poziom1 bez efektu pasywnego. | C6: W źródle prośba o przypomnienie premii. | D6: UZGODNIONE
A7: Ręczne błogosławieństwo | B7: +50 każdego z6 zasobów i+20 szczęścia wszystkim na1h. Dotąd liczba darmowych użyć=poziom kaplicy; bez nakładania. | C7: Nowy opis pojawił się przy latarni, z odstępami+25%. | D7: PRZYNALEŻNOŚĆ/ODSTĘPY ODŁOŻONE
A8: Latarnia: premia rozbudowy | B8: 100 szczęścia i produkcja materiałów×2. Obie premie24h×osiągnięty poziom; podatki/transport bez mnożnika. Tu ma być nie + 100 tylko 100 wszyscy są na maksa zadowoleni | C8: =Budynki!F17 -> ŁĄCZNIE6T: transportT +budowa4T. | D8: PREMIA UZGODNIONA
A9: Cooldown i zakupy | B9: Dotąd brak drugiego efektu podczas aktywnej godziny. | C9: Momenty0,1,215; kolejne odstępy+25%; zakup/challenge/share/reklama daje pojedyncze użycie natychmiast. | D9: ODŁOŻONE DO PÓŹNIEJ
A10: Reklamy | B10: Brak zatwierdzonej pełnej mechaniki. | C10: 60s reklamy; pozostałe czekanie/2; limit2reklamy na1h gry. | D10: ODŁOŻONE DO PÓŹNIEJ

Sheet Zrodlo
A1: ŹRÓDŁO • oryginalny wklejony tekst
A2: Treść użytkownika zachowana bez poprawiania literówek ani zmiany wartości. Późniejsze doprecyzowania są zapisane w Start i Decyzje i konflikty. Ten arkusz nie jest modelem ani deklaracją wdrożenia.
A5: Budynek | B5: Po co jest w grze | C5: Liczba ludzi — start / limit | D5: Co daje rozbudowa | E5: Koszty rozbudowy | F5: Czas rozbudowy | G5: Stan | H5: Notyfikacja / Uwagi | I5: Uwagi 2 | J5: Płatatne 1 kasa 2 fb/instagram 3 reklama | K5: szacunek czasu rozbudowy l1-l2 (doable path) | L5: szacunek czasu rozbudowy l2-l3 (doable path) | M5: szacunek czasu rozbudowy l3-l4 (doable path)
A6: Ratusz | B6: Wyznacza poziom gry i limity rozwoju, jest też skarbcem | C6: brak własnych pracowników | D6: +24 limitu mieszkańców, wyższy limit innych budynków, +1 budowa i kolejka, +200 pojemności każdego producenta | E6: 500 × L każdego zasobu | F6: 3T | G6: Gotowe | H6: zawsze notyfikacja o zakończonej budowie | J6: tbc
A7: Dom | B7: Zapewnia mieszkania | C7: brak własnych pracowników ale brak miejsc przy podniesionym poziomie wpływa na szczęście zgodnie z algoprytmem (wpisz go tu) | D7: +24 miejsca; ogranicza karę za przeludnienie | E7: 500 × L każdego zasobu | F7: 3T | G7: Gotowe | H7: zawsze notyfikacja o zakończonej budowie, dodatkowo o przeludnieniu | J7: tbc
A8: Farma | B8: Produkuje zboże | C8: 0/ limit | D8: Korzyść z własnego poziomu do ustalenia | E8: L × (72 drewna + 72 kamienia + 120 zboża) | F8: 2T | G8: Produkcja działa; efekt rozbudowy wieksza możliwosć produkcji zboża bo mogę mieć wiecej pracowników | H8: zawsze notyfikacja o zakończonej budowie, ; pełny magazyn | I8: jak pełny magazyn to spadek szczęscia zgodnie z ustaleniem (napisz), srawdz także jaki jest czas "dojscia zejscia pracownika z gospdarki do domu | J8: tbc
A9: Młyn | B9: 2 zboża → 1 żywność | C9: 0/ limit | D9: Korzyść z własnego poziomu do ustalenia | E9: L × (72 drewna + 72 kamienia + 120 żywności) | F9: 2T | G9: Produkcja działa; efekt rozbudowy wieksza możliwosć produkcji bo mogę mieć wiecej pracowników | H9: zawsze notyfikacja o zakończonej budowie, ; pełny magazyn | I9: jak pełny magazyn to spadek szczęscia zgodnie z ustaleniem (napisz), srawdz także jaki jest czas "dojscia zejscia pracownika z gospdarki do domu | J9: tbc
A10: Drwale | B10: Produkują drewno | C10: 0/ limit | D10: Korzyść z własnego poziomu do ustalenia | E10: L × (192 drewna + 72 kamienia) | F10: 2T | G10: Produkcja działa; efekt rozbudowy wieksza możliwosć produkcji bo mogę mieć wiecej pracowników | H10: zawsze notyfikacja o zakończonej budowie, ; pełny magazyn | I10: jak pełny magazyn to spadek szczęscia zgodnie z ustaleniem (napisz), srawdz także jaki jest czas "dojscia zejscia pracownika z gospdarki do domu | J10: tbc
A11: Tartak | B11: 2 drewna → 1 deska | C11: 0/ limit | D11: Korzyść z własnego poziomu do ustalenia | E11: L × (72 drewna + 72 kamienia + 120 desek) | F11: 2T | G11: Produkcja działa; efekt rozbudowy wieksza możliwosć produkcji bo mogę mieć wiecej pracowników | H11: zawsze notyfikacja o zakończonej budowie, ; pełny magazyn | I11: jak pełny magazyn to spadek szczęscia zgodnie z ustaleniem (napisz), srawdz także jaki jest czas "dojscia zejscia pracownika z gospdarki do domu | J11: tbc
A12: Kamieniołom | B12: Produkuje kamień | C12: 0/ limit | D12: Korzyść z własnego poziomu do ustalenia | E12: L × (72 drewna + 192 kamienia) | F12: 2T | G12: Produkcja działa; efekt rozbudowy wieksza możliwosć produkcji bo mogę mieć wiecej pracowników | H12: zawsze notyfikacja o zakończonej budowie, ; pełny magazyn | I12: jak pełny magazyn to spadek szczęscia zgodnie z ustaleniem (napisz), srawdz także jaki jest czas "dojscia zejscia pracownika z gospdarki do domu | J12: tbc
A13: Magazyn | B13: Przechowuje i transportuje materiały | C13: 0/ limit | D13: Pojemność na rodzaj i łączna ×1,5 | E13: 500 × L każdego zasobu | F13: 2T | G13: Produkcja działa; efekt rozbudowy wieksza możliwosć produkcji bo mogę mieć wiecej pracowników, na każdym lewelu zwiększa sie też o 10% pojemność tragaży. Zwykła produkcję np drewno lub materioały do rozbudowy np farmy muszą na miejsce zanieść tragaże z magazynu, natomiast jedzenie ludzie pobierają w sposób automagiczny bez koniecznosci jakiejkolwiek akcji jeżeli tylko jest w magazynie, jeżeli w magazynie jest mniej niż 50 jedzenia tragaże nie mogą go wynieść bo to jest rezerwa na żywienie | H13: zawsze notyfikacja o zakończonej budowie, ; pełny magazyn. | I13: Jaka tu była pojemność ustalona przypomnij taką samą daj w przytani ale tam za towar który jest dłużej nić 24 godziny skasuj 10 monet | J13: tbc
A14: Targ | B14: Od poziomu 2 wymienia towary z marżą 10% | C14: 0 / limit po odblokowaniu | D14: Pojemność ×1,5: 1000, 1500, 2250… | E14: 500 × L każdego zasobu | F14: 2T | G14: Gotowe | H14: zawsze notyfikacja o zakończonej budowie, ; pełny magazyn | J14: tbc
A15: Przystań | B15: Od poziomu 4 umożliwia handel za monety | C15: 0 / limit po odblokowaniu | D15: Korzyść kolejnych poziomów do ustalenia | E15: 500 × L każdego zasobu | F15: 2T | G15: Handel działa; kupować I sprzedawać można wszystko dostając złoto lub płacąc złotem, załoga przystani ma ładować statki wiec potyrzebny jest czas na przyniesienie z magazynu (ludzie z magazybnu nie zaopatrują przystani) oraz identyczny czas na załadowanie statku, handować można tylko pełnymi setkami, ceny drewno kamien i zboże 40 sprzedaż 50 kupno (za 100) deski i żywnośći 70 i 80 ale przy każdym drugim zakupie (drugi ilość a nie wartość) i kolejnym w cuiągu ostatnuich 3 hj dodawaj 10% do cen | H15: zawsze notyfikacja o zakończonej budowie, notyfikacja o pełnym magazynie | J15: tbc
A16: Kaplica | B16: Premie szczęścia, podatków i błogosławieństwa | C16: brak ludzi | D16: +1 użycie błogosławieństwa; +10 × N szczęścia i podatki ×2 przez 10 h | E16: Tymczasowo N × (180 monet + 20 drewna + 60 kamienia + 10 desek) | F16: 4T | G16: Premie gotowe; koszt do ustalenia | H16: zawsze notyfikacja o zakończonej budowie; | I16: premia (przypomij jaka); błogosławieństwo | J16: tbc
A17: Latarnia | B17: Wspiera szczęście i produkcję | C17: brak ludzi | D17: +100 szczęścia i produkcja ×2 przez 24 h × N | E17: 500 × max(1, L) każdego zasobu | F17: 6T | G17: Gotowe | H17: zawsze notyfikacja o zakończonej budowie;; uruchomienie premii | I17: Błogosławieństwo: +50 każdego zasobu, +20 szczęścia na 1 h, każde kolejne możłiwe jest + 25% czas później czyli 0, 1 , 215, etc można dokupić albio płacąc albo przec challenge albo przez udostępnienie albo przez reklamę, dokupienuie daje pojedyńcze błofgosławieństwo, natychmiast, jak obejrzyz reklamę 60 sek to zmjniejsza sie czas oczekiwania o połowę, możesz obejrzeć 2 reklamy na 1h grania | J17: tbc
A19: Do tego co napisaliśmy o człowiekach czy ustatliliśmy ilu przybywa jak jest szczęście a ilu umiera jak go nie ma
