Workbook

Sheet Start
A1: HARBORLIGHT V8 • pełne zasady i zmiany interfejsu
A2: Źródło: niezmieniony HARBORLIGHT7-zasady.xlsx, 17 decyzji D01–D17 oraz WSZYSTKIE późniejsze zaakceptowane zmiany frontendu i gospodarki. Nowe arkusze: Zmiany v8, Frontend v8, Atrakcje, Atrakcje - kalkulator, Sciezki, Sciezki - transport, Efekty i notyfikacje, Sprawdzenia v8. Archiwalne źródła i 48 komentarzy użytkownika zachowano. Nowsze decyzje w Zmiany v8 mają pierwszeństwo.
A5: Obszar | B5: Co zmieniono | C5: Gdzie sprawdzić
A6: Główna tabela | B6: 12 budynków + asset Człowiek; własne bufory producentów, dotychczasowe limity pracy i najnowsze widoki bez podatków. | C6: Budynki
A7: Czasy | B7: Pełny bazowy kurs 5 min; ścieżki przyspieszają kursy i od poziomu 3 zwiększają ładunek. Budynki 2T; latarnia 5T; kaplica 4T/7T/10T. | C7: Czas budowy: 74 warianty (37 etapów × bazowy/kolejka).
A8: Kolejka | B8: Pełny koszt przy zleceniu +10%; dopłata materiałowa zmienia liczbę kursów i czas. | C8: Normalnie L budów + L miejsc kolejki. Czekanie w kolejce jest wyłączone z estymat.
A9: Zatrudnienie | B9: Limit 12 × własny poziom, produkcja 10/12/13/14…, 5 min do pracy. Podatki naliczane bez zmian, ale informacja o nich usunięta z UI. | C9: Czlowiek / Produkcja
A10: Offline | B10: Cała gospodarka działa również offline: podatki, jedzenie, szczęście, populacja, produkcja, transport i budowa. | C10: Transport i priorytety; Czlowiek | E10: Front usunąć znaczki czasu
A11: Koszty | B11: Magazyn/Targ: 300 L każdego zasobu; Port: 400 L; Ratusz/Dom: 500 L; Latarnia: 500 × max(1, L). | C11: Parametry / Czas budowy
A12: Transport | B12: Do trzech trwałych numerowanych priorytetów, w tym Construction. Podział kursów 8/2 losowe, 5/3/2 losowe lub 5/3/2. Ratunkowe Food zachowuje ochronę. | C12: Transport i priorytety / Czlowiek. Ratunkowy próg Food oraz rezerwa 50 × poziom magazynu są potwierdzone w V5.
A13: Ceny | B13: Port: podstawowe 40/50, produkty 140/150 za 100; podwyżki zakupowe +10% liniowo. Ostatnia korekta dotyczy PORTU, nie TARGU. | C13: Przystan; Targ: bez monet, marża 10%.
A14: Terminy | B14: Towar w porcie/targu nieodebrany przez 24 h przepada; portowa opłata 10 monet została zniesiona. | C14: Terminy zegarowe, również offline.
A15: Premie i wizyty | B15: Płatne błogosławieństwo: 100 × poziom kaplicy monet; +50 każdego zasobu i +20 pp na 1 h. Kolejne płatne użycie 4 h od KOŃCA efektu: 12:00–13:00 → następne 17:00. Nie można nakładać aktywnych błogosławieństw. Premie od powrotu: uczestnik 100% na 24 h i blokada ponownej wizyty przez te same 24 h; każda osobno wysłana grupa daje populacji +10 pp przez 6 h. Premie grup sumują się w czasie nakładania. | C15: Czlowiek / Blogoslawienstwa / Decyzje v7 D01–D02, D15.
A16: Premium | B16: 25/50/75/100% pozostałej fazy budowania, bez transportu. Cena = MAX(5, FLOOR(zaoszczędzone sekundy / 60)) monet. Transport jest osobno rozliczany za potrzebne kursy. Pełny zakup budynku od poziomu gracza 4: wszystkie materiały według proporcjonalnych bazowych cen zakupu portu ×1,25 + nominalne monety budynku + natychmiastowy transport (10 monet za każdy potrzebny kurs, także niepełny). Nic nie pobieramy z własnych materiałów. Gotowe po 10 s; bez wymogu rzeczywistych tragarzy. | C16: Premium / trzy kalkulatory / Planowanie Premium. | F16: Front w każdej bnudowli możliwość skrócenia CZASU budowy z kosztem oraz możliwość zakupu budyunku z kosztem
A17: Ludzie i ranking | B17: Najpierw dom i ludzie w drodze; potem największa załoga. Remis: port → targ → tartak → kamieniołom → drwale → farma → młyn → magazyn. Zwiedzający i uczestnicy modlitwy chronieni; jeżeli brak osoby uprawnionej, odejście nie zachodzi. Minimum 6. Ranking = Ratusz × monety, aktualizowany co pełną godzinę. | C17: Czlowiek / Populacja i szczescie. | F17: tu nie ma konfliktu opisałem już zabieraz najpierw z domu, później z miejsca gdzie jesty najwiecej w przypadku remisu kolejność, port, bazar, tartak, kamieniołom drwal, farma młyn transport, musisz kreatywnie chronić produkcji I transportu żywności
A18: Twoje wpisy | B18: Zachowano wszystkie 75 tekstowych różnic, również notatki w komórkach, nie tylko komentarze Excel. | C18: Twoje wpisy v1 / Odpowiedzi i zmiany
A19: Niewybrane szczegóły | B19: D01–D17 zamknięte. Na później: integracje kont/płatności, social, reklamy, docelowy balans ekspedycji, osobna modlitwa i wartości nagród lojalności. | C19: Decyzje v7 / Na pozniej.
A20: Nowe pomysły z repozytorium | B20: Ekspedycje i wyzwania latarni otrzymały nowe reguły; sterowanie labiryntem/piłeczką pozostaje do opisania. | C20: Zadania latarni / Ekspedycje / Zrodlo v3.
A21: Zadania latarni | B21: Zawsze 3 oferty, tylko 1 aktywne zadanie. Podświetlony postęp każdego produktu w obu widokach; pozostałe wyszarzone. Po sukcesie fajerwerki, wibracja telefonu i opcjonalny Share on Facebook za 500 monet. | C21: Zadania latarni / Zadania przyklady / Zadania - zegary / Narracje latarni.
A22: Ekspedycje | B22: 50 monet po pierwszym poziomie; każda dalsza wygrana podwaja pulę, a przegrana ją zeruje. Dodatkowe ruchy/czas: monety lub reklama ≤30 s. | C22: Ekspedycje / Ekspedycje - poziomy.
A23: Social i polecenia | B23: Nagrody społecznościowe: 1000/500 monet; polecenie: 1000 monet oraz 500 wszystkiego w 3. aktywnym dniu; 1000 monet za każdy 3. post na FB. | C23: Social i polecenia / Platformy.
A24: Balans i niejasności | B24: Nagrody skalowane od L3 i przechowywane przy braku miejsca; minimum przyspieszenia 5 monet; ekspedycje podwajają pulę. Duże zadania nadal mogą wymagać wcześniejszych zapasów. | C24: Bilans V3; zamknięte kwestie oznaczono wynikiem.
A25: Nowe koszty V5 | B25: Młyn, drwale, tartak, kamieniołom: koszt ×2; farma bez zmian. Czasy i kolejka +10% przeliczone. | C25: Budynki / Czas budowy
A26: Wymaganie interfejsu | B26: Angielskie etykiety liczb, statusy, ETA transportu i budowy; bez podatków; Resources = zapas lokalny / centralny; zarządzanie budową tylko ratusz, pracownikami tylko dom. | C26: Frontend v8 / Zmiany v8; stare notatki w kolumnach E/F są źródłowe.
A27: Dom i nowe osoby | B27: Pula domu = liczba mieszkańców przy odnowieniu, w pełnych pp, raz na 24 h. Ręczne punkty dodają H; nie kasują kar ani ich liczników. O 23 h 58 min automat rozdaje wyłącznie resztę, po 1 pp najniższemu H; remis losowy. Pula nie jest wydawana drugi raz. Każdy nowy mieszkaniec ma zamrożone 0% szczęścia przez pierwsze 24 h, również podczas premii; później zwykłe naliczanie od 0%. Początkowych 12 osób nie obejmuje zamrożenie. | C27: Czlowiek / Decyzje v7 D03–D04, D13
A28: Pakiet i prognozy | B28: Pakiet: 1000 × poziom ratusza monet za 24 h; +4 aktywne budowy, dowolna kolejka, planowanie dostaw. Dopłata kolejki +10% pozostaje; ponowny zakup przedłuża ważność. W aktywnym pakiecie plan ma koszt kolejki +10% (każdy składnik w górę), plus opłatę 25% bazowej portowej wartości zakupu braków centralnych. Baza 300 kamienia, centrala 200 → wymagane 330, brak 130; bufor producenta nie jest centralą. Materiały muszą rzeczywiście dotrzeć. | C28: Premium / Planowanie Premium
A29: Status wdrożenia | B29: Reguły w V8 są zatwierdzone. Prototyp frontendowy ma lokalny zapis; konta, OAuth, płatności i reklamy nie są integrowane. Końcowy commit, publikację i wyniki testów gry zapisujemy w docs/IMPLEMENTATION-LOG.md. | C29: Szczegóły wdrożenia i testów: docs/IMPLEMENTATION-LOG.md; Na pozniej.
... A34: Archiwum | B34: 36 zakładek źródła zachowanych; dawne rejestry i wpisy źródłowe są historią. Aktualny rejestr poprawiono i rozszerzono. | C34: Rejestr historyczny v7 / Rejestr historyczny v6

Sheet Zmiany v8
A1: ZMIANY V8 • komplet późniejszych uzgodnień
A2: Rozmowa po Excelu 7; zaakceptowany pakiet frontend v11 oraz późniejszy pakiet zatwierdzony „go”. Nowsza decyzja zastępuje poprzednią wersję tego samego widoku. Nowsze usunięcie podatków oraz zapasy lokalne/centralne na kartach Resources zastępują wcześniejsze wersje tych samych elementów.
A5: ID | B5: Obszar | C5: Asset / widok | D5: Ostateczna zasada | E5: Uwagi / źródło
A6: V8-001 | B6: Wersja | C6: Wszystkie | D6: V8 opiera się na niezmienionym pliku V7 i późniejszych uzgodnieniach. 17 decyzji D01–D17 nadal obowiązuje poza jawnymi nowszymi korektami. | E6: Decyzje v 7 są zachowane; źródła historyczne nie są nowymi wymaganiami.
A7: V8-002 | B7: Start | C7: Nowy gracz | D7: Ratusz 1, Dom 1, 12 mieszkańców w domu, 0 pracowników, 0% szczęścia; każdy z 6 zasobów po 100. Ścieżki: wszystkie 100 odcinków na 0. | E7: Normalny start nie przyznaje testowego magazynu ani 10 000 monet.
A8: V8-003 | B8: Start | C8: Podgląd testowy | D8: W dotychczasowym podglądzie jednorazowo uzupełniamy centralę do limitu na rodzaj i łącznie oraz do minimum 10 000 monet; większe saldo i postęp zachowane. | E8: Znacznik zapisu zapobiega ponownemu grantowi po odświeżeniu. To migracja piaskownicy, nie zasada startu.
A9: V8-004 | B9: Start | C9: Oddzielny nowy gracz | D9: Link profile=new-player używa oddzielnego zapisu i normalnych wartości startowych. Nie kasuje bieżącej wyspy; późniejsze otwarcie kontynuuje zapis tego profilu. | E9: Link i stan wdrożenia: docs/IMPLEMENTATION-LOG.md.
A10: V8-005 | B10: Produkcja | C10: Pięciu producentów | D10: Lokalny magazyn = 200 × WŁASNY poziom producenta. Następny poziom ma 200 × (L+1). Wczytanie nie usuwa starszej nadwyżki. | E10: Zastępuje zależność lokalnego bufora od ratusza.
A11: V8-006 | B11: Ludzie | C11: Osiem miejsc pracy | D11: Limit pozostaje 12 × własny poziom zakładu; przydział jest ograniczony wspólną pulą wolnych osób w domu. | E11: Wyświetlanie trzech liczb nie zmienia poziomu wyznaczającego limit.
A12: V8-007 | B12: Frontend | C12: Wszystkie budynki | D12: U góry panelu status odpowiedni do funkcji. Producent: Producing / Waiting for workers / Storage full / Waiting for resources. | E12: Status odświeża się według rzeczywistego stanu.
A13: V8-008 | B13: Frontend | C13: Produkcja | D13: Producing wskazuje produkt, liczbę najbliższych sztuk i czas ich złożenia w lokalnym magazynie. | E13: Uwzględnia rzeczywiste fazy pracy, dojście, głód, surowiec wejściowy i wolne miejsce.
A14: V8-009 | B14: Frontend | C14: Storage | D14: Trzy wartości: In stock / Current cap. / Next level cap. Krótkie podpisy znajdują się pod każdą liczbą. | E14: Np. 50 / 200 / 400; ostatnia liczba oznacza najbliższe ulepszenie, nie końcowy limit gry.
A15: V8-010 | B15: Frontend | C15: Workers | D15: Trzy wartości: Assigned / Free at home / Max workers; małe +/− korzystają z rzeczywistej dostępności mieszkańców. | E15: Np. 5 / 0 / 12. Osoba wracająca lub idąca nie jest wolna w domu.
A16: V8-011 | B16: Frontend | C16: Podatki | D16: Usuń wszystkie informacje o podatkach z interfejsu: nagłówka, ratusza, kart budynków, zarządzania ludźmi i objaśnień. Sam rachunek podatków pozostaje bez zmiany. | E16: Silnik nadal: 1 moneta/os./h po dotarciu, także przy przestoju; kaplica czasowo ×2. Excel dokumentuje tę regułę.
... A53: V8-048 | B53: Stan | C53: Język i zapis | D53: Aktywny interfejs po angielsku. Zachowujemy istniejące zasoby, mieszkańców, budowy, ładunki i zadania; osobne profile nie nadpisują sobie zapisów. | E53: Oryginalny Excel 7 pozostaje niezmieniony. Prawdziwe konta, OAuth, płatności i reklamy nadal wymagają osobnych integracji.

Sheet Frontend v8
A1: FRONTEND V8 • finalne zachowanie interfejsu
A2: Krótkie angielskie podpisy w grze, polski opis zasad. Późniejsza instrukcja usuwa Taxes ze wszystkich widoków i zastępuje dolne free/max na Resources zapasami lokalny/centralny. Rachunek podatków pozostaje bez zmiany.
A5: Widok | B5: Element / podpis | C5: Wartości i zachowanie | D5: Reguła / wyjątek
A6: Panel producenta | B6: Level | C6: Mniejsze pole po lewej. | D6: Pole Taxes zostało usunięte.
A7: Panel producenta | B7: Storage | C7: In stock / Current cap. / Next level cap. | D7: Zapas lokalny / 200 × L / 200 × (L+1).
A8: Miejsce pracy | B8: Workers | C8: Assigned / Free at home / Max workers | D8: Trzy podpisy pod liczbami, np. 5 / 0 / 12.
A9: Miejsce pracy | B9: +/− | C9: Przydział z faktycznie dostępnych osób. | D9: Droga trwa 5 min; brak wolnych osób blokuje plus.
A10: Każdy budynek | B10: Status | C10: Produkcja, blokada albo status odpowiedni do funkcji. | D10: Przy produkcji: produkt, ilość oraz ETA złożenia w lokalnym magazynie.
A11: Wszystkie widoki | B11: Podatki | C11: Bez wyświetlania podatków i ich opisu. | D11: Rachunek i premia kaplicy pozostają bez zmiany.
A12: House | B12: Housing capacity | C12: Populacja / limit ratusza / łóżka / przyrost lub spadek. | D12: Opisy znajdują się pod i.
A13: House | B13: House happiness | C13: Pula i zegar widoczne; opis pod i. | D13: Manage all workers otwierane wyłącznie tutaj.
A14: Town Hall | B14: Construction and queue | C14: Jedyny panel z licznikiem i zarządzaniem kolejką. | D14: Inne budynki zachowują własny Upgrade.
A15: Town Hall | B15: Active effects | C15: Aktywne błogosławieństwa, premie i kary u góry karty. | D15: Źródło, wartość, odbiorcy, czas lub warunek zakończenia; bez podatków.
A16: Producent | B16: Building upgrade | C16: Upgrade, dwa małe czasy i sąsiednia ramka Premium z dwoma przyciskami. | D16: Buy building package / Deliver local stock now. Opisy Coins/Instant pod i.
... A29: New player | B29: profile=new-player | C29: Oddzielny zapis, normalny start po 100 zasobów i 12 osób. | D29: Nie usuwa wyspy testowej; bez grantu 10 000 monet.

Sheet Decyzje v7
A1: DECYZJE V7 • 17 odpowiedzi zamkniętych
A2: Komplet rozstrzygnięć użytkownika z 23.10.2026 po analizie pliku 6. Wszystkie D01–D17 są zaakceptowane. Osobno pozostają jawnie odłożone tematy; nie blokują wydania tego arkusza.
A5: ID | B5: Temat | C5: Zatwierdzona zasada | D5: Źródło / zastosowanie
A6: D01 | B6: Długość premii populacji po latarni | C6: Premie od powrotu: uczestnik 100% na 24 h i blokada ponownej wizyty przez te same 24 h; każda osobno wysłana grupa daje populacji +10 pp przez 6 h. Premie grup sumują się w czasie nakładania. | D6: Odpowiedź użytkownika 23.10.2026; Czlowiek!C31, Blogoslawienstwa!B9, Decyzje i konflikty!G41, rozmowa23.10
A7: D02 | B7: Limit zwiedzania i płatne pakiety | C7: Darmowo 2 × poziom latarni wejść w ruchomych 24 h. Do 3 dodatkowych pakietów/24 h, każdy daje 2L wejść; cena 300 × numer pakietu (2, 3, 4) × L. Pakiet nie zwiększa liczby miejsc jednocześnie. | D7: Odpowiedź użytkownika 23.10.2026; Premium!G27, rozmowa23.10
A8: D03 | B8: Dom: efekt ręcznie rozdawanego szczęścia | C8: Punkty domu dodają pełne pp do H; kary i ich liczniki pozostają. Przykład: −50 +1 = −49%. | D8: Odpowiedź użytkownika 23.10.2026; Budynki!K7
A9: D04 | B9: Dom: pula i automat23h58 | C9: Pula domu = liczba mieszkańców przy odnowieniu, w pełnych pp, raz na 24 h. Ręczne punkty dodają H; nie kasują kar ani ich liczników. O 23 h 58 min automat rozdaje wyłącznie resztę, po 1 pp najniższemu H; remis losowy. Pula nie jest wydawana drugi raz. | D9: Odpowiedź użytkownika 23.10.2026; Budynki!K7
A10: D05 | B10: Zadania: trzy rozmiary czy kolejka dowolnych rozmiarów | C10: Zawsze 3 zadania. Początkowo małe/średnie/duże; kolejne losowego rozmiaru trafiają na koniec FIFO, dopuszczalne 3 małe lub 3 duże. Nowe po sukcesie natychmiast. | D10: Odpowiedź użytkownika 23.10.2026; Zadania latarni!C6, Zadania latarni!G19, Decyzje i konflikty!G33
A11: D06 | B11: Zadania: kotwica zegara i natychmiastowe odnowienie | C11: Trzy niezależne łańcuchy. Początkowy termin 6 h. Pierwsze ukończenie kotwiczy kolejne odnowienia do tej godziny następnego dnia (Europe/Warsaw). Wcześniejszy sukces natychmiast daje następcę z zachowaniem tej samej dobowej kotwicy; termin nie resetuje się do kolejnych 6 h. | D11: Odpowiedź użytkownika 23.10.2026; Zadania latarni!G12, Zadania latarni!G18, Decyzje i konflikty!G35
A12: D07 | B12: Zadania: wzór opłacalnej nagrody | C12: Stare zakresy stanowią bazę na poziomie ratusza 3: małe 100–200, średnie do 400, duże do 600 monet oraz 50–1000 każdego rodzaju towaru. Inne poziomy: współczynnik 12 × L × p(L) / 468; całe ilości w dół, minimum 1. Rodzajów nagrody: 1/2/3 dla małego/średniego/dużego. Mnożnik szybkiej reakcji dopiero od tej bazy. | D12: Odpowiedź użytkownika 23.10.2026; Zadania latarni!G25, Zadania latarni!G13, Zadania przyklady
A13: D08 | B13: Zadania: liczba rodzajów nagrody | C13: Nagroda towarowa małego: 1 rodzaj; średniego: 2 różne; dużego: 3 różne. Zakres dotyczy każdego rodzaju. | D13: Odpowiedź użytkownika 23.10.2026; Zadania latarni!E14, Decyzje i konflikty!G36
A14: D09 | B14: Pakiet budowlany: czas działania | C14: Pakiet: 1000 × poziom ratusza monet za 24 h; +4 aktywne budowy, dowolna kolejka, planowanie dostaw. Dopłata kolejki +10% pozostaje; ponowny zakup przedłuża ważność. | D14: Odpowiedź użytkownika 23.10.2026; Premium!G18, Premium!A18:E22
A15: D10 | B15: Planowanie przyszłej budowy: dopłaty i brakujące materiały | C15: W aktywnym pakiecie plan ma koszt kolejki +10% (każdy składnik w górę), plus opłatę 25% bazowej portowej wartości zakupu braków centralnych. Baza 300 kamienia, centrala 200 → wymagane 330, brak 130; bufor producenta nie jest centralą. Materiały muszą rzeczywiście dotrzeć. | D15: Odpowiedź użytkownika 23.10.2026; Budynki!J6, Premium!G22, Ustalenia - uwagi!V2-016
A16: D11 | B16: Kupno budynku: co kończy się natychmiast | C16: Pełny zakup budynku od poziomu gracza 4: wszystkie materiały według proporcjonalnych bazowych cen zakupu portu ×1,25 + nominalne monety budynku + natychmiastowy transport (10 monet za każdy potrzebny kurs, także niepełny). Nic nie pobieramy z własnych materiałów. Gotowe po 10 s; bez wymogu rzeczywistych tragarzy. | D16: Odpowiedź użytkownika 23.10.2026; Premium!G16, Decyzje i konflikty!G24, Premium!C16
... A22: D17 | B22: Kaplica: cena rozbudowy | C22: Zatwierdzono: nowy poziom N × (180 monet + 20 drewna + 60 kamienia + 10 desek). To koszt rozbudowy, odrębny od ceny użycia błogosławieństwa. | D22: Odpowiedź użytkownika 23.10.2026; Decyzje i konflikty!Q14, Budynki!E16

Sheet Budynki
A1: BUDYNKI V8 • aktualne reguły
A2: 12 budynków + asset Człowiek. Aktualne zasady: V7 + Zmiany v8. Kolumna K i komentarze są zachowaną historią użytkownika. Bufory producentów: 200 × własny poziom. Rachunek podatków zachowany, ich informacje usunięte z interfejsu. Czasy porównawcze zależą od parametrów: transport + budowa, bez zbierania i czekania w kolejce.
A5: Budynek / asset | B5: Po co jest | C5: Ludzie | D5: Co daje rozbudowa | E5: Koszt bazowy | F5: Czas łączny | G5: Stan | H5: Notyfikacje | I5: Uwagi i reguły | J5: Premium | K5: Twoje wpisy źródłowe — historia | L5: Źródło zmian | M5: 1→2 transport+budowa | N5: 2→3 transport+budowa | O5: 3→4 transport+budowa
A6: Ratusz | B6: Wyznacza poziom gry i limity rozwoju; skarbiec monet. U góry karty pokazuje aktywne błogosławieństwa, premie i kary. | C6: Brak własnych pracowników. | D6: Maksymalna populacja 24×L, wyższy limit ulepszeń, L budów + L miejsc kolejki. Lokalny magazyn producenta zależy od jego własnego poziomu, nie od ratusza. | E6: 500×L KAŻDEGO z 6 zasobów | F6: 2T = T transportu + T budowy | G6: Uzgodnione w V8; prototyp frontendowy. Szczegóły bieżącego wdrożenia i testów: docs/IMPLEMENTATION-LOG.md. Backend i integracje: Na pozniej. | H6: ZAWSZE: ukończenie budowy. Wcześniej także zlecenie/start/dostawa. Premie/kary: powiadomienie przy aktywacji, zmianie i końcu oraz aktywna lista u góry Town Hall. | I6: Ranking = poziom ratusza × monety. L budów + L miejsc kolejki; zlecenia zakolejkowane mają koszt wyższy o 10%. Ranking: aktualizacja o każdej pełnej godzinie według zastanego stanu ratusza i monet. | J6: Pakiet: 1000 × poziom ratusza monet za 24 h; +4 aktywne budowy, dowolna kolejka, planowanie dostaw. Dopłata kolejki +10% pozostaje; ponowny zakup przedłuża ważność. W aktywnym pakiecie plan ma koszt kolejki +10% (każdy składnik w górę), plus opłatę 25% bazowej portowej wartości zakupu braków centralnych. Baza 300 kamienia, centrala 200 → wymagane 330, brak 130; bufor producenta nie jest centralą. Materiały muszą rzeczywiście dotrzeć. | K6: Budowa: Ratusz na poziomie 1 daje możliwość 1 rozbudowy w tym samym czasie i (o ile mam surowce) jednej zakolejkowanej, ale na tą zakolejkowaną muszę mieć surowce w momencie zlecania. Ratusz na poziomie 2 daje prawo do 2 budów I dwóch obiektów w kolejce pod tym samym warunkiem. Budynki zakolejkowane są o 10 % droższe niż te budowane bez kolejki. Później dopiszemy co oferuje premium (na pewno jedną z opcji będzie skróć czas budowy) | L6: Budynki!wiersz 6; potwierdzenia w Odpowiedzi i zmiany | M6: =TEXT('Czas budowy'!Y6,"0")&" min bazowo; T="&TEXT('Czas budowy'!V6,"0")&" min; budowa="&TEXT('Czas budowy'!X6,"0")&" min. Kolejka +10%: "&TEXT('Czas budowy'!Y7,"0")&" min (bez czekania)." -> 80 min bazowo; T=40 min; budowa=40 min. Kolejka +10%: 90 min (bez czekania). | N6: =TEXT('Czas budowy'!Y8,"0")&" min bazowo; T="&TEXT('Czas budowy'!V8,"0")&" min; budowa="&TEXT('Czas budowy'!X8,"0")&" min. Kolejka +10%: "&TEXT('Czas budowy'!Y9,"0")&" min (bez czekania)." -> 140 min bazowo; T=70 min; budowa=70 min. Kolejka +10%: 150 min (bez czekania). | O6: =TEXT('Czas budowy'!Y10,"0")&" min bazowo; T="&TEXT('Czas budowy'!V10,"0")&" min; budowa="&TEXT('Czas budowy'!X10,"0")&" min. Kolejka +10%: "&TEXT('Czas budowy'!Y11,"0")&" min (bez czekania)." -> 180 min bazowo; T=90 min; budowa=90 min. Kolejka +10%: 200 min (bez czekania).
A7: Dom | B7: Zapewnia miejsca mieszkalne, osobno od maksymalnego limitu ratusza. | C7: Brak własnych pracowników. | D7: Miejsca: 24 × poziom domu; zmniejszenie kary przeludnienia. Panel pokazuje ludzi i przydziały oraz pozwala wysyłać wizyty do kaplicy i latarni. Manage all workers dostępne wyłącznie z domu. Cztery wskaźniki: populacja, limit ratusza, łóżka, przyrost/spadek; opisy pod i. | E7: 500×L KAŻDEGO z 6 zasobów | F7: 2T = T transportu + T budowy | G7: Uzgodnione w V8; prototyp frontendowy. Szczegóły bieżącego wdrożenia i testów: docs/IMPLEMENTATION-LOG.md. Backend i integracje: Na pozniej. | H7: ZAWSZE: ukończenie budowy. Wcześniej także zlecenie/start/dostawa. NOWE: przeludnienie; proponujemy na zmianę stanu, nie co klatkę. Premie/kary: powiadomienie przy aktywacji, zmianie i końcu oraz aktywna lista u góry Town Hall. | I7: Kara przeludnienia: max(0, P − 24 × poziom domu) pp/h każdej osobie. Nowi mieszkańcy zawsze trafiają do domu. Pula domu = liczba mieszkańców przy odnowieniu, w pełnych pp, raz na 24 h. Ręczne punkty dodają H; nie kasują kar ani ich liczników. O 23 h 58 min automat rozdaje wyłącznie resztę, po 1 pp najniższemu H; remis losowy. Pula nie jest wydawana drugi raz. | J7: Premium od L4: 25/50/75/100% pozostałej fazy budowania, bez transportu. Cena = MAX(5, FLOOR(zaoszczędzone sekundy / 60)) monet. Transport jest osobno rozliczany za potrzebne kursy. Pełny zakup budynku od poziomu gracza 4: wszystkie materiały według proporcjonalnych bazowych cen zakupu portu ×1,25 + nominalne monety budynku + natychmiastowy transport (10 monet za każdy potrzebny kurs, także niepełny). Nic nie pobieramy z własnych materiałów. Gotowe po 10 s; bez wymogu rzeczywistych tragarzy. | K7: Z poziomu domu widzę wszystkich ludzi gdzie są dopisani, mogę ich stąd wysyłać do kaplicy lub na latarnię. Mogę podejrzeć szczęście każdego mieszkańca indywidualnie. Dom dostaje 1 x na 24 h doładowanie szczęscia równe 1 pp x aktualna ilość mieszkańców, z poziomu domu mogę to szczęście dać indywidualnej osobie, czylui jeżeli mam 24 osoby podnieść jej szczęscie z 0 do 24 albo dać wszystkim po 1 pp., automat (tem co nada wszystkim) działa po 23h i 58 min i później przychodzi nowa pula. Doładiowanie szczęscia nadpisuje kary za bezrobocie i wszelkie inne. | L7: Budynki!wiersz 7; potwierdzenia w Odpowiedzi i zmiany | M7: =TEXT('Czas budowy'!Y12,"0")&" min bazowo; T="&TEXT('Czas budowy'!V12,"0")&" min; budowa="&TEXT('Czas budowy'!X12,"0")&" min. Kolejka +10%: "&TEXT('Czas budowy'!Y13,"0")&" min (bez czekania)." -> 80 min bazowo; T=40 min; budowa=40 min. Kolejka +10%: 90 min (bez czekania). | N7: =TEXT('Czas budowy'!Y14,"0")&" min bazowo; T="&TEXT('Czas budowy'!V14,"0")&" min; budowa="&TEXT('Czas budowy'!X14,"0")&" min. Kolejka +10%: "&TEXT('Czas budowy'!Y15,"0")&" min (bez czekania)." -> 140 min bazowo; T=70 min; budowa=70 min. Kolejka +10%: 150 min (bez czekania). | O7: =TEXT('Czas budowy'!Y16,"0")&" min bazowo; T="&TEXT('Czas budowy'!V16,"0")&" min; budowa="&TEXT('Czas budowy'!X16,"0")&" min. Kolejka +10%: "&TEXT('Czas budowy'!Y17,"0")&" min (bez czekania)." -> 180 min bazowo; T=90 min; budowa=90 min. Kolejka +10%: 200 min (bez czekania).
A8: Farma | B8: Produkuje zboże do młyna, budowy i wymiany. | C8: Start: 0; limit 12 × WŁASNY poziom budynku, ograniczony liczbą istniejących dostępnych ludzi. Ratusz tylko ogranicza poziom rozbudowy. | D8: Własny poziom daje limit 12 × L pracowników i wydajność na osobę/h: 10, 12, 13, 14…; L1 = 10, L ≥ 2: L + 10. Bufor lokalny: 200 × własny poziom producenta. | E8: L×(72 drewna+72 kamienia+120 zboża) | F8: 2T = T transportu + T budowy | G8: Uzgodnione w V8; prototyp frontendowy. Szczegóły bieżącego wdrożenia i testów: docs/IMPLEMENTATION-LOG.md. Backend i integracje: Na pozniej. | H8: ZAWSZE: ukończenie budowy. Wcześniej także zlecenie/start/dostawa. Powiadomienie o pełnym magazynie. Premie/kary: powiadomienie przy aktywacji, zmianie i końcu oraz aktywna lista u góry Town Hall. | I8: Przestój: podatek płynie, brak +1 pp/h za pracę i brak dodatkowej kary bezrobocia. Kara −10 od początku, kolejne −10 co 24 h, maksymalnie −50 z samego przestoju. Inne kary mogą obniżyć całe H poniżej −50. Reset licznika w drodze do domu. | J8: Premium od L4: 25/50/75/100% pozostałej fazy budowania, bez transportu. Cena = MAX(5, FLOOR(zaoszczędzone sekundy / 60)) monet. Transport jest osobno rozliczany za potrzebne kursy. Pełny zakup budynku od poziomu gracza 4: wszystkie materiały według proporcjonalnych bazowych cen zakupu portu ×1,25 + nominalne monety budynku + natychmiastowy transport (10 monet za każdy potrzebny kurs, także niepełny). Nic nie pobieramy z własnych materiałów. Gotowe po 10 s; bez wymogu rzeczywistych tragarzy. | K8: Do wszystkich produkcyjnych, zwiększenie levelu zwiększa produkcję na 1 h, dla levelu 1 jest to 10 szt / h dla levelu 2 będzie to 12, dla levelu 3 -13 dla 4 - 14 etc W premium dla wszystkich produkcyjnych możłiwość natychmiastowego transportu do magazynu oneclickiem. | L8: Budynki!wiersz 8; potwierdzenia w Odpowiedzi i zmiany | M8: =TEXT('Czas budowy'!Y18,"0")&" min bazowo; T="&TEXT('Czas budowy'!V18,"0")&" min; budowa="&TEXT('Czas budowy'!X18,"0")&" min. Kolejka +10%: "&TEXT('Czas budowy'!Y19,"0")&" min (bez czekania)." -> 10 min bazowo; T=5 min; budowa=5 min. Kolejka +10%: 20 min (bez czekania). | N8: =TEXT('Czas budowy'!Y20,"0")&" min bazowo; T="&TEXT('Czas budowy'!V20,"0")&" min; budowa="&TEXT('Czas budowy'!X20,"0")&" min. Kolejka +10%: "&TEXT('Czas budowy'!Y21,"0")&" min (bez czekania)." -> 20 min bazowo; T=10 min; budowa=10 min. Kolejka +10%: 20 min (bez czekania). | O8: =TEXT('Czas budowy'!Y22,"0")&" min bazowo; T="&TEXT('Czas budowy'!V22,"0")&" min; budowa="&TEXT('Czas budowy'!X22,"0")&" min. Kolejka +10%: "&TEXT('Czas budowy'!Y23,"0")&" min (bez czekania)." -> 20 min bazowo; T=10 min; budowa=10 min. Kolejka +10%: 30 min (bez czekania).
A9: Młyn | B9: Przetwarza 2 zboża z centrali→1 żywność do lokalnego bufora. | C9: Start: 0; limit 12 × WŁASNY poziom budynku, ograniczony liczbą istniejących dostępnych ludzi. Ratusz tylko ogranicza poziom rozbudowy. | D9: Własny poziom daje limit 12 × L pracowników i wydajność na osobę/h: 10, 12, 13, 14…; L1 = 10, L ≥ 2: L + 10. Bufor lokalny: 200 × własny poziom producenta. | E9: 2L×(72 drewna+72 kamienia+120 żywności) | F9: 2T = T transportu + T budowy | G9: Uzgodnione w V8; prototyp frontendowy. Szczegóły bieżącego wdrożenia i testów: docs/IMPLEMENTATION-LOG.md. Backend i integracje: Na pozniej. | H9: ZAWSZE: ukończenie budowy. Wcześniej także zlecenie/start/dostawa. Powiadomienie o pełnym magazynie. Premie/kary: powiadomienie przy aktywacji, zmianie i końcu oraz aktywna lista u góry Town Hall. | I9: Przestój: podatek płynie, brak +1 pp/h za pracę i brak dodatkowej kary bezrobocia. Kara −10 od początku, kolejne −10 co 24 h, maksymalnie −50 z samego przestoju. Inne kary mogą obniżyć całe H poniżej −50. Reset licznika w drodze do domu. | J9: Premium od L4: 25/50/75/100% pozostałej fazy budowania, bez transportu. Cena = MAX(5, FLOOR(zaoszczędzone sekundy / 60)) monet. Transport jest osobno rozliczany za potrzebne kursy. Pełny zakup budynku od poziomu gracza 4: wszystkie materiały według proporcjonalnych bazowych cen zakupu portu ×1,25 + nominalne monety budynku + natychmiastowy transport (10 monet za każdy potrzebny kurs, także niepełny). Nic nie pobieramy z własnych materiałów. Gotowe po 10 s; bez wymogu rzeczywistych tragarzy. | L9: Budynki!wiersz 9; potwierdzenia w Odpowiedzi i zmiany | M9: =TEXT('Czas budowy'!Y24,"0")&" min bazowo; T="&TEXT('Czas budowy'!V24,"0")&" min; budowa="&TEXT('Czas budowy'!X24,"0")&" min. Kolejka +10%: "&TEXT('Czas budowy'!Y25,"0")&" min (bez czekania)." -> 20 min bazowo; T=10 min; budowa=10 min. Kolejka +10%: 20 min (bez czekania). | N9: =TEXT('Czas budowy'!Y26,"0")&" min bazowo; T="&TEXT('Czas budowy'!V26,"0")&" min; budowa="&TEXT('Czas budowy'!X26,"0")&" min. Kolejka +10%: "&TEXT('Czas budowy'!Y27,"0")&" min (bez czekania)." -> 30 min bazowo; T=15 min; budowa=15 min. Kolejka +10%: 30 min (bez czekania). | O9: =TEXT('Czas budowy'!Y28,"0")&" min bazowo; T="&TEXT('Czas budowy'!V28,"0")&" min; budowa="&TEXT('Czas budowy'!X28,"0")&" min. Kolejka +10%: "&TEXT('Czas budowy'!Y29,"0")&" min (bez czekania)." -> 40 min bazowo; T=20 min; budowa=20 min. Kolejka +10%: 50 min (bez czekania).
A10: Drwale | B10: Produkują drewno do tartaku i budowy. | C10: Start: 0; limit 12 × WŁASNY poziom budynku, ograniczony liczbą istniejących dostępnych ludzi. Ratusz tylko ogranicza poziom rozbudowy. | D10: Własny poziom daje limit 12 × L pracowników i wydajność na osobę/h: 10, 12, 13, 14…; L1 = 10, L ≥ 2: L + 10. Bufor lokalny: 200 × własny poziom producenta. | E10: 2L×(192 drewna+72 kamienia) | F10: 2T = T transportu + T budowy | G10: Uzgodnione w V8; prototyp frontendowy. Szczegóły bieżącego wdrożenia i testów: docs/IMPLEMENTATION-LOG.md. Backend i integracje: Na pozniej. | H10: ZAWSZE: ukończenie budowy. Wcześniej także zlecenie/start/dostawa. Powiadomienie o pełnym magazynie. Premie/kary: powiadomienie przy aktywacji, zmianie i końcu oraz aktywna lista u góry Town Hall. | I10: Przestój: podatek płynie, brak +1 pp/h za pracę i brak dodatkowej kary bezrobocia. Kara −10 od początku, kolejne −10 co 24 h, maksymalnie −50 z samego przestoju. Inne kary mogą obniżyć całe H poniżej −50. Reset licznika w drodze do domu. | J10: Premium od L4: 25/50/75/100% pozostałej fazy budowania, bez transportu. Cena = MAX(5, FLOOR(zaoszczędzone sekundy / 60)) monet. Transport jest osobno rozliczany za potrzebne kursy. Pełny zakup budynku od poziomu gracza 4: wszystkie materiały według proporcjonalnych bazowych cen zakupu portu ×1,25 + nominalne monety budynku + natychmiastowy transport (10 monet za każdy potrzebny kurs, także niepełny). Nic nie pobieramy z własnych materiałów. Gotowe po 10 s; bez wymogu rzeczywistych tragarzy. | L10: Budynki!wiersz 10; potwierdzenia w Odpowiedzi i zmiany | M10: =TEXT('Czas budowy'!Y30,"0")&" min bazowo; T="&TEXT('Czas budowy'!V30,"0")&" min; budowa="&TEXT('Czas budowy'!X30,"0")&" min. Kolejka +10%: "&TEXT('Czas budowy'!Y31,"0")&" min (bez czekania)." -> 20 min bazowo; T=10 min; budowa=10 min. Kolejka +10%: 20 min (bez czekania). | N10: =TEXT('Czas budowy'!Y32,"0")&" min bazowo; T="&TEXT('Czas budowy'!V32,"0")&" min; budowa="&TEXT('Czas budowy'!X32,"0")&" min. Kolejka +10%: "&TEXT('Czas budowy'!Y33,"0")&" min (bez czekania)." -> 30 min bazowo; T=15 min; budowa=15 min. Kolejka +10%: 30 min (bez czekania). | O10: =TEXT('Czas budowy'!Y34,"0")&" min bazowo; T="&TEXT('Czas budowy'!V34,"0")&" min; budowa="&TEXT('Czas budowy'!X34,"0")&" min. Kolejka +10%: "&TEXT('Czas budowy'!Y35,"0")&" min (bez czekania)." -> 40 min bazowo; T=20 min; budowa=20 min. Kolejka +10%: 50 min (bez czekania).
A11: Tartak | B11: Przetwarza 2 drewna z centrali→1 deskę do lokalnego bufora. | C11: Start: 0; limit 12 × WŁASNY poziom budynku, ograniczony liczbą istniejących dostępnych ludzi. Ratusz tylko ogranicza poziom rozbudowy. | D11: Własny poziom daje limit 12 × L pracowników i wydajność na osobę/h: 10, 12, 13, 14…; L1 = 10, L ≥ 2: L + 10. Bufor lokalny: 200 × własny poziom producenta. | E11: 2L×(72 drewna+72 kamienia+120 desek) | F11: 2T = T transportu + T budowy | G11: Uzgodnione w V8; prototyp frontendowy. Szczegóły bieżącego wdrożenia i testów: docs/IMPLEMENTATION-LOG.md. Backend i integracje: Na pozniej. | H11: ZAWSZE: ukończenie budowy. Wcześniej także zlecenie/start/dostawa. Powiadomienie o pełnym magazynie. Premie/kary: powiadomienie przy aktywacji, zmianie i końcu oraz aktywna lista u góry Town Hall. | I11: Przestój: podatek płynie, brak +1 pp/h za pracę i brak dodatkowej kary bezrobocia. Kara −10 od początku, kolejne −10 co 24 h, maksymalnie −50 z samego przestoju. Inne kary mogą obniżyć całe H poniżej −50. Reset licznika w drodze do domu. | J11: Premium od L4: 25/50/75/100% pozostałej fazy budowania, bez transportu. Cena = MAX(5, FLOOR(zaoszczędzone sekundy / 60)) monet. Transport jest osobno rozliczany za potrzebne kursy. Pełny zakup budynku od poziomu gracza 4: wszystkie materiały według proporcjonalnych bazowych cen zakupu portu ×1,25 + nominalne monety budynku + natychmiastowy transport (10 monet za każdy potrzebny kurs, także niepełny). Nic nie pobieramy z własnych materiałów. Gotowe po 10 s; bez wymogu rzeczywistych tragarzy. | L11: Budynki!wiersz 11; potwierdzenia w Odpowiedzi i zmiany | M11: =TEXT('Czas budowy'!Y36,"0")&" min bazowo; T="&TEXT('Czas budowy'!V36,"0")&" min; budowa="&TEXT('Czas budowy'!X36,"0")&" min. Kolejka +10%: "&TEXT('Czas budowy'!Y37,"0")&" min (bez czekania)." -> 20 min bazowo; T=10 min; budowa=10 min. Kolejka +10%: 20 min (bez czekania). | N11: =TEXT('Czas budowy'!Y38,"0")&" min bazowo; T="&TEXT('Czas budowy'!V38,"0")&" min; budowa="&TEXT('Czas budowy'!X38,"0")&" min. Kolejka +10%: "&TEXT('Czas budowy'!Y39,"0")&" min (bez czekania)." -> 30 min bazowo; T=15 min; budowa=15 min. Kolejka +10%: 30 min (bez czekania). | O11: =TEXT('Czas budowy'!Y40,"0")&" min bazowo; T="&TEXT('Czas budowy'!V40,"0")&" min; budowa="&TEXT('Czas budowy'!X40,"0")&" min. Kolejka +10%: "&TEXT('Czas budowy'!Y41,"0")&" min (bez czekania)." -> 40 min bazowo; T=20 min; budowa=20 min. Kolejka +10%: 50 min (bez czekania).
A12: Kamieniołom | B12: Produkuje kamień do budowy i wymiany. | C12: Start: 0; limit 12 × WŁASNY poziom budynku, ograniczony liczbą istniejących dostępnych ludzi. Ratusz tylko ogranicza poziom rozbudowy. | D12: Własny poziom daje limit 12 × L pracowników i wydajność na osobę/h: 10, 12, 13, 14…; L1 = 10, L ≥ 2: L + 10. Bufor lokalny: 200 × własny poziom producenta. | E12: 2L×(72 drewna+192 kamienia) | F12: 2T = T transportu + T budowy | G12: Uzgodnione w V8; prototyp frontendowy. Szczegóły bieżącego wdrożenia i testów: docs/IMPLEMENTATION-LOG.md. Backend i integracje: Na pozniej. | H12: ZAWSZE: ukończenie budowy. Wcześniej także zlecenie/start/dostawa. Powiadomienie o pełnym magazynie. Premie/kary: powiadomienie przy aktywacji, zmianie i końcu oraz aktywna lista u góry Town Hall. | I12: Przestój: podatek płynie, brak +1 pp/h za pracę i brak dodatkowej kary bezrobocia. Kara −10 od początku, kolejne −10 co 24 h, maksymalnie −50 z samego przestoju. Inne kary mogą obniżyć całe H poniżej −50. Reset licznika w drodze do domu. | J12: Premium od L4: 25/50/75/100% pozostałej fazy budowania, bez transportu. Cena = MAX(5, FLOOR(zaoszczędzone sekundy / 60)) monet. Transport jest osobno rozliczany za potrzebne kursy. Pełny zakup budynku od poziomu gracza 4: wszystkie materiały według proporcjonalnych bazowych cen zakupu portu ×1,25 + nominalne monety budynku + natychmiastowy transport (10 monet za każdy potrzebny kurs, także niepełny). Nic nie pobieramy z własnych materiałów. Gotowe po 10 s; bez wymogu rzeczywistych tragarzy. | L12: Budynki!wiersz 12; potwierdzenia w Odpowiedzi i zmiany | M12: =TEXT('Czas budowy'!Y42,"0")&" min bazowo; T="&TEXT('Czas budowy'!V42,"0")&" min; budowa="&TEXT('Czas budowy'!X42,"0")&" min. Kolejka +10%: "&TEXT('Czas budowy'!Y43,"0")&" min (bez czekania)." -> 20 min bazowo; T=10 min; budowa=10 min. Kolejka +10%: 20 min (bez czekania). | N12: =TEXT('Czas budowy'!Y44,"0")&" min bazowo; T="&TEXT('Czas budowy'!V44,"0")&" min; budowa="&TEXT('Czas budowy'!X44,"0")&" min. Kolejka +10%: "&TEXT('Czas budowy'!Y45,"0")&" min (bez czekania)." -> 30 min bazowo; T=15 min; budowa=15 min. Kolejka +10%: 30 min (bez czekania). | O12: =TEXT('Czas budowy'!Y46,"0")&" min bazowo; T="&TEXT('Czas budowy'!V46,"0")&" min; budowa="&TEXT('Czas budowy'!X46,"0")&" min. Kolejka +10%: "&TEXT('Czas budowy'!Y47,"0")&" min (bez czekania)." -> 40 min bazowo; T=20 min; budowa=20 min. Kolejka +10%: 50 min (bez czekania).
A13: Magazyn | B13: Przechowuje materiały; własna załoga nosi produkcję do centrali i materiały na budowy. Ludzie jedzą z centrali automatycznie. | C13: Start: 0; limit 12 × WŁASNY poziom budynku, ograniczony liczbą istniejących dostępnych ludzi. Ratusz tylko ogranicza poziom rozbudowy. | D13: Limit załogi: 12 × własny L; ładunek na kurs +10%/poziom. Pojemność ×1.5/poziom; magazyn/port: 1000 na rodzaj i 4000 łącznie na poziomie 1; targ: 1000 łącznie na poziomie 1. | E13: 300 × L każdego z 6 zasobów; w kolejce ×1,1. | F13: 2T = T transportu + T budowy | G13: Uzgodnione w V8; prototyp frontendowy. Szczegóły bieżącego wdrożenia i testów: docs/IMPLEMENTATION-LOG.md. Backend i integracje: Na pozniej. | H13: ZAWSZE: ukończenie budowy. Wcześniej także zlecenie/start/dostawa. Powiadomienie o pełnym magazynie. Premie/kary: powiadomienie przy aktywacji, zmianie i końcu oraz aktywna lista u góry Town Hall. | I13: Rezerwa i próg ratunkowego Food: 50 × poziom magazynu. Gdy Food jest poniżej minimum, a czeka w młynie, nie można ręcznie wycofać całej obsady transportu. ETA budowy przeliczamy po zmianie priorytetów. Podgląd każdej osoby: ładunek, źródło→cel i ETA. Trzy trwałe priorytety spośród produktów i Construction, podział kursów 8/2, 5/3/2 lub 5/3/2. | J13: Premium od L4: 25/50/75/100% pozostałej fazy budowania, bez transportu. Cena = MAX(5, FLOOR(zaoszczędzone sekundy / 60)) monet. Transport jest osobno rozliczany za potrzebne kursy. Pełny zakup budynku od poziomu gracza 4: wszystkie materiały według proporcjonalnych bazowych cen zakupu portu ×1,25 + nominalne monety budynku + natychmiastowy transport (10 monet za każdy potrzebny kurs, także niepełny). Nic nie pobieramy z własnych materiałów. Gotowe po 10 s; bez wymogu rzeczywistych tragarzy. | K13: Transport. Nie rozróżniamy odległości, transport produków zawsze trwa 5 min z/do magazynu x capacity tragarza czyli jeżeli tragarz bierze 60 a potrzebuje przenieść 100 to I tak musi wykonać 2 kursy w jednym bierze 60 w drugim 40, tragarz nie może brać 2 produktow na raz, nie może czekać na towar. Jak klikam rozbudowa np drwala podświetla sie napis ile potrzeba surowców a ile zostało już dostarczonych np 60 /100 i estymowany czas zakońćzenia budowy czyli suma czasu transportu przy aktualnych ustawieniach priorytetów, i budowy. Z poziomu magazynu domyślne prirytety jest najpierw zaopatrz magazyn pózniej budowy, można je zmieniać, dodatkowo też można zmienić ustalić prio na konkretne gospodarstwo bądz konretną budowę, 1 tragarz zawsze będzie nosił żywność o ile jest wyprodukowana a w magazynie jest mniej niż 50 Premium szybszy transport do puntu odbioru | L13: Budynki!wiersz 13; potwierdzenia w Odpowiedzi i zmiany | M13: =TEXT('Czas budowy'!Y48,"0")&" min bazowo; T="&TEXT('Czas budowy'!V48,"0")&" min; budowa="&TEXT('Czas budowy'!X48,"0")&" min. Kolejka +10%: "&TEXT('Czas budowy'!Y49,"0")&" min (bez czekania)." -> 50 min bazowo; T=25 min; budowa=25 min. Kolejka +10%: 50 min (bez czekania). | N13: =TEXT('Czas budowy'!Y50,"0")&" min bazowo; T="&TEXT('Czas budowy'!V50,"0")&" min; budowa="&TEXT('Czas budowy'!X50,"0")&" min. Kolejka +10%: "&TEXT('Czas budowy'!Y51,"0")&" min (bez czekania)." -> 90 min bazowo; T=45 min; budowa=45 min. Kolejka +10%: 90 min (bez czekania). | O13: =TEXT('Czas budowy'!Y52,"0")&" min bazowo; T="&TEXT('Czas budowy'!V52,"0")&" min; budowa="&TEXT('Czas budowy'!X52,"0")&" min. Kolejka +10%: "&TEXT('Czas budowy'!Y53,"0")&" min (bez czekania)." -> 110 min bazowo; T=55 min; budowa=55 min. Kolejka +10%: 120 min (bez czekania).
A14: Targ | B14: Od poziomu gracza 2: wymiana w grupach drewno/kamień/zboże lub deski/żywność, nominalnie 1:1 z marżą 10%. Bez kupowania za monety. | C14: Start: 0; limit 12 × WŁASNY poziom budynku, ograniczony liczbą istniejących dostępnych ludzi. Ratusz tylko ogranicza poziom rozbudowy. | D14: Limit załogi: 12 × własny L; ładunek na kurs +10%/poziom. Pojemność ×1.5/poziom; magazyn/port: 1000 na rodzaj i 4000 łącznie na poziomie 1; targ: 1000 łącznie na poziomie 1. | E14: 300 × L każdego z 6 zasobów; w kolejce ×1,1. | F14: 2T = T transportu + T budowy | G14: Uzgodnione w V8; prototyp frontendowy. Szczegóły bieżącego wdrożenia i testów: docs/IMPLEMENTATION-LOG.md. Backend i integracje: Na pozniej. | H14: ZAWSZE: ukończenie budowy. Wcześniej także zlecenie/start/dostawa. Powiadomienie o pełnym magazynie. Premie/kary: powiadomienie przy aktywacji, zmianie i końcu oraz aktywna lista u góry Town Hall. | I14: Własna załoga w obu kierunkach. Barter w 2 grupach, marża 10%, bez monet. Pozostaje blokada dostaw 1 h; zapas przepada po 24 h od przyniesienia/wymiany. | J14: Premium od L4: 25/50/75/100% pozostałej fazy budowania, bez transportu. Cena = MAX(5, FLOOR(zaoszczędzone sekundy / 60)) monet. Transport jest osobno rozliczany za potrzebne kursy. Pełny zakup budynku od poziomu gracza 4: wszystkie materiały według proporcjonalnych bazowych cen zakupu portu ×1,25 + nominalne monety budynku + natychmiastowy transport (10 monet za każdy potrzebny kurs, także niepełny). Nic nie pobieramy z własnych materiałów. Gotowe po 10 s; bez wymogu rzeczywistych tragarzy. | K14: Premium transport oneclick Ceny grupa 2 140/150 | L14: Budynki!wiersz 14; potwierdzenia w Odpowiedzi i zmiany | M14: =TEXT('Czas budowy'!Y54,"0")&" min bazowo; T="&TEXT('Czas budowy'!V54,"0")&" min; budowa="&TEXT('Czas budowy'!X54,"0")&" min. Kolejka +10%: "&TEXT('Czas budowy'!Y55,"0")&" min (bez czekania)." -> 50 min bazowo; T=25 min; budowa=25 min. Kolejka +10%: 50 min (bez czekania). | N14: =TEXT('Czas budowy'!Y56,"0")&" min bazowo; T="&TEXT('Czas budowy'!V56,"0")&" min; budowa="&TEXT('Czas budowy'!X56,"0")&" min. Kolejka +10%: "&TEXT('Czas budowy'!Y57,"0")&" min (bez czekania)." -> 90 min bazowo; T=45 min; budowa=45 min. Kolejka +10%: 90 min (bez czekania). | O14: =TEXT('Czas budowy'!Y58,"0")&" min bazowo; T="&TEXT('Czas budowy'!V58,"0")&" min; budowa="&TEXT('Czas budowy'!X58,"0")&" min. Kolejka +10%: "&TEXT('Czas budowy'!Y59,"0")&" min (bez czekania)." -> 110 min bazowo; T=55 min; budowa=55 min. Kolejka +10%: 120 min (bez czekania).
A15: Przystań | B15: Od poziomu gracza 4: kupno i sprzedaż pięciu materiałów za monety. Wyłącznie pełne paczki 100. Monety są środkiem płatności, nie osobnym towarem. | C15: Start: 0; limit 12 × WŁASNY poziom budynku, ograniczony liczbą istniejących dostępnych ludzi. Ratusz tylko ogranicza poziom rozbudowy. | D15: Limit załogi: 12 × własny L; ładunek na kurs +10%/poziom. Pojemność ×1.5/poziom; magazyn/port: 1000 na rodzaj i 4000 łącznie na poziomie 1; targ: 1000 łącznie na poziomie 1. | E15: 400 × L każdego z 6 zasobów; w kolejce ×1,1. | F15: 2T = T transportu + T budowy | G15: Uzgodnione w V8; prototyp frontendowy. Szczegóły bieżącego wdrożenia i testów: docs/IMPLEMENTATION-LOG.md. Backend i integracje: Na pozniej. | H15: ZAWSZE: ukończenie budowy. Wcześniej także zlecenie/start/dostawa. Powiadomienie o pełnym magazynie. Premie/kary: powiadomienie przy aktywacji, zmianie i końcu oraz aktywna lista u góry Town Hall. | I15: Kliknięcie kup/sprzedaj: pobranie monet lub rezerwacja towaru. Sprzedaż: dwa etapy transportu, wypłata przy wypłynięciu; rejs 5 min. Osobny licznik dla KAŻDEGO produktu w ruchomych 3 h. Kolejne paczki zakupu po 100 podnoszą cenę liniowo o 10% ceny bazowej. Cena zamrożona przy kliknięciu zamówienia; kupno 100 drewna nie podnosi ceny kamienia. | J15: Premium od L4: 25/50/75/100% pozostałej fazy budowania, bez transportu. Cena = MAX(5, FLOOR(zaoszczędzone sekundy / 60)) monet. Transport jest osobno rozliczany za potrzebne kursy. Pełny zakup budynku od poziomu gracza 4: wszystkie materiały według proporcjonalnych bazowych cen zakupu portu ×1,25 + nominalne monety budynku + natychmiastowy transport (10 monet za każdy potrzebny kurs, także niepełny). Nic nie pobieramy z własnych materiałów. Gotowe po 10 s; bez wymogu rzeczywistych tragarzy. | K15: Tempo załogi jak w magazynie, premium jak w magazynie | L15: Budynki!wiersz 15; potwierdzenia w Odpowiedzi i zmiany | M15: =TEXT('Czas budowy'!Y60,"0")&" min bazowo; T="&TEXT('Czas budowy'!V60,"0")&" min; budowa="&TEXT('Czas budowy'!X60,"0")&" min. Kolejka +10%: "&TEXT('Czas budowy'!Y61,"0")&" min (bez czekania)." -> 60 min bazowo; T=30 min; budowa=30 min. Kolejka +10%: 70 min (bez czekania). | N15: =TEXT('Czas budowy'!Y62,"0")&" min bazowo; T="&TEXT('Czas budowy'!V62,"0")&" min; budowa="&TEXT('Czas budowy'!X62,"0")&" min. Kolejka +10%: "&TEXT('Czas budowy'!Y63,"0")&" min (bez czekania)." -> 110 min bazowo; T=55 min; budowa=55 min. Kolejka +10%: 120 min (bez czekania). | O15: =TEXT('Czas budowy'!Y64,"0")&" min bazowo; T="&TEXT('Czas budowy'!V64,"0")&" min; budowa="&TEXT('Czas budowy'!X64,"0")&" min. Kolejka +10%: "&TEXT('Czas budowy'!Y65,"0")&" min (bez czekania)." -> 150 min bazowo; T=75 min; budowa=75 min. Kolejka +10%: 160 min (bez czekania).
A16: Kaplica | B16: Daje premie szczęścia i podatków po rozbudowie; dotychczas była miejscem ręcznych błogosławieństw. | C16: Brak etatów; wizyty nie są zatrudnieniem. | D16: +1 użycie dotychczasowego błogosławieństwa; rozbudowa do N: +10 × N szczęścia, podatki ×2 na 10 h. Kaplica = błogosławieństwo. | E16: Zatwierdzono: nowy poziom N × (180 monet + 20 drewna + 60 kamienia + 10 desek). To koszt rozbudowy, odrębny od ceny użycia błogosławieństwa. | F16: T transportu + 3T × (N − 1) budowy; N = nowy poziom. Łącznie: 4T, 7T, 10T… | G16: Uzgodnione w V8; prototyp frontendowy. Szczegóły bieżącego wdrożenia i testów: docs/IMPLEMENTATION-LOG.md. Backend i integracje: Na pozniej. | H16: ZAWSZE: ukończenie budowy. Wcześniej także zlecenie/start/dostawa. Uruchomienie premii i ręczne błogosławieństwo. Premie/kary: powiadomienie przy aktywacji, zmianie i końcu oraz aktywna lista u góry Town Hall. | I16: Płatne błogosławieństwo: 100 × poziom kaplicy monet; +50 każdego zasobu i +20 pp na 1 h. Kolejne płatne użycie 4 h od KOŃCA efektu: 12:00–13:00 → następne 17:00. Nie można nakładać aktywnych błogosławieństw. | J16: Premium od L4: 25/50/75/100% pozostałej fazy budowania, bez transportu. Cena = MAX(5, FLOOR(zaoszczędzone sekundy / 60)) monet. Transport jest osobno rozliczany za potrzebne kursy. Pełny zakup budynku od poziomu gracza 4: wszystkie materiały według proporcjonalnych bazowych cen zakupu portu ×1,25 + nominalne monety budynku + natychmiastowy transport (10 monet za każdy potrzebny kurs, także niepełny). Nic nie pobieramy z własnych materiałów. Gotowe po 10 s; bez wymogu rzeczywistych tragarzy. | L16: Budynki!wiersz 16; potwierdzenia w Odpowiedzi i zmiany | M16: =TEXT('Czas budowy'!Y66,"0")&" min bazowo; T="&TEXT('Czas budowy'!V66,"0")&" min; budowa="&TEXT('Czas budowy'!X66,"0")&" min. Kolejka +10%: "&TEXT('Czas budowy'!Y67,"0")&" min (bez czekania)." -> 20 min bazowo; T=5 min; budowa=15 min. Kolejka +10%: 20 min (bez czekania). | N16: =TEXT('Czas budowy'!Y68,"0")&" min bazowo; T="&TEXT('Czas budowy'!V68,"0")&" min; budowa="&TEXT('Czas budowy'!X68,"0")&" min. Kolejka +10%: "&TEXT('Czas budowy'!Y69,"0")&" min (bez czekania)." -> 35 min bazowo; T=5 min; budowa=30 min. Kolejka +10%: 35 min (bez czekania). | O16: =TEXT('Czas budowy'!Y70,"0")&" min bazowo; T="&TEXT('Czas budowy'!V70,"0")&" min; budowa="&TEXT('Czas budowy'!X70,"0")&" min. Kolejka +10%: "&TEXT('Czas budowy'!Y71,"0")&" min (bez czekania)." -> 100 min bazowo; T=10 min; budowa=90 min. Kolejka +10%: 100 min (bez czekania).
A17: Latarnia | B17: Daje premie szczęścia i produkcji po ukończeniu poziomu. | C17: Brak etatów; wizyty nie są zatrudnieniem. | D17: Rozbudowa: szczęście 100% i produkcja ×2 przez 24 h × nowy poziom; podatki bez mnożnika. Premie od powrotu: uczestnik 100% na 24 h i blokada ponownej wizyty przez te same 24 h; każda osobno wysłana grupa daje populacji +10 pp przez 6 h. Premie grup sumują się w czasie nakładania. | E17: 500×max(1, L) KAŻDEGO z 6 zasobów. Pierwsza budowa 0→1:500 każdego. | F17: 5T = T transportu + 4T budowy | G17: Uzgodnione w V8; prototyp frontendowy. Szczegóły bieżącego wdrożenia i testów: docs/IMPLEMENTATION-LOG.md. Backend i integracje: Na pozniej. | H17: ZAWSZE: ukończenie budowy. Wcześniej także zlecenie/start/dostawa. Uruchomienie premii latarni. Premie/kary: powiadomienie przy aktywacji, zmianie i końcu oraz aktywna lista u góry Town Hall. | I17: Pobyt 4 h, bez czasu dojścia i możliwości wycofania. Wyłącznie wolne osoby z domu; jednocześnie 2 × poziom latarni miejsc. Darmowo 2 × poziom latarni wejść w ruchomych 24 h. Do 3 dodatkowych pakietów/24 h, każdy daje 2L wejść; cena 300 × numer pakietu (2, 3, 4) × L. Pakiet nie zwiększa liczby miejsc jednocześnie. Po premii powrót do wcześniejszego osobistego stanu. Każdy nowy mieszkaniec ma zamrożone 0% szczęścia przez pierwsze 24 h, również podczas premii; później zwykłe naliczanie od 0%. Początkowych 12 osób nie obejmuje zamrożenie. | J17: Premium od L4: 25/50/75/100% pozostałej fazy budowania, bez transportu. Cena = MAX(5, FLOOR(zaoszczędzone sekundy / 60)) monet. Transport jest osobno rozliczany za potrzebne kursy. Pełny zakup budynku od poziomu gracza 4: wszystkie materiały według proporcjonalnych bazowych cen zakupu portu ×1,25 + nominalne monety budynku + natychmiastowy transport (10 monet za każdy potrzebny kurs, także niepełny). Nic nie pobieramy z własnych materiałów. Gotowe po 10 s; bez wymogu rzeczywistych tragarzy. | K17: Nowe błogosławieństwo: kasa/challenge/udostępnienie/reklama. Zgodnie z decyzją użytkownika szczegóły ODŁOŻONE. Brak cen ani zatwierdzonej integracji. | L17: Budynki!wiersz 17; potwierdzenia w Odpowiedzi i zmiany | M17: =TEXT('Czas budowy'!Y72,"0")&" min bazowo; T="&TEXT('Czas budowy'!V72,"0")&" min; budowa="&TEXT('Czas budowy'!X72,"0")&" min. Kolejka +10%: "&TEXT('Czas budowy'!Y73,"0")&" min (bez czekania)." -> 200 min bazowo; T=40 min; budowa=160 min. Kolejka +10%: 225 min (bez czekania). | N17: =TEXT('Czas budowy'!Y74,"0")&" min bazowo; T="&TEXT('Czas budowy'!V74,"0")&" min; budowa="&TEXT('Czas budowy'!X74,"0")&" min. Kolejka +10%: "&TEXT('Czas budowy'!Y75,"0")&" min (bez czekania)." -> 350 min bazowo; T=70 min; budowa=280 min. Kolejka +10%: 375 min (bez czekania). | O17: =TEXT('Czas budowy'!Y76,"0")&" min bazowo; T="&TEXT('Czas budowy'!V76,"0")&" min; budowa="&TEXT('Czas budowy'!X76,"0")&" min. Kolejka +10%: "&TEXT('Czas budowy'!Y77,"0")&" min (bez czekania)." -> 450 min bazowo; T=90 min; budowa=360 min. Kolejka +10%: 500 min (bez czekania).
A18: CZŁOWIEK — ASSET | B18: Je, pracuje, produkuje/nosi, płaci podatki; własna historia szczęścia. | C18: 12 na starcie w domu; min. 6, max. 24 × Ratusz; jedno zatrudnienie, limit 12 × własny poziom budynku. | D18: Nie ulepsza się osoby poziomem; zmieniają się warunki życia i pracy. | E18: Utrzymanie: 1 Food/os./h; kupowania ludzi nie ustalono. | F18: Demografia zależy od średniego H, liczona zegarowo także offline. | G18: Uzgodnione w V8; prototyp frontendowy. Szczegóły bieżącego wdrożenia i testów: docs/IMPLEMENTATION-LOG.md. Backend i integracje: Na pozniej. | H18: Odejście, nigdy śmierć; nowy mieszkaniec zawsze w domu. Premie/kary: powiadomienie przy aktywacji, zmianie i końcu oraz aktywna lista u góry Town Hall. | I18: +1 za jedzenie, +1 za pracę; po 12 h braku danego warunku −5; oba braki −10/h. Przeludnienie i osobne kary pełnego bufora. Podatki 1/h; wizyty po zdefiniowaniu. | J18: Brak oferty sprzedaży osób. | K18: Odejścia:najpierwDom,potemnajwiększazałoga;remisywgpriorytetów;patrzCzlowiek. | L18: Czlowiek/Ustalenia/Populacja; potwierdzeniaoffline. | M18: Nie dotyczy. | N18: Nie dotyczy. | O18: Nie dotyczy.

Sheet Czlowiek
A1: CZŁOWIEK • zaktualizowany asset
A2: Pełne zasady człowieka po 17 decyzjach: indywidualne szczęście, praca i podatek od dotarcia, brak bonusu pracy przy przestoju, osobne kary, pula domu, zwiedzanie, zamrożenie nowych osób i gospodarka offline. V8 dodaje czasowe atrakcje dla wybranych osób; podatki nadal naliczane, ich informacji nie pokazujemy w UI. Workers ma podpisane Assigned / Free at home / Max workers.
A5: Stan / obszar | B5: Zasada | C5: Wzór / liczby | D5: Konsekwencje | E5: Status
A6: Rola assetu | B6: Każda osoba ma trwałe ID, własne szczęście, stan pracy/pobytu i niezależne liczniki głodu oraz bezrobocia. | C6: 12 na starcie; minimum 6; maksimum 24 × poziom ratusza. | D6: Nowe osoby trafiają do domu. Ubytek oznacza odejście, nie śmierć. | E6: UZGODNIONE; NOWE DOPRECYZOWANIA
A7: Start i dom | B7: Na starcie wszyscy ludzie są w domu, bez przypisania do gospodarki. Z domu widać ich przydziały; można kierować do kaplicy i latarni. | C7: 12 w domu, 0 pracowników we wszystkich budynkach; każdy zasób na starcie 100. | D7: Przed pierwszym przydziałem nie ma produkcji ani podatków, ale ludzie jedzą. | E7: UZGODNIONE / NOWE
A8: Limit miejsca pracy | B8: Limit zależy od poziomu konkretnego miejsca pracy, nie samego ratusza. Jedna wspólna pula wolnych ludzi. | C8: 0…12 × poziom budynku; nowy przydział ograniczony faktycznie wolnymi osobami w domu. | D8: Ratusz 2 i drwale 1: limit drwali nadal 12. Drwale 2: limit 24, jeżeli tylu wolnych istnieje. Nie wolno ulepszyć ponad ratusz. | E8: ZMIENIONE I WYJAŚNIONE
A9: Jedzenie | B9: Każdy je automatycznie wyłącznie z magazynu centralnego, niezależnie od pracy lub drogi. | C9: 1 Food/os./h zegarowej. | D9: Lokalny młyn, targ i port nie karmią bez przewiezienia do centrali. Rezerwę można zjadać. | E9: UZGODNIONE; CZAS ZEGAROWY
A10: Rezerwa jedzenia | B10: Rezerwa na żywienie rośnie z poziomem magazynu. Operacje nieżywieniowe mają ją zachować. | C10: Minimum Food = 50 × poziom magazynu. | D10: Potwierdzone minimum i próg ratunkowego transportu:50 × poziom magazynu. Przy gotowym Food w młynie nie można ręcznie wycofać wszystkich magazynierów, gdy centrala jest poniżej minimum. | E10: ROZSTRZYGNIĘTE V5
A11: Praca producenta | B11: Wydajność na osobę wynika z własnego poziomu producenta. | C11: Poziomy 1,2,3,4: dokładnie 10,12,13,14 szt./h; dalej +1 szt./h na poziom. | D11: Wybrany dosłowny ciąg zastępuje sprzeczny ogólny zapis +10%. Głód ×0,5, premia latarni ×2. | E11: POTWIERDZONE W ODPOWIEDZI
A12: Całe sztuki | B12: Każdy pracownik nalicza własny postęp; niedokończone części różnych osób nie łączą się. Zwolnienie odrzuca jego niedokończoną sztukę. | C12: Na poziomie 1: jedna sztuka/6 min; po 7 min 1, po 13 min 2. Na wyższych poziomach odstęp = 3600 / wydajność sekund. | D12: Gotowy produkt zostaje w lokalnym buforze i wymaga transportu. | E12: UZGODNIONE; DOSTOSOWANE DO WYDAJNOŚCI
A13: Przeróbka | B13: Młyn i tartak zużywają surowce centralne; zboże i drewno idą przez magazyn. | C13: 2 zboża → 1 Food; 2 drewna → 1 deska. | D13: Brak wejścia lub miejsca powoduje przestój i karę według reguły przestoju; przypisani pracownicy nadal płacą podatek. Nie dokładamy drugiej kary bezrobocia za tę samą blokadę. | E13: DOPRECYZOWANE V5
A14: Transport | B14: Tragarz wiezie jeden rodzaj towaru, nie czeka na pełne obłożenie. Pojemność to ładunek na kurs, nie sztuki na godzinę. | C14: Poziom 1: 60 szt./kurs; pełny kurs z powrotem 5 min; pojemność rośnie o 10% na poziom miejsca pracy. | D14: 100 jednego towaru wymaga dwóch kursów: 60 i 40. Magazyn, targ i port stosują takie same bazowe zasady; własne załogi. Ścieżki po ukończeniu całego poziomu zwiększają szybkość; od poziomu 3 również ładunek. | E14: POTWIERDZONE V7: FLOOR(60 × 1,1^(L−1))
A15: Podatek przy pracy | B15: Podatek zaczyna się po dojściu do zakładu i płynie także podczas przestoju, dopóki osoba pozostaje przypisana. Bezrobotny, idący do pracy, wracający i zwiedzający nie płaci. | C15: 1 moneta/os./h zegarowej; podczas premii kaplicy 2. | D15: Brak surowca lub miejsca nie zatrzymuje podatku. Kara przestoju obniża szczęście przypisanych osób. Premia kaplicy nadal podwaja podatek. V8: wartość i opis podatku ukryte we wszystkich widokach gry; to zmiana prezentacji, nie rachunku. | E15: POTWIERDZONE V5
A16: Je i pracuje | B16: Sumują się bonus jedzenia i bonus pracy. | C16: +1 pp/h za jedzenie +1 pp/h za pracę = +2 pp/h. | D16: Od osobistego 0% po 10 h takiego stanu ma 20%. | E16: UZGODNIONE
... A40: Informacja o efektach | B40: Wszystkie aktywne premie i kary mają źródło, wartość, odbiorców i czas/warunek zakończenia. | C40: Powiadomienia + góra Town Hall. | D40: Wpis na zmianę stanu, nie co klatkę. | E40: POTWIERDZONE V8

Sheet Atrakcje
A1: ATRAKCJE • 20 dekoracji i wydarzeń
A2: Pięć ofert zmienia się co 24 h. Y jest całkowite od 5 do 100 i zapisane w ofercie. Cena: Y × bieżący poziom ratusza L. Premia: Y × współczynnik przyzwyczajenia pp dla L osób przez 6 h. Każdy rodzaj ma osobny licznik; reset po 24 h bez jego zakupu. Przy zerowej premii zakup zablokowany.
A5: ID | B5: Nazwa w grze | C5: Znaczenie | D5: Typ | E5: Cena | F5: Efekt | G5: Czas | H5: Przyzwyczajanie
A6: flower-beds | B6: Flower beds | C6: Rabaty kwiatowe | D6: Dekoracja | E6: Y × L monet | F6: Y × współczynnik pp dla L osób | G6: 6 | H6: 100% →75% →50% →25% →0%; osobny reset 24 h
A7: village-benches | B7: Village benches | C7: Ławki we wsi | D7: Dekoracja | E7: Y × L monet | F7: Y × współczynnik pp dla L osób | G7: 6 | H7: 100% →75% →50% →25% →0%; osobny reset 24 h
A8: lantern-strings | B8: Lantern strings | C8: Girlandy lampionów | D8: Dekoracja | E8: Y × L monet | F8: Y × współczynnik pp dla L osób | G8: 6 | H8: 100% →75% →50% →25% →0%; osobny reset 24 h
A9: harbor-flags | B9: Harbor flags | C9: Flagi przystani | D9: Dekoracja | E9: Y × L monet | F9: Y × współczynnik pp dla L osób | G9: 6 | H9: 100% →75% →50% →25% →0%; osobny reset 24 h
A10: village-fountain | B10: Village fountain | C10: Fontanna wiejska | D10: Dekoracja | E10: Y × L monet | F10: Y × współczynnik pp dla L osób | G10: 6 | H10: 100% →75% →50% →25% →0%; osobny reset 24 h
A11: garden-pond | B11: Garden pond | C11: Oczko ogrodowe | D11: Dekoracja | E11: Y × L monet | F11: Y × współczynnik pp dla L osób | G11: 6 | H11: 100% →75% →50% →25% →0%; osobny reset 24 h
A12: wooden-sculptures | B12: Wooden sculptures | C12: Drewniane rzeźby | D12: Dekoracja | E12: Y × L monet | F12: Y × współczynnik pp dla L osób | G12: 6 | H12: 100% →75% →50% →25% →0%; osobny reset 24 h
A13: seaside-mural | B13: Seaside mural | C13: Mural nad morzem | D13: Dekoracja | E13: Y × L monet | F13: Y × współczynnik pp dla L osób | G13: 6 | H13: 100% →75% →50% →25% →0%; osobny reset 24 h
A14: lighthouse-garden | B14: Lighthouse garden | C14: Ogród przy latarni | D14: Dekoracja | E14: Y × L monet | F14: Y × współczynnik pp dla L osób | G14: 6 | H14: 100% →75% →50% →25% →0%; osobny reset 24 h
A15: ornamental-sails | B15: Ornamental sails | C15: Ozdobne żagle | D15: Dekoracja | E15: Y × L monet | F15: Y × współczynnik pp dla L osób | G15: 6 | H15: 100% →75% →50% →25% →0%; osobny reset 24 h
A16: travelling-circus | B16: Travelling circus | C16: Wędrowny cyrk | D16: Wydarzenie | E16: Y × L monet | F16: Y × współczynnik pp dla L osób | G16: 6 | H16: 100% →75% →50% →25% →0%; osobny reset 24 h
A17: theatre-troupe | B17: Theatre troupe | C17: Grupa teatralna | D17: Wydarzenie | E17: Y × L monet | F17: Y × współczynnik pp dla L osób | G17: 6 | H17: 100% →75% →50% →25% →0%; osobny reset 24 h
... A25: harbor-fair | B25: Harbor fair | C25: Jarmark portowy | D25: Wydarzenie | E25: Y × L monet | F25: Y × współczynnik pp dla L osób | G25: 6 | H25: 100% →75% →50% →25% →0%; osobny reset 24 h

Sheet Atrakcje - kalkulator
A1: ATRAKCJE • cena i przyzwyczajanie
A2: Niebieskie pola A/B/C: poziom ratusza L, ofertowe Y i numer użycia. F zawiera dokładny składnik szczęścia; G prezentację w pełnych pp, zaokrągloną w górę. Osobiste H nadal ograniczamy do ±100%. Wiersze są niezależnymi przykładami, a nie cenami jednej oferty.
A5: Ratusz L | B5: Y | C5: Użycie typu | D5: Współczynnik | E5: Cena nominalna | F5: Dokładna premia pp | G5: Prezentacja pp | H5: Maks.osób | I5: Czas h | J5: Dostępność | K5: Uwagi
A6: 1 | B6: 5 | C6: 1 | D6: =MAX(0,1-(C6-1)*0.25) -> 1 | E6: =A6*B6 -> 5 | F6: =B6*D6 -> 5 | G6: =ROUNDUP(F6,0) -> 5 | H6: =A6 -> 1 | I6: =Parametry!$C$76 -> 6 | J6: =IF(D6>0,"MOŻNA KUPIĆ","ZABLOKOWANE — bez opłaty") -> MOŻNA KUPIĆ | K6: Każdy rodzaj ma osobny licznik; każdy zakup ma własne 6 h. Przy zerowej skuteczności nominalna cena z E nie jest pobierana.
A7: 1 | B7: 5 | C7: 2 | D7: =MAX(0,1-(C7-1)*0.25) -> 0.75 | E7: =A7*B7 -> 5 | F7: =B7*D7 -> 3.75 | G7: =ROUNDUP(F7,0) -> 4 | H7: =A7 -> 1 | I7: =Parametry!$C$76 -> 6 | J7: =IF(D7>0,"MOŻNA KUPIĆ","ZABLOKOWANE — bez opłaty") -> MOŻNA KUPIĆ | K7: Każdy rodzaj ma osobny licznik; każdy zakup ma własne 6 h. Przy zerowej skuteczności nominalna cena z E nie jest pobierana.
A8: 1 | B8: 5 | C8: 3 | D8: =MAX(0,1-(C8-1)*0.25) -> 0.5 | E8: =A8*B8 -> 5 | F8: =B8*D8 -> 2.5 | G8: =ROUNDUP(F8,0) -> 3 | H8: =A8 -> 1 | I8: =Parametry!$C$76 -> 6 | J8: =IF(D8>0,"MOŻNA KUPIĆ","ZABLOKOWANE — bez opłaty") -> MOŻNA KUPIĆ | K8: Każdy rodzaj ma osobny licznik; każdy zakup ma własne 6 h. Przy zerowej skuteczności nominalna cena z E nie jest pobierana.
A9: 1 | B9: 5 | C9: 4 | D9: =MAX(0,1-(C9-1)*0.25) -> 0.25 | E9: =A9*B9 -> 5 | F9: =B9*D9 -> 1.25 | G9: =ROUNDUP(F9,0) -> 2 | H9: =A9 -> 1 | I9: =Parametry!$C$76 -> 6 | J9: =IF(D9>0,"MOŻNA KUPIĆ","ZABLOKOWANE — bez opłaty") -> MOŻNA KUPIĆ | K9: Każdy rodzaj ma osobny licznik; każdy zakup ma własne 6 h. Przy zerowej skuteczności nominalna cena z E nie jest pobierana.
A10: 1 | B10: 5 | C10: 5 | D10: =MAX(0,1-(C10-1)*0.25) -> 0 | E10: =A10*B10 -> 5 | F10: =B10*D10 -> 0 | G10: =ROUNDUP(F10,0) -> 0 | H10: =A10 -> 1 | I10: =Parametry!$C$76 -> 6 | J10: =IF(D10>0,"MOŻNA KUPIĆ","ZABLOKOWANE — bez opłaty") -> ZABLOKOWANE — bez opłaty | K10: Każdy rodzaj ma osobny licznik; każdy zakup ma własne 6 h. Przy zerowej skuteczności nominalna cena z E nie jest pobierana.
A11: 1 | B11: 25 | C11: 1 | D11: =MAX(0,1-(C11-1)*0.25) -> 1 | E11: =A11*B11 -> 25 | F11: =B11*D11 -> 25 | G11: =ROUNDUP(F11,0) -> 25 | H11: =A11 -> 1 | I11: =Parametry!$C$76 -> 6 | J11: =IF(D11>0,"MOŻNA KUPIĆ","ZABLOKOWANE — bez opłaty") -> MOŻNA KUPIĆ | K11: Każdy rodzaj ma osobny licznik; każdy zakup ma własne 6 h. Przy zerowej skuteczności nominalna cena z E nie jest pobierana.
A12: 1 | B12: 25 | C12: 2 | D12: =MAX(0,1-(C12-1)*0.25) -> 0.75 | E12: =A12*B12 -> 25 | F12: =B12*D12 -> 18.75 | G12: =ROUNDUP(F12,0) -> 19 | H12: =A12 -> 1 | I12: =Parametry!$C$76 -> 6 | J12: =IF(D12>0,"MOŻNA KUPIĆ","ZABLOKOWANE — bez opłaty") -> MOŻNA KUPIĆ | K12: Każdy rodzaj ma osobny licznik; każdy zakup ma własne 6 h. Przy zerowej skuteczności nominalna cena z E nie jest pobierana.
A13: 1 | B13: 25 | C13: 3 | D13: =MAX(0,1-(C13-1)*0.25) -> 0.5 | E13: =A13*B13 -> 25 | F13: =B13*D13 -> 12.5 | G13: =ROUNDUP(F13,0) -> 13 | H13: =A13 -> 1 | I13: =Parametry!$C$76 -> 6 | J13: =IF(D13>0,"MOŻNA KUPIĆ","ZABLOKOWANE — bez opłaty") -> MOŻNA KUPIĆ | K13: Każdy rodzaj ma osobny licznik; każdy zakup ma własne 6 h. Przy zerowej skuteczności nominalna cena z E nie jest pobierana.
A14: 1 | B14: 25 | C14: 4 | D14: =MAX(0,1-(C14-1)*0.25) -> 0.25 | E14: =A14*B14 -> 25 | F14: =B14*D14 -> 6.25 | G14: =ROUNDUP(F14,0) -> 7 | H14: =A14 -> 1 | I14: =Parametry!$C$76 -> 6 | J14: =IF(D14>0,"MOŻNA KUPIĆ","ZABLOKOWANE — bez opłaty") -> MOŻNA KUPIĆ | K14: Każdy rodzaj ma osobny licznik; każdy zakup ma własne 6 h. Przy zerowej skuteczności nominalna cena z E nie jest pobierana.
A15: 1 | B15: 25 | C15: 5 | D15: =MAX(0,1-(C15-1)*0.25) -> 0 | E15: =A15*B15 -> 25 | F15: =B15*D15 -> 0 | G15: =ROUNDUP(F15,0) -> 0 | H15: =A15 -> 1 | I15: =Parametry!$C$76 -> 6 | J15: =IF(D15>0,"MOŻNA KUPIĆ","ZABLOKOWANE — bez opłaty") -> ZABLOKOWANE — bez opłaty | K15: Każdy rodzaj ma osobny licznik; każdy zakup ma własne 6 h. Przy zerowej skuteczności nominalna cena z E nie jest pobierana.
A16: 1 | B16: 50 | C16: 1 | D16: =MAX(0,1-(C16-1)*0.25) -> 1 | E16: =A16*B16 -> 50 | F16: =B16*D16 -> 50 | G16: =ROUNDUP(F16,0) -> 50 | H16: =A16 -> 1 | I16: =Parametry!$C$76 -> 6 | J16: =IF(D16>0,"MOŻNA KUPIĆ","ZABLOKOWANE — bez opłaty") -> MOŻNA KUPIĆ | K16: Każdy rodzaj ma osobny licznik; każdy zakup ma własne 6 h. Przy zerowej skuteczności nominalna cena z E nie jest pobierana.
A17: 1 | B17: 50 | C17: 2 | D17: =MAX(0,1-(C17-1)*0.25) -> 0.75 | E17: =A17*B17 -> 50 | F17: =B17*D17 -> 37.5 | G17: =ROUNDUP(F17,0) -> 38 | H17: =A17 -> 1 | I17: =Parametry!$C$76 -> 6 | J17: =IF(D17>0,"MOŻNA KUPIĆ","ZABLOKOWANE — bez opłaty") -> MOŻNA KUPIĆ | K17: Każdy rodzaj ma osobny licznik; każdy zakup ma własne 6 h. Przy zerowej skuteczności nominalna cena z E nie jest pobierana.
... A105: 10 | B105: 100 | C105: 5 | D105: =MAX(0,1-(C105-1)*0.25) -> 0 | E105: =A105*B105 -> 1000 | F105: =B105*D105 -> 0 | G105: =ROUNDUP(F105,0) -> 0 | H105: =A105 -> 10 | I105: =Parametry!$C$76 -> 6 | J105: =IF(D105>0,"MOŻNA KUPIĆ","ZABLOKOWANE — bez opłaty") -> ZABLOKOWANE — bez opłaty | K105: Każdy rodzaj ma osobny licznik; każdy zakup ma własne 6 h. Przy zerowej skuteczności nominalna cena z E nie jest pobierana.

Sheet Sciezki
A1: ŚCIEŻKI • 100 odcinków, poziomy 0–5
A2: Na starcie jest 100 odcinków na poziomie 0. Kliknięcie ulepsza jeden odcinek o jeden poziom za 100 kamienia. Poziom N jest dostępny dopiero, gdy wszystkie odcinki mają N−1. Ukończony poziom to minimum poziomów wszystkich odcinków; dopiero wtedy działa premia. Drogi nie dodają pasywnego szczęścia.
A5: Ukończony poziom | B5: Odcinki ukończone | C5: Cena kroku | D5: Koszt całego poziomu | E5: Koszt od 0 | F5: Bonus szybkości | G5: Mnożnik szybkości | H5: Bonus ładunku | I5: Mnożnik ładunku | J5: Kurs bazowy s | K5: Warunek
A6: 0 | B6: 0 | C6: =Parametry!$C$70 -> 100 | D6: =IF(A6=0,0,Parametry!$C$68*C6) -> 0 | E6: =A6*Parametry!$C$68*C6 -> 0 | F6: =A6*Parametry!$C$71 -> 0 | G6: =1+F6 -> 1 | H6: =MAX(0,A6-2)*Parametry!$C$72 -> 0 | I6: =1+H6 -> 1 | J6: =300/G6 -> 300 | K6: Premia po ukończeniu 100/100 tego poziomu. Zakup następnego poziomu wymaga pełnej setki poprzedniego.
A7: 1 | B7: 100 | C7: =Parametry!$C$70 -> 100 | D7: =IF(A7=0,0,Parametry!$C$68*C7) -> 10000 | E7: =A7*Parametry!$C$68*C7 -> 10000 | F7: =A7*Parametry!$C$71 -> 0.1 | G7: =1+F7 -> 1.1 | H7: =MAX(0,A7-2)*Parametry!$C$72 -> 0 | I7: =1+H7 -> 1 | J7: =300/G7 -> 272.72727 | K7: Premia po ukończeniu 100/100 tego poziomu. Zakup następnego poziomu wymaga pełnej setki poprzedniego.
A8: 2 | B8: 100 | C8: =Parametry!$C$70 -> 100 | D8: =IF(A8=0,0,Parametry!$C$68*C8) -> 10000 | E8: =A8*Parametry!$C$68*C8 -> 20000 | F8: =A8*Parametry!$C$71 -> 0.2 | G8: =1+F8 -> 1.2 | H8: =MAX(0,A8-2)*Parametry!$C$72 -> 0 | I8: =1+H8 -> 1 | J8: =300/G8 -> 250 | K8: Premia po ukończeniu 100/100 tego poziomu. Zakup następnego poziomu wymaga pełnej setki poprzedniego.
A9: 3 | B9: 100 | C9: =Parametry!$C$70 -> 100 | D9: =IF(A9=0,0,Parametry!$C$68*C9) -> 10000 | E9: =A9*Parametry!$C$68*C9 -> 30000 | F9: =A9*Parametry!$C$71 -> 0.3 | G9: =1+F9 -> 1.3 | H9: =MAX(0,A9-2)*Parametry!$C$72 -> 0.1 | I9: =1+H9 -> 1.1 | J9: =300/G9 -> 230.76923 | K9: Premia po ukończeniu 100/100 tego poziomu. Zakup następnego poziomu wymaga pełnej setki poprzedniego.
A10: 4 | B10: 100 | C10: =Parametry!$C$70 -> 100 | D10: =IF(A10=0,0,Parametry!$C$68*C10) -> 10000 | E10: =A10*Parametry!$C$68*C10 -> 40000 | F10: =A10*Parametry!$C$71 -> 0.4 | G10: =1+F10 -> 1.4 | H10: =MAX(0,A10-2)*Parametry!$C$72 -> 0.2 | I10: =1+H10 -> 1.2 | J10: =300/G10 -> 214.28571 | K10: Premia po ukończeniu 100/100 tego poziomu. Zakup następnego poziomu wymaga pełnej setki poprzedniego.
A11: 5 | B11: 100 | C11: =Parametry!$C$70 -> 100 | D11: =IF(A11=0,0,Parametry!$C$68*C11) -> 10000 | E11: =A11*Parametry!$C$68*C11 -> 50000 | F11: =A11*Parametry!$C$71 -> 0.5 | G11: =1+F11 -> 1.5 | H11: =MAX(0,A11-2)*Parametry!$C$72 -> 0.3 | I11: =1+H11 -> 1.3 | J11: =300/G11 -> 200 | K11: Premia po ukończeniu 100/100 tego poziomu. Zakup następnego poziomu wymaga pełnej setki poprzedniego.

Sheet Sciezki - transport
A1: ŚCIEŻKI • działanie na czas i ładunek
A2: Ładunek = FLOOR(FLOOR(60 × 1,1^(własny L−1)) × mnożnik dróg). Czas kursu = 300 / (1 + 0,1 × poziom dróg). Głód osobno zmniejsza szybkość do połowy. B to poziom dróg, A to własny poziom miejsca pracy. Cena Premium nadal wynosi 10 monet za potrzebny kurs.
A5: Własny L | B5: Drogi 0…5 | C5: Bazowy ładunek | D5: Mnożnik dróg | E5: Ładunek wynik | F5: Mnożnik szybkości | G5: Kurs nakarmiony s | H5: Kurs głodny s | I5: Towar do przewozu | J5: Potrzebne kursy | K5: Transport s | L5: Premium monety | M5: Założenia
A6: 1 | B6: 0 | C6: =ROUNDDOWN(Parametry!$C$9*Parametry!$C$10^(A6-1),0) -> 60 | D6: =1+Parametry!$C$72*MAX(0,B6-2) -> 1 | E6: =ROUNDDOWN(C6*D6,0) -> 60 | F6: =1+Parametry!$C$71*B6 -> 1 | G6: =300/F6 -> 300 | H6: =G6/0.5 -> 600 | I6: 100 | J6: =ROUNDUP(I6/E6,0) -> 2 | K6: =J6*G6 -> 600 | L6: =J6*Parametry!$C$43 -> 20 | M6: Jedna osoba, jeden rodzaj towaru, 100 gotowych sztuk, bez konkurujących kursów. Rejs statku i droga do pracy nie są skracane.
A7: 1 | B7: 1 | C7: =ROUNDDOWN(Parametry!$C$9*Parametry!$C$10^(A7-1),0) -> 60 | D7: =1+Parametry!$C$72*MAX(0,B7-2) -> 1 | E7: =ROUNDDOWN(C7*D7,0) -> 60 | F7: =1+Parametry!$C$71*B7 -> 1.1 | G7: =300/F7 -> 272.72727 | H7: =G7/0.5 -> 545.45455 | I7: 100 | J7: =ROUNDUP(I7/E7,0) -> 2 | K7: =J7*G7 -> 545.45455 | L7: =J7*Parametry!$C$43 -> 20 | M7: Jedna osoba, jeden rodzaj towaru, 100 gotowych sztuk, bez konkurujących kursów. Rejs statku i droga do pracy nie są skracane.
A8: 1 | B8: 2 | C8: =ROUNDDOWN(Parametry!$C$9*Parametry!$C$10^(A8-1),0) -> 60 | D8: =1+Parametry!$C$72*MAX(0,B8-2) -> 1 | E8: =ROUNDDOWN(C8*D8,0) -> 60 | F8: =1+Parametry!$C$71*B8 -> 1.2 | G8: =300/F8 -> 250 | H8: =G8/0.5 -> 500 | I8: 100 | J8: =ROUNDUP(I8/E8,0) -> 2 | K8: =J8*G8 -> 500 | L8: =J8*Parametry!$C$43 -> 20 | M8: Jedna osoba, jeden rodzaj towaru, 100 gotowych sztuk, bez konkurujących kursów. Rejs statku i droga do pracy nie są skracane.
A9: 1 | B9: 3 | C9: =ROUNDDOWN(Parametry!$C$9*Parametry!$C$10^(A9-1),0) -> 60 | D9: =1+Parametry!$C$72*MAX(0,B9-2) -> 1.1 | E9: =ROUNDDOWN(C9*D9,0) -> 66 | F9: =1+Parametry!$C$71*B9 -> 1.3 | G9: =300/F9 -> 230.76923 | H9: =G9/0.5 -> 461.53846 | I9: 100 | J9: =ROUNDUP(I9/E9,0) -> 2 | K9: =J9*G9 -> 461.53846 | L9: =J9*Parametry!$C$43 -> 20 | M9: Jedna osoba, jeden rodzaj towaru, 100 gotowych sztuk, bez konkurujących kursów. Rejs statku i droga do pracy nie są skracane.
A10: 1 | B10: 4 | C10: =ROUNDDOWN(Parametry!$C$9*Parametry!$C$10^(A10-1),0) -> 60 | D10: =1+Parametry!$C$72*MAX(0,B10-2) -> 1.2 | E10: =ROUNDDOWN(C10*D10,0) -> 72 | F10: =1+Parametry!$C$71*B10 -> 1.4 | G10: =300/F10 -> 214.28571 | H10: =G10/0.5 -> 428.57143 | I10: 100 | J10: =ROUNDUP(I10/E10,0) -> 2 | K10: =J10*G10 -> 428.57143 | L10: =J10*Parametry!$C$43 -> 20 | M10: Jedna osoba, jeden rodzaj towaru, 100 gotowych sztuk, bez konkurujących kursów. Rejs statku i droga do pracy nie są skracane.
A11: 1 | B11: 5 | C11: =ROUNDDOWN(Parametry!$C$9*Parametry!$C$10^(A11-1),0) -> 60 | D11: =1+Parametry!$C$72*MAX(0,B11-2) -> 1.3 | E11: =ROUNDDOWN(C11*D11,0) -> 78 | F11: =1+Parametry!$C$71*B11 -> 1.5 | G11: =300/F11 -> 200 | H11: =G11/0.5 -> 400 | I11: 100 | J11: =ROUNDUP(I11/E11,0) -> 2 | K11: =J11*G11 -> 400 | L11: =J11*Parametry!$C$43 -> 20 | M11: Jedna osoba, jeden rodzaj towaru, 100 gotowych sztuk, bez konkurujących kursów. Rejs statku i droga do pracy nie są skracane.
A12: 2 | B12: 0 | C12: =ROUNDDOWN(Parametry!$C$9*Parametry!$C$10^(A12-1),0) -> 66 | D12: =1+Parametry!$C$72*MAX(0,B12-2) -> 1 | E12: =ROUNDDOWN(C12*D12,0) -> 66 | F12: =1+Parametry!$C$71*B12 -> 1 | G12: =300/F12 -> 300 | H12: =G12/0.5 -> 600 | I12: 100 | J12: =ROUNDUP(I12/E12,0) -> 2 | K12: =J12*G12 -> 600 | L12: =J12*Parametry!$C$43 -> 20 | M12: Jedna osoba, jeden rodzaj towaru, 100 gotowych sztuk, bez konkurujących kursów. Rejs statku i droga do pracy nie są skracane.
A13: 2 | B13: 1 | C13: =ROUNDDOWN(Parametry!$C$9*Parametry!$C$10^(A13-1),0) -> 66 | D13: =1+Parametry!$C$72*MAX(0,B13-2) -> 1 | E13: =ROUNDDOWN(C13*D13,0) -> 66 | F13: =1+Parametry!$C$71*B13 -> 1.1 | G13: =300/F13 -> 272.72727 | H13: =G13/0.5 -> 545.45455 | I13: 100 | J13: =ROUNDUP(I13/E13,0) -> 2 | K13: =J13*G13 -> 545.45455 | L13: =J13*Parametry!$C$43 -> 20 | M13: Jedna osoba, jeden rodzaj towaru, 100 gotowych sztuk, bez konkurujących kursów. Rejs statku i droga do pracy nie są skracane.
A14: 2 | B14: 2 | C14: =ROUNDDOWN(Parametry!$C$9*Parametry!$C$10^(A14-1),0) -> 66 | D14: =1+Parametry!$C$72*MAX(0,B14-2) -> 1 | E14: =ROUNDDOWN(C14*D14,0) -> 66 | F14: =1+Parametry!$C$71*B14 -> 1.2 | G14: =300/F14 -> 250 | H14: =G14/0.5 -> 500 | I14: 100 | J14: =ROUNDUP(I14/E14,0) -> 2 | K14: =J14*G14 -> 500 | L14: =J14*Parametry!$C$43 -> 20 | M14: Jedna osoba, jeden rodzaj towaru, 100 gotowych sztuk, bez konkurujących kursów. Rejs statku i droga do pracy nie są skracane.
A15: 2 | B15: 3 | C15: =ROUNDDOWN(Parametry!$C$9*Parametry!$C$10^(A15-1),0) -> 66 | D15: =1+Parametry!$C$72*MAX(0,B15-2) -> 1.1 | E15: =ROUNDDOWN(C15*D15,0) -> 72 | F15: =1+Parametry!$C$71*B15 -> 1.3 | G15: =300/F15 -> 230.76923 | H15: =G15/0.5 -> 461.53846 | I15: 100 | J15: =ROUNDUP(I15/E15,0) -> 2 | K15: =J15*G15 -> 461.53846 | L15: =J15*Parametry!$C$43 -> 20 | M15: Jedna osoba, jeden rodzaj towaru, 100 gotowych sztuk, bez konkurujących kursów. Rejs statku i droga do pracy nie są skracane.
A16: 2 | B16: 4 | C16: =ROUNDDOWN(Parametry!$C$9*Parametry!$C$10^(A16-1),0) -> 66 | D16: =1+Parametry!$C$72*MAX(0,B16-2) -> 1.2 | E16: =ROUNDDOWN(C16*D16,0) -> 79 | F16: =1+Parametry!$C$71*B16 -> 1.4 | G16: =300/F16 -> 214.28571 | H16: =G16/0.5 -> 428.57143 | I16: 100 | J16: =ROUNDUP(I16/E16,0) -> 2 | K16: =J16*G16 -> 428.57143 | L16: =J16*Parametry!$C$43 -> 20 | M16: Jedna osoba, jeden rodzaj towaru, 100 gotowych sztuk, bez konkurujących kursów. Rejs statku i droga do pracy nie są skracane.
A17: 2 | B17: 5 | C17: =ROUNDDOWN(Parametry!$C$9*Parametry!$C$10^(A17-1),0) -> 66 | D17: =1+Parametry!$C$72*MAX(0,B17-2) -> 1.3 | E17: =ROUNDDOWN(C17*D17,0) -> 85 | F17: =1+Parametry!$C$71*B17 -> 1.5 | G17: =300/F17 -> 200 | H17: =G17/0.5 -> 400 | I17: 100 | J17: =ROUNDUP(I17/E17,0) -> 2 | K17: =J17*G17 -> 400 | L17: =J17*Parametry!$C$43 -> 20 | M17: Jedna osoba, jeden rodzaj towaru, 100 gotowych sztuk, bez konkurujących kursów. Rejs statku i droga do pracy nie są skracane.
... A29: 4 | B29: 5 | C29: =ROUNDDOWN(Parametry!$C$9*Parametry!$C$10^(A29-1),0) -> 79 | D29: =1+Parametry!$C$72*MAX(0,B29-2) -> 1.3 | E29: =ROUNDDOWN(C29*D29,0) -> 102 | F29: =1+Parametry!$C$71*B29 -> 1.5 | G29: =300/F29 -> 200 | H29: =G29/0.5 -> 400 | I29: 100 | J29: =ROUNDUP(I29/E29,0) -> 1 | K29: =J29*G29 -> 200 | L29: =J29*Parametry!$C$43 -> 10 | M29: Jedna osoba, jeden rodzaj towaru, 100 gotowych sztuk, bez konkurujących kursów. Rejs statku i droga do pracy nie są skracane.

Sheet Efekty i notyfikacje
A1: EFEKTY • powiadomienia i góra Town Hall
A2: Każdy efekt ma źródło, wartość, odbiorców oraz czas albo warunek zakończenia. Powiadomienia pojawiają się przy aktywacji, zmianie i końcu, bez powtórzeń przy odświeżaniu. Ratusz pokazuje aktywne efekty; jednorazowe zdarzenia pozostają w historii. Informacji o podatkach nie pokazujemy w UI.
A5: Źródło | B5: Wartość / skutek | C5: Kogo dotyczy | D5: Czas / koniec | E5: Powiadomienie | F5: Widoczność
A6: Jedzenie | B6: +1 pp/os./h | C6: Najedzeni mieszkańcy | D6: Dopóki mają posiłek | E6: Zmiana stanu karmienia | F6: Tak; bez informacji podatkowych
A7: Praca | B7: +1 pp/os./h | C7: Osoby po dotarciu, faktycznie pracujące | D7: Dopóki pracują bez blokady | E7: Start, koniec lub zmiana liczby osób | F7: Tak
A8: Głód | B8: Po 12 h: −5 pp/os./h; wydajność od razu ×0,5 | C8: Głodni mieszkańcy; zamrożenie H zachowane | D8: Do posiłku; licznik głodu jest resetowany | E8: Początek, próg kary, koniec | F8: Tak
A9: Bezrobocie | B9: Po 12 h: −5 pp/os./h | C9: Niepracujący; oddzielny licznik | D9: Do podjęcia pracy | E9: Początek, próg kary, koniec | F9: Tak
A10: Przestój | B10: −10 pp od razu, potem −10 co 24 h; minimum −50 tego składnika | C10: Przypisani do zablokowanego producenta | D10: Do odblokowania lub zwolnienia | E10: Zmiana blokady albo stopnia kary | F10: Tak
A11: Przeludnienie | B11: −1 pp/os./h za każdą osobę bez łóżka | C11: Cała populacja | D11: Do zapewnienia miejsc; zależne od braków | E11: Początek, zmiana liczby braków, koniec | F11: Tak
A12: Pula domu | B12: Ręczny przydział dodatnich pp; automat reszty po 23 h 58 min | C12: Wybrani / najmniej szczęśliwi | D12: Punkty trwałe, pula odnawiana co 24 h | E12: Przydział, automat, odnowienie | F12: Zdarzenia w historii; bez fikcyjnego czasu wygaśnięcia
A13: Kaplica: rozbudowa | B13: +10 × osiągnięty poziom pp | C13: Populacja | D13: 10 h | E13: Początek, odświeżenie, koniec | F13: Tak; podatki mechanicznie ×2, lecz opis ukryty w UI
A14: Kaplica: błogosławieństwo | B14: +50 każdego zasobu oraz +20 pp | C14: Populacja | D14: 1 h; kolejne płatne 4 h po końcu | E14: Początek, koniec | F14: Tak
A15: Latarnia: rozbudowa | B15: 100% H i produkcja materiałów ×2 | C15: Populacja; nowe osoby nadal 0% przez 24 h | D15: 24 h × osiągnięty poziom | E15: Początek, odświeżenie, koniec | F15: Tak
A16: Latarnia: uczestnik wizyty | B16: 100% H | C16: Uczestnicy po powrocie | D16: 24 h od powrotu; wizyta trwa 4 h | E16: Powrót, koniec | F16: Tak
... A24: Wygaśnięcie zadania | B24: Utrata nieodwracalnych wpłat | C24: Zadanie | D24: W chwili terminu | E24: Raz na wygasłe ID | F24: Powiadomienie

Sheet Sprawdzenia v8
A1: SPRAWDZENIA V8 • przeliczone przykłady
A2: TRUE w kolumnie D oznacza zgodność wyniku formuły z niezależnie obliczoną wartością oczekiwaną. Przed publikacją wszystkie formuły przeliczono w LibreOffice. Walidator sprawdza brak błędów i pustych wyników, zachowanie komentarzy i źródeł oraz niezmienioną sumę SHA-256 pliku V7.
A5: Sprawdzenie | B5: Wynik formuły | C5: Oczekiwane | D5: Zgodne | E5: Uwagi
A6: Źródło V7 — liczba osób | B6: =Parametry!C6 -> 12 | C6: 12 | D6: =B6=C6 -> TRUE
A7: Własny limit pracy | B7: =Parametry!C8 -> 12 | C7: 12 | D7: =B7=C7 -> TRUE
A8: Podatek — silnik bez zmiany | B8: =Parametry!C27 -> 1 | C8: 1 | D8: =B8=C8 -> TRUE | E8: UIbez podatków, rachunek nadal 1 moneta.
A9: Premia Share 500 | B9: =Parametry!$C$81 -> 500 | C9: 500 | D9: =B9=C9 -> TRUE
A10: Katalog 20 | B10: =COUNTA(Atrakcje!A6:A25) -> 20 | C10: 20 | D10: =B10=C10 -> TRUE
A11: Widoczne oferty 5 | B11: =Parametry!$C$80 -> 5 | C11: 5 | D11: =B11=C11 -> TRUE
A12: Rotacja 24 h | B12: =Parametry!$C$78 -> 24 | C12: 24 | D12: =B12=C12 -> TRUE
A13: Przerwa 24 h | B13: =Parametry!$C$77 -> 24 | C13: 24 | D13: =B13=C13 -> TRUE
A14: Premia 6 h | B14: =Parametry!$C$76 -> 6 | C14: 6 | D14: =B14=C14 -> TRUE
A15: Drogi 0:szybkość | B15: =Sciezki!G6 -> 1 | C15: 1 | D15: =B15=C15 -> TRUE
A16: Drogi 0:ładunek | B16: =Sciezki!I6 -> 1 | C16: 1 | D16: =B16=C16 -> TRUE
A17: Drogi 0:kosztod 0 | B17: =Sciezki!E6 -> 0 | C17: 0 | D17: =B17=C17 -> TRUE
A18: Drogi 1:szybkość | B18: =Sciezki!G7 -> 1.1 | C18: 1.1 | D18: =B18=C18 -> TRUE
A19: Drogi 1:ładunek | B19: =Sciezki!I7 -> 1 | C19: 1 | D19: =B19=C19 -> TRUE
A20: Drogi 1:kosztod 0 | B20: =Sciezki!E7 -> 10000 | C20: 10000 | D20: =B20=C20 -> TRUE
A21: Drogi 2:szybkość | B21: =Sciezki!G8 -> 1.2 | C21: 1.2 | D21: =B21=C21 -> TRUE
A22: Drogi 2:ładunek | B22: =Sciezki!I8 -> 1 | C22: 1 | D22: =B22=C22 -> TRUE
A23: Drogi 2:kosztod 0 | B23: =Sciezki!E8 -> 20000 | C23: 20000 | D23: =B23=C23 -> TRUE
A24: Drogi 3:szybkość | B24: =Sciezki!G9 -> 1.3 | C24: 1.3 | D24: =B24=C24 -> TRUE
A25: Drogi 3:ładunek | B25: =Sciezki!I9 -> 1.1 | C25: 1.1 | D25: =B25=C25 -> TRUE
A26: Drogi 3:kosztod 0 | B26: =Sciezki!E9 -> 30000 | C26: 30000 | D26: =B26=C26 -> TRUE
A27: Drogi 4:szybkość | B27: =Sciezki!G10 -> 1.4 | C27: 1.4 | D27: =B27=C27 -> TRUE
A28: Drogi 4:ładunek | B28: =Sciezki!I10 -> 1.2 | C28: 1.2 | D28: =B28=C28 -> TRUE
A29: Drogi 4:kosztod 0 | B29: =Sciezki!E10 -> 40000 | C29: 40000 | D29: =B29=C29 -> TRUE
A30: Drogi 5:szybkość | B30: =Sciezki!G11 -> 1.5 | C30: 1.5 | D30: =B30=C30 -> TRUE
A31: Drogi 5:ładunek | B31: =Sciezki!I11 -> 1.3 | C31: 1.3 | D31: =B31=C31 -> TRUE
A32: Drogi 5:kosztod 0 | B32: =Sciezki!E11 -> 50000 | C32: 50000 | D32: =B32=C32 -> TRUE
A33: Wszystkie 5 poziomów — kamień | B33: =Sciezki!E11 -> 50000 | C33: 50000 | D33: =B33=C33 -> TRUE
A34: Pierwszepoziom+10%nie−10%czasu | B34: =ROUND(Sciezki!J7,6) -> 272.72727 | C34: 272.72727 | D34: =B34=C34 -> TRUE
A35: AtrakcjaL1Y5 u 1:cena | B35: ='Atrakcje - kalkulator'!E6 -> 5 | C35: 5 | D35: =B35=C35 -> TRUE
A36: AtrakcjaL1Y5 u 1:premia | B36: ='Atrakcje - kalkulator'!F6 -> 5 | C36: 5 | D36: =B36=C36 -> TRUE
A37: AtrakcjaL1Y5 u 2:cena | B37: ='Atrakcje - kalkulator'!E7 -> 5 | C37: 5 | D37: =B37=C37 -> TRUE
A38: AtrakcjaL1Y5 u 2:premia | B38: ='Atrakcje - kalkulator'!F7 -> 3.75 | C38: 3.75 | D38: =B38=C38 -> TRUE
A39: AtrakcjaL1Y5 u 3:cena | B39: ='Atrakcje - kalkulator'!E8 -> 5 | C39: 5 | D39: =B39=C39 -> TRUE
A40: AtrakcjaL1Y5 u 3:premia | B40: ='Atrakcje - kalkulator'!F8 -> 2.5 | C40: 2.5 | D40: =B40=C40 -> TRUE
A41: AtrakcjaL1Y5 u 4:cena | B41: ='Atrakcje - kalkulator'!E9 -> 5 | C41: 5 | D41: =B41=C41 -> TRUE
A42: AtrakcjaL1Y5 u 4:premia | B42: ='Atrakcje - kalkulator'!F9 -> 1.25 | C42: 1.25 | D42: =B42=C42 -> TRUE
A43: AtrakcjaL1Y5 u 5:cena | B43: ='Atrakcje - kalkulator'!E10 -> 5 | C43: 5 | D43: =B43=C43 -> TRUE
A44: AtrakcjaL1Y5 u 5:premia | B44: ='Atrakcje - kalkulator'!F10 -> 0 | C44: 0 | D44: =B44=C44 -> TRUE
A45: AtrakcjaL1Y25 u 1:cena | B45: ='Atrakcje - kalkulator'!E11 -> 25 | C45: 25 | D45: =B45=C45 -> TRUE
A46: AtrakcjaL1Y25 u 1:premia | B46: ='Atrakcje - kalkulator'!F11 -> 25 | C46: 25 | D46: =B46=C46 -> TRUE
A47: AtrakcjaL1Y25 u 2:cena | B47: ='Atrakcje - kalkulator'!E12 -> 25 | C47: 25 | D47: =B47=C47 -> TRUE
A48: AtrakcjaL1Y25 u 2:premia | B48: ='Atrakcje - kalkulator'!F12 -> 18.75 | C48: 18.75 | D48: =B48=C48 -> TRUE
A49: AtrakcjaL1Y25 u 3:cena | B49: ='Atrakcje - kalkulator'!E13 -> 25 | C49: 25 | D49: =B49=C49 -> TRUE
A50: AtrakcjaL1Y25 u 3:premia | B50: ='Atrakcje - kalkulator'!F13 -> 12.5 | C50: 12.5 | D50: =B50=C50 -> TRUE
A51: AtrakcjaL1Y25 u 4:cena | B51: ='Atrakcje - kalkulator'!E14 -> 25 | C51: 25 | D51: =B51=C51 -> TRUE
A52: AtrakcjaL1Y25 u 4:premia | B52: ='Atrakcje - kalkulator'!F14 -> 6.25 | C52: 6.25 | D52: =B52=C52 -> TRUE
A53: AtrakcjaL1Y25 u 5:cena | B53: ='Atrakcje - kalkulator'!E15 -> 25 | C53: 25 | D53: =B53=C53 -> TRUE
A54: AtrakcjaL1Y25 u 5:premia | B54: ='Atrakcje - kalkulator'!F15 -> 0 | C54: 0 | D54: =B54=C54 -> TRUE
A55: AtrakcjaL1Y50 u 1:cena | B55: ='Atrakcje - kalkulator'!E16 -> 50 | C55: 50 | D55: =B55=C55 -> TRUE
A56: AtrakcjaL1Y50 u 1:premia | B56: ='Atrakcje - kalkulator'!F16 -> 50 | C56: 50 | D56: =B56=C56 -> TRUE
A57: AtrakcjaL1Y50 u 2:cena | B57: ='Atrakcje - kalkulator'!E17 -> 50 | C57: 50 | D57: =B57=C57 -> TRUE
A58: AtrakcjaL1Y50 u 2:premia | B58: ='Atrakcje - kalkulator'!F17 -> 37.5 | C58: 37.5 | D58: =B58=C58 -> TRUE
A59: AtrakcjaL1Y50 u 3:cena | B59: ='Atrakcje - kalkulator'!E18 -> 50 | C59: 50 | D59: =B59=C59 -> TRUE
A60: AtrakcjaL1Y50 u 3:premia | B60: ='Atrakcje - kalkulator'!F18 -> 25 | C60: 25 | D60: =B60=C60 -> TRUE
A61: AtrakcjaL1Y50 u 4:cena | B61: ='Atrakcje - kalkulator'!E19 -> 50 | C61: 50 | D61: =B61=C61 -> TRUE
A62: AtrakcjaL1Y50 u 4:premia | B62: ='Atrakcje - kalkulator'!F19 -> 12.5 | C62: 12.5 | D62: =B62=C62 -> TRUE
A63: AtrakcjaL1Y50 u 5:cena | B63: ='Atrakcje - kalkulator'!E20 -> 50 | C63: 50 | D63: =B63=C63 -> TRUE
A64: AtrakcjaL1Y50 u 5:premia | B64: ='Atrakcje - kalkulator'!F20 -> 0 | C64: 0 | D64: =B64=C64 -> TRUE
A65: AtrakcjaL1Y100 u 1:cena | B65: ='Atrakcje - kalkulator'!E21 -> 100 | C65: 100 | D65: =B65=C65 -> TRUE
A66: AtrakcjaL1Y100 u 1:premia | B66: ='Atrakcje - kalkulator'!F21 -> 100 | C66: 100 | D66: =B66=C66 -> TRUE
A67: AtrakcjaL1Y100 u 2:cena | B67: ='Atrakcje - kalkulator'!E22 -> 100 | C67: 100 | D67: =B67=C67 -> TRUE
A68: AtrakcjaL1Y100 u 2:premia | B68: ='Atrakcje - kalkulator'!F22 -> 75 | C68: 75 | D68: =B68=C68 -> TRUE
A69: AtrakcjaL1Y100 u 3:cena | B69: ='Atrakcje - kalkulator'!E23 -> 100 | C69: 100 | D69: =B69=C69 -> TRUE
A70: AtrakcjaL1Y100 u 3:premia | B70: ='Atrakcje - kalkulator'!F23 -> 50 | C70: 50 | D70: =B70=C70 -> TRUE
A71: AtrakcjaL1Y100 u 4:cena | B71: ='Atrakcje - kalkulator'!E24 -> 100 | C71: 100 | D71: =B71=C71 -> TRUE
A72: AtrakcjaL1Y100 u 4:premia | B72: ='Atrakcje - kalkulator'!F24 -> 25 | C72: 25 | D72: =B72=C72 -> TRUE
A73: AtrakcjaL1Y100 u 5:cena | B73: ='Atrakcje - kalkulator'!E25 -> 100 | C73: 100 | D73: =B73=C73 -> TRUE
A74: AtrakcjaL1Y100 u 5:premia | B74: ='Atrakcje - kalkulator'!F25 -> 0 | C74: 0 | D74: =B74=C74 -> TRUE
A75: AtrakcjaL2Y5 u 1:cena | B75: ='Atrakcje - kalkulator'!E26 -> 10 | C75: 10 | D75: =B75=C75 -> TRUE
A76: AtrakcjaL2Y5 u 1:premia | B76: ='Atrakcje - kalkulator'!F26 -> 5 | C76: 5 | D76: =B76=C76 -> TRUE
A77: AtrakcjaL2Y5 u 2:cena | B77: ='Atrakcje - kalkulator'!E27 -> 10 | C77: 10 | D77: =B77=C77 -> TRUE
A78: AtrakcjaL2Y5 u 2:premia | B78: ='Atrakcje - kalkulator'!F27 -> 3.75 | C78: 3.75 | D78: =B78=C78 -> TRUE
A79: AtrakcjaL2Y5 u 3:cena | B79: ='Atrakcje - kalkulator'!E28 -> 10 | C79: 10 | D79: =B79=C79 -> TRUE
A80: AtrakcjaL2Y5 u 3:premia | B80: ='Atrakcje - kalkulator'!F28 -> 2.5 | C80: 2.5 | D80: =B80=C80 -> TRUE
A81: AtrakcjaL2Y5 u 4:cena | B81: ='Atrakcje - kalkulator'!E29 -> 10 | C81: 10 | D81: =B81=C81 -> TRUE
A82: AtrakcjaL2Y5 u 4:premia | B82: ='Atrakcje - kalkulator'!F29 -> 1.25 | C82: 1.25 | D82: =B82=C82 -> TRUE
A83: AtrakcjaL2Y5 u 5:cena | B83: ='Atrakcje - kalkulator'!E30 -> 10 | C83: 10 | D83: =B83=C83 -> TRUE
A84: AtrakcjaL2Y5 u 5:premia | B84: ='Atrakcje - kalkulator'!F30 -> 0 | C84: 0 | D84: =B84=C84 -> TRUE
A85: AtrakcjaL2Y25 u 1:cena | B85: ='Atrakcje - kalkulator'!E31 -> 50 | C85: 50 | D85: =B85=C85 -> TRUE
A86: AtrakcjaL2Y25 u 1:premia | B86: ='Atrakcje - kalkulator'!F31 -> 25 | C86: 25 | D86: =B86=C86 -> TRUE
A87: AtrakcjaL2Y25 u 2:cena | B87: ='Atrakcje - kalkulator'!E32 -> 50 | C87: 50 | D87: =B87=C87 -> TRUE
A88: AtrakcjaL2Y25 u 2:premia | B88: ='Atrakcje - kalkulator'!F32 -> 18.75 | C88: 18.75 | D88: =B88=C88 -> TRUE
A89: AtrakcjaL2Y25 u 3:cena | B89: ='Atrakcje - kalkulator'!E33 -> 50 | C89: 50 | D89: =B89=C89 -> TRUE
A90: AtrakcjaL2Y25 u 3:premia | B90: ='Atrakcje - kalkulator'!F33 -> 12.5 | C90: 12.5 | D90: =B90=C90 -> TRUE
A91: AtrakcjaL2Y25 u 4:cena | B91: ='Atrakcje - kalkulator'!E34 -> 50 | C91: 50 | D91: =B91=C91 -> TRUE
A92: AtrakcjaL2Y25 u 4:premia | B92: ='Atrakcje - kalkulator'!F34 -> 6.25 | C92: 6.25 | D92: =B92=C92 -> TRUE
A93: AtrakcjaL2Y25 u 5:cena | B93: ='Atrakcje - kalkulator'!E35 -> 50 | C93: 50 | D93: =B93=C93 -> TRUE
A94: AtrakcjaL2Y25 u 5:premia | B94: ='Atrakcje - kalkulator'!F35 -> 0 | C94: 0 | D94: =B94=C94 -> TRUE
A95: AtrakcjaL2Y50 u 1:cena | B95: ='Atrakcje - kalkulator'!E36 -> 100 | C95: 100 | D95: =B95=C95 -> TRUE
A96: AtrakcjaL2Y50 u 1:premia | B96: ='Atrakcje - kalkulator'!F36 -> 50 | C96: 50 | D96: =B96=C96 -> TRUE
A97: AtrakcjaL2Y50 u 2:cena | B97: ='Atrakcje - kalkulator'!E37 -> 100 | C97: 100 | D97: =B97=C97 -> TRUE
A98: AtrakcjaL2Y50 u 2:premia | B98: ='Atrakcje - kalkulator'!F37 -> 37.5 | C98: 37.5 | D98: =B98=C98 -> TRUE
A99: AtrakcjaL2Y50 u 3:cena | B99: ='Atrakcje - kalkulator'!E38 -> 100 | C99: 100 | D99: =B99=C99 -> TRUE
A100: AtrakcjaL2Y50 u 3:premia | B100: ='Atrakcje - kalkulator'!F38 -> 25 | C100: 25 | D100: =B100=C100 -> TRUE
A101: AtrakcjaL2Y50 u 4:cena | B101: ='Atrakcje - kalkulator'!E39 -> 100 | C101: 100 | D101: =B101=C101 -> TRUE
A102: AtrakcjaL2Y50 u 4:premia | B102: ='Atrakcje - kalkulator'!F39 -> 12.5 | C102: 12.5 | D102: =B102=C102 -> TRUE
...

Sheet Premium
A1: PREMIUM V7 • ceny i warunki
A2: Jedna pula monet (złoto), kupionych i zarobionych. 1 PLN = 10 monet jest ceną zakupu, bez wypłaty na pieniądze. Ceny w prototypie nie oznaczają uruchomienia rzeczywistych płatności. Poniżej uwzględniono D09–D12 i D15.
A5: Akcja | B5: Zasada | C5: Wzór / stawka | D5: Uwagi | E5: Status | G5: Twoje wpisy źródłowe — historia
A6: Przelicznik płatności | B6: 1 PLN = 10 monet. | C6: Cena w PLN = cena w monetach / 10. | D6: Ustalono przelicznik; nie zdefiniowano wypłaty monet na PLN. | E6: POTWIERDZONE
A7: Waluta | B7: Monety = złoto; jedna pula kupiona i zarobiona. | C7: 1 PLN = 10 monet; brak prawa wymiany monet na PLN. | D7: Zarobione monety mogą kupować te same usługi co kupione. | E7: ROZSTRZYGNIĘTE V7 | G7: monety = złoto jest jedna waluta w grze
A8: Przyspieszenie 25% | B8: 25/50/75/100% pozostałej fazy budowania, bez transportu. Cena = MAX(5, FLOOR(zaoszczędzone sekundy / 60)) monet. Transport jest osobno rozliczany za potrzebne kursy. | C8: MAX(5, FLOOR(pozostała budowa [s] × procent / 60)) monet. | D8: Transport rozliczany osobno za kursy; wyświetlamy czas i cenę przed kliknięciem. | E8: ROZSTRZYGNIĘTE V7 D12 | G8: jeżeli budowa czegoś trwa 60 min zostało 50 do wybudowania chce przyspieszyć o połowę czyli o 25 min to musze zapłacić 25 monet tak samo dla innych procentów, sekundy zzaokrąglasz w dół
A9: Przyspieszenie 50% | B9: 25/50/75/100% pozostałej fazy budowania, bez transportu. Cena = MAX(5, FLOOR(zaoszczędzone sekundy / 60)) monet. Transport jest osobno rozliczany za potrzebne kursy. | C9: MAX(5, FLOOR(pozostała budowa [s] × procent / 60)) monet. | D9: Transport rozliczany osobno za kursy; wyświetlamy czas i cenę przed kliknięciem. | E9: ROZSTRZYGNIĘTE V7 D12
A10: Przyspieszenie 75% | B10: 25/50/75/100% pozostałej fazy budowania, bez transportu. Cena = MAX(5, FLOOR(zaoszczędzone sekundy / 60)) monet. Transport jest osobno rozliczany za potrzebne kursy. | C10: MAX(5, FLOOR(pozostała budowa [s] × procent / 60)) monet. | D10: Transport rozliczany osobno za kursy; wyświetlamy czas i cenę przed kliknięciem. | E10: ROZSTRZYGNIĘTE V7 D12
A11: Budowa natychmiast z zasobami | B11: Natychmiastowe zakończenie pozostałej fazy budowania (100%). Transport pozostaje osobną usługą. | C11: MAX(5, FLOOR(pozostała budowa [s] × procent / 60)) monet. | D11: Transport rozliczany osobno za kursy; wyświetlamy czas i cenę przed kliknięciem. | E11: ROZSTRZYGNIĘTE V7 D12 | G11: cały czas potrzebny przeliczony jak wyżej na monety
A12: Transport całego bufora producenta (dostępne od levelu 4) | B12: Natychmiastowe wysłanie całego gotowego lokalnego zapasu do centrali. | C12: 10 monet × liczba kursów potrzebnych do przewozu. | D12: Potwierdzone: kursy = ROUNDUP(ilość / ładunek, 0). Ostatni niepełny kurs jest płatny. Dla 100 sztuk i ładunku 60 potrzeba 2 kursów, więc cena wynosi 20 monet. | E12: POTWIERDZONE
A13: Magazyn → budowa (dostępne od levelu 4) | B13: Natychmiastowy przewóz materiałów centralnych na konkretną budowę. | C13: 10 monet × SUMA CEILING(ilość każdego materiału / ładunek). | D13: Jedno zlecenie obejmuje wymagane, dostępne materiały dla wybranej budowy; monety bez transportu. | E13: POTWIERDZONE | G13: w menu budowy widze ile trwa transport I ile trwa sama budowa mogę za montety przyspieszyć oba, sama budowa jak wyżej, logika ceny natychmiastowego transportu, system liczy ilość kursów tragarza x 10 monet za kurs
A14: Magazyn ↔ targ (dostępne od levelu 4) | B14: Takie samo rozliczenie transportu towarów w obu kierunkach. | C14: 10 monet za potrzebny kurs właściwej załogi, osobno dla każdego materiału. | D14: Transport Premium nie omija blokady 1 h ani nie tworzy towarów i wolnego miejsca; zachowujemy terminy partii. | E14: STAWKA POTWIERDZONA | G14: analogicznie jak wyżej
A15: Magazyn ↔ port (dostępne od levelu 4) | B15: Takie samo rozliczenie transportu towarów w obu kierunkach. | C15: 10 monet za potrzebny kurs właściwej załogi, osobno dla każdego materiału. | D15: Dwie opłaty: przewóz centrala↔port oraz osobny załadunek/rozładunek port↔statek, każdy według liczby kursów. | E15: ROZSTRZYGNIĘTE V7 | G15: dwie opłaty jedna za transoport do portu druga za załadunek
A16: Kup budynek bez surowców (dostępne od levelu 4) | B16: Pełny zakup budynku od poziomu gracza 4: wszystkie materiały według proporcjonalnych bazowych cen zakupu portu ×1,25 + nominalne monety budynku + natychmiastowy transport (10 monet za każdy potrzebny kurs, także niepełny). Nic nie pobieramy z własnych materiałów. Gotowe po 10 s; bez wymogu rzeczywistych tragarzy. | C16: ROUNDUP(1,25 × portowa wartość pełnych materiałów + nominalne monety + 10 × SUMA CEIL(materiał/ładunek), 0). | D16: Gotowe po 10 sekundach. Materiały w cenie pełnego zakupu nie są pobierane z własnych zapasów. Nie doliczamy wcześniejszej opłaty za minuty. | E16: ROZSTRZYGNIĘTE V7 D11 | G16: koszt transportu natychmiastowego + materiały droższe niż w porcie o 25 %
A17: Monety w koszcie kupowanego budynku | B17: Monety zapisane w koszcie budynku doliczamy osobno w wymaganej wysokości. | C17: Nominalne monety + pełne materiały ×1,25 + natychmiastowy transport; gotowe w 10 s. | D17: Potwierdzone: monety nie są materiałem kupowanym w porcie i nie podlegają dopłacie 25%. | E17: POTWIERDZONE
A18: Pakiet budowlany | B18: Pakiet: 1000 × poziom ratusza monet za 24 h; +4 aktywne budowy, dowolna kolejka, planowanie dostaw. Dopłata kolejki +10% pozostaje; ponowny zakup przedłuża ważność. | C18: 1000 × poziom Ratusza monet / 24 h. | D18: Kolejka nadal +10%; kolejny zakup przedłuża ważność. | E18: ROZSTRZYGNIĘTE V7 D09 | G18: ustawmy koszt pakietu na 1000 monet
A19: Błogosławieństwa Premium | B19: Płatne błogosławieństwo: 100 × poziom kaplicy monet; +50 każdego zasobu i +20 pp na 1 h. Kolejne płatne użycie 4 h od KOŃCA efektu: 12:00–13:00 → następne 17:00. Nie można nakładać aktywnych błogosławieństw. | C19: 100 × poziom Kaplicy monet. Następne 4 h od końca godzinnego efektu. | D19: Bezpłatne użycia zależne od poziomu pozostają; zakaz nakładania aktywnych efektów. | E19: ROZSTRZYGNIĘTE V7 D15
A20: Pakiet +4 aktywne budowy | B20: W czasie pakietu limit aktywnych budów = poziom ratusza +4. | C20: 1000 × poziom Ratusza monet / 24 h, łącznie w pakiecie. | D20: Zwykłe opłacone budowy wymagają materiałów; zakupy bez surowców to osobna nowa oferta. Dodatkowe sloty nie produkują materiałów ani nie tworzą transportu. | E20: WCZEŚNIEJ UZGODNIONY ZAKRES
A21: Dowolnie długa kolejka | B21: Podczas pakietu brak zwykłego limitu długości kolejki. | C21: Dowolna kolejka w aktywnym pakiecie; koszt każdego zakolejkowanego projektu +10%. | D21: Pełny koszt zwykłej kolejki rezerwowany przy zleceniu. Prognoza wymaga dodatkowej opłaty. | E21: WCZEŚNIEJ UZGODNIONE + NOWA DOPŁATA
A22: Planowanie z estymaty dostaw | B22: W aktywnym pakiecie plan ma koszt kolejki +10% (każdy składnik w górę), plus opłatę 25% bazowej portowej wartości zakupu braków centralnych. Baza 300 kamienia, centrala 200 → wymagane 330, brak 130; bufor producenta nie jest centralą. Materiały muszą rzeczywiście dotrzeć. | C22: 25% bazowej portowej wartości braków centralnych po +10% kosztu kolejki. | D22: Wymaga aktywnego pakietu. Nie kupuje ani nie tworzy brakujących materiałów. | E22: ROZSTRZYGNIĘTE V7 D10 | G22: opisane w innym miejscu
A23: Płatne błogosławieństwo | B23: Płatne błogosławieństwo: 100 × poziom kaplicy monet; +50 każdego zasobu i +20 pp na 1 h. Kolejne płatne użycie 4 h od KOŃCA efektu: 12:00–13:00 → następne 17:00. Nie można nakładać aktywnych błogosławieństw. | C23: 100 × poziom Kaplicy monet. Następne 4 h od końca godzinnego efektu. | D23: Bezpłatne użycia zależne od poziomu pozostają; zakaz nakładania aktywnych efektów. | E23: ROZSTRZYGNIĘTE V7 D15
A24: Błogosławieństwo za challenge | B24: Dodatkowe użycie po wyzwaniu. | C24: Limity i nagrody nieustalone. | D24: Treść i warunki challenge nieustalone. Wpływ na aktywny efekt i cooldown nieustalony. | E24: ODŁOŻONE
A25: Błogosławieństwo za social | B25: Dodatkowe użycie za udostępnienie, np. FB/Instagram. | C25: Limity nieustalone. | D25: Sposób weryfikacji nieustalony. Wpływ na aktywny efekt i cooldown nieustalony. | E25: ODŁOŻONE
A26: Reklama i oczekiwanie | B26: Notatka: reklama 60 s skraca pozostałe czekanie o połowę; do 2 reklam na godzinę gry. | C26: 2/h w źródle; pełne warunki odłożone. | D26: Nagroda po reklamie — szczegóły nieustalone. Zgodność z aktywnym efektem, rodzaj godziny i reset nieustalone. | E26: ODŁOŻONE
A27: Premia za zwiedzanie | B27: Pobyt 4 h, bez czasu dojścia i możliwości wycofania. Wyłącznie wolne osoby z domu; jednocześnie 2 × poziom latarni miejsc. Darmowo 2 × poziom latarni wejść w ruchomych 24 h. Do 3 dodatkowych pakietów/24 h, każdy daje 2L wejść; cena 300 × numer pakietu (2, 3, 4) × L. Pakiet nie zwiększa liczby miejsc jednocześnie. | C27: Premie od powrotu: uczestnik 100% na 24 h i blokada ponownej wizyty przez te same 24 h; każda osobno wysłana grupa daje populacji +10 pp przez 6 h. Premie grup sumują się w czasie nakładania. | D27: Miejsca, pula wejść i indywidualna blokada to trzy osobne limity. Zwiedzający je, nie pracuje i nie płaci podatku. | E27: ROZSTRZYGNIĘTE V7 D01–D02 | G27: 2x poziom na 24 h dostępna zawsze dla wszystkich bez dopłat, Możliwosć dokupienia nie wiecej niż 3 pakietów, czyli w sumie 4 na 24 h, koszt dodatkowego 300xnumer pakietu w dobie x level czyli jestem na levelu 6 cche dodatkowe zwiedzanie, pierwsze dodatkowe, drugie w ostatniej dobie, 6 x 2 x 300= 3600

Sheet Premium - czas
A1: PRZYSPIESZENIA • kalkulator ceny
A2: 25/50/75/100% pozostałej fazy budowania, bez transportu. Cena = MAX(5, FLOOR(zaoszczędzone sekundy / 60)) monet. Transport jest osobno rozliczany za potrzebne kursy. Niebieskie pola są edytowalne. Minimum 5 obowiązuje także przy 1–4 pełnych minutach, a nie wyłącznie wyniku zero.
A5: Pozostała budowa [min] | B5: Skrócenie | C5: Zaoszczędzony czas [min] | D5: Pozostało [min] | E5: Cena [monety] | F5: Cena zakupu monet [PLN] | G5: Uwagi
A6: 1.5 | B6: 0.25 | C6: =A6*B6 -> 0.375 | D6: =A6-C6 -> 1.125 | E6: =MAX(Parametry!$C$52,ROUNDDOWN(C6,0)*Parametry!$C$42) -> 5 | F6: =E6/Parametry!$C$41 -> 0.5 | G6: Cena minimalna zawsze 5 monet; pełne zaoszczędzone minuty zaokrąglamy w dół. | J6: jeżeli kalkulacja pozostałego czasu wskazuje że cena przyspieszenia wynosi 0 kasuj na stałe 5
A7: 1.5 | B7: 0.5 | C7: =A7*B7 -> 0.75 | D7: =A7-C7 -> 0.75 | E7: =MAX(Parametry!$C$52,ROUNDDOWN(C7,0)*Parametry!$C$42) -> 5 | F7: =E7/Parametry!$C$41 -> 0.5 | G7: Cena minimalna zawsze 5 monet; pełne zaoszczędzone minuty zaokrąglamy w dół.
A8: 1.5 | B8: 0.75 | C8: =A8*B8 -> 1.125 | D8: =A8-C8 -> 0.375 | E8: =MAX(Parametry!$C$52,ROUNDDOWN(C8,0)*Parametry!$C$42) -> 5 | F8: =E8/Parametry!$C$41 -> 0.5 | G8: Cena minimalna zawsze 5 monet; pełne zaoszczędzone minuty zaokrąglamy w dół.
A9: 10 | B9: 0.25 | C9: =A9*B9 -> 2.5 | D9: =A9-C9 -> 7.5 | E9: =MAX(Parametry!$C$52,ROUNDDOWN(C9,0)*Parametry!$C$42) -> 5 | F9: =E9/Parametry!$C$41 -> 0.5 | G9: Cena minimalna zawsze 5 monet; pełne zaoszczędzone minuty zaokrąglamy w dół.
A10: 10 | B10: 0.5 | C10: =A10*B10 -> 5 | D10: =A10-C10 -> 5 | E10: =MAX(Parametry!$C$52,ROUNDDOWN(C10,0)*Parametry!$C$42) -> 5 | F10: =E10/Parametry!$C$41 -> 0.5 | G10: Cena minimalna zawsze 5 monet; pełne zaoszczędzone minuty zaokrąglamy w dół.
A11: 10 | B11: 0.75 | C11: =A11*B11 -> 7.5 | D11: =A11-C11 -> 2.5 | E11: =MAX(Parametry!$C$52,ROUNDDOWN(C11,0)*Parametry!$C$42) -> 7 | F11: =E11/Parametry!$C$41 -> 0.7 | G11: Cena minimalna zawsze 5 monet; pełne zaoszczędzone minuty zaokrąglamy w dół.
A12: 25 | B12: 0.25 | C12: =A12*B12 -> 6.25 | D12: =A12-C12 -> 18.75 | E12: =MAX(Parametry!$C$52,ROUNDDOWN(C12,0)*Parametry!$C$42) -> 6 | F12: =E12/Parametry!$C$41 -> 0.6 | G12: Cena minimalna zawsze 5 monet; pełne zaoszczędzone minuty zaokrąglamy w dół.
A13: 25 | B13: 0.5 | C13: =A13*B13 -> 12.5 | D13: =A13-C13 -> 12.5 | E13: =MAX(Parametry!$C$52,ROUNDDOWN(C13,0)*Parametry!$C$42) -> 12 | F13: =E13/Parametry!$C$41 -> 1.2 | G13: Cena minimalna zawsze 5 monet; pełne zaoszczędzone minuty zaokrąglamy w dół.
A14: 25 | B14: 0.75 | C14: =A14*B14 -> 18.75 | D14: =A14-C14 -> 6.25 | E14: =MAX(Parametry!$C$52,ROUNDDOWN(C14,0)*Parametry!$C$42) -> 18 | F14: =E14/Parametry!$C$41 -> 1.8 | G14: Cena minimalna zawsze 5 monet; pełne zaoszczędzone minuty zaokrąglamy w dół.
A15: 60 | B15: 0.25 | C15: =A15*B15 -> 15 | D15: =A15-C15 -> 45 | E15: =MAX(Parametry!$C$52,ROUNDDOWN(C15,0)*Parametry!$C$42) -> 15 | F15: =E15/Parametry!$C$41 -> 1.5 | G15: Cena minimalna zawsze 5 monet; pełne zaoszczędzone minuty zaokrąglamy w dół.
A16: 60 | B16: 0.5 | C16: =A16*B16 -> 30 | D16: =A16-C16 -> 30 | E16: =MAX(Parametry!$C$52,ROUNDDOWN(C16,0)*Parametry!$C$42) -> 30 | F16: =E16/Parametry!$C$41 -> 3 | G16: Cena minimalna zawsze 5 monet; pełne zaoszczędzone minuty zaokrąglamy w dół.
A17: 60 | B17: 0.75 | C17: =A17*B17 -> 45 | D17: =A17-C17 -> 15 | E17: =MAX(Parametry!$C$52,ROUNDDOWN(C17,0)*Parametry!$C$42) -> 45 | F17: =E17/Parametry!$C$41 -> 4.5 | G17: Cena minimalna zawsze 5 monet; pełne zaoszczędzone minuty zaokrąglamy w dół.
A18: 120 | B18: 0.25 | C18: =A18*B18 -> 30 | D18: =A18-C18 -> 90 | E18: =MAX(Parametry!$C$52,ROUNDDOWN(C18,0)*Parametry!$C$42) -> 30 | F18: =E18/Parametry!$C$41 -> 3 | G18: Cena minimalna zawsze 5 monet; pełne zaoszczędzone minuty zaokrąglamy w dół.
... A25: 5 | B25: 1 | C25: =A25*B25 -> 5 | D25: =A25-C25 -> 0 | E25: =MAX(Parametry!$C$52,ROUNDDOWN(C25,0)*Parametry!$C$42) -> 5 | F25: =E25/Parametry!$C$41 -> 0.5 | G25: Opcja 100%; sprawdzenie granicy minimum.

Sheet Premium - transport
A1: TRANSPORT PREMIUM • kursy i cena
A2: Potwierdzone: każdy potrzebny kurs jest płatny, również ostatni niepełny. Cena = SUMA(ROUNDUP(ilość rodzaju / ładunek)) × liczba odcinków × 10 monet. Dwa rodzaje nie dzielą kursu. Liczba pracowników zmienia czas, a nie liczbę płatnych kursów. Zakres jednego kliknięcia i etapu port–statek pozostaje otwarty. V8: ładunek przykładów uwzględnia premię ścieżek z Parametry (domyślnie0); liczba kursów i cena przeliczają się razem.
A5: Trasa / przykład | B5: Towar A [szt.] | C5: Towar B [szt.] | D5: Ładunek/kurs | E5: Liczba odcinków | F5: Kursy A | G5: Kursy B | H5: Kursy razem | I5: Monety | J5: Cena zakupu monet [PLN] | K5: Uwagi
A6: Produkcja → magazyn: 40 | B6: 40 | C6: 0 | D6: =ROUNDDOWN(60*(1+Parametry!$C$72*MAX(0,Parametry!$C$73-2)),0) -> 60 | E6: 1 | F6: =ROUNDUP(B6/D6,0) -> 1 | G6: =ROUNDUP(C6/D6,0) -> 0 | H6: =(F6+G6)*E6 -> 1 | I6: =H6*Parametry!$C$43 -> 10 | J6: =I6/Parametry!$C$41 -> 1 | K6: Cena zależy od potrzebnych kursów. Przykład 2 odcinków nie przesądza zakresu jednego kliknięcia portowego; doprecyzować załadunek i rozładunek.
A7: Produkcja → magazyn: 60 | B7: 60 | C7: 0 | D7: =ROUNDDOWN(60*(1+Parametry!$C$72*MAX(0,Parametry!$C$73-2)),0) -> 60 | E7: 1 | F7: =ROUNDUP(B7/D7,0) -> 1 | G7: =ROUNDUP(C7/D7,0) -> 0 | H7: =(F7+G7)*E7 -> 1 | I7: =H7*Parametry!$C$43 -> 10 | J7: =I7/Parametry!$C$41 -> 1 | K7: Cena zależy od potrzebnych kursów. Przykład 2 odcinków nie przesądza zakresu jednego kliknięcia portowego; doprecyzować załadunek i rozładunek.
A8: Produkcja → magazyn: 100 | B8: 100 | C8: 0 | D8: =ROUNDDOWN(60*(1+Parametry!$C$72*MAX(0,Parametry!$C$73-2)),0) -> 60 | E8: 1 | F8: =ROUNDUP(B8/D8,0) -> 2 | G8: =ROUNDUP(C8/D8,0) -> 0 | H8: =(F8+G8)*E8 -> 2 | I8: =H8*Parametry!$C$43 -> 20 | J8: =I8/Parametry!$C$41 -> 2 | K8: Cena zależy od potrzebnych kursów. Przykład 2 odcinków nie przesądza zakresu jednego kliknięcia portowego; doprecyzować załadunek i rozładunek.
A9: Magazyn → budowa: 180 | B9: 180 | C9: 0 | D9: =ROUNDDOWN(60*(1+Parametry!$C$72*MAX(0,Parametry!$C$73-2)),0) -> 60 | E9: 1 | F9: =ROUNDUP(B9/D9,0) -> 3 | G9: =ROUNDUP(C9/D9,0) -> 0 | H9: =(F9+G9)*E9 -> 3 | I9: =H9*Parametry!$C$43 -> 30 | J9: =I9/Parametry!$C$41 -> 3 | K9: Cena zależy od potrzebnych kursów. Przykład 2 odcinków nie przesądza zakresu jednego kliknięcia portowego; doprecyzować załadunek i rozładunek.
A10: Magazyn → budowa: 181 | B10: 181 | C10: 0 | D10: =ROUNDDOWN(60*(1+Parametry!$C$72*MAX(0,Parametry!$C$73-2)),0) -> 60 | E10: 1 | F10: =ROUNDUP(B10/D10,0) -> 4 | G10: =ROUNDUP(C10/D10,0) -> 0 | H10: =(F10+G10)*E10 -> 4 | I10: =H10*Parametry!$C$43 -> 40 | J10: =I10/Parametry!$C$41 -> 4 | K10: Cena zależy od potrzebnych kursów. Przykład 2 odcinków nie przesądza zakresu jednego kliknięcia portowego; doprecyzować załadunek i rozładunek.
A11: Dwa rodzaje po 100 | B11: 100 | C11: 100 | D11: =ROUNDDOWN(60*(1+Parametry!$C$72*MAX(0,Parametry!$C$73-2)),0) -> 60 | E11: 1 | F11: =ROUNDUP(B11/D11,0) -> 2 | G11: =ROUNDUP(C11/D11,0) -> 2 | H11: =(F11+G11)*E11 -> 4 | I11: =H11*Parametry!$C$43 -> 40 | J11: =I11/Parametry!$C$41 -> 4 | K11: Cena zależy od potrzebnych kursów. Przykład 2 odcinków nie przesądza zakresu jednego kliknięcia portowego; doprecyzować załadunek i rozładunek.
A12: Magazyn → targ | B12: 200 | C12: 0 | D12: =ROUNDDOWN(60*(1+Parametry!$C$72*MAX(0,Parametry!$C$73-2)),0) -> 60 | E12: 1 | F12: =ROUNDUP(B12/D12,0) -> 4 | G12: =ROUNDUP(C12/D12,0) -> 0 | H12: =(F12+G12)*E12 -> 4 | I12: =H12*Parametry!$C$43 -> 40 | J12: =I12/Parametry!$C$41 -> 4 | K12: Cena zależy od potrzebnych kursów. Przykład 2 odcinków nie przesądza zakresu jednego kliknięcia portowego; doprecyzować załadunek i rozładunek.
A13: Targ → magazyn | B13: 200 | C13: 0 | D13: =ROUNDDOWN(60*(1+Parametry!$C$72*MAX(0,Parametry!$C$73-2)),0) -> 60 | E13: 1 | F13: =ROUNDUP(B13/D13,0) -> 4 | G13: =ROUNDUP(C13/D13,0) -> 0 | H13: =(F13+G13)*E13 -> 4 | I13: =H13*Parametry!$C$43 -> 40 | J13: =I13/Parametry!$C$41 -> 4 | K13: Cena zależy od potrzebnych kursów. Przykład 2 odcinków nie przesądza zakresu jednego kliknięcia portowego; doprecyzować załadunek i rozładunek.
A14: Magazyn → port | B14: 200 | C14: 0 | D14: =ROUNDDOWN(60*(1+Parametry!$C$72*MAX(0,Parametry!$C$73-2)),0) -> 60 | E14: 1 | F14: =ROUNDUP(B14/D14,0) -> 4 | G14: =ROUNDUP(C14/D14,0) -> 0 | H14: =(F14+G14)*E14 -> 4 | I14: =H14*Parametry!$C$43 -> 40 | J14: =I14/Parametry!$C$41 -> 4 | K14: Cena zależy od potrzebnych kursów. Przykład 2 odcinków nie przesądza zakresu jednego kliknięcia portowego; doprecyzować załadunek i rozładunek.
A15: Port → magazyn | B15: 200 | C15: 0 | D15: =ROUNDDOWN(60*(1+Parametry!$C$72*MAX(0,Parametry!$C$73-2)),0) -> 60 | E15: 1 | F15: =ROUNDUP(B15/D15,0) -> 4 | G15: =ROUNDUP(C15/D15,0) -> 0 | H15: =(F15+G15)*E15 -> 4 | I15: =H15*Parametry!$C$43 -> 40 | J15: =I15/Parametry!$C$41 -> 4 | K15: Cena zależy od potrzebnych kursów. Przykład 2 odcinków nie przesądza zakresu jednego kliknięcia portowego; doprecyzować załadunek i rozładunek.
A16: Dwa odcinki portowe — model | B16: 100 | C16: 0 | D16: =ROUNDDOWN(60*(1+Parametry!$C$72*MAX(0,Parametry!$C$73-2)),0) -> 60 | E16: 2 | F16: =ROUNDUP(B16/D16,0) -> 2 | G16: =ROUNDUP(C16/D16,0) -> 0 | H16: =(F16+G16)*E16 -> 4 | I16: =H16*Parametry!$C$43 -> 40 | J16: =I16/Parametry!$C$41 -> 4 | K16: Cena zależy od potrzebnych kursów. Przykład 2 odcinków nie przesądza zakresu jednego kliknięcia portowego; doprecyzować załadunek i rozładunek.
A17: Ładunek wyższego poziomu | B17: 200 | C17: 0 | D17: =ROUNDDOWN(66*(1+Parametry!$C$72*MAX(0,Parametry!$C$73-2)),0) -> 66 | E17: 1 | F17: =ROUNDUP(B17/D17,0) -> 4 | G17: =ROUNDUP(C17/D17,0) -> 0 | H17: =(F17+G17)*E17 -> 4 | I17: =H17*Parametry!$C$43 -> 40 | J17: =I17/Parametry!$C$41 -> 4 | K17: Cena zależy od potrzebnych kursów. Przykład 2 odcinków nie przesądza zakresu jednego kliknięcia portowego; doprecyzować załadunek i rozładunek.
A18: Brak towaru | B18: 0 | C18: 0 | D18: =ROUNDDOWN(60*(1+Parametry!$C$72*MAX(0,Parametry!$C$73-2)),0) -> 60 | E18: 1 | F18: =ROUNDUP(B18/D18,0) -> 0 | G18: =ROUNDUP(C18/D18,0) -> 0 | H18: =(F18+G18)*E18 -> 0 | I18: =H18*Parametry!$C$43 -> 0 | J18: =I18/Parametry!$C$41 -> 0 | K18: Cena zależy od potrzebnych kursów. Przykład 2 odcinków nie przesądza zakresu jednego kliknięcia portowego; doprecyzować załadunek i rozładunek.

Sheet Premium - budynek
A1: PEŁNY ZAKUP • gotowe w 10 sekund
A2: Pełny zakup budynku od poziomu gracza 4: wszystkie materiały według proporcjonalnych bazowych cen zakupu portu ×1,25 + nominalne monety budynku + natychmiastowy transport (10 monet za każdy potrzebny kurs, także niepełny). Nic nie pobieramy z własnych materiałów. Gotowe po 10 s; bez wymogu rzeczywistych tragarzy. Końcową cenę usługi prezentujemy w pełnych monetach, zaokrąglając w górę tak jak w zatwierdzonym kalkulatorze. Kolumny I/O są wyłącznie odrzuconym porównaniem paczek po 100. Ładunek wyceny uwzględnia aktualny parametr ścieżek, ale budynek nadal jest gotowy po10s.
A5: Przykład | B5: Monety w koszcie | C5: Drewno | D5: Kamień | E5: Zboże | F5: Food | G5: Deski | H5: Port: wycena proporcjonalna — aktualna | I5: Paczki 100 — wariant odrzucony | J5: Materiały +25% — zatwierdzone | K5: Poziom magazynu | L5: Ładunek na kurs | M5: Natychmiastowy transport [monety] | N5: Pełny zakup — cena aktualna | O5: Odrzucone paczki 100 — porównanie | P5: PLN — aktualna wycena | Q5: Uwagi | R5: Kursy materiałów razem | S5: Gotowe po [s] | T5: Wpis źródłowy — historia
A6: 100 drewna +100 Food | B6: 0 | C6: 100 | D6: 0 | E6: 0 | F6: 100 | G6: 0 | H6: =(C6+D6+E6)*Parametry!$C$32/100+(F6+G6)*Parametry!$C$34/100 -> 200 | I6: =(ROUNDUP(C6/100,0)+ROUNDUP(D6/100,0)+ROUNDUP(E6/100,0))*Parametry!$C$32+(ROUNDUP(F6/100,0)+ROUNDUP(G6/100,0))*Parametry!$C$34 -> 200 | J6: =H6*Parametry!$C$44 -> 250 | K6: 1 | L6: =ROUNDDOWN(ROUNDDOWN(Parametry!$C$9*Parametry!$C$10^(K6-1),0)*(1+Parametry!$C$72*MAX(0,Parametry!$C$73-2)),0) -> 60 | M6: =R6*Parametry!$C$43 -> 40 | N6: =ROUNDUP(B6+J6+M6,0) -> 290 | O6: =ROUNDUP(B6+I6*Parametry!$C$44+M6,0) -> 290 | P6: =N6/Parametry!$C$41 -> 29 | Q6: Pełne materiały, żadnego pobrania własnych zasobów. Osobno nominalne monety i transport. Brak dopłaty za minuty; gotowe po 10 s. Poziom 1 magazynu to parametr wyceny, nie poziom odblokowania usługi (ta od Ratusza 4). | R6: =ROUNDUP(C6/L6,0)+ROUNDUP(D6/L6,0)+ROUNDUP(E6/L6,0)+ROUNDUP(F6/L6,0)+ROUNDUP(G6/L6,0) -> 4 | S6: =Parametry!$C$56 -> 10 | T6: tak jest dobrze
A7: Farma 1→2 | B7: 0 | C7: 72 | D7: 72 | E7: 120 | F7: 0 | G7: 0 | H7: =(C7+D7+E7)*Parametry!$C$32/100+(F7+G7)*Parametry!$C$34/100 -> 132 | I7: =(ROUNDUP(C7/100,0)+ROUNDUP(D7/100,0)+ROUNDUP(E7/100,0))*Parametry!$C$32+(ROUNDUP(F7/100,0)+ROUNDUP(G7/100,0))*Parametry!$C$34 -> 200 | J7: =H7*Parametry!$C$44 -> 165 | K7: 1 | L7: =ROUNDDOWN(ROUNDDOWN(Parametry!$C$9*Parametry!$C$10^(K7-1),0)*(1+Parametry!$C$72*MAX(0,Parametry!$C$73-2)),0) -> 60 | M7: =R7*Parametry!$C$43 -> 60 | N7: =ROUNDUP(B7+J7+M7,0) -> 225 | O7: =ROUNDUP(B7+I7*Parametry!$C$44+M7,0) -> 310 | P7: =N7/Parametry!$C$41 -> 22.5 | Q7: Pełne materiały, żadnego pobrania własnych zasobów. Osobno nominalne monety i transport. Brak dopłaty za minuty; gotowe po 10 s. Poziom 1 magazynu to parametr wyceny, nie poziom odblokowania usługi (ta od Ratusza 4). | R7: =ROUNDUP(C7/L7,0)+ROUNDUP(D7/L7,0)+ROUNDUP(E7/L7,0)+ROUNDUP(F7/L7,0)+ROUNDUP(G7/L7,0) -> 6 | S7: =Parametry!$C$56 -> 10
A8: Ratusz 1→2 | B8: 500 | C8: 500 | D8: 500 | E8: 500 | F8: 500 | G8: 500 | H8: =(C8+D8+E8)*Parametry!$C$32/100+(F8+G8)*Parametry!$C$34/100 -> 2250 | I8: =(ROUNDUP(C8/100,0)+ROUNDUP(D8/100,0)+ROUNDUP(E8/100,0))*Parametry!$C$32+(ROUNDUP(F8/100,0)+ROUNDUP(G8/100,0))*Parametry!$C$34 -> 2250 | J8: =H8*Parametry!$C$44 -> 2812.5 | K8: 1 | L8: =ROUNDDOWN(ROUNDDOWN(Parametry!$C$9*Parametry!$C$10^(K8-1),0)*(1+Parametry!$C$72*MAX(0,Parametry!$C$73-2)),0) -> 60 | M8: =R8*Parametry!$C$43 -> 450 | N8: =ROUNDUP(B8+J8+M8,0) -> 3763 | O8: =ROUNDUP(B8+I8*Parametry!$C$44+M8,0) -> 3763 | P8: =N8/Parametry!$C$41 -> 376.3 | Q8: Pełne materiały, żadnego pobrania własnych zasobów. Osobno nominalne monety i transport. Brak dopłaty za minuty; gotowe po 10 s. Poziom 1 magazynu to parametr wyceny, nie poziom odblokowania usługi (ta od Ratusza 4). | R8: =ROUNDUP(C8/L8,0)+ROUNDUP(D8/L8,0)+ROUNDUP(E8/L8,0)+ROUNDUP(F8/L8,0)+ROUNDUP(G8/L8,0) -> 45 | S8: =Parametry!$C$56 -> 10

Sheet Social i polecenia
A1: NAGRODY SPOŁECZNOŚCIOWE • kwoty i warunki
A2: Kwoty zapisane według użytkownika. Limity, potwierdzanie publikacji i nakładanie nagród nie są zdefiniowane. Przeliczenie na PLN pokazuje cenę zakupu takiej liczby monet, nie możliwość ich wypłaty. Platformy mają osobną zakładkę.
A5: Akcja | B5: Nagroda | C5: Warunek | D5: Otwarte szczegóły | E5: Wartość zakupu monet [PLN]
A6: Pochwalenie się, że gram | B6: 1000 | C6: Publikacja informująca o grze. | D6: Nie ustalono kanałów, limitu na konto, powtórzeń ani sposobu potwierdzania publikacji. | E6: =B6/Parametry!$C$41 -> 100
A7: Informacja o następnym poziomie | B7: 500 | C7: Publikacja po rzeczywistym osiągnięciu kolejnego poziomu ratusza. | D7: Jedna nagroda na osiągnięty poziom jest propozycją; zasady wielu platform i usuwania postów są nieustalone. | E7: =B7/Parametry!$C$41 -> 50
A8: Polecenie: nowe logowanie | B8: 1000 | C8: Polecona osoba rzeczywiście się zaloguje. | D8: Nie określono, czy nagrodę dostaje tylko polecający czy także polecony; źródłowo roboczo zapisano nagrodę polecającego. Kryterium nowego konta i limit poleceń nieustalone. | E8: =B8/Parametry!$C$41 -> 100
A9: Polecenie: trzeci aktywny dzień | B9: 500 każdego zasobu | C9: Polecona osoba jest aktywna w trzecim dniu. | D9: Do ustalenia: trzeci dzień od rejestracji czy trzy dni aktywności, minimalna aktywność, odbiorca premii, czy „każdy zasób” obejmuje monety oraz jak przyjąć materiały przy pełnej centrali. | E9: Zależne od zakresu „wszystkiego”
A10: Każdy trzeci post na Facebooku | B10: 1000 | C10: Nagroda za trzeci, szósty, dziewiąty itd. kwalifikowany post. | D10: Nie określono okresu, limitu, wymagań treści ani tego, czy posty „gram” i „kolejny poziom” liczą się do tej samej serii. Zgodność konkretnej akcji z regulaminem platformy wymaga weryfikacji. | E10: =B10/Parametry!$C$41 -> 100
A11: Ukończenie zadania: Share on Facebook | B11: 500 | C11: Kliknięcie opcjonalnego Share po rzeczywistym ukończeniu zadania; jeden raz na ID ukończonego zadania. | D11: Bez integracjiFB. Skip nie odbiera nagrody. To osobna akcja od pozostałych kwot w tej tabeli. | E11: =Parametry!$C$81/Parametry!$C$41 -> 50

Sheet Platformy
A1: PLATFORMY • kandydaci do publikacji graczy
A2: Lista serwisów podobnych lub uzupełniających Facebooka. Nie potwierdzono aktualnego brzmienia ich zasad: dostęp do próbowanych oficjalnych źródeł blokowało HTTP 403. Adresy służą do późniejszej weryfikacji programu nagród, nie stanowią potwierdzenia jego dopuszczalności.
A5: Platforma | B5: Pasujący format | C5: Zastosowanie | D5: Istotna zasada / kwestia do sprawdzenia | E5: Oficjalne adresy | F5: Status źródła | G5: Uwagi o nagrodach
A6: Facebook | B6: Post, informacja o poziomie, polecenie z linkiem. | C6: Nie dopisujemy automatycznych masowych publikacji ani publikacji do cudzych grup. | D6: Reguły promocji Facebooka znane z dotychczasowej dokumentacji ograniczają użycie prywatnych osi czasu i znajomych do udziału w promocjach, np. „udostępnij, aby dostać nagrodę”. Wymaga sprawdzenia aktualnych warunków przed wdrożeniem nagrody za post. | E6: https://www.facebook.com/policies_center/pages_groups_events | F6: Aktualne warunki niepotwierdzone online. Dostęp do próbowanych źródeł blokowało HTTP 403; nie wszystkie adresy odpytywano oddzielnie. | G6: Kwoty 1000 / 500 / 1000 za każdy 3. post są propozycją ekonomii gry; wykonalność programu promocyjnego nie została potwierdzona.
A7: Instagram | B7: Grafika wyspy, post, relacja lub krótki film Reels. | C7: Kandydat do ręcznego udostępnienia przez gracza. | D7: Sprawdzić wytyczne promocji, prawidłowe oznaczanie i zasady przeciw sztucznemu pozyskiwaniu aktywności. Nie zakładać, że polubienia lub obserwacje mogą być obowiązkowym warunkiem. | E7: https://help.instagram.com/179379842258600 | F7: Aktualne warunki niepotwierdzone online. Dostęp do próbowanych źródeł blokowało HTTP 403; nie wszystkie adresy odpytywano oddzielnie. | G7: Nagrody dla tej platformy i sposób weryfikacji do ustalenia.
A8: Threads | B8: Krótki wpis i zrzut wyspy; link polecający. | C8: Kandydat do dobrowolnej publikacji. | D8: Obowiązują zasady Meta przeciw spamowi; sprawdzić aktualną możliwość i zasady nagradzania publikacji. | E8: https://transparency.meta.com/policies/community-standards/spam/ | F8: Aktualne warunki niepotwierdzone online. Dostęp do próbowanych źródeł blokowało HTTP 403; nie wszystkie adresy odpytywano oddzielnie. | G8: Nagrody nie zostały automatycznie skopiowane z Facebooka.
A9: TikTok | B9: Krótki film z wyspą, budową albo ekspedycją. | C9: Kandydat do treści tworzonych przez graczy. | D9: Wytyczne integralności i autentyczności obejmują sztuczną aktywność. Zasady nagradzanych filmów oraz oznaczania zachęt wymagają weryfikacji. | E9: https://www.tiktok.com/community-guidelines/en/integrity-authenticity/ | F9: Aktualne warunki niepotwierdzone online. Dostęp do próbowanych źródeł blokowało HTTP 403; nie wszystkie adresy odpytywano oddzielnie. | G9: Nie uzależniać nagrody od liczby sztucznych wyświetleń, komentarzy czy obserwujących.
A10: YouTube / Shorts | B10: Krótki film lub dłuższy pokaz gry. | C10: Kandydat do materiałów graczy. | D10: YouTube ma odrębne zasady fake engagement oraz konkursów. Wynagradzanie za manipulowanie wyświetleniami, polubieniami lub innymi wskaźnikami jest ryzykowne; sprawdzić aktualne warunki konkretnego programu. | E10: https://support.google.com/youtube/answer/3399767?hl=en https://support.google.com/youtube/answer/1620498?hl=en | F10: Aktualne warunki niepotwierdzone online. Dostęp do próbowanych źródeł blokowało HTTP 403; nie wszystkie adresy odpytywano oddzielnie. | G10: Treść i dobrowolne polecenie odróżnić od kupowania aktywności.
A11: Discord | B11: Własny serwer gry i kanał do pokazywania wysp. | C11: Dobry kandydat do społeczności gry. | D11: Zasady Discorda zabraniają spamu i manipulowania platformą. Publikacja tylko w przeznaczonych do tego kanałach oraz zgodnie z zasadami konkretnego serwera. | E11: https://discord.com/guidelines | F11: Aktualne warunki niepotwierdzone online. Dostęp do próbowanych źródeł blokowało HTTP 403; nie wszystkie adresy odpytywano oddzielnie. | G11: Bez masowych wiadomości prywatnych lub botów rozsyłających polecenia.
A12: Reddit | B12: Wpisy o postępach gry, grafice i dziennik rozwoju. | C12: Kandydat warunkowy: właściwy subreddit i zgoda moderatorów. | D12: Reddit i poszczególne subreddity mają zasady dotyczące spamu, autopromocji oraz manipulacji głosami. Nagroda za powielane wpisy promocyjne wymaga szczególnej weryfikacji. | E12: https://support.reddithelp.com/hc/en-us/articles/360043504051-Spam | F12: Aktualne warunki niepotwierdzone online. Dostęp do próbowanych źródeł blokowało HTTP 403; nie wszystkie adresy odpytywano oddzielnie. | G12: Nie zakładać prawa do reklamowania gry w dowolnej społeczności.
A13: X | B13: Krótki post, obraz wyspy i link polecający. | C13: Kandydat do dobrowolnego udostępniania. | D13: Sprawdzić zasady promocji i manipulacji platformą; powtarzane identyczne wpisy oraz zduplikowane konta nie powinny generować nagród. | E13: https://help.x.com/en/rules-and-policies/platform-manipulation https://help.x.com/en/rules-and-policies/x-contest-rules | F13: Aktualne warunki niepotwierdzone online. Dostęp do próbowanych źródeł blokowało HTTP 403; nie wszystkie adresy odpytywano oddzielnie. | G13: Próg i ewentualny limit nagrody do ustalenia.
A14: Bluesky | B14: Post z obrazem wyspy i linkiem. | C14: Kandydat do dobrowolnego udostępniania. | D14: Wytyczne społeczności obejmują spam i zakłócanie działania. Sprawdzić zasady promocji przed uruchomieniem programu nagród. | E14: https://bsky.social/about/support/community-guidelines | F14: Aktualne warunki niepotwierdzone online. Dostęp do próbowanych źródeł blokowało HTTP 403; nie wszystkie adresy odpytywano oddzielnie. | G14: Nie zakładać automatycznej weryfikacji publikacji bez osobnego projektu.
A15: Mastodon | B15: Post z wyspą na wybranym serwerze. | C15: Kandydat warunkowy: reguły wybranego serwera. | D15: Mastodon jest siecią wielu serwerów. Zasady reklamy, promocji i spamu zależą od instancji; nie ma jednego zezwolenia obejmującego całą sieć. | E15: https://joinmastodon.org/ https://joinmastodon.org/covenant | F15: Aktualne warunki niepotwierdzone online. Dostęp do próbowanych źródeł blokowało HTTP 403; nie wszystkie adresy odpytywano oddzielnie. | G15: Nagrody i dopuszczalne serwery do ustalenia.
A16: Snapchat | B16: Dobrowolna relacja lub krótki film o grze. | C16: Kandydat do wizualnej prezentacji postępu. | D16: Sprawdzić wytyczne społeczności, zasady promocji i treści sponsorowanych; nie zakładać, że masowe rozsyłanie zaproszeń będzie dozwolone. | E16: https://values.snap.com/policy/policy-community-guidelines | F16: Aktualne warunki niepotwierdzone online. Dostęp do próbowanych źródeł blokowało HTTP 403; nie wszystkie adresy odpytywano oddzielnie. | G16: Kwoty oraz sposób weryfikacji relacji do ustalenia.

Sheet Zadania latarni
A1: ZADANIA LATARNI V8 • jedno aktywne, postęp i celebracja
A2: Wymagania według własnego poziomu producenta; nagrody skalowane względem Ratusza 3. Trzy zadania pozostają niezależne. Oryginalne dopiski w G zachowano historycznie; poniżej aktualne rozstrzygnięcia.
A5: Obszar | B5: Status | C5: Zasada | D5: Wzór / liczby | E5: Uwagi | G5: Twoje wpisy źródłowe — historia
A6: Panel | B6: POTWIERDZONE V7 | C6: Zawsze 3 zadania. Początkowo małe/średnie/duże; kolejne losowego rozmiaru trafiają na koniec FIFO, dopuszczalne 3 małe lub 3 duże. Nowe po sukcesie natychmiast. Jednocześnie wykonywane tylko1; pozostałe oferty wyszarzone. | D6: 3 miejsca; start S/M/L, potem dowolne rozmiary FIFO. | E6: Nagrody zawsze widoczne, koszty i nagrody zamrożone przy wygenerowaniu.
A7: Losowanie | B7: POTWIERDZONE V7 | C7: Koszty, wymagane produkty i nagrody losujemy przy pojawieniu się zadania. | D7: Małe: 2 produkty; średnie: 2–3; duże: 4 | E7: W przykładach losujemy różne rodzaje spośród drewna, kamienia, zboża, żywności i desek. Rodzaje nagród i koszty powinny być stałe przez życie zadania.
A8: Norma produkcyjna | B8: ROZSTRZYGNIĘTE V7 | C8: Koszt rodzaju i liczymy z maksymalnej obsady obecnego poziomu jego producenta, niezależnie od faktycznej obsady. | D8: R_i = 12 × L_i × p(L_i); p(1)=10, p(L≥2)=L+10; koszt_i = R_i × h | E8: Własny aktualny poziom KAŻDEGO producenta; bez chwilowych bonusów, głodu i faktycznej obsady. | G8: maksymalny teoretycznie możliwy wynikający z poziomu budynku
A9: Małe | B9: POTWIERDZONE V7 | C9: Wymagane są dwa produkty, w ilości odpowiadającej 2–6 h maksymalnej produkcji. | D9: 2 rodzaje; h∈[2,6] | E9: L1: 12 osób × 10 szt./h = 120 szt./h, więc 240–720 każdego rodzaju.
A10: Średnie | B10: POTWIERDZONE V7 | C10: Wymagane są dwa lub trzy produkty, w ilości odpowiadającej 3–8 h maksymalnej produkcji, nie mniej niż bieżące małe. | D10: 2–3 rodzaje; h∈[3,8] | E10: Przy generowaniu h_średnie ≥ największe h aktualnych małych (jeśli są). Istniejące zadania pozostają zamrożone.
A11: Duże | B11: POTWIERDZONE V7 | C11: Wymagane są cztery produkty, w ilości odpowiadającej 4–10 h maksymalnej produkcji, nie mniej niż bieżące średnie. | D11: 4 rodzaje; h∈[4,10] | E11: Przy generowaniu h_duże ≥ największe h aktualnych średnich (jeśli są). Nie jest to obietnica zebrania od zera w czasie zadania.
A12: Ramy losowania | B12: POTWIERDZONE V7 | C12: Trzy niezależne łańcuchy. Początkowy termin 6 h. Pierwsze ukończenie kotwiczy kolejne odnowienia do tej godziny następnego dnia (Europe/Warsaw). Wcześniejszy sukces natychmiast daje następcę z zachowaniem tej samej dobowej kotwicy; termin nie resetuje się do kolejnych 6 h. | D12: Pierwsze 6 h → po pierwszym sukcesie dzienna kotwica, osobna dla każdego z 3 łańcuchów. | E12: Przykład: ukończenie 13:12, następne 14:00 → kolejne od razu, termin nadal następnego dnia 13:12. Europe/Warsaw; dzień zmiany czasu może mieć 23/25 h. | G12: ustalenia zaczynasz z 3 zadaniami jak user skończy pierwsze to ustawiasz czas np 13:12 I zawsze o tej robisz zadanie, drugie zrobił o 17:19 etc etc
A13: Nagroda w monetach | B13: POTWIERDZONE V7 | C13: Stare zakresy stanowią bazę na poziomie ratusza 3: małe 100–200, średnie do 400, duże do 600 monet oraz 50–1000 każdego rodzaju towaru. Inne poziomy: współczynnik 12 × L × p(L) / 468; całe ilości w dół, minimum 1. Rodzajów nagrody: 1/2/3 dla małego/średniego/dużego. Mnożnik szybkiej reakcji dopiero od tej bazy. | D13: Skala = 12 × L_Ratusza × p(L_Ratusza) / 468. | E13: Zakresy bazowe odnoszą się do L3. Wśród WSZYSTKICH aktualnych ofert obowiązuje kolejność bazowych nagród monetowych: małe < średnie < duże. Już pokazanych nagród nie zmieniamy. Losujemy wyłącznie spośród rozmiarów, których aktualny skalowany zakres pozwala zachować tę kolejność. Po zmianie poziomu niektóre rozmiary mogą chwilowo nie pasować; nie obiecano jednakowych prawdopodobieństw rozmiarów. | G13: tak ale ta granica jest dyunamicznie wyznaczana że z aktualnie wylosowanych średnia nie może być niższa niż mała etc, wiec w najgorszym scanraiuszu mała 100, średnia 101, duża 102
A14: Nagroda towarowa | B14: POTWIERDZONE V7 | C14: Małe: 1 losowy rodzaj; średnie: 2 różne; duże: 3 różne. Każdy rodzaj bazowo 50–1000 na L3, skalowany i zamrożony przy pojawieniu. | D14: Na L3 przed ×2/×3: 50–1000 KAŻDEGO wybranego rodzaju. | E14: Nagroda najpierw wypełnia centralę do limitów; nadmiar czeka w buforze i automatycznie dosypuje się przy zużyciu lub rozbudowie, z powiadomieniem. Nic nie przepada z braku miejsca.
A15: Premia szybkiej reakcji | B15: POTWIERDZONE V7 | C15: Kliknięcie zadania w pierwszych 15 sekundach daje nagrodę ×3; później do 5 minut daje ×2; następnie ×1. | D15: Wiek przy pierwszym kliknięciu: <15 s → ×3; 15 s ≤ wiek <300 s → ×2; od 300 s → ×1. | E15: Potwierdzone: ×3 ma pierwszeństwo, nie mnoży się przez ×2. Mnożnik zapisuje pierwsze kliknięcie zadania.
A16: Utrwalenie premii | B16: POTWIERDZONE V7 | C16: Pierwsze kliknięcie konkretnego zadania zapisuje mnożnik aż do jego ukończenia; późniejszy upływ czasu nie zmniejsza zapisanego mnożnika. | D16: Nagroda końcowa = bazowa nagroda × utrwalony mnożnik | E16: Nagroda po pełnej wpłacie przed aktualnym terminem łańcucha. Samo kliknięcie nie daje nagrody; wpłaty po przedawnieniu przepadają.
A17: Termin | B17: POTWIERDZONE V7 | C17: Trzy niezależne łańcuchy. Początkowy termin 6 h. Pierwsze ukończenie kotwiczy kolejne odnowienia do tej godziny następnego dnia (Europe/Warsaw). Wcześniejszy sukces natychmiast daje następcę z zachowaniem tej samej dobowej kotwicy; termin nie resetuje się do kolejnych 6 h. | D17: Niezależny termin każdego łańcucha; po pierwszym sukcesie kotwica dobowa. | E17: Zegar działa offline; po powrocie nie dostaje się nowego okna ×3 za zadanie, które pojawiło się wcześniej offline.
A18: Zastępowanie zadań | B18: POTWIERDZONE V7 | C18: Zawsze 3 zadania. Początkowo małe/średnie/duże; kolejne losowego rozmiaru trafiają na koniec FIFO, dopuszczalne 3 małe lub 3 duże. Nowe po sukcesie natychmiast. | D18: Nowe zadanie na końcu kolejki, zachowuje ID łańcucha i jego kotwicę. | E18: Po wygaśnięciu łańcuch odnawia się przy kolejnej dobowej kotwicy; przed pierwszym sukcesem pozostaje cykl początkowych 6 h. | G18: tak zrób tak
A19: Porównanie rozmiarów po odnowieniu | B19: POTWIERDZONE V7 | C19: Nowy rozmiar losowy. Warunki godzinowe sprawdzamy przy generowaniu: średnie nie mniej godzin niż aktualne małe, duże nie mniej niż aktualne średnie. Nowe małe może wymagać WIĘCEJ GODZIN lub większej liczby materiałów niż stare średnie; ta możliwość NIE dotyczy nagrody monetowej. Starych wymagań i nagród nie przepisujemy. | D19: Koszty i nagrody istniejących zadań nie zmieniają się. | E19: FIFO nie zmienia etykiet. Możliwe 3 małe lub 3 duże. Globalna kolejność małe < średnie < duże dotyczy bazowych nagród MONETOWYCH, a warunki godzinowe sprawdzamy przy generowaniu. Jeśli skalowany zakres nagrody danego rozmiaru nie pasuje do istniejących ofert, losujemy inny możliwy rozmiar. | G19: tak akceptuje to
A20: Wpłaty | B20: POTWIERDZONE V7 | C20: Można wpłacać wymagane towary partiami. Towar trafia bezpośrednio z magazynu centralnego do zadania, bez tragarza. | D20: Każdy składnik ma licznik dostarczono/wymagane, np. 100/200 | E20: Wpłata nie jest pożyczką ani tymczasową rezerwacją: jest nieodwracalna. W przykładzie nie wpłacamy powyżej pozostałego wymagania.
A21: Przedawnienie | B21: POTWIERDZONE V7 | C21: Po upływie terminu niewykonane zadanie przepada wraz ze wszystkimi dotychczasowymi wpłatami. | D21: Zwrot wpłat = 0 | E21: Wymagane wyraźne ostrzeżenie i pokazanie czasu pozostałego przed potwierdzeniem wpłaty; powiadomienia to projekt interfejsu.
A22: Żywność na zadania | B22: POTWIERDZONE V7 | C22: Wpłaty i inne cele niż karmienie chronią Food = 50 × poziom magazynu. W zadaniach używamy tylko nadwyżki; ludzie mogą zjadać rezerwę. | D22: Food dostępne na wpłatę = MAX(0, Food w centrali − 50 × poziom magazynu). | E22: Rezerwa przeznaczona wyłącznie na karmienie. | G22: chronimy food, można wpłacić tylko to co jest ponad limit
A23: Nagroda i pojemność | B23: POTWIERDZONE V7 | C23: Nagroda najpierw wypełnia centralę do limitów; nadmiar czeka w buforze i automatycznie dosypuje się przy zużyciu lub rozbudowie, z powiadomieniem. Nic nie przepada z braku miejsca. | D23: Bufor nadmiaru nagród; automatyczne uzupełnianie i notyfikacja. | E23: Pieniądze trafiają do skarbca; limity materiałów nie dotyczą monet. | G23: uzupełniasz najpierw magazyn główny ewentualny nadmiar dosypujesz w miarę zużywania lub podonoszenia poziomu magazynu informujesz gracza notyfikacją
A24: Notyfikacje | B24: POTWIERDZONE V7 | C24: Powiadomienia o aktywacji i mnożniku, wpłacie, ukończeniu i wygaśnięciu. Ukończenie: popup z fajerwerkami, krótka wibracja telefonu i opcjonalny ekran Share your achievement. | D24: Zawsze widoczne: tytuł, rozmiar, nagroda, mnożnik, czas i postęp | E24: Nie dodajemy wymyślonego czasu przypomnienia ani automatycznych wpłat.
A25: Skalowanie | B25: ROZSTRZYGNIĘTE V7 D07 | C25: Stare zakresy stanowią bazę na poziomie ratusza 3: małe 100–200, średnie do 400, duże do 600 monet oraz 50–1000 każdego rodzaju towaru. Inne poziomy: współczynnik 12 × L × p(L) / 468; całe ilości w dół, minimum 1. Rodzajów nagrody: 1/2/3 dla małego/średniego/dużego. Mnożnik szybkiej reakcji dopiero od tej bazy. | D25: L1: 120/468; L2: 288/468; L3: 1; L4: 672/468. | E25: Skalowanie nie gwarantuje zwrotu portowej wartości wszystkich wpłat; jest zatwierdzonym wzorem nagród. | G25: podnieśmy tak samo nagrody niech sie opłaca proporcjonalnie do opłacalności np na 3 poziomie
A26: Produkcja maksymalna a realny czas | B26: UWAGA BALANSOWA | C26: Pełna załoga 12 × L w każdym z 2–4 zakładów nie może być założona jednocześnie przy jednej wspólnej populacji. | D26: L1: 12 osób na start, maks. 24; duże: 4 zakłady × 12 = 48 stanowisk | E26: Norma określa wymagania, nie realny czas zebrania przy wspólnej populacji. Zbierania, karmienia i wcześniejszych rozbudów nie doliczamy do tabeli czasu budowy. | G26: wyjasnione powyżej
A27: Aktywność | B27: POTWIERDZONE V8 | C27: Tylko jedno aktywne zadanie. Active i postęp każdego produktu w obu widokach; pozostałe oferty szare, bez startu/wpłaty. | D27: Wymagania i nagrody można nadal obejrzeć. | E27: Stare wpłaty, terminy i utrwalone mnożniki zachowane.
A28: Bonus udostępnienia | B28: POTWIERDZONE V8 | C28: Share on Facebook przyznaje500monet raz na ukończone zadanie; Skip zachowuje zwykłą nagrodę. | D28: Bez integracjiFacebook; kliknięcie prototypowego przycisku, nie potwierdzenie publikacji. | E28: Najnowsza odpowiedź użytkownika:500monet.

Sheet Zadania przyklady
A1: ZADANIA V7 • zamrożone przykłady po skalowaniu
A2: 12 przykładów S/M/L na poziomach 1–4; dla czytelności wszystkie własne poziomy producentów i Ratusza równe D. Nagrody bazują na L3: skala G/468. 1/2/3 rodzaje nagród. W towarach kolumny AA–AF pokazują dodatkowe rodzaje; mnożnik ×2/×3 obejmuje wszystkie. Kolumna W dotyczy wyłącznie pierwszego, 6-godzinnego terminu, nie dobowych następców.
A5: Zestaw | B5: Rozmiar | C5: Nazwa / narracja | D5: Poziom producentów | E5: Maks. ludzi/producent | F5: Szt./os./h | G5: Maks. szt./h | H5: Norma godzin/rodzaj | I5: Liczba rodzajów | J5: Drewno | K5: Kamień | L5: Zboże | M5: Food | N5: Deski | O5: Wpłaty: format | P5: Złoto bazowe | Q5: Towar nagrody | R5: Ilość bazowa | S5: Złoto ×2 | T5: Złoto ×3 | U5: Towar ×2 | V5: Towar ×3 | W5: Termin [h] | X5: Uwagi | Y5: Skala nagród względem L3 | Z5: Monety bazowe na L3 | AA5: Nagroda: drugi rodzaj | AB5: Drugi: baza na L3 | AC5: Drugi: ilość po skalowaniu | AD5: Nagroda: trzeci rodzaj | AE5: Trzeci: baza na L3 | AF5: Trzeci: ilość po skalowaniu | AG5: Pierwszy: baza na L3 | AH5: Liczba rodzajów nagrody
A6: 1 | B6: Małe | C6: Naprawa poręczy na schodach | D6: 1 | E6: =D6*12 -> 12 | F6: =IF(D6=1,10,D6+10) -> 10 | G6: =E6*F6 -> 120 | H6: 4 | I6: 2 | J6: =G6*H6 -> 480 | K6: =G6*H6 -> 480 | L6: 0 | M6: 0 | N6: 0 | O6: 0/480 drewno; 0/480 kamień | P6: =MAX(1,ROUNDDOWN(Z6*Y6,0)) -> 33 | Q6: kamień | R6: =MAX(1,ROUNDDOWN(AG6*Y6,0)) -> 13 | S6: =P6*2 -> 66 | T6: =P6*3 -> 99 | U6: =R6*2 -> 26 | V6: =R6*3 -> 39 | W6: =Parametry!$C$45 -> 6 | X6: Skala nagród z L3, bez chwilowej premii produkcji. Nagrody wszystkich rodzajów w R/AC/AF; ×2/×3 obejmuje każdą. Wymagania w J:N dotyczą własnych poziomów producentów, tu równych dla przykładu. Pierwszy termin 6 h; następcy według kotwicy dobowej. | Y6: =G6/468 -> 0.25641026 | Z6: 130 | AA6: — | AB6: 0 | AC6: =IF(AH6>=2,MAX(1,ROUNDDOWN(AB6*Y6,0)),0) -> 0 | AD6: — | AE6: 0 | AF6: =IF(AH6>=3,MAX(1,ROUNDDOWN(AE6*Y6,0)),0) -> 0 | AG6: 52 | AH6: 1
A7: 1 | B7: Średnie | C7: Remont barierek dla zwiedzających | D7: 1 | E7: =D7*12 -> 12 | F7: =IF(D7=1,10,D7+10) -> 10 | G7: =E7*F7 -> 120 | H7: 8 | I7: 2 | J7: 0 | K7: =G7*H7 -> 960 | L7: 0 | M7: 0 | N7: =G7*H7 -> 960 | O7: 0/960 deski; 0/960 kamień | P7: =MAX(1,ROUNDDOWN(Z7*Y7,0)) -> 51 | Q7: drewno | R7: =MAX(1,ROUNDDOWN(AG7*Y7,0)) -> 63 | S7: =P7*2 -> 102 | T7: =P7*3 -> 153 | U7: =R7*2 -> 126 | V7: =R7*3 -> 189 | W7: =Parametry!$C$45 -> 6 | X7: Skala nagród z L3, bez chwilowej premii produkcji. Nagrody wszystkich rodzajów w R/AC/AF; ×2/×3 obejmuje każdą. Wymagania w J:N dotyczą własnych poziomów producentów, tu równych dla przykładu. Pierwszy termin 6 h; następcy według kotwicy dobowej. | Y7: =G7/468 -> 0.25641026 | Z7: 201 | AA7: kamień | AB7: 499 | AC7: =IF(AH7>=2,MAX(1,ROUNDDOWN(AB7*Y7,0)),0) -> 127 | AD7: — | AE7: 0 | AF7: =IF(AH7>=3,MAX(1,ROUNDDOWN(AE7*Y7,0)),0) -> 0 | AG7: 248 | AH7: 2
A8: 1 | B8: Duże | C8: Generalny remont galerii widokowej | D8: 1 | E8: =D8*12 -> 12 | F8: =IF(D8=1,10,D8+10) -> 10 | G8: =E8*F8 -> 120 | H8: 9 | I8: 4 | J8: =G8*H8 -> 1080 | K8: 0 | L8: =G8*H8 -> 1080 | M8: =G8*H8 -> 1080 | N8: =G8*H8 -> 1080 | O8: 0/1080 zboże; 0/1080 drewno; 0/1080 deski; 0/1080 żywność | P8: =MAX(1,ROUNDDOWN(Z8*Y8,0)) -> 92 | Q8: kamień | R8: =MAX(1,ROUNDDOWN(AG8*Y8,0)) -> 43 | S8: =P8*2 -> 184 | T8: =P8*3 -> 276 | U8: =R8*2 -> 86 | V8: =R8*3 -> 129 | W8: =Parametry!$C$45 -> 6 | X8: Skala nagród z L3, bez chwilowej premii produkcji. Nagrody wszystkich rodzajów w R/AC/AF; ×2/×3 obejmuje każdą. Wymagania w J:N dotyczą własnych poziomów producentów, tu równych dla przykładu. Pierwszy termin 6 h; następcy według kotwicy dobowej. | Y8: =G8/468 -> 0.25641026 | Z8: 360 | AA8: drewno | AB8: 530 | AC8: =IF(AH8>=2,MAX(1,ROUNDDOWN(AB8*Y8,0)),0) -> 135 | AD8: zboże | AE8: 571 | AF8: =IF(AH8>=3,MAX(1,ROUNDDOWN(AE8*Y8,0)),0) -> 146 | AG8: 168 | AH8: 3
A9: 2 | B9: Małe | C9: Łatanie podestu wejściowego | D9: 2 | E9: =D9*12 -> 24 | F9: =IF(D9=1,10,D9+10) -> 12 | G9: =E9*F9 -> 288 | H9: 3 | I9: 2 | J9: =G9*H9 -> 864 | K9: 0 | L9: 0 | M9: 0 | N9: =G9*H9 -> 864 | O9: 0/864 deski; 0/864 drewno | P9: =MAX(1,ROUNDDOWN(Z9*Y9,0)) -> 72 | Q9: zboże | R9: =MAX(1,ROUNDDOWN(AG9*Y9,0)) -> 398 | S9: =P9*2 -> 144 | T9: =P9*3 -> 216 | U9: =R9*2 -> 796 | V9: =R9*3 -> 1194 | W9: =Parametry!$C$45 -> 6 | X9: Skala nagród z L3, bez chwilowej premii produkcji. Nagrody wszystkich rodzajów w R/AC/AF; ×2/×3 obejmuje każdą. Wymagania w J:N dotyczą własnych poziomów producentów, tu równych dla przykładu. Pierwszy termin 6 h; następcy według kotwicy dobowej. | Y9: =G9/468 -> 0.61538462 | Z9: 118 | AA9: — | AB9: 0 | AC9: =IF(AH9>=2,MAX(1,ROUNDDOWN(AB9*Y9,0)),0) -> 0 | AD9: — | AE9: 0 | AF9: =IF(AH9>=3,MAX(1,ROUNDDOWN(AE9*Y9,0)),0) -> 0 | AG9: 648 | AH9: 1
A10: 2 | B10: Średnie | C10: Wymiana osłon lampy | D10: 2 | E10: =D10*12 -> 24 | F10: =IF(D10=1,10,D10+10) -> 12 | G10: =E10*F10 -> 288 | H10: 7 | I10: 2 | J10: 0 | K10: 0 | L10: =G10*H10 -> 2016 | M10: =G10*H10 -> 2016 | N10: 0 | O10: 0/2016 zboże; 0/2016 żywność | P10: =MAX(1,ROUNDDOWN(Z10*Y10,0)) -> 80 | Q10: drewno | R10: =MAX(1,ROUNDDOWN(AG10*Y10,0)) -> 555 | S10: =P10*2 -> 160 | T10: =P10*3 -> 240 | U10: =R10*2 -> 1110 | V10: =R10*3 -> 1665 | W10: =Parametry!$C$45 -> 6 | X10: Skala nagród z L3, bez chwilowej premii produkcji. Nagrody wszystkich rodzajów w R/AC/AF; ×2/×3 obejmuje każdą. Wymagania w J:N dotyczą własnych poziomów producentów, tu równych dla przykładu. Pierwszy termin 6 h; następcy według kotwicy dobowej. | Y10: =G10/468 -> 0.61538462 | Z10: 131 | AA10: kamień | AB10: 592 | AC10: =IF(AH10>=2,MAX(1,ROUNDDOWN(AB10*Y10,0)),0) -> 364 | AD10: — | AE10: 0 | AF10: =IF(AH10>=3,MAX(1,ROUNDDOWN(AE10*Y10,0)),0) -> 0 | AG10: 903 | AH10: 2
A11: 2 | B11: Duże | C11: Odbudowa zaplecza latarników | D11: 2 | E11: =D11*12 -> 24 | F11: =IF(D11=1,10,D11+10) -> 12 | G11: =E11*F11 -> 288 | H11: 10 | I11: 4 | J11: =G11*H11 -> 2880 | K11: =G11*H11 -> 2880 | L11: 0 | M11: =G11*H11 -> 2880 | N11: =G11*H11 -> 2880 | O11: 0/2880 kamień; 0/2880 deski; 0/2880 żywność; 0/2880 drewno | P11: =MAX(1,ROUNDDOWN(Z11*Y11,0)) -> 238 | Q11: drewno | R11: =MAX(1,ROUNDDOWN(AG11*Y11,0)) -> 171 | S11: =P11*2 -> 476 | T11: =P11*3 -> 714 | U11: =R11*2 -> 342 | V11: =R11*3 -> 513 | W11: =Parametry!$C$45 -> 6 | X11: Skala nagród z L3, bez chwilowej premii produkcji. Nagrody wszystkich rodzajów w R/AC/AF; ×2/×3 obejmuje każdą. Wymagania w J:N dotyczą własnych poziomów producentów, tu równych dla przykładu. Pierwszy termin 6 h; następcy według kotwicy dobowej. | Y11: =G11/468 -> 0.61538462 | Z11: 388 | AA11: kamień | AB11: 623 | AC11: =IF(AH11>=2,MAX(1,ROUNDDOWN(AB11*Y11,0)),0) -> 383 | AD11: zboże | AE11: 664 | AF11: =IF(AH11>=3,MAX(1,ROUNDDOWN(AE11*Y11,0)),0) -> 408 | AG11: 279 | AH11: 3
A12: 3 | B12: Małe | C12: Zabezpieczenie ścieżki do latarni | D12: 3 | E12: =D12*12 -> 36 | F12: =IF(D12=1,10,D12+10) -> 13 | G12: =E12*F12 -> 468 | H12: 6 | I12: 2 | J12: 0 | K12: =G12*H12 -> 2808 | L12: 0 | M12: =G12*H12 -> 2808 | N12: 0 | O12: 0/2808 kamień; 0/2808 żywność | P12: =MAX(1,ROUNDDOWN(Z12*Y12,0)) -> 197 | Q12: deski | R12: =MAX(1,ROUNDDOWN(AG12*Y12,0)) -> 476 | S12: =P12*2 -> 394 | T12: =P12*3 -> 591 | U12: =R12*2 -> 952 | V12: =R12*3 -> 1428 | W12: =Parametry!$C$45 -> 6 | X12: Skala nagród z L3, bez chwilowej premii produkcji. Nagrody wszystkich rodzajów w R/AC/AF; ×2/×3 obejmuje każdą. Wymagania w J:N dotyczą własnych poziomów producentów, tu równych dla przykładu. Pierwszy termin 6 h; następcy według kotwicy dobowej. | Y12: =G12/468 -> 1 | Z12: 197 | AA12: — | AB12: 0 | AC12: =IF(AH12>=2,MAX(1,ROUNDDOWN(AB12*Y12,0)),0) -> 0 | AD12: — | AE12: 0 | AF12: =IF(AH12>=3,MAX(1,ROUNDDOWN(AE12*Y12,0)),0) -> 0 | AG12: 476 | AH12: 1
A13: 3 | B13: Średnie | C13: Naprawa schodów na galerię | D13: 3 | E13: =D13*12 -> 36 | F13: =IF(D13=1,10,D13+10) -> 13 | G13: =E13*F13 -> 468 | H13: 8 | I13: 2 | J13: =G13*H13 -> 3744 | K13: 0 | L13: 0 | M13: =G13*H13 -> 3744 | N13: 0 | O13: 0/3744 drewno; 0/3744 żywność | P13: =MAX(1,ROUNDDOWN(Z13*Y13,0)) -> 198 | Q13: żywność | R13: =MAX(1,ROUNDDOWN(AG13*Y13,0)) -> 179 | S13: =P13*2 -> 396 | T13: =P13*3 -> 594 | U13: =R13*2 -> 358 | V13: =R13*3 -> 537 | W13: =Parametry!$C$45 -> 6 | X13: Skala nagród z L3, bez chwilowej premii produkcji. Nagrody wszystkich rodzajów w R/AC/AF; ×2/×3 obejmuje każdą. Wymagania w J:N dotyczą własnych poziomów producentów, tu równych dla przykładu. Pierwszy termin 6 h; następcy według kotwicy dobowej. | Y13: =G13/468 -> 1 | Z13: 198 | AA13: drewno | AB13: 685 | AC13: =IF(AH13>=2,MAX(1,ROUNDDOWN(AB13*Y13,0)),0) -> 685 | AD13: — | AE13: 0 | AF13: =IF(AH13>=3,MAX(1,ROUNDDOWN(AE13*Y13,0)),0) -> 0 | AG13: 179 | AH13: 2
A14: 3 | B14: Duże | C14: Renowacja wieży po sztormie | D14: 3 | E14: =D14*12 -> 36 | F14: =IF(D14=1,10,D14+10) -> 13 | G14: =E14*F14 -> 468 | H14: 9 | I14: 4 | J14: =G14*H14 -> 4212 | K14: =G14*H14 -> 4212 | L14: =G14*H14 -> 4212 | M14: =G14*H14 -> 4212 | N14: 0 | O14: 0/4212 żywność; 0/4212 kamień; 0/4212 drewno; 0/4212 zboże | P14: =MAX(1,ROUNDDOWN(Z14*Y14,0)) -> 199 | Q14: zboże | R14: =MAX(1,ROUNDDOWN(AG14*Y14,0)) -> 354 | S14: =P14*2 -> 398 | T14: =P14*3 -> 597 | U14: =R14*2 -> 708 | V14: =R14*3 -> 1062 | W14: =Parametry!$C$45 -> 6 | X14: Skala nagród z L3, bez chwilowej premii produkcji. Nagrody wszystkich rodzajów w R/AC/AF; ×2/×3 obejmuje każdą. Wymagania w J:N dotyczą własnych poziomów producentów, tu równych dla przykładu. Pierwszy termin 6 h; następcy według kotwicy dobowej. | Y14: =G14/468 -> 1 | Z14: 199 | AA14: drewno | AB14: 716 | AC14: =IF(AH14>=2,MAX(1,ROUNDDOWN(AB14*Y14,0)),0) -> 716 | AD14: kamień | AE14: 757 | AF14: =IF(AH14>=3,MAX(1,ROUNDDOWN(AE14*Y14,0)),0) -> 757 | AG14: 354 | AH14: 3
A15: 4 | B15: Małe | C15: Zaopatrzenie ekipy przeglądowej | D15: 4 | E15: =D15*12 -> 48 | F15: =IF(D15=1,10,D15+10) -> 14 | G15: =E15*F15 -> 672 | H15: 6 | I15: 2 | J15: =G15*H15 -> 4032 | K15: 0 | L15: 0 | M15: =G15*H15 -> 4032 | N15: 0 | O15: 0/4032 drewno; 0/4032 żywność | P15: =MAX(1,ROUNDDOWN(Z15*Y15,0)) -> 246 | Q15: kamień | R15: =MAX(1,ROUNDDOWN(AG15*Y15,0)) -> 786 | S15: =P15*2 -> 492 | T15: =P15*3 -> 738 | U15: =R15*2 -> 1572 | V15: =R15*3 -> 2358 | W15: =Parametry!$C$45 -> 6 | X15: Skala nagród z L3, bez chwilowej premii produkcji. Nagrody wszystkich rodzajów w R/AC/AF; ×2/×3 obejmuje każdą. Wymagania w J:N dotyczą własnych poziomów producentów, tu równych dla przykładu. Pierwszy termin 6 h; następcy według kotwicy dobowej. | Y15: =G15/468 -> 1.4358974 | Z15: 172 | AA15: — | AB15: 0 | AC15: =IF(AH15>=2,MAX(1,ROUNDDOWN(AB15*Y15,0)),0) -> 0 | AD15: — | AE15: 0 | AF15: =IF(AH15>=3,MAX(1,ROUNDDOWN(AE15*Y15,0)),0) -> 0 | AG15: 548 | AH15: 1
A16: 4 | B16: Średnie | C16: Odtworzenie pomostu widokowego | D16: 4 | E16: =D16*12 -> 48 | F16: =IF(D16=1,10,D16+10) -> 14 | G16: =E16*F16 -> 672 | H16: 6 | I16: 2 | J16: =G16*H16 -> 4032 | K16: 0 | L16: 0 | M16: =G16*H16 -> 4032 | N16: 0 | O16: 0/4032 żywność; 0/4032 drewno | P16: =MAX(1,ROUNDDOWN(Z16*Y16,0)) -> 248 | Q16: deski | R16: =MAX(1,ROUNDDOWN(AG16*Y16,0)) -> 608 | S16: =P16*2 -> 496 | T16: =P16*3 -> 744 | U16: =R16*2 -> 1216 | V16: =R16*3 -> 1824 | W16: =Parametry!$C$45 -> 6 | X16: Skala nagród z L3, bez chwilowej premii produkcji. Nagrody wszystkich rodzajów w R/AC/AF; ×2/×3 obejmuje każdą. Wymagania w J:N dotyczą własnych poziomów producentów, tu równych dla przykładu. Pierwszy termin 6 h; następcy według kotwicy dobowej. | Y16: =G16/468 -> 1.4358974 | Z16: 173 | AA16: drewno | AB16: 778 | AC16: =IF(AH16>=2,MAX(1,ROUNDDOWN(AB16*Y16,0)),0) -> 1117 | AD16: — | AE16: 0 | AF16: =IF(AH16>=3,MAX(1,ROUNDDOWN(AE16*Y16,0)),0) -> 0 | AG16: 424 | AH16: 2
A17: 4 | B17: Duże | C17: Przygotowanie latarni do sezonu | D17: 4 | E17: =D17*12 -> 48 | F17: =IF(D17=1,10,D17+10) -> 14 | G17: =E17*F17 -> 672 | H17: 6 | I17: 4 | J17: =G17*H17 -> 4032 | K17: =G17*H17 -> 4032 | L17: 0 | M17: =G17*H17 -> 4032 | N17: =G17*H17 -> 4032 | O17: 0/4032 drewno; 0/4032 żywność; 0/4032 deski; 0/4032 kamień | P17: =MAX(1,ROUNDDOWN(Z17*Y17,0)) -> 317 | Q17: drewno | R17: =MAX(1,ROUNDDOWN(AG17*Y17,0)) -> 1372 | S17: =P17*2 -> 634 | T17: =P17*3 -> 951 | U17: =R17*2 -> 2744 | V17: =R17*3 -> 4116 | W17: =Parametry!$C$45 -> 6 | X17: Skala nagród z L3, bez chwilowej premii produkcji. Nagrody wszystkich rodzajów w R/AC/AF; ×2/×3 obejmuje każdą. Wymagania w J:N dotyczą własnych poziomów producentów, tu równych dla przykładu. Pierwszy termin 6 h; następcy według kotwicy dobowej. | Y17: =G17/468 -> 1.4358974 | Z17: 221 | AA17: kamień | AB17: 809 | AC17: =IF(AH17>=2,MAX(1,ROUNDDOWN(AB17*Y17,0)),0) -> 1161 | AD17: zboże | AE17: 850 | AF17: =IF(AH17>=3,MAX(1,ROUNDDOWN(AE17*Y17,0)),0) -> 1220 | AG17: 956 | AH17: 3
C19: dopisz zadania musi być ich ze 100

Sheet Zadania - zegary
A1: LATARNIA • niezależne zegary i raty
A2: Przykłady pierwszego 6-godzinnego terminu, kliknięcia i nieodwracalnych rat. Po pierwszym sukcesie każdy łańcuch przechodzi na dobową kotwicę. Mnożnik utrwala pierwsze kliknięcie: <15 s ×3; 15–<300 s ×2; od300 s ×1. Nie jest resetowany po wczytaniu zapisu.
A5: Przykład | B5: Wiek przy pierwszym kliknięciu [s] | C5: Pozostało w chwili kliknięcia [min] | D5: Utrwalony mnożnik | E5: Wymagane | F5: Wpłacono | G5: Brakuje | H5: Następna rata | I5: Stan po racie | J5: Zwrot po terminie | K5: Uwagi
A6: Małe — szybkie przyjęcie | B6: 10 | C6: =MAX(0,(Parametry!$C$45*3600-B6)/60) -> 359.83333 | D6: =IF(B6<15,3,IF(B6<300,2,1)) -> 3 | E6: 200 | F6: 100 | G6: =MAX(0,E6-F6) -> 100 | H6: 50 | I6: =IF(C6>0,MIN(E6,F6+H6),0) -> 150 | J6: 0 | K6: Rata pobierana z centrali bez transportu; po terminie wpłaty przepadają. Zerowy stan po przedawnieniu oznacza utratę wpłat, nie wypłatę graczowi.
A7: Średnie — szybkie przyjęcie | B7: 120 | C7: =MAX(0,(Parametry!$C$45*3600-B7)/60) -> 358 | D7: =IF(B7<15,3,IF(B7<300,2,1)) -> 2 | E7: 400 | F7: 100 | G7: =MAX(0,E7-F7) -> 300 | H7: 300 | I7: =IF(C7>0,MIN(E7,F7+H7),0) -> 400 | J7: 0 | K7: Rata pobierana z centrali bez transportu; po terminie wpłaty przepadają. Zerowy stan po przedawnieniu oznacza utratę wpłat, nie wypłatę graczowi.
A8: Duże — zwykłe przyjęcie | B8: 1800 | C8: =MAX(0,(Parametry!$C$45*3600-B8)/60) -> 330 | D8: =IF(B8<15,3,IF(B8<300,2,1)) -> 1 | E8: 1200 | F8: 600 | G8: =MAX(0,E8-F8) -> 600 | H8: 100 | I8: =IF(C8>0,MIN(E8,F8+H8),0) -> 700 | J8: 0 | K8: Rata pobierana z centrali bez transportu; po terminie wpłaty przepadają. Zerowy stan po przedawnieniu oznacza utratę wpłat, nie wypłatę graczowi.
A9: Granica 15 sekund | B9: 15 | C9: =MAX(0,(Parametry!$C$45*3600-B9)/60) -> 359.75 | D9: =IF(B9<15,3,IF(B9<300,2,1)) -> 2 | E9: 200 | F9: 0 | G9: =MAX(0,E9-F9) -> 200 | H9: 0 | I9: =IF(C9>0,MIN(E9,F9+H9),0) -> 0 | J9: 0 | K9: Rata pobierana z centrali bez transportu; po terminie wpłaty przepadają. Zerowy stan po przedawnieniu oznacza utratę wpłat, nie wypłatę graczowi.
A10: Granica 5 minut | B10: 300 | C10: =MAX(0,(Parametry!$C$45*3600-B10)/60) -> 355 | D10: =IF(B10<15,3,IF(B10<300,2,1)) -> 1 | E10: 200 | F10: 0 | G10: =MAX(0,E10-F10) -> 200 | H10: 0 | I10: =IF(C10>0,MIN(E10,F10+H10),0) -> 0 | J10: 0 | K10: Rata pobierana z centrali bez transportu; po terminie wpłaty przepadają. Zerowy stan po przedawnieniu oznacza utratę wpłat, nie wypłatę graczowi.
A11: Zadanie przedawnione | B11: 21600 | C11: =MAX(0,(Parametry!$C$45*3600-B11)/60) -> 0 | D11: =IF(B11<15,3,IF(B11<300,2,1)) -> 1 | E11: 200 | F11: 100 | G11: =MAX(0,E11-F11) -> 100 | H11: 0 | I11: =IF(C11>0,MIN(E11,F11+H11),0) -> 0 | J11: 0 | K11: Rata pobierana z centrali bez transportu; po terminie wpłaty przepadają. Zerowy stan po przedawnieniu oznacza utratę wpłat, nie wypłatę graczowi.
A13: Przykłady dobowych kotwic
A14: Łańcuch A: pierwszy sukces | B14: 23.10 13:12 | C14: 24.10 13:12 | D14: Następca natychmiast; kotwica dzienna.
A15: A: kolejny sukces tego samego dnia | B15: 23.10 14:00 | C15: 24.10 13:12 | D15: Nowe zadanie natychmiast; deadline pozostaje.
A16: Łańcuch B: niezależny sukces | B16: 23.10 17:19 | C16: 24.10 17:19 | D16: Nie resetuje łańcucha A.
A17: A: wygaśnięcie | B17: 24.10 13:12 | C17: 25.10 13:12 | D17: Utrata wpłat, następca z nowym terminem dobowym.
A18: Zmiana czasu zimowego | B18: 24.10 13:12 | C18: 25.10 13:12 | D18: 25 godzin rzeczywistych, ta sama godzina Europe/Warsaw.

Sheet Ekspedycje
A1: EKSPEDYCJE • przebieg i nagrody
A2: Panel poniżej zadań po prawej. Nagrody wyłącznie w monetach. Plansze, sterowanie, trudność, koszty dodatkowego czasu/ruchów i zasady jednosekundowego kodu pozostają do późniejszego opisania.
A5: Obszar | B5: Zasada | C5: Uwagi | D5: Status
A6: Umiejscowienie | B6: Po prawej stronie, pod bieżącymi zadaniami latarni. | C6: Zawsze dostępnych kilka ekspedycji. Konkretna liczba i rotacja nieustalone. | D6: POTWIERDZONE; LICZBA OTWARTA
A7: Rodzaje gry | B7: Plansza z labiryntem i piłeczką do przeprowadzenia do środka albo dobieranie takich samych puzzli. | C7: Dokładne sterowanie, plansze i zasady użytkownik opisze później. | D7: POTWIERDZONE; SZCZEGÓŁY PÓŹNIEJ
A8: Nagroda | B8: Wyłącznie złoto / monety. | C8: Ekspedycja nie przyznaje materiałów ani szczęścia. Nazwa waluty do ujednolicenia. | D8: POTWIERDZONE
A9: Pierwszy wygrany poziom | B9: 50 monet w nieodebranej puli. | C9: Można wypłacić pulę na wyspę albo postawić ją na dalszą grę. | D9: POTWIERDZONE
A10: Każda kolejna wygrana | B10: Podwaja całą dotychczasową pulę. | C10: Poziom n: 50 × 2^(n−1) monet. To nowa łączna pula, nie dodatkowa nagroda dodawana do poprzedniej. | D10: POTWIERDZONE
A11: Wypłata | B11: Przeniesienie aktualnej puli do gry na wyspie. | C11: Po wypłacie ekspedycja powinna zamknąć serię; to logiczna propozycja, nie zatwierdzony osobny szczegół. Nie określono restartów i opłaty wejściowej. | D11: WYBÓR WYPŁATY POTWIERDZONY
A12: Przegrana | B12: Utrata całej niewypłaconej puli danej serii. | C12: Nie ma podstaw do odbierania istniejących wcześniej monet z wyspy. Płatności za dodatkowe ruchy/czas nie są nagrodą i zasady ich zwrotu nie zostały określone. | D12: POTWIERDZONE; WYDATKI DO DOPRECYZOWANIA
A13: Ograniczenie poziomu | B13: Limit czasu albo liczby ruchów. | C13: Ilości i trudność poszczególnych poziomów nieustalone. Zatrzymywanie podczas reklam i po zamknięciu karty wymaga osobnej reguły. | D13: POTWIERDZONE; LIMITY OTWARTE
A14: Dodatkowy czas lub ruchy | B14: Zakup monetami albo obejrzenie reklamy. | C14: Nie ustalono ceny, przyrostu czasu/ruchów, liczby zakupów, momentu zakupu ani czy można uratować już przegraną próbę. | D14: POTWIERDZONE; CENNIK OTWARTY
A15: Reklama ekspedycji | B15: Najpierw materiał o własnej grze, później reklamy zewnętrzne; maksymalnie 30 sekund. | C15: To reguła reklam ekspedycyjnych. Wcześniejsze odłożone reklamy kaplicy miały 60 s; nie zastępować ich bez decyzji. | D15: POTWIERDZONE
A16: Jednosekundowy przekaz | B16: Reklama ma zawierać przez 1 sekundę przekaz do późniejszego wpisania. | C16: Przekaz pokazywany przez 1 sekundę; treść, miejsce wpisania, warunek uznania reklamy i ewentualna nagroda zostaną opisane później. | D16: POMYSŁ ZACHOWANY; DZIAŁANIE PÓŹNIEJ
A17: Brak limitu poziomów | B17: Obecny opis nie wyznacza końca serii. | C17: Podwajanie jest wykładnicze: poziom 10 = 25 600, poziom 20 = 26 214 400 monet. Limit, trudność i koszt ratowania mogą być potrzebne do balansu. | D17: UWAGA BALANSOWA, NIE NOWA REGUŁA

Sheet Ekspedycje - poziomy
A1: EKSPEDYCJE • podwajanie puli
A2: Pula = 50 × 2^(n−1). Każda wygrana podwaja aktualną pulę; nie dodajemy wszystkich poprzednich pul. Wypłata trafia na wyspę. Przegrana odbiera niewypłaconą pulę serii. Maksymalna liczba poziomów nie została ustalona.
A5: Wygrany poziom | B5: Pula do wypłaty [monety] | C5: Przyrost względem poprzedniego | D5: Po przegranej kolejnego | E5: Cena zakupu takiej liczby monet [PLN] | F5: Dodatkowy czas/ruchy | G5: Uwagi
A6: 1 | B6: =Parametry!$C$48*Parametry!$C$49^(A6-1) -> 50 | C6: =IF(A6=1,B6,B6/2) -> 50 | D6: 0 | E6: =B6/Parametry!$C$41 -> 5 | F6: Monety lub reklama ≤30 s; cena i ilość do ustalenia. | G6: Przeliczenie PLN opisuje cenę zakupu monet, nie wypłatę pieniędzy. Nagroda poziomu 20 pokazuje ryzyko wykładniczego wzrostu.
A7: 2 | B7: =Parametry!$C$48*Parametry!$C$49^(A7-1) -> 100 | C7: =IF(A7=1,B7,B7/2) -> 50 | D7: 0 | E7: =B7/Parametry!$C$41 -> 10 | F7: Monety lub reklama ≤30 s; cena i ilość do ustalenia. | G7: Przeliczenie PLN opisuje cenę zakupu monet, nie wypłatę pieniędzy. Nagroda poziomu 20 pokazuje ryzyko wykładniczego wzrostu.
A8: 3 | B8: =Parametry!$C$48*Parametry!$C$49^(A8-1) -> 200 | C8: =IF(A8=1,B8,B8/2) -> 100 | D8: 0 | E8: =B8/Parametry!$C$41 -> 20 | F8: Monety lub reklama ≤30 s; cena i ilość do ustalenia. | G8: Przeliczenie PLN opisuje cenę zakupu monet, nie wypłatę pieniędzy. Nagroda poziomu 20 pokazuje ryzyko wykładniczego wzrostu.
A9: 4 | B9: =Parametry!$C$48*Parametry!$C$49^(A9-1) -> 400 | C9: =IF(A9=1,B9,B9/2) -> 200 | D9: 0 | E9: =B9/Parametry!$C$41 -> 40 | F9: Monety lub reklama ≤30 s; cena i ilość do ustalenia. | G9: Przeliczenie PLN opisuje cenę zakupu monet, nie wypłatę pieniędzy. Nagroda poziomu 20 pokazuje ryzyko wykładniczego wzrostu.
A10: 5 | B10: =Parametry!$C$48*Parametry!$C$49^(A10-1) -> 800 | C10: =IF(A10=1,B10,B10/2) -> 400 | D10: 0 | E10: =B10/Parametry!$C$41 -> 80 | F10: Monety lub reklama ≤30 s; cena i ilość do ustalenia. | G10: Przeliczenie PLN opisuje cenę zakupu monet, nie wypłatę pieniędzy. Nagroda poziomu 20 pokazuje ryzyko wykładniczego wzrostu.
A11: 6 | B11: =Parametry!$C$48*Parametry!$C$49^(A11-1) -> 1600 | C11: =IF(A11=1,B11,B11/2) -> 800 | D11: 0 | E11: =B11/Parametry!$C$41 -> 160 | F11: Monety lub reklama ≤30 s; cena i ilość do ustalenia. | G11: Przeliczenie PLN opisuje cenę zakupu monet, nie wypłatę pieniędzy. Nagroda poziomu 20 pokazuje ryzyko wykładniczego wzrostu.
A12: 7 | B12: =Parametry!$C$48*Parametry!$C$49^(A12-1) -> 3200 | C12: =IF(A12=1,B12,B12/2) -> 1600 | D12: 0 | E12: =B12/Parametry!$C$41 -> 320 | F12: Monety lub reklama ≤30 s; cena i ilość do ustalenia. | G12: Przeliczenie PLN opisuje cenę zakupu monet, nie wypłatę pieniędzy. Nagroda poziomu 20 pokazuje ryzyko wykładniczego wzrostu.
A13: 8 | B13: =Parametry!$C$48*Parametry!$C$49^(A13-1) -> 6400 | C13: =IF(A13=1,B13,B13/2) -> 3200 | D13: 0 | E13: =B13/Parametry!$C$41 -> 640 | F13: Monety lub reklama ≤30 s; cena i ilość do ustalenia. | G13: Przeliczenie PLN opisuje cenę zakupu monet, nie wypłatę pieniędzy. Nagroda poziomu 20 pokazuje ryzyko wykładniczego wzrostu.
A14: 9 | B14: =Parametry!$C$48*Parametry!$C$49^(A14-1) -> 12800 | C14: =IF(A14=1,B14,B14/2) -> 6400 | D14: 0 | E14: =B14/Parametry!$C$41 -> 1280 | F14: Monety lub reklama ≤30 s; cena i ilość do ustalenia. | G14: Przeliczenie PLN opisuje cenę zakupu monet, nie wypłatę pieniędzy. Nagroda poziomu 20 pokazuje ryzyko wykładniczego wzrostu.
A15: 10 | B15: =Parametry!$C$48*Parametry!$C$49^(A15-1) -> 25600 | C15: =IF(A15=1,B15,B15/2) -> 12800 | D15: 0 | E15: =B15/Parametry!$C$41 -> 2560 | F15: Monety lub reklama ≤30 s; cena i ilość do ustalenia. | G15: Przeliczenie PLN opisuje cenę zakupu monet, nie wypłatę pieniędzy. Nagroda poziomu 20 pokazuje ryzyko wykładniczego wzrostu.
A16: 11 | B16: =Parametry!$C$48*Parametry!$C$49^(A16-1) -> 51200 | C16: =IF(A16=1,B16,B16/2) -> 25600 | D16: 0 | E16: =B16/Parametry!$C$41 -> 5120 | F16: Monety lub reklama ≤30 s; cena i ilość do ustalenia. | G16: Przeliczenie PLN opisuje cenę zakupu monet, nie wypłatę pieniędzy. Nagroda poziomu 20 pokazuje ryzyko wykładniczego wzrostu.
A17: 12 | B17: =Parametry!$C$48*Parametry!$C$49^(A17-1) -> 102400 | C17: =IF(A17=1,B17,B17/2) -> 51200 | D17: 0 | E17: =B17/Parametry!$C$41 -> 10240 | F17: Monety lub reklama ≤30 s; cena i ilość do ustalenia. | G17: Przeliczenie PLN opisuje cenę zakupu monet, nie wypłatę pieniędzy. Nagroda poziomu 20 pokazuje ryzyko wykładniczego wzrostu.
... A19: 20 | B19: =Parametry!$C$48*Parametry!$C$49^(A19-1) -> 26214400 | C19: =IF(A19=1,B19,B19/2) -> 13107200 | D19: 0 | E19: =B19/Parametry!$C$41 -> 2621440 | F19: Monety lub reklama ≤30 s; cena i ilość do ustalenia. | G19: Przeliczenie PLN opisuje cenę zakupu monet, nie wypłatę pieniędzy. Nagroda poziomu 20 pokazuje ryzyko wykładniczego wzrostu.

Sheet Bilans V3
A1: BILANS • konsekwencje zatwierdzonych zasad
A2: Nie zmieniamy zatwierdzonych wartości. Początkowe zadania mają6h; po pierwszym sukcesie obowiązuje dobowa kotwica. Normy wymagań i wspólna populacja nadal oznaczają potrzebę wcześniejszych zapasów.
A5: Temat | B5: Liczby / konsekwencje | C5: Status / uwaga
A6: Społecznościowe 1000 monet | B6: Przy 1 PLN = 10 monet nagroda odpowiada cenie zakupu 100 PLN. Przy 12 pracujących to 83 h 20 min podatków; nagrodę można wydać na 1000 min skrócenia budowy. | C6: To porównanie siły nabywczej, nie wypłata prawdziwych pieniędzy.
A7: Społecznościowe 500 monet | B7: Równowartość ceny zakupu 50 PLN; przy 12 pracujących: 41 h 40 min podatków. | C7: Do ustalenia częstotliwość i kumulacja.
A8: Transport a opłacalność | B8: 200 Food przy ładunku 60 to 4 kursy = 40 monet; bazowa wartość zakupu to 300 monet. Przewóz 200 drewna również kosztuje 40 monet, ale zakup tylko 100. | C8: Cena przewozu zależy od objętości, nie wartości produktu; to spójne z cennikiem użytkownika.
A9: Ekspedycja poziom 10 | B9: 25 600 monet; przy 12 pracujących: 2133 h 20 min podatków. | C9: Jeżeli seria powtarzalna i łatwa, nagrody mogą dominować nad ekonomią wyspy.
A10: Minimalna szansa dalszej wygranej | B10: Ryzykując pulę B o podwojenie, oczekiwana pula po próbie to 2pB. Arytmetyczny próg rentowności p = 50%, przed kosztami ratunku. | C10: To analiza balansu; nie zakładamy losowości ani stawki prawdopodobieństwa w zręcznościowej minigrze.
A11: Zadania latarni | B11: L1: małe: 6 h = 720 na rodzaj, nie 1440; 1440 to suma dwóch rodzajów. Duże: 10 h = 1200 na rodzaj > 1000 pojemności typu w magazynie L1; raty umożliwiają wykonanie bez jednoczesnego zapasu całego kosztu. | C11: UWAGA DO BALANSU
A12: Zadania latarni | B12: L2: małe: 6 h = 1728 na rodzaj > 1500 pojemności typu magazynu L2; wymagane raty nie są błędem, lecz muszą być czytelne. | C12: UWAGA DO BALANSU
A13: Zadania latarni | B13: Początkowe zadanie z normą8–10h może wymagać wcześniejszych zapasów przy6hterminie. Po pierwszym sukcesie następcy trzymają niezależnądobowąkotwicę. | C13: UWAGA DO BALANSU
A14: Zadania latarni | B14: Nagrody skalujemy odL3 relacją12L×p(L)/468. Tenwzór nie gwarantuje zwrotu portowejwartościwszystkichwpłat. | C14: ZATWIERDZONE D07; świadoma konsekwencja balansu.
A15: Duże zadanie L1 od zera | B15: Minimum: 4 rodzaje × 4 h × 12 osób × 10/h = 1920 produktów. Przy 12 osobach to co najmniej 16 h sumarycznej pracy producentów, przed jedzeniem, zużyciem wejściowym 2:1 i transportem. Termin zadania wynosi 6 h. | C15: Zadanie jest celem na wcześniejsze zapasy lub wymaga oceny kosztów.
A16: Nagroda towarowa ×3 | B16: Bazowe 1000 ×3 = 3000 sztuk jednego towaru; magazyn poziomu 1 mieści 1000 każdego rodzaju i 4000 łącznie. | C16: Nagroda najpierw wypełnia centralę do limitów; nadmiar czeka w buforze i automatycznie dosypuje się przy zużyciu lub rozbudowie, z powiadomieniem. Nic nie przepada z braku miejsca.
... A19: Serie publikacji | B19: Bez limitu powtarzania i definicji kwalifikowanego posta kwoty za każdy 3. post tworzą nieograniczony przychód. | C19: Zasady nagradzania oraz weryfikacja platform pozostają otwarte.

Sheet Produkcja
A1: PRODUKCJA I ŁADUNEK • korzyść własnego poziomu
A2: Użytkownik potwierdził dokładnie 10, 12, 13, 14… zamiast ogólnego +10%. Poziom producenta wpływa na wydajność i limit 12 × L; Ratusz jest warunkiem rozbudowy. Ładunek dotyczy własnego poziomu budynku transportowego; głód obniża efektywną wydajność transportu o połowę. V8: lokalna pojemność =200×własny poziom producenta; kolumnaE uwzględnia poziom ścieżek ze scenariusza Parametry.
A5: Poziom budynku | B5: Wydajność/os./h | C5: Wydajność głodnego/os./h | D5: Limit załogi | E5: Ładunek magazyn/targ/port | F5: Uwagi
A6: 1 | B6: =IF(A6=1,10,A6+10) -> 10 | C6: =B6/2 -> 5 | D6: =A6*Parametry!$C$8 -> 12 | E6: =ROUNDDOWN(ROUNDDOWN(Parametry!$C$9*Parametry!$C$10^(A6-1),0)*(1+Parametry!$C$72*MAX(0,Parametry!$C$73-2)),0) -> 60 | F6: Każda osoba osobno; całe sztuki i własna faza pracy. Młyn/tartak nadal 2:1. Bufor lokalny nadal 200×własny poziom producenta.
A7: 2 | B7: =IF(A7=1,10,A7+10) -> 12 | C7: =B7/2 -> 6 | D7: =A7*Parametry!$C$8 -> 24 | E7: =ROUNDDOWN(ROUNDDOWN(Parametry!$C$9*Parametry!$C$10^(A7-1),0)*(1+Parametry!$C$72*MAX(0,Parametry!$C$73-2)),0) -> 66 | F7: Każda osoba osobno; całe sztuki i własna faza pracy. Młyn/tartak nadal 2:1. Bufor lokalny nadal 200×własny poziom producenta.
A8: 3 | B8: =IF(A8=1,10,A8+10) -> 13 | C8: =B8/2 -> 6.5 | D8: =A8*Parametry!$C$8 -> 36 | E8: =ROUNDDOWN(ROUNDDOWN(Parametry!$C$9*Parametry!$C$10^(A8-1),0)*(1+Parametry!$C$72*MAX(0,Parametry!$C$73-2)),0) -> 72 | F8: Każda osoba osobno; całe sztuki i własna faza pracy. Młyn/tartak nadal 2:1. Bufor lokalny nadal 200×własny poziom producenta.
A9: 4 | B9: =IF(A9=1,10,A9+10) -> 14 | C9: =B9/2 -> 7 | D9: =A9*Parametry!$C$8 -> 48 | E9: =ROUNDDOWN(ROUNDDOWN(Parametry!$C$9*Parametry!$C$10^(A9-1),0)*(1+Parametry!$C$72*MAX(0,Parametry!$C$73-2)),0) -> 79 | F9: Każda osoba osobno; całe sztuki i własna faza pracy. Młyn/tartak nadal 2:1. Bufor lokalny nadal 200×własny poziom producenta.
A10: 5 | B10: =IF(A10=1,10,A10+10) -> 15 | C10: =B10/2 -> 7.5 | D10: =A10*Parametry!$C$8 -> 60 | E10: =ROUNDDOWN(ROUNDDOWN(Parametry!$C$9*Parametry!$C$10^(A10-1),0)*(1+Parametry!$C$72*MAX(0,Parametry!$C$73-2)),0) -> 87 | F10: Każda osoba osobno; całe sztuki i własna faza pracy. Młyn/tartak nadal 2:1. Bufor lokalny nadal 200×własny poziom producenta.
A11: 6 | B11: =IF(A11=1,10,A11+10) -> 16 | C11: =B11/2 -> 8 | D11: =A11*Parametry!$C$8 -> 72 | E11: =ROUNDDOWN(ROUNDDOWN(Parametry!$C$9*Parametry!$C$10^(A11-1),0)*(1+Parametry!$C$72*MAX(0,Parametry!$C$73-2)),0) -> 96 | F11: Każda osoba osobno; całe sztuki i własna faza pracy. Młyn/tartak nadal 2:1. Bufor lokalny nadal 200×własny poziom producenta.
A12: 7 | B12: =IF(A12=1,10,A12+10) -> 17 | C12: =B12/2 -> 8.5 | D12: =A12*Parametry!$C$8 -> 84 | E12: =ROUNDDOWN(ROUNDDOWN(Parametry!$C$9*Parametry!$C$10^(A12-1),0)*(1+Parametry!$C$72*MAX(0,Parametry!$C$73-2)),0) -> 106 | F12: Każda osoba osobno; całe sztuki i własna faza pracy. Młyn/tartak nadal 2:1. Bufor lokalny nadal 200×własny poziom producenta.
A13: 8 | B13: =IF(A13=1,10,A13+10) -> 18 | C13: =B13/2 -> 9 | D13: =A13*Parametry!$C$8 -> 96 | E13: =ROUNDDOWN(ROUNDDOWN(Parametry!$C$9*Parametry!$C$10^(A13-1),0)*(1+Parametry!$C$72*MAX(0,Parametry!$C$73-2)),0) -> 116 | F13: Każda osoba osobno; całe sztuki i własna faza pracy. Młyn/tartak nadal 2:1. Bufor lokalny nadal 200×własny poziom producenta.
A14: 9 | B14: =IF(A14=1,10,A14+10) -> 19 | C14: =B14/2 -> 9.5 | D14: =A14*Parametry!$C$8 -> 108 | E14: =ROUNDDOWN(ROUNDDOWN(Parametry!$C$9*Parametry!$C$10^(A14-1),0)*(1+Parametry!$C$72*MAX(0,Parametry!$C$73-2)),0) -> 128 | F14: Każda osoba osobno; całe sztuki i własna faza pracy. Młyn/tartak nadal 2:1. Bufor lokalny nadal 200×własny poziom producenta.
A15: 10 | B15: =IF(A15=1,10,A15+10) -> 20 | C15: =B15/2 -> 10 | D15: =A15*Parametry!$C$8 -> 120 | E15: =ROUNDDOWN(ROUNDDOWN(Parametry!$C$9*Parametry!$C$10^(A15-1),0)*(1+Parametry!$C$72*MAX(0,Parametry!$C$73-2)),0) -> 141 | F15: Każda osoba osobno; całe sztuki i własna faza pracy. Młyn/tartak nadal 2:1. Bufor lokalny nadal 200×własny poziom producenta.

Sheet Czas budowy
A1: NOWE CZASY • liczymy kursy, nie sztuki na godzinę
A2: 74 warianty transportu i budowy. Młyn/drwale/tartak/kamieniołom koszt×2; farma bez zmian; kolejka+10%. Uwzględniono edytowalny ukończony poziom dróg (Parametry; domyślnie0), jego szybkość i ładunek. 6 dostępnych nakarmionych tragarzy. Bez zbierania i czekania; rzeczywisty scheduler może mieć dodatkowe konkurujące kursy.
A5: Budynek | B5: Etap | C5: Tryb kosztu | D5: Obecny L | E5: Nowy N | F5: Poziom magazynu | G5: Dostępni tragarze | H5: Ładunek/os./kurs | I5: Monety | J5: Drewno | K5: Kamień | L5: Zboże | M5: Food | N5: Deski | O5: Kursy drewno | P5: Kursy kamień | Q5: Kursy zboże | R5: Kursy Food | S5: Kursy deski | T5: Kursy razem | U5: Fale | V5: Transport T [min] | W5: Łącznie ×T | X5: Sama budowa [min] | Y5: Razem [min] | Z5: Materiały razem | AA5: Założenia
A6: Ratusz | B6: 1→2 | C6: Bez kolejki | D6: 1 | E6: =D6+1 -> 2 | F6: 1 | G6: =Parametry!$C$12 -> 6 | H6: =ROUNDDOWN(ROUNDDOWN(Parametry!$C$9*Parametry!$C$10^(F6-1),0)*(1+Parametry!$C$72*MAX(0,Parametry!$C$73-2)),0) -> 60 | I6: =ROUNDUP((Parametry!$C$20*MAX(1,D6))*1,0) -> 500 | J6: =ROUNDUP((Parametry!$C$20*MAX(1,D6))*1,0) -> 500 | K6: =ROUNDUP((Parametry!$C$20*MAX(1,D6))*1,0) -> 500 | L6: =ROUNDUP((Parametry!$C$20*MAX(1,D6))*1,0) -> 500 | M6: =ROUNDUP((Parametry!$C$20*MAX(1,D6))*1,0) -> 500 | N6: =ROUNDUP((Parametry!$C$20*MAX(1,D6))*1,0) -> 500 | O6: =ROUNDUP(J6/H6,0) -> 9 | P6: =ROUNDUP(K6/H6,0) -> 9 | Q6: =ROUNDUP(L6/H6,0) -> 9 | R6: =ROUNDUP(M6/H6,0) -> 9 | S6: =ROUNDUP(N6/H6,0) -> 9 | T6: =SUM(O6:S6) -> 45 | U6: =ROUNDUP(T6/G6,0) -> 8 | V6: =U6*Parametry!$C$11/(1+Parametry!$C$71*Parametry!$C$73) -> 40 | W6: =2 -> 2 | X6: =V6*(W6-1) -> 40 | Y6: =V6*W6 -> 80 | Z6: =SUM(J6:N6) -> 2500 | AA6: Tylko ta budowa; 6 dostępnych nakarmionych tragarzy; poziom magazynu według F. Poziom ścieżek z Parametry; domyślnie0. Rywalizujące kursy i priorytety w grze mogą wydłużyć ETA.
A7: Ratusz | B7: 1→2 | C7: Kolejka +10% | D7: 1 | E7: =D7+1 -> 2 | F7: 1 | G7: =Parametry!$C$12 -> 6 | H7: =ROUNDDOWN(ROUNDDOWN(Parametry!$C$9*Parametry!$C$10^(F7-1),0)*(1+Parametry!$C$72*MAX(0,Parametry!$C$73-2)),0) -> 60 | I7: =ROUNDUP((Parametry!$C$20*MAX(1,D7))*Parametry!$C$15,0) -> 550 | J7: =ROUNDUP((Parametry!$C$20*MAX(1,D7))*Parametry!$C$15,0) -> 550 | K7: =ROUNDUP((Parametry!$C$20*MAX(1,D7))*Parametry!$C$15,0) -> 550 | L7: =ROUNDUP((Parametry!$C$20*MAX(1,D7))*Parametry!$C$15,0) -> 550 | M7: =ROUNDUP((Parametry!$C$20*MAX(1,D7))*Parametry!$C$15,0) -> 550 | N7: =ROUNDUP((Parametry!$C$20*MAX(1,D7))*Parametry!$C$15,0) -> 550 | O7: =ROUNDUP(J7/H7,0) -> 10 | P7: =ROUNDUP(K7/H7,0) -> 10 | Q7: =ROUNDUP(L7/H7,0) -> 10 | R7: =ROUNDUP(M7/H7,0) -> 10 | S7: =ROUNDUP(N7/H7,0) -> 10 | T7: =SUM(O7:S7) -> 50 | U7: =ROUNDUP(T7/G7,0) -> 9 | V7: =U7*Parametry!$C$11/(1+Parametry!$C$71*Parametry!$C$73) -> 45 | W7: =2 -> 2 | X7: =V7*(W7-1) -> 45 | Y7: =V7*W7 -> 90 | Z7: =SUM(J7:N7) -> 2750 | AA7: Tylko ta budowa; 6 dostępnych nakarmionych tragarzy; poziom magazynu według F. Poziom ścieżek z Parametry; domyślnie0. Rywalizujące kursy i priorytety w grze mogą wydłużyć ETA.
A8: Ratusz | B8: 2→3 | C8: Bez kolejki | D8: 2 | E8: =D8+1 -> 3 | F8: 2 | G8: =Parametry!$C$12 -> 6 | H8: =ROUNDDOWN(ROUNDDOWN(Parametry!$C$9*Parametry!$C$10^(F8-1),0)*(1+Parametry!$C$72*MAX(0,Parametry!$C$73-2)),0) -> 66 | I8: =ROUNDUP((Parametry!$C$20*MAX(1,D8))*1,0) -> 1000 | J8: =ROUNDUP((Parametry!$C$20*MAX(1,D8))*1,0) -> 1000 | K8: =ROUNDUP((Parametry!$C$20*MAX(1,D8))*1,0) -> 1000 | L8: =ROUNDUP((Parametry!$C$20*MAX(1,D8))*1,0) -> 1000 | M8: =ROUNDUP((Parametry!$C$20*MAX(1,D8))*1,0) -> 1000 | N8: =ROUNDUP((Parametry!$C$20*MAX(1,D8))*1,0) -> 1000 | O8: =ROUNDUP(J8/H8,0) -> 16 | P8: =ROUNDUP(K8/H8,0) -> 16 | Q8: =ROUNDUP(L8/H8,0) -> 16 | R8: =ROUNDUP(M8/H8,0) -> 16 | S8: =ROUNDUP(N8/H8,0) -> 16 | T8: =SUM(O8:S8) -> 80 | U8: =ROUNDUP(T8/G8,0) -> 14 | V8: =U8*Parametry!$C$11/(1+Parametry!$C$71*Parametry!$C$73) -> 70 | W8: =2 -> 2 | X8: =V8*(W8-1) -> 70 | Y8: =V8*W8 -> 140 | Z8: =SUM(J8:N8) -> 5000 | AA8: Tylko ta budowa; 6 dostępnych nakarmionych tragarzy; poziom magazynu według F. Poziom ścieżek z Parametry; domyślnie0. Rywalizujące kursy i priorytety w grze mogą wydłużyć ETA.
A9: Ratusz | B9: 2→3 | C9: Kolejka +10% | D9: 2 | E9: =D9+1 -> 3 | F9: 2 | G9: =Parametry!$C$12 -> 6 | H9: =ROUNDDOWN(ROUNDDOWN(Parametry!$C$9*Parametry!$C$10^(F9-1),0)*(1+Parametry!$C$72*MAX(0,Parametry!$C$73-2)),0) -> 66 | I9: =ROUNDUP((Parametry!$C$20*MAX(1,D9))*Parametry!$C$15,0) -> 1100 | J9: =ROUNDUP((Parametry!$C$20*MAX(1,D9))*Parametry!$C$15,0) -> 1100 | K9: =ROUNDUP((Parametry!$C$20*MAX(1,D9))*Parametry!$C$15,0) -> 1100 | L9: =ROUNDUP((Parametry!$C$20*MAX(1,D9))*Parametry!$C$15,0) -> 1100 | M9: =ROUNDUP((Parametry!$C$20*MAX(1,D9))*Parametry!$C$15,0) -> 1100 | N9: =ROUNDUP((Parametry!$C$20*MAX(1,D9))*Parametry!$C$15,0) -> 1100 | O9: =ROUNDUP(J9/H9,0) -> 17 | P9: =ROUNDUP(K9/H9,0) -> 17 | Q9: =ROUNDUP(L9/H9,0) -> 17 | R9: =ROUNDUP(M9/H9,0) -> 17 | S9: =ROUNDUP(N9/H9,0) -> 17 | T9: =SUM(O9:S9) -> 85 | U9: =ROUNDUP(T9/G9,0) -> 15 | V9: =U9*Parametry!$C$11/(1+Parametry!$C$71*Parametry!$C$73) -> 75 | W9: =2 -> 2 | X9: =V9*(W9-1) -> 75 | Y9: =V9*W9 -> 150 | Z9: =SUM(J9:N9) -> 5500 | AA9: Tylko ta budowa; 6 dostępnych nakarmionych tragarzy; poziom magazynu według F. Poziom ścieżek z Parametry; domyślnie0. Rywalizujące kursy i priorytety w grze mogą wydłużyć ETA.
A10: Ratusz | B10: 3→4 | C10: Bez kolejki | D10: 3 | E10: =D10+1 -> 4 | F10: 3 | G10: =Parametry!$C$12 -> 6 | H10: =ROUNDDOWN(ROUNDDOWN(Parametry!$C$9*Parametry!$C$10^(F10-1),0)*(1+Parametry!$C$72*MAX(0,Parametry!$C$73-2)),0) -> 72 | I10: =ROUNDUP((Parametry!$C$20*MAX(1,D10))*1,0) -> 1500 | J10: =ROUNDUP((Parametry!$C$20*MAX(1,D10))*1,0) -> 1500 | K10: =ROUNDUP((Parametry!$C$20*MAX(1,D10))*1,0) -> 1500 | L10: =ROUNDUP((Parametry!$C$20*MAX(1,D10))*1,0) -> 1500 | M10: =ROUNDUP((Parametry!$C$20*MAX(1,D10))*1,0) -> 1500 | N10: =ROUNDUP((Parametry!$C$20*MAX(1,D10))*1,0) -> 1500 | O10: =ROUNDUP(J10/H10,0) -> 21 | P10: =ROUNDUP(K10/H10,0) -> 21 | Q10: =ROUNDUP(L10/H10,0) -> 21 | R10: =ROUNDUP(M10/H10,0) -> 21 | S10: =ROUNDUP(N10/H10,0) -> 21 | T10: =SUM(O10:S10) -> 105 | U10: =ROUNDUP(T10/G10,0) -> 18 | V10: =U10*Parametry!$C$11/(1+Parametry!$C$71*Parametry!$C$73) -> 90 | W10: =2 -> 2 | X10: =V10*(W10-1) -> 90 | Y10: =V10*W10 -> 180 | Z10: =SUM(J10:N10) -> 7500 | AA10: Tylko ta budowa; 6 dostępnych nakarmionych tragarzy; poziom magazynu według F. Poziom ścieżek z Parametry; domyślnie0. Rywalizujące kursy i priorytety w grze mogą wydłużyć ETA.
A11: Ratusz | B11: 3→4 | C11: Kolejka +10% | D11: 3 | E11: =D11+1 -> 4 | F11: 3 | G11: =Parametry!$C$12 -> 6 | H11: =ROUNDDOWN(ROUNDDOWN(Parametry!$C$9*Parametry!$C$10^(F11-1),0)*(1+Parametry!$C$72*MAX(0,Parametry!$C$73-2)),0) -> 72 | I11: =ROUNDUP((Parametry!$C$20*MAX(1,D11))*Parametry!$C$15,0) -> 1650 | J11: =ROUNDUP((Parametry!$C$20*MAX(1,D11))*Parametry!$C$15,0) -> 1650 | K11: =ROUNDUP((Parametry!$C$20*MAX(1,D11))*Parametry!$C$15,0) -> 1650 | L11: =ROUNDUP((Parametry!$C$20*MAX(1,D11))*Parametry!$C$15,0) -> 1650 | M11: =ROUNDUP((Parametry!$C$20*MAX(1,D11))*Parametry!$C$15,0) -> 1650 | N11: =ROUNDUP((Parametry!$C$20*MAX(1,D11))*Parametry!$C$15,0) -> 1650 | O11: =ROUNDUP(J11/H11,0) -> 23 | P11: =ROUNDUP(K11/H11,0) -> 23 | Q11: =ROUNDUP(L11/H11,0) -> 23 | R11: =ROUNDUP(M11/H11,0) -> 23 | S11: =ROUNDUP(N11/H11,0) -> 23 | T11: =SUM(O11:S11) -> 115 | U11: =ROUNDUP(T11/G11,0) -> 20 | V11: =U11*Parametry!$C$11/(1+Parametry!$C$71*Parametry!$C$73) -> 100 | W11: =2 -> 2 | X11: =V11*(W11-1) -> 100 | Y11: =V11*W11 -> 200 | Z11: =SUM(J11:N11) -> 8250 | AA11: Tylko ta budowa; 6 dostępnych nakarmionych tragarzy; poziom magazynu według F. Poziom ścieżek z Parametry; domyślnie0. Rywalizujące kursy i priorytety w grze mogą wydłużyć ETA.
A12: Dom | B12: 1→2 | C12: Bez kolejki | D12: 1 | E12: =D12+1 -> 2 | F12: 1 | G12: =Parametry!$C$12 -> 6 | H12: =ROUNDDOWN(ROUNDDOWN(Parametry!$C$9*Parametry!$C$10^(F12-1),0)*(1+Parametry!$C$72*MAX(0,Parametry!$C$73-2)),0) -> 60 | I12: =ROUNDUP((Parametry!$C$20*MAX(1,D12))*1,0) -> 500 | J12: =ROUNDUP((Parametry!$C$20*MAX(1,D12))*1,0) -> 500 | K12: =ROUNDUP((Parametry!$C$20*MAX(1,D12))*1,0) -> 500 | L12: =ROUNDUP((Parametry!$C$20*MAX(1,D12))*1,0) -> 500 | M12: =ROUNDUP((Parametry!$C$20*MAX(1,D12))*1,0) -> 500 | N12: =ROUNDUP((Parametry!$C$20*MAX(1,D12))*1,0) -> 500 | O12: =ROUNDUP(J12/H12,0) -> 9 | P12: =ROUNDUP(K12/H12,0) -> 9 | Q12: =ROUNDUP(L12/H12,0) -> 9 | R12: =ROUNDUP(M12/H12,0) -> 9 | S12: =ROUNDUP(N12/H12,0) -> 9 | T12: =SUM(O12:S12) -> 45 | U12: =ROUNDUP(T12/G12,0) -> 8 | V12: =U12*Parametry!$C$11/(1+Parametry!$C$71*Parametry!$C$73) -> 40 | W12: =2 -> 2 | X12: =V12*(W12-1) -> 40 | Y12: =V12*W12 -> 80 | Z12: =SUM(J12:N12) -> 2500 | AA12: Tylko ta budowa; 6 dostępnych nakarmionych tragarzy; poziom magazynu według F. Poziom ścieżek z Parametry; domyślnie0. Rywalizujące kursy i priorytety w grze mogą wydłużyć ETA.
A13: Dom | B13: 1→2 | C13: Kolejka +10% | D13: 1 | E13: =D13+1 -> 2 | F13: 1 | G13: =Parametry!$C$12 -> 6 | H13: =ROUNDDOWN(ROUNDDOWN(Parametry!$C$9*Parametry!$C$10^(F13-1),0)*(1+Parametry!$C$72*MAX(0,Parametry!$C$73-2)),0) -> 60 | I13: =ROUNDUP((Parametry!$C$20*MAX(1,D13))*Parametry!$C$15,0) -> 550 | J13: =ROUNDUP((Parametry!$C$20*MAX(1,D13))*Parametry!$C$15,0) -> 550 | K13: =ROUNDUP((Parametry!$C$20*MAX(1,D13))*Parametry!$C$15,0) -> 550 | L13: =ROUNDUP((Parametry!$C$20*MAX(1,D13))*Parametry!$C$15,0) -> 550 | M13: =ROUNDUP((Parametry!$C$20*MAX(1,D13))*Parametry!$C$15,0) -> 550 | N13: =ROUNDUP((Parametry!$C$20*MAX(1,D13))*Parametry!$C$15,0) -> 550 | O13: =ROUNDUP(J13/H13,0) -> 10 | P13: =ROUNDUP(K13/H13,0) -> 10 | Q13: =ROUNDUP(L13/H13,0) -> 10 | R13: =ROUNDUP(M13/H13,0) -> 10 | S13: =ROUNDUP(N13/H13,0) -> 10 | T13: =SUM(O13:S13) -> 50 | U13: =ROUNDUP(T13/G13,0) -> 9 | V13: =U13*Parametry!$C$11/(1+Parametry!$C$71*Parametry!$C$73) -> 45 | W13: =2 -> 2 | X13: =V13*(W13-1) -> 45 | Y13: =V13*W13 -> 90 | Z13: =SUM(J13:N13) -> 2750 | AA13: Tylko ta budowa; 6 dostępnych nakarmionych tragarzy; poziom magazynu według F. Poziom ścieżek z Parametry; domyślnie0. Rywalizujące kursy i priorytety w grze mogą wydłużyć ETA.
A14: Dom | B14: 2→3 | C14: Bez kolejki | D14: 2 | E14: =D14+1 -> 3 | F14: 2 | G14: =Parametry!$C$12 -> 6 | H14: =ROUNDDOWN(ROUNDDOWN(Parametry!$C$9*Parametry!$C$10^(F14-1),0)*(1+Parametry!$C$72*MAX(0,Parametry!$C$73-2)),0) -> 66 | I14: =ROUNDUP((Parametry!$C$20*MAX(1,D14))*1,0) -> 1000 | J14: =ROUNDUP((Parametry!$C$20*MAX(1,D14))*1,0) -> 1000 | K14: =ROUNDUP((Parametry!$C$20*MAX(1,D14))*1,0) -> 1000 | L14: =ROUNDUP((Parametry!$C$20*MAX(1,D14))*1,0) -> 1000 | M14: =ROUNDUP((Parametry!$C$20*MAX(1,D14))*1,0) -> 1000 | N14: =ROUNDUP((Parametry!$C$20*MAX(1,D14))*1,0) -> 1000 | O14: =ROUNDUP(J14/H14,0) -> 16 | P14: =ROUNDUP(K14/H14,0) -> 16 | Q14: =ROUNDUP(L14/H14,0) -> 16 | R14: =ROUNDUP(M14/H14,0) -> 16 | S14: =ROUNDUP(N14/H14,0) -> 16 | T14: =SUM(O14:S14) -> 80 | U14: =ROUNDUP(T14/G14,0) -> 14 | V14: =U14*Parametry!$C$11/(1+Parametry!$C$71*Parametry!$C$73) -> 70 | W14: =2 -> 2 | X14: =V14*(W14-1) -> 70 | Y14: =V14*W14 -> 140 | Z14: =SUM(J14:N14) -> 5000 | AA14: Tylko ta budowa; 6 dostępnych nakarmionych tragarzy; poziom magazynu według F. Poziom ścieżek z Parametry; domyślnie0. Rywalizujące kursy i priorytety w grze mogą wydłużyć ETA.
A15: Dom | B15: 2→3 | C15: Kolejka +10% | D15: 2 | E15: =D15+1 -> 3 | F15: 2 | G15: =Parametry!$C$12 -> 6 | H15: =ROUNDDOWN(ROUNDDOWN(Parametry!$C$9*Parametry!$C$10^(F15-1),0)*(1+Parametry!$C$72*MAX(0,Parametry!$C$73-2)),0) -> 66 | I15: =ROUNDUP((Parametry!$C$20*MAX(1,D15))*Parametry!$C$15,0) -> 1100 | J15: =ROUNDUP((Parametry!$C$20*MAX(1,D15))*Parametry!$C$15,0) -> 1100 | K15: =ROUNDUP((Parametry!$C$20*MAX(1,D15))*Parametry!$C$15,0) -> 1100 | L15: =ROUNDUP((Parametry!$C$20*MAX(1,D15))*Parametry!$C$15,0) -> 1100 | M15: =ROUNDUP((Parametry!$C$20*MAX(1,D15))*Parametry!$C$15,0) -> 1100 | N15: =ROUNDUP((Parametry!$C$20*MAX(1,D15))*Parametry!$C$15,0) -> 1100 | O15: =ROUNDUP(J15/H15,0) -> 17 | P15: =ROUNDUP(K15/H15,0) -> 17 | Q15: =ROUNDUP(L15/H15,0) -> 17 | R15: =ROUNDUP(M15/H15,0) -> 17 | S15: =ROUNDUP(N15/H15,0) -> 17 | T15: =SUM(O15:S15) -> 85 | U15: =ROUNDUP(T15/G15,0) -> 15 | V15: =U15*Parametry!$C$11/(1+Parametry!$C$71*Parametry!$C$73) -> 75 | W15: =2 -> 2 | X15: =V15*(W15-1) -> 75 | Y15: =V15*W15 -> 150 | Z15: =SUM(J15:N15) -> 5500 | AA15: Tylko ta budowa; 6 dostępnych nakarmionych tragarzy; poziom magazynu według F. Poziom ścieżek z Parametry; domyślnie0. Rywalizujące kursy i priorytety w grze mogą wydłużyć ETA.
A16: Dom | B16: 3→4 | C16: Bez kolejki | D16: 3 | E16: =D16+1 -> 4 | F16: 3 | G16: =Parametry!$C$12 -> 6 | H16: =ROUNDDOWN(ROUNDDOWN(Parametry!$C$9*Parametry!$C$10^(F16-1),0)*(1+Parametry!$C$72*MAX(0,Parametry!$C$73-2)),0) -> 72 | I16: =ROUNDUP((Parametry!$C$20*MAX(1,D16))*1,0) -> 1500 | J16: =ROUNDUP((Parametry!$C$20*MAX(1,D16))*1,0) -> 1500 | K16: =ROUNDUP((Parametry!$C$20*MAX(1,D16))*1,0) -> 1500 | L16: =ROUNDUP((Parametry!$C$20*MAX(1,D16))*1,0) -> 1500 | M16: =ROUNDUP((Parametry!$C$20*MAX(1,D16))*1,0) -> 1500 | N16: =ROUNDUP((Parametry!$C$20*MAX(1,D16))*1,0) -> 1500 | O16: =ROUNDUP(J16/H16,0) -> 21 | P16: =ROUNDUP(K16/H16,0) -> 21 | Q16: =ROUNDUP(L16/H16,0) -> 21 | R16: =ROUNDUP(M16/H16,0) -> 21 | S16: =ROUNDUP(N16/H16,0) -> 21 | T16: =SUM(O16:S16) -> 105 | U16: =ROUNDUP(T16/G16,0) -> 18 | V16: =U16*Parametry!$C$11/(1+Parametry!$C$71*Parametry!$C$73) -> 90 | W16: =2 -> 2 | X16: =V16*(W16-1) -> 90 | Y16: =V16*W16 -> 180 | Z16: =SUM(J16:N16) -> 7500 | AA16: Tylko ta budowa; 6 dostępnych nakarmionych tragarzy; poziom magazynu według F. Poziom ścieżek z Parametry; domyślnie0. Rywalizujące kursy i priorytety w grze mogą wydłużyć ETA.
A17: Dom | B17: 3→4 | C17: Kolejka +10% | D17: 3 | E17: =D17+1 -> 4 | F17: 3 | G17: =Parametry!$C$12 -> 6 | H17: =ROUNDDOWN(ROUNDDOWN(Parametry!$C$9*Parametry!$C$10^(F17-1),0)*(1+Parametry!$C$72*MAX(0,Parametry!$C$73-2)),0) -> 72 | I17: =ROUNDUP((Parametry!$C$20*MAX(1,D17))*Parametry!$C$15,0) -> 1650 | J17: =ROUNDUP((Parametry!$C$20*MAX(1,D17))*Parametry!$C$15,0) -> 1650 | K17: =ROUNDUP((Parametry!$C$20*MAX(1,D17))*Parametry!$C$15,0) -> 1650 | L17: =ROUNDUP((Parametry!$C$20*MAX(1,D17))*Parametry!$C$15,0) -> 1650 | M17: =ROUNDUP((Parametry!$C$20*MAX(1,D17))*Parametry!$C$15,0) -> 1650 | N17: =ROUNDUP((Parametry!$C$20*MAX(1,D17))*Parametry!$C$15,0) -> 1650 | O17: =ROUNDUP(J17/H17,0) -> 23 | P17: =ROUNDUP(K17/H17,0) -> 23 | Q17: =ROUNDUP(L17/H17,0) -> 23 | R17: =ROUNDUP(M17/H17,0) -> 23 | S17: =ROUNDUP(N17/H17,0) -> 23 | T17: =SUM(O17:S17) -> 115 | U17: =ROUNDUP(T17/G17,0) -> 20 | V17: =U17*Parametry!$C$11/(1+Parametry!$C$71*Parametry!$C$73) -> 100 | W17: =2 -> 2 | X17: =V17*(W17-1) -> 100 | Y17: =V17*W17 -> 200 | Z17: =SUM(J17:N17) -> 8250 | AA17: Tylko ta budowa; 6 dostępnych nakarmionych tragarzy; poziom magazynu według F. Poziom ścieżek z Parametry; domyślnie0. Rywalizujące kursy i priorytety w grze mogą wydłużyć ETA.
A18: Farma | B18: 1→2 | C18: Bez kolejki | D18: 1 | E18: =D18+1 -> 2 | F18: 1 | G18: =Parametry!$C$12 -> 6 | H18: =ROUNDDOWN(ROUNDDOWN(Parametry!$C$9*Parametry!$C$10^(F18-1),0)*(1+Parametry!$C$72*MAX(0,Parametry!$C$73-2)),0) -> 60 | I18: =ROUNDUP((0)*1,0) -> 0 | J18: =ROUNDUP((Parametry!$C$16*Parametry!$C$17*D18)*1,0) -> 72 | K18: =ROUNDUP((Parametry!$C$16*Parametry!$C$18*D18)*1,0) -> 72 | L18: =ROUNDUP((Parametry!$C$16*Parametry!$C$19*D18)*1,0) -> 120 | M18: =ROUNDUP((0)*1,0) -> 0 | N18: =ROUNDUP((0)*1,0) -> 0 | O18: =ROUNDUP(J18/H18,0) -> 2 | P18: =ROUNDUP(K18/H18,0) -> 2 | Q18: =ROUNDUP(L18/H18,0) -> 2 | R18: =ROUNDUP(M18/H18,0) -> 0 | S18: =ROUNDUP(N18/H18,0) -> 0 | T18: =SUM(O18:S18) -> 6 | U18: =ROUNDUP(T18/G18,0) -> 1 | V18: =U18*Parametry!$C$11/(1+Parametry!$C$71*Parametry!$C$73) -> 5 | W18: =2 -> 2 | X18: =V18*(W18-1) -> 5 | Y18: =V18*W18 -> 10 | Z18: =SUM(J18:N18) -> 264 | AA18: Tylko ta budowa; 6 dostępnych nakarmionych tragarzy; poziom magazynu według F. Poziom ścieżek z Parametry; domyślnie0. Rywalizujące kursy i priorytety w grze mogą wydłużyć ETA.
A19: Farma | B19: 1→2 | C19: Kolejka +10% | D19: 1 | E19: =D19+1 -> 2 | F19: 1 | G19: =Parametry!$C$12 -> 6 | H19: =ROUNDDOWN(ROUNDDOWN(Parametry!$C$9*Parametry!$C$10^(F19-1),0)*(1+Parametry!$C$72*MAX(0,Parametry!$C$73-2)),0) -> 60 | I19: =ROUNDUP((0)*Parametry!$C$15,0) -> 0 | J19: =ROUNDUP((Parametry!$C$16*Parametry!$C$17*D19)*Parametry!$C$15,0) -> 80 | K19: =ROUNDUP((Parametry!$C$16*Parametry!$C$18*D19)*Parametry!$C$15,0) -> 80 | L19: =ROUNDUP((Parametry!$C$16*Parametry!$C$19*D19)*Parametry!$C$15,0) -> 132 | M19: =ROUNDUP((0)*Parametry!$C$15,0) -> 0 | N19: =ROUNDUP((0)*Parametry!$C$15,0) -> 0 | O19: =ROUNDUP(J19/H19,0) -> 2 | P19: =ROUNDUP(K19/H19,0) -> 2 | Q19: =ROUNDUP(L19/H19,0) -> 3 | R19: =ROUNDUP(M19/H19,0) -> 0 | S19: =ROUNDUP(N19/H19,0) -> 0 | T19: =SUM(O19:S19) -> 7 | U19: =ROUNDUP(T19/G19,0) -> 2 | V19: =U19*Parametry!$C$11/(1+Parametry!$C$71*Parametry!$C$73) -> 10 | W19: =2 -> 2 | X19: =V19*(W19-1) -> 10 | Y19: =V19*W19 -> 20 | Z19: =SUM(J19:N19) -> 292 | AA19: Tylko ta budowa; 6 dostępnych nakarmionych tragarzy; poziom magazynu według F. Poziom ścieżek z Parametry; domyślnie0. Rywalizujące kursy i priorytety w grze mogą wydłużyć ETA.
A20: Farma | B20: 2→3 | C20: Bez kolejki | D20: 2 | E20: =D20+1 -> 3 | F20: 2 | G20: =Parametry!$C$12 -> 6 | H20: =ROUNDDOWN(ROUNDDOWN(Parametry!$C$9*Parametry!$C$10^(F20-1),0)*(1+Parametry!$C$72*MAX(0,Parametry!$C$73-2)),0) -> 66 | I20: =ROUNDUP((0)*1,0) -> 0 | J20: =ROUNDUP((Parametry!$C$16*Parametry!$C$17*D20)*1,0) -> 144 | K20: =ROUNDUP((Parametry!$C$16*Parametry!$C$18*D20)*1,0) -> 144 | L20: =ROUNDUP((Parametry!$C$16*Parametry!$C$19*D20)*1,0) -> 240 | M20: =ROUNDUP((0)*1,0) -> 0 | N20: =ROUNDUP((0)*1,0) -> 0 | O20: =ROUNDUP(J20/H20,0) -> 3 | P20: =ROUNDUP(K20/H20,0) -> 3 | Q20: =ROUNDUP(L20/H20,0) -> 4 | R20: =ROUNDUP(M20/H20,0) -> 0 | S20: =ROUNDUP(N20/H20,0) -> 0 | T20: =SUM(O20:S20) -> 10 | U20: =ROUNDUP(T20/G20,0) -> 2 | V20: =U20*Parametry!$C$11/(1+Parametry!$C$71*Parametry!$C$73) -> 10 | W20: =2 -> 2 | X20: =V20*(W20-1) -> 10 | Y20: =V20*W20 -> 20 | Z20: =SUM(J20:N20) -> 528 | AA20: Tylko ta budowa; 6 dostępnych nakarmionych tragarzy; poziom magazynu według F. Poziom ścieżek z Parametry; domyślnie0. Rywalizujące kursy i priorytety w grze mogą wydłużyć ETA.
A21: Farma | B21: 2→3 | C21: Kolejka +10% | D21: 2 | E21: =D21+1 -> 3 | F21: 2 | G21: =Parametry!$C$12 -> 6 | H21: =ROUNDDOWN(ROUNDDOWN(Parametry!$C$9*Parametry!$C$10^(F21-1),0)*(1+Parametry!$C$72*MAX(0,Parametry!$C$73-2)),0) -> 66 | I21: =ROUNDUP((0)*Parametry!$C$15,0) -> 0 | J21: =ROUNDUP((Parametry!$C$16*Parametry!$C$17*D21)*Parametry!$C$15,0) -> 159 | K21: =ROUNDUP((Parametry!$C$16*Parametry!$C$18*D21)*Parametry!$C$15,0) -> 159 | L21: =ROUNDUP((Parametry!$C$16*Parametry!$C$19*D21)*Parametry!$C$15,0) -> 264 | M21: =ROUNDUP((0)*Parametry!$C$15,0) -> 0 | N21: =ROUNDUP((0)*Parametry!$C$15,0) -> 0 | O21: =ROUNDUP(J21/H21,0) -> 3 | P21: =ROUNDUP(K21/H21,0) -> 3 | Q21: =ROUNDUP(L21/H21,0) -> 4 | R21: =ROUNDUP(M21/H21,0) -> 0 | S21: =ROUNDUP(N21/H21,0) -> 0 | T21: =SUM(O21:S21) -> 10 | U21: =ROUNDUP(T21/G21,0) -> 2 | V21: =U21*Parametry!$C$11/(1+Parametry!$C$71*Parametry!$C$73) -> 10 | W21: =2 -> 2 | X21: =V21*(W21-1) -> 10 | Y21: =V21*W21 -> 20 | Z21: =SUM(J21:N21) -> 582 | AA21: Tylko ta budowa; 6 dostępnych nakarmionych tragarzy; poziom magazynu według F. Poziom ścieżek z Parametry; domyślnie0. Rywalizujące kursy i priorytety w grze mogą wydłużyć ETA.
A22: Farma | B22: 3→4 | C22: Bez kolejki | D22: 3 | E22: =D22+1 -> 4 | F22: 3 | G22: =Parametry!$C$12 -> 6 | H22: =ROUNDDOWN(ROUNDDOWN(Parametry!$C$9*Parametry!$C$10^(F22-1),0)*(1+Parametry!$C$72*MAX(0,Parametry!$C$73-2)),0) -> 72 | I22: =ROUNDUP((0)*1,0) -> 0 | J22: =ROUNDUP((Parametry!$C$16*Parametry!$C$17*D22)*1,0) -> 216 | K22: =ROUNDUP((Parametry!$C$16*Parametry!$C$18*D22)*1,0) -> 216 | L22: =ROUNDUP((Parametry!$C$16*Parametry!$C$19*D22)*1,0) -> 360 | M22: =ROUNDUP((0)*1,0) -> 0 | N22: =ROUNDUP((0)*1,0) -> 0 | O22: =ROUNDUP(J22/H22,0) -> 3 | P22: =ROUNDUP(K22/H22,0) -> 3 | Q22: =ROUNDUP(L22/H22,0) -> 5 | R22: =ROUNDUP(M22/H22,0) -> 0 | S22: =ROUNDUP(N22/H22,0) -> 0 | T22: =SUM(O22:S22) -> 11 | U22: =ROUNDUP(T22/G22,0) -> 2 | V22: =U22*Parametry!$C$11/(1+Parametry!$C$71*Parametry!$C$73) -> 10 | W22: =2 -> 2 | X22: =V22*(W22-1) -> 10 | Y22: =V22*W22 -> 20 | Z22: =SUM(J22:N22) -> 792 | AA22: Tylko ta budowa; 6 dostępnych nakarmionych tragarzy; poziom magazynu według F. Poziom ścieżek z Parametry; domyślnie0. Rywalizujące kursy i priorytety w grze mogą wydłużyć ETA.
A23: Farma | B23: 3→4 | C23: Kolejka +10% | D23: 3 | E23: =D23+1 -> 4 | F23: 3 | G23: =Parametry!$C$12 -> 6 | H23: =ROUNDDOWN(ROUNDDOWN(Parametry!$C$9*Parametry!$C$10^(F23-1),0)*(1+Parametry!$C$72*MAX(0,Parametry!$C$73-2)),0) -> 72 | I23: =ROUNDUP((0)*Parametry!$C$15,0) -> 0 | J23: =ROUNDUP((Parametry!$C$16*Parametry!$C$17*D23)*Parametry!$C$15,0) -> 238 | K23: =ROUNDUP((Parametry!$C$16*Parametry!$C$18*D23)*Parametry!$C$15,0) -> 238 | L23: =ROUNDUP((Parametry!$C$16*Parametry!$C$19*D23)*Parametry!$C$15,0) -> 396 | M23: =ROUNDUP((0)*Parametry!$C$15,0) -> 0 | N23: =ROUNDUP((0)*Parametry!$C$15,0) -> 0 | O23: =ROUNDUP(J23/H23,0) -> 4 | P23: =ROUNDUP(K23/H23,0) -> 4 | Q23: =ROUNDUP(L23/H23,0) -> 6 | R23: =ROUNDUP(M23/H23,0) -> 0 | S23: =ROUNDUP(N23/H23,0) -> 0 | T23: =SUM(O23:S23) -> 14 | U23: =ROUNDUP(T23/G23,0) -> 3 | V23: =U23*Parametry!$C$11/(1+Parametry!$C$71*Parametry!$C$73) -> 15 | W23: =2 -> 2 | X23: =V23*(W23-1) -> 15 | Y23: =V23*W23 -> 30 | Z23: =SUM(J23:N23) -> 872 | AA23: Tylko ta budowa; 6 dostępnych nakarmionych tragarzy; poziom magazynu według F. Poziom ścieżek z Parametry; domyślnie0. Rywalizujące kursy i priorytety w grze mogą wydłużyć ETA.
A24: Młyn | B24: 1→2 | C24: Bez kolejki | D24: 1 | E24: =D24+1 -> 2 | F24: 1 | G24: =Parametry!$C$12 -> 6 | H24: =ROUNDDOWN(ROUNDDOWN(Parametry!$C$9*Parametry!$C$10^(F24-1),0)*(1+Parametry!$C$72*MAX(0,Parametry!$C$73-2)),0) -> 60 | I24: =ROUNDUP((2*(0))*1,0) -> 0 | J24: =ROUNDUP((2*(Parametry!$C$16*Parametry!$C$17*D24))*1,0) -> 144 | K24: =ROUNDUP((2*(Parametry!$C$16*Parametry!$C$18*D24))*1,0) -> 144 | L24: =ROUNDUP((2*(0))*1,0) -> 0 | M24: =ROUNDUP((2*(Parametry!$C$16*Parametry!$C$19*D24))*1,0) -> 240 | N24: =ROUNDUP((2*(0))*1,0) -> 0 | O24: =ROUNDUP(J24/H24,0) -> 3 | P24: =ROUNDUP(K24/H24,0) -> 3 | Q24: =ROUNDUP(L24/H24,0) -> 0 | R24: =ROUNDUP(M24/H24,0) -> 4 | S24: =ROUNDUP(N24/H24,0) -> 0 | T24: =SUM(O24:S24) -> 10 | U24: =ROUNDUP(T24/G24,0) -> 2 | V24: =U24*Parametry!$C$11/(1+Parametry!$C$71*Parametry!$C$73) -> 10 | W24: =2 -> 2 | X24: =V24*(W24-1) -> 10 | Y24: =V24*W24 -> 20 | Z24: =SUM(J24:N24) -> 528 | AA24: Tylko ta budowa; 6 dostępnych nakarmionych tragarzy; poziom magazynu według F. Poziom ścieżek z Parametry; domyślnie0. Rywalizujące kursy i priorytety w grze mogą wydłużyć ETA.
A25: Młyn | B25: 1→2 | C25: Kolejka +10% | D25: 1 | E25: =D25+1 -> 2 | F25: 1 | G25: =Parametry!$C$12 -> 6 | H25: =ROUNDDOWN(ROUNDDOWN(Parametry!$C$9*Parametry!$C$10^(F25-1),0)*(1+Parametry!$C$72*MAX(0,Parametry!$C$73-2)),0) -> 60 | I25: =ROUNDUP((2*(0))*Parametry!$C$15,0) -> 0 | J25: =ROUNDUP((2*(Parametry!$C$16*Parametry!$C$17*D25))*Parametry!$C$15,0) -> 159 | K25: =ROUNDUP((2*(Parametry!$C$16*Parametry!$C$18*D25))*Parametry!$C$15,0) -> 159 | L25: =ROUNDUP((2*(0))*Parametry!$C$15,0) -> 0 | M25: =ROUNDUP((2*(Parametry!$C$16*Parametry!$C$19*D25))*Parametry!$C$15,0) -> 264 | N25: =ROUNDUP((2*(0))*Parametry!$C$15,0) -> 0 | O25: =ROUNDUP(J25/H25,0) -> 3 | P25: =ROUNDUP(K25/H25,0) -> 3 | Q25: =ROUNDUP(L25/H25,0) -> 0 | R25: =ROUNDUP(M25/H25,0) -> 5 | S25: =ROUNDUP(N25/H25,0) -> 0 | T25: =SUM(O25:S25) -> 11 | U25: =ROUNDUP(T25/G25,0) -> 2 | V25: =U25*Parametry!$C$11/(1+Parametry!$C$71*Parametry!$C$73) -> 10 | W25: =2 -> 2 | X25: =V25*(W25-1) -> 10 | Y25: =V25*W25 -> 20 | Z25: =SUM(J25:N25) -> 582 | AA25: Tylko ta budowa; 6 dostępnych nakarmionych tragarzy; poziom magazynu według F. Poziom ścieżek z Parametry; domyślnie0. Rywalizujące kursy i priorytety w grze mogą wydłużyć ETA.
A26: Młyn | B26: 2→3 | C26: Bez kolejki | D26: 2 | E26: =D26+1 -> 3 | F26: 2 | G26: =Parametry!$C$12 -> 6 | H26: =ROUNDDOWN(ROUNDDOWN(Parametry!$C$9*Parametry!$C$10^(F26-1),0)*(1+Parametry!$C$72*MAX(0,Parametry!$C$73-2)),0) -> 66 | I26: =ROUNDUP((2*(0))*1,0) -> 0 | J26: =ROUNDUP((2*(Parametry!$C$16*Parametry!$C$17*D26))*1,0) -> 288 | K26: =ROUNDUP((2*(Parametry!$C$16*Parametry!$C$18*D26))*1,0) -> 288 | L26: =ROUNDUP((2*(0))*1,0) -> 0 | M26: =ROUNDUP((2*(Parametry!$C$16*Parametry!$C$19*D26))*1,0) -> 480 | N26: =ROUNDUP((2*(0))*1,0) -> 0 | O26: =ROUNDUP(J26/H26,0) -> 5 | P26: =ROUNDUP(K26/H26,0) -> 5 | Q26: =ROUNDUP(L26/H26,0) -> 0 | R26: =ROUNDUP(M26/H26,0) -> 8 | S26: =ROUNDUP(N26/H26,0) -> 0 | T26: =SUM(O26:S26) -> 18 | U26: =ROUNDUP(T26/G26,0) -> 3 | V26: =U26*Parametry!$C$11/(1+Parametry!$C$71*Parametry!$C$73) -> 15 | W26: =2 -> 2 | X26: =V26*(W26-1) -> 15 | Y26: =V26*W26 -> 30 | Z26: =SUM(J26:N26) -> 1056 | AA26: Tylko ta budowa; 6 dostępnych nakarmionych tragarzy; poziom magazynu według F. Poziom ścieżek z Parametry; domyślnie0. Rywalizujące kursy i priorytety w grze mogą wydłużyć ETA.
A27: Młyn | B27: 2→3 | C27: Kolejka +10% | D27: 2 | E27: =D27+1 -> 3 | F27: 2 | G27: =Parametry!$C$12 -> 6 | H27: =ROUNDDOWN(ROUNDDOWN(Parametry!$C$9*Parametry!$C$10^(F27-1),0)*(1+Parametry!$C$72*MAX(0,Parametry!$C$73-2)),0) -> 66 | I27: =ROUNDUP((2*(0))*Parametry!$C$15,0) -> 0 | J27: =ROUNDUP((2*(Parametry!$C$16*Parametry!$C$17*D27))*Parametry!$C$15,0) -> 317 | K27: =ROUNDUP((2*(Parametry!$C$16*Parametry!$C$18*D27))*Parametry!$C$15,0) -> 317 | L27: =ROUNDUP((2*(0))*Parametry!$C$15,0) -> 0 | M27: =ROUNDUP((2*(Parametry!$C$16*Parametry!$C$19*D27))*Parametry!$C$15,0) -> 528 | N27: =ROUNDUP((2*(0))*Parametry!$C$15,0) -> 0 | O27: =ROUNDUP(J27/H27,0) -> 5 | P27: =ROUNDUP(K27/H27,0) -> 5 | Q27: =ROUNDUP(L27/H27,0) -> 0 | R27: =ROUNDUP(M27/H27,0) -> 8 | S27: =ROUNDUP(N27/H27,0) -> 0 | T27: =SUM(O27:S27) -> 18 | U27: =ROUNDUP(T27/G27,0) -> 3 | V27: =U27*Parametry!$C$11/(1+Parametry!$C$71*Parametry!$C$73) -> 15 | W27: =2 -> 2 | X27: =V27*(W27-1) -> 15 | Y27: =V27*W27 -> 30 | Z27: =SUM(J27:N27) -> 1162 | AA27: Tylko ta budowa; 6 dostępnych nakarmionych tragarzy; poziom magazynu według F. Poziom ścieżek z Parametry; domyślnie0. Rywalizujące kursy i priorytety w grze mogą wydłużyć ETA.
A28: Młyn | B28: 3→4 | C28: Bez kolejki | D28: 3 | E28: =D28+1 -> 4 | F28: 3 | G28: =Parametry!$C$12 -> 6 | H28: =ROUNDDOWN(ROUNDDOWN(Parametry!$C$9*Parametry!$C$10^(F28-1),0)*(1+Parametry!$C$72*MAX(0,Parametry!$C$73-2)),0) -> 72 | I28: =ROUNDUP((2*(0))*1,0) -> 0 | J28: =ROUNDUP((2*(Parametry!$C$16*Parametry!$C$17*D28))*1,0) -> 432 | K28: =ROUNDUP((2*(Parametry!$C$16*Parametry!$C$18*D28))*1,0) -> 432 | L28: =ROUNDUP((2*(0))*1,0) -> 0 | M28: =ROUNDUP((2*(Parametry!$C$16*Parametry!$C$19*D28))*1,0) -> 720 | N28: =ROUNDUP((2*(0))*1,0) -> 0 | O28: =ROUNDUP(J28/H28,0) -> 6 | P28: =ROUNDUP(K28/H28,0) -> 6 | Q28: =ROUNDUP(L28/H28,0) -> 0 | R28: =ROUNDUP(M28/H28,0) -> 10 | S28: =ROUNDUP(N28/H28,0) -> 0 | T28: =SUM(O28:S28) -> 22 | U28: =ROUNDUP(T28/G28,0) -> 4 | V28: =U28*Parametry!$C$11/(1+Parametry!$C$71*Parametry!$C$73) -> 20 | W28: =2 -> 2 | X28: =V28*(W28-1) -> 20 | Y28: =V28*W28 -> 40 | Z28: =SUM(J28:N28) -> 1584 | AA28: Tylko ta budowa; 6 dostępnych nakarmionych tragarzy; poziom magazynu według F. Poziom ścieżek z Parametry; domyślnie0. Rywalizujące kursy i priorytety w grze mogą wydłużyć ETA.
A29: Młyn | B29: 3→4 | C29: Kolejka +10% | D29: 3 | E29: =D29+1 -> 4 | F29: 3 | G29: =Parametry!$C$12 -> 6 | H29: =ROUNDDOWN(ROUNDDOWN(Parametry!$C$9*Parametry!$C$10^(F29-1),0)*(1+Parametry!$C$72*MAX(0,Parametry!$C$73-2)),0) -> 72 | I29: =ROUNDUP((2*(0))*Parametry!$C$15,0) -> 0 | J29: =ROUNDUP((2*(Parametry!$C$16*Parametry!$C$17*D29))*Parametry!$C$15,0) -> 476 | K29: =ROUNDUP((2*(Parametry!$C$16*Parametry!$C$18*D29))*Parametry!$C$15,0) -> 476 | L29: =ROUNDUP((2*(0))*Parametry!$C$15,0) -> 0 | M29: =ROUNDUP((2*(Parametry!$C$16*Parametry!$C$19*D29))*Parametry!$C$15,0) -> 792 | N29: =ROUNDUP((2*(0))*Parametry!$C$15,0) -> 0 | O29: =ROUNDUP(J29/H29,0) -> 7 | P29: =ROUNDUP(K29/H29,0) -> 7 | Q29: =ROUNDUP(L29/H29,0) -> 0 | R29: =ROUNDUP(M29/H29,0) -> 11 | S29: =ROUNDUP(N29/H29,0) -> 0 | T29: =SUM(O29:S29) -> 25 | U29: =ROUNDUP(T29/G29,0) -> 5 | V29: =U29*Parametry!$C$11/(1+Parametry!$C$71*Parametry!$C$73) -> 25 | W29: =2 -> 2 | X29: =V29*(W29-1) -> 25 | Y29: =V29*W29 -> 50 | Z29: =SUM(J29:N29) -> 1744 | AA29: Tylko ta budowa; 6 dostępnych nakarmionych tragarzy; poziom magazynu według F. Poziom ścieżek z Parametry; domyślnie0. Rywalizujące kursy i priorytety w grze mogą wydłużyć ETA.
A30: Drwale | B30: 1→2 | C30: Bez kolejki | D30: 1 | E30: =D30+1 -> 2 | F30: 1 | G30: =Parametry!$C$12 -> 6 | H30: =ROUNDDOWN(ROUNDDOWN(Parametry!$C$9*Parametry!$C$10^(F30-1),0)*(1+Parametry!$C$72*MAX(0,Parametry!$C$73-2)),0) -> 60 | I30: =ROUNDUP((2*(0))*1,0) -> 0 | J30: =ROUNDUP((2*(Parametry!$C$16*Parametry!$C$17*D30+Parametry!$C$16*Parametry!$C$19*D30))*1,0) -> 384 | K30: =ROUNDUP((2*(Parametry!$C$16*Parametry!$C$18*D30))*1,0) -> 144 | L30: =ROUNDUP((2*(0))*1,0) -> 0 | M30: =ROUNDUP((2*(0))*1,0) -> 0 | N30: =ROUNDUP((2*(0))*1,0) -> 0 | O30: =ROUNDUP(J30/H30,0) -> 7 | P30: =ROUNDUP(K30/H30,0) -> 3 | Q30: =ROUNDUP(L30/H30,0) -> 0 | R30: =ROUNDUP(M30/H30,0) -> 0 | S30: =ROUNDUP(N30/H30,0) -> 0 | T30: =SUM(O30:S30) -> 10 | U30: =ROUNDUP(T30/G30,0) -> 2 | V30: =U30*Parametry!$C$11/(1+Parametry!$C$71*Parametry!$C$73) -> 10 | W30: =2 -> 2 | X30: =V30*(W30-1) -> 10 | Y30: =V30*W30 -> 20 | Z30: =SUM(J30:N30) -> 528 | AA30: Tylko ta budowa; 6 dostępnych nakarmionych tragarzy; poziom magazynu według F. Poziom ścieżek z Parametry; domyślnie0. Rywalizujące kursy i priorytety w grze mogą wydłużyć ETA.
A31: Drwale | B31: 1→2 | C31: Kolejka +10% | D31: 1 | E31: =D31+1 -> 2 | F31: 1 | G31: =Parametry!$C$12 -> 6 | H31: =ROUNDDOWN(ROUNDDOWN(Parametry!$C$9*Parametry!$C$10^(F31-1),0)*(1+Parametry!$C$72*MAX(0,Parametry!$C$73-2)),0) -> 60 | I31: =ROUNDUP((2*(0))*Parametry!$C$15,0) -> 0 | J31: =ROUNDUP((2*(Parametry!$C$16*Parametry!$C$17*D31+Parametry!$C$16*Parametry!$C$19*D31))*Parametry!$C$15,0) -> 423 | K31: =ROUNDUP((2*(Parametry!$C$16*Parametry!$C$18*D31))*Parametry!$C$15,0) -> 159 | L31: =ROUNDUP((2*(0))*Parametry!$C$15,0) -> 0 | M31: =ROUNDUP((2*(0))*Parametry!$C$15,0) -> 0 | N31: =ROUNDUP((2*(0))*Parametry!$C$15,0) -> 0 | O31: =ROUNDUP(J31/H31,0) -> 8 | P31: =ROUNDUP(K31/H31,0) -> 3 | Q31: =ROUNDUP(L31/H31,0) -> 0 | R31: =ROUNDUP(M31/H31,0) -> 0 | S31: =ROUNDUP(N31/H31,0) -> 0 | T31: =SUM(O31:S31) -> 11 | U31: =ROUNDUP(T31/G31,0) -> 2 | V31: =U31*Parametry!$C$11/(1+Parametry!$C$71*Parametry!$C$73) -> 10 | W31: =2 -> 2 | X31: =V31*(W31-1) -> 10 | Y31: =V31*W31 -> 20 | Z31: =SUM(J31:N31) -> 582 | AA31: Tylko ta budowa; 6 dostępnych nakarmionych tragarzy; poziom magazynu według F. Poziom ścieżek z Parametry; domyślnie0. Rywalizujące kursy i priorytety w grze mogą wydłużyć ETA.
A32: Drwale | B32: 2→3 | C32: Bez kolejki | D32: 2 | E32: =D32+1 -> 3 | F32: 2 | G32: =Parametry!$C$12 -> 6 | H32: =ROUNDDOWN(ROUNDDOWN(Parametry!$C$9*Parametry!$C$10^(F32-1),0)*(1+Parametry!$C$72*MAX(0,Parametry!$C$73-2)),0) -> 66 | I32: =ROUNDUP((2*(0))*1,0) -> 0 | J32: =ROUNDUP((2*(Parametry!$C$16*Parametry!$C$17*D32+Parametry!$C$16*Parametry!$C$19*D32))*1,0) -> 768 | K32: =ROUNDUP((2*(Parametry!$C$16*Parametry!$C$18*D32))*1,0) -> 288 | L32: =ROUNDUP((2*(0))*1,0) -> 0 | M32: =ROUNDUP((2*(0))*1,0) -> 0 | N32: =ROUNDUP((2*(0))*1,0) -> 0 | O32: =ROUNDUP(J32/H32,0) -> 12 | P32: =ROUNDUP(K32/H32,0) -> 5 | Q32: =ROUNDUP(L32/H32,0) -> 0 | R32: =ROUNDUP(M32/H32,0) -> 0 | S32: =ROUNDUP(N32/H32,0) -> 0 | T32: =SUM(O32:S32) -> 17 | U32: =ROUNDUP(T32/G32,0) -> 3 | V32: =U32*Parametry!$C$11/(1+Parametry!$C$71*Parametry!$C$73) -> 15 | W32: =2 -> 2 | X32: =V32*(W32-1) -> 15 | Y32: =V32*W32 -> 30 | Z32: =SUM(J32:N32) -> 1056 | AA32: Tylko ta budowa; 6 dostępnych nakarmionych tragarzy; poziom magazynu według F. Poziom ścieżek z Parametry; domyślnie0. Rywalizujące kursy i priorytety w grze mogą wydłużyć ETA.
A33: Drwale | B33: 2→3 | C33: Kolejka +10% | D33: 2 | E33: =D33+1 -> 3 | F33: 2 | G33: =Parametry!$C$12 -> 6 | H33: =ROUNDDOWN(ROUNDDOWN(Parametry!$C$9*Parametry!$C$10^(F33-1),0)*(1+Parametry!$C$72*MAX(0,Parametry!$C$73-2)),0) -> 66 | I33: =ROUNDUP((2*(0))*Parametry!$C$15,0) -> 0 | J33: =ROUNDUP((2*(Parametry!$C$16*Parametry!$C$17*D33+Parametry!$C$16*Parametry!$C$19*D33))*Parametry!$C$15,0) -> 845 | K33: =ROUNDUP((2*(Parametry!$C$16*Parametry!$C$18*D33))*Parametry!$C$15,0) -> 317 | L33: =ROUNDUP((2*(0))*Parametry!$C$15,0) -> 0 | M33: =ROUNDUP((2*(0))*Parametry!$C$15,0) -> 0 | N33: =ROUNDUP((2*(0))*Parametry!$C$15,0) -> 0 | O33: =ROUNDUP(J33/H33,0) -> 13 | P33: =ROUNDUP(K33/H33,0) -> 5 | Q33: =ROUNDUP(L33/H33,0) -> 0 | R33: =ROUNDUP(M33/H33,0) -> 0 | S33: =ROUNDUP(N33/H33,0) -> 0 | T33: =SUM(O33:S33) -> 18 | U33: =ROUNDUP(T33/G33,0) -> 3 | V33: =U33*Parametry!$C$11/(1+Parametry!$C$71*Parametry!$C$73) -> 15 | W33: =2 -> 2 | X33: =V33*(W33-1) -> 15 | Y33: =V33*W33 -> 30 | Z33: =SUM(J33:N33) -> 1162 | AA33: Tylko ta budowa; 6 dostępnych nakarmionych tragarzy; poziom magazynu według F. Poziom ścieżek z Parametry; domyślnie0. Rywalizujące kursy i priorytety w grze mogą wydłużyć ETA.
A34: Drwale | B34: 3→4 | C34: Bez kolejki | D34: 3 | E34: =D34+1 -> 4 | F34: 3 | G34: =Parametry!$C$12 -> 6 | H34: =ROUNDDOWN(ROUNDDOWN(Parametry!$C$9*Parametry!$C$10^(F34-1),0)*(1+Parametry!$C$72*MAX(0,Parametry!$C$73-2)),0) -> 72 | I34: =ROUNDUP((2*(0))*1,0) -> 0 | J34: =ROUNDUP((2*(Parametry!$C$16*Parametry!$C$17*D34+Parametry!$C$16*Parametry!$C$19*D34))*1,0) -> 1152 | K34: =ROUNDUP((2*(Parametry!$C$16*Parametry!$C$18*D34))*1,0) -> 432 | L34: =ROUNDUP((2*(0))*1,0) -> 0 | M34: =ROUNDUP((2*(0))*1,0) -> 0 | N34: =ROUNDUP((2*(0))*1,0) -> 0 | O34: =ROUNDUP(J34/H34,0) -> 16 | P34: =ROUNDUP(K34/H34,0) -> 6 | Q34: =ROUNDUP(L34/H34,0) -> 0 | R34: =ROUNDUP(M34/H34,0) -> 0 | S34: =ROUNDUP(N34/H34,0) -> 0 | T34: =SUM(O34:S34) -> 22 | U34: =ROUNDUP(T34/G34,0) -> 4 | V34: =U34*Parametry!$C$11/(1+Parametry!$C$71*Parametry!$C$73) -> 20 | W34: =2 -> 2 | X34: =V34*(W34-1) -> 20 | Y34: =V34*W34 -> 40 | Z34: =SUM(J34:N34) -> 1584 | AA34: Tylko ta budowa; 6 dostępnych nakarmionych tragarzy; poziom magazynu według F. Poziom ścieżek z Parametry; domyślnie0. Rywalizujące kursy i priorytety w grze mogą wydłużyć ETA.
A35: Drwale | B35: 3→4 | C35: Kolejka +10% | D35: 3 | E35: =D35+1 -> 4 | F35: 3 | G35: =Parametry!$C$12 -> 6 | H35: =ROUNDDOWN(ROUNDDOWN(Parametry!$C$9*Parametry!$C$10^(F35-1),0)*(1+Parametry!$C$72*MAX(0,Parametry!$C$73-2)),0) -> 72 | I35: =ROUNDUP((2*(0))*Parametry!$C$15,0) -> 0 | J35: =ROUNDUP((2*(Parametry!$C$16*Parametry!$C$17*D35+Parametry!$C$16*Parametry!$C$19*D35))*Parametry!$C$15,0) -> 1268 | K35: =ROUNDUP((2*(Parametry!$C$16*Parametry!$C$18*D35))*Parametry!$C$15,0) -> 476 | L35: =ROUNDUP((2*(0))*Parametry!$C$15,0) -> 0 | M35: =ROUNDUP((2*(0))*Parametry!$C$15,0) -> 0 | N35: =ROUNDUP((2*(0))*Parametry!$C$15,0) -> 0 | O35: =ROUNDUP(J35/H35,0) -> 18 | P35: =ROUNDUP(K35/H35,0) -> 7 | Q35: =ROUNDUP(L35/H35,0) -> 0 | R35: =ROUNDUP(M35/H35,0) -> 0 | S35: =ROUNDUP(N35/H35,0) -> 0 | T35: =SUM(O35:S35) -> 25 | U35: =ROUNDUP(T35/G35,0) -> 5 | V35: =U35*Parametry!$C$11/(1+Parametry!$C$71*Parametry!$C$73) -> 25 | W35: =2 -> 2 | X35: =V35*(W35-1) -> 25 | Y35: =V35*W35 -> 50 | Z35: =SUM(J35:N35) -> 1744 | AA35: Tylko ta budowa; 6 dostępnych nakarmionych tragarzy; poziom magazynu według F. Poziom ścieżek z Parametry; domyślnie0. Rywalizujące kursy i priorytety w grze mogą wydłużyć ETA.
A36: Tartak | B36: 1→2 | C36: Bez kolejki | D36: 1 | E36: =D36+1 -> 2 | F36: 1 | G36: =Parametry!$C$12 -> 6 | H36: =ROUNDDOWN(ROUNDDOWN(Parametry!$C$9*Parametry!$C$10^(F36-1),0)*(1+Parametry!$C$72*MAX(0,Parametry!$C$73-2)),0) -> 60 | I36: =ROUNDUP((2*(0))*1,0) -> 0 | J36: =ROUNDUP((2*(Parametry!$C$16*Parametry!$C$17*D36))*1,0) -> 144 | K36: =ROUNDUP((2*(Parametry!$C$16*Parametry!$C$18*D36))*1,0) -> 144 | L36: =ROUNDUP((2*(0))*1,0) -> 0 | M36: =ROUNDUP((2*(0))*1,0) -> 0 | N36: =ROUNDUP((2*(Parametry!$C$16*Parametry!$C$19*D36))*1,0) -> 240 | O36: =ROUNDUP(J36/H36,0) -> 3 | P36: =ROUNDUP(K36/H36,0) -> 3 | Q36: =ROUNDUP(L36/H36,0) -> 0 | R36: =ROUNDUP(M36/H36,0) -> 0 | S36: =ROUNDUP(N36/H36,0) -> 4 | T36: =SUM(O36:S36) -> 10 | U36: =ROUNDUP(T36/G36,0) -> 2 | V36: =U36*Parametry!$C$11/(1+Parametry!$C$71*Parametry!$C$73) -> 10 | W36: =2 -> 2 | X36: =V36*(W36-1) -> 10 | Y36: =V36*W36 -> 20 | Z36: =SUM(J36:N36) -> 528 | AA36: Tylko ta budowa; 6 dostępnych nakarmionych tragarzy; poziom magazynu według F. Poziom ścieżek z Parametry; domyślnie0. Rywalizujące kursy i priorytety w grze mogą wydłużyć ETA.
